Workbook

Sheet Model Scorecard
A1: ="Louisiana HAP Portfolio Scorecard — "&TEXT(TODAY(),"m/d/yyyy") -> Louisiana HAP Portfolio Scorecard — 8/6/2026
A2: Metric | B2: Threshold | C2: CH | D2: NZ | E2: LOM | F2: SA | G2: Severity | H2: Citation
A3: DSCR
A4: ='Dashboard Calc'!L3 -> Bridge-period DSCR | B4: ='Dashboard Calc'!M3 -> >= 1.00x | C4: ='Dashboard Calc'!N3 -> FAIL | D4: ='Dashboard Calc'!O3 -> PASS | E4: ='Dashboard Calc'!P3 -> PASS | F4: ='Dashboard Calc'!Q3 -> N/A | G4: ='Dashboard Calc'!R3 -> warning | H4: ='Dashboard Calc'!S3 -> house rule; spec Sec. 5.7
A5: ='Dashboard Calc'!L4 -> Post-resyn DSCR band (Yr2-17) | B5: ='Dashboard Calc'!M4 -> >= floor, <= ceiling | C5: ='Dashboard Calc'!N4 -> FAIL | D5: ='Dashboard Calc'!O4 -> FAIL | E5: ='Dashboard Calc'!P4 -> FAIL | F5: ='Dashboard Calc'!Q4 -> FAIL | G5: ='Dashboard Calc'!R4 -> error | H5: ='Dashboard Calc'!S4 -> QAP UW standards; register UW rules
A6: CASH FLOW & DEFERRED FEE
A7: ='Dashboard Calc'!L5 -> Deferred fee repaid <= 15 yrs | B7: ='Dashboard Calc'!M5 -> payback year <= 15 | C7: ='Dashboard Calc'!N5 -> FAIL | D7: ='Dashboard Calc'!O5 -> FAIL | E7: ='Dashboard Calc'!P5 -> FAIL | F7: ='Dashboard Calc'!Q5 -> FAIL | G7: ='Dashboard Calc'!R5 -> error | H7: ='Dashboard Calc'!S5 -> IRC Sec.42 / QAP deferred-fee standard
A8: COST, FEES & TDC
A9: ='Dashboard Calc'!L6 -> Developer fee % <= QAP cap | B9: ='Dashboard Calc'!M6 -> <= DevFeeCapPct | C9: ='Dashboard Calc'!N6 -> PASS | D9: ='Dashboard Calc'!O6 -> PASS | E9: ='Dashboard Calc'!P6 -> PASS | F9: ='Dashboard Calc'!Q6 -> PASS | G9: ='Dashboard Calc'!R6 -> error | H9: ='Dashboard Calc'!S6 -> QAP fee limits (LA 2025 — PENDING 2026)
A10: ='Dashboard Calc'!L7 -> TDC/unit vs HUD/LHC limit | B10: ='Dashboard Calc'!M7 -> <= regional limit | C10: ='Dashboard Calc'!N7 -> PASS | D10: ='Dashboard Calc'!O7 -> PASS | E10: ='Dashboard Calc'!P7 -> PASS | F10: ='Dashboard Calc'!Q7 -> PASS | G10: ='Dashboard Calc'!R7 -> error | H10: ='Dashboard Calc'!S7 -> HUD/LHC Unit TDC Limits (2024 vintage)
A11: RENTS & REHAB
A12: ='Dashboard Calc'!L8 -> Post-rehab rents <= caps | B12: ='Dashboard Calc'!M8 -> <= MIN(High HAP, 150% SAFMR) / LIHTC max | C12: ='Dashboard Calc'!N8 -> PASS | D12: ='Dashboard Calc'!O8 -> PASS | E12: ='Dashboard Calc'!P8 -> PASS | F12: ='Dashboard Calc'!Q8 -> PASS | G12: ='Dashboard Calc'!R8 -> error | H12: ='Dashboard Calc'!S8 -> Sec. 8 renewal policy / SAFMR; spec Sec. 5.2
A13: ='Dashboard Calc'!L9 -> Min rehab $/unit (IRC) | B13: ='Dashboard Calc'!M9 -> >= MinRehabIRC | C13: ='Dashboard Calc'!N9 -> PASS | D13: ='Dashboard Calc'!O9 -> PASS | E13: ='Dashboard Calc'!P9 -> PASS | F13: ='Dashboard Calc'!Q9 -> PASS | G13: ='Dashboard Calc'!R9 -> error | H13: ='Dashboard Calc'!S9 -> IRC Sec.42(e)(3)(A)(ii) — indexed min PLACEHOLDER
A14: ='Dashboard Calc'!L10 -> Min rehab $/unit (LA QAP) | B14: ='Dashboard Calc'!M10 -> 2026 QAP value unconfirmed | C14: ='Dashboard Calc'!N10 -> PENDING | D14: ='Dashboard Calc'!O10 -> PENDING | E14: ='Dashboard Calc'!P10 -> PENDING | F14: ='Dashboard Calc'!Q10 -> PENDING | G14: ='Dashboard Calc'!R10 -> warning | H14: ='Dashboard Calc'!S10 -> LA QAP rehab standard — PENDING
A15: CREDIT STRUCTURE & SIZING
A16: ='Dashboard Calc'!L11 -> Tax-exempt bond test | B16: ='Dashboard Calc'!M11 -> >= 25% of aggregate basis (OBBBA) | C16: ='Dashboard Calc'!N11 -> PASS | D16: ='Dashboard Calc'!O11 -> PASS | E16: ='Dashboard Calc'!P11 -> PASS | F16: ='Dashboard Calc'!Q11 -> PASS | G16: ='Dashboard Calc'!R11 -> error | H16: ='Dashboard Calc'!S11 -> IRC Sec.42(h)(4) as amended (OBBBA P.L. 119-21)
A17: ='Dashboard Calc'!L15 -> Sources = Uses w/o unfunded soft gap | B17: ='Dashboard Calc'!M15 -> required soft funds = 0 | C17: ='Dashboard Calc'!N15 -> FAIL | D17: ='Dashboard Calc'!O15 -> FAIL | E17: ='Dashboard Calc'!P15 -> PASS | F17: ='Dashboard Calc'!Q15 -> PASS | G17: ='Dashboard Calc'!R15 -> error | H17: ='Dashboard Calc'!S15 -> arithmetic check; spec Sec. 9.5
A18: OPERATING & PRICING
A19: ='Dashboard Calc'!L12 -> Underwritten vacancy floor | B19: ='Dashboard Calc'!M12 -> >= VacancyMin | C19: ='Dashboard Calc'!N12 -> FAIL | D19: ='Dashboard Calc'!O12 -> FAIL | E19: ='Dashboard Calc'!P12 -> PASS | F19: ='Dashboard Calc'!Q12 -> PASS | G19: ='Dashboard Calc'!R12 -> warning | H19: ='Dashboard Calc'!S12 -> QAP UW standards
A20: ='Dashboard Calc'!L13 -> Expense PUPA floor | B20: ='Dashboard Calc'!M13 -> >= OpexMinPU | C20: ='Dashboard Calc'!N13 -> PASS | D20: ='Dashboard Calc'!O13 -> PASS | E20: ='Dashboard Calc'!P13 -> PASS | F20: ='Dashboard Calc'!Q13 -> PASS | G20: ='Dashboard Calc'!R13 -> warning | H20: ='Dashboard Calc'!S13 -> QAP UW standards
A21: ='Dashboard Calc'!L14 -> Solved price/unit vs OM comps | B21: ='Dashboard Calc'!M14 -> sanity: <= comp wtd avg | C21: ='Dashboard Calc'!N14 -> REVIEW | D21: ='Dashboard Calc'!O14 -> REVIEW | E21: ='Dashboard Calc'!P14 -> PASS | F21: ='Dashboard Calc'!Q14 -> PASS | G21: ='Dashboard Calc'!R14 -> info | H21: ='Dashboard Calc'!S14 -> OM sale comps pp.11/18/25/32 (market-rate sales)
A22: PENDING ITEMS
A23: ='Dashboard Calc'!L16 -> URA applicability | B23: ='Dashboard Calc'!M16 -> funding stack final? | C23: ='Dashboard Calc'!N16 -> PENDING | D23: ='Dashboard Calc'!O16 -> PENDING | E23: ='Dashboard Calc'!P16 -> PENDING | F23: ='Dashboard Calc'!Q16 -> PENDING | G23: ='Dashboard Calc'!R16 -> warning | H23: ='Dashboard Calc'!S16 -> 49 CFR Part 24; NZ HOME loan in existing stack
A24: ='Dashboard Calc'!L17 -> QAP vintage (2026 confirm) | B24: ='Dashboard Calc'!M17 -> register = LA 2025 QAP | C24: ='Dashboard Calc'!N17 -> PENDING | D24: ='Dashboard Calc'!O17 -> PENDING | E24: ='Dashboard Calc'!P17 -> PENDING | F24: ='Dashboard Calc'!Q17 -> PENDING | G24: ='Dashboard Calc'!R17 -> warning | H24: ='Dashboard Calc'!S17 -> spec Gap #6
A26: VERDICT (per property) | C26: ='Dashboard Calc'!N22 -> FAIL | D26: ='Dashboard Calc'!O22 -> FAIL | E26: ='Dashboard Calc'!P22 -> FAIL | F26: ='Dashboard Calc'!Q22 -> FAIL
A27: PORTFOLIO VERDICT | C27: ='Dashboard Calc'!N23 -> FAIL

Sheet Dashboard Calc
A1: DASHBOARD CALC — DEAL INPUTS & KPI ENGINE | J1: KPI RULE REGISTER (per-property status engine — Scorecard pulls from here)
B2: Deal Inputs | C2: Clear Horizons | D2: New Zion | E2: Live Oak Manor | F2: Spanish Arms | G2: Portfolio | J2: # | K2: kpi_id | L2: metric | M2: threshold | N2: CH | O2: NZ | P2: LOM | Q2: SA | R2: severity | S2: citation
B3: Property Name | C3: Clear Horizons | D3: New Zion | E3: Live Oak Manor | F3: Spanish Arms | J3: 1 | K3: UW-DSCR-BRIDGE | L3: Bridge-period DSCR | M3: >= 1.00x | N3: =IF(CH_BridgeDSCR="n/a","N/A",IF(CH_BridgeDSCR>=1,"PASS","FAIL")) -> FAIL | O3: =IF(NZ_BridgeDSCR="n/a","N/A",IF(NZ_BridgeDSCR>=1,"PASS","FAIL")) -> PASS | P3: =IF(LOM_BridgeDSCR="n/a","N/A",IF(LOM_BridgeDSCR>=1,"PASS","FAIL")) -> PASS | Q3: =IF(SA_BridgeDSCR="n/a","N/A",IF(SA_BridgeDSCR>=1,"PASS","FAIL")) -> N/A | R3: warning | S3: house rule; spec Sec. 5.7
B4: Units | C4: 84 | D4: 100 | E4: 119 | F4: 204 | G4: =SUM(C4:F4) -> 507 | J4: 2 | K4: UW-DSCR-BAND | L4: Post-resyn DSCR band (Yr2-17) | M4: >= floor, <= ceiling | N4: =IF(AND(MIN('CH - Pro Forma'!$E$39:$S$39)>=DSCRFloor,MAX('CH - Pro Forma'!$E$39:$S$39)<=DSCRCeil),"PASS","FAIL") -> FAIL | O4: =IF(AND(MIN('NZ - Pro Forma'!$E$39:$S$39)>=DSCRFloor,MAX('NZ - Pro Forma'!$E$39:$S$39)<=DSCRCeil),"PASS","FAIL") -> FAIL | P4: =IF(AND(MIN('LOM - Pro Forma'!$E$39:$S$39)>=DSCRFloor,MAX('LOM - Pro Forma'!$E$39:$S$39)<=DSCRCeil),"PASS","FAIL") -> FAIL | Q4: =IF(AND(MIN('SA - Pro Forma'!$E$39:$S$39)>=DSCRFloor,MAX('SA - Pro Forma'!$E$39:$S$39)<=DSCRCeil),"PASS","FAIL") -> FAIL | R4: error | S4: QAP UW standards; register UW rules
B5: HAP Units | C5: 84 | D5: 100 | E5: 119 | F5: 123 | G5: =SUM(C5:F5) -> 426 | J5: 3 | K5: UW-DDF-15YR | L5: Deferred fee repaid <= 15 yrs | M5: payback year <= 15 | N5: =IF(CH_DDF=0,"N/A",IF(ISNUMBER(CH_DDFPayback),IF(CH_DDFPayback<=15,"PASS","FAIL"),"FAIL")) -> FAIL | O5: =IF(NZ_DDF=0,"N/A",IF(ISNUMBER(NZ_DDFPayback),IF(NZ_DDFPayback<=15,"PASS","FAIL"),"FAIL")) -> FAIL | P5: =IF(LOM_DDF=0,"N/A",IF(ISNUMBER(LOM_DDFPayback),IF(LOM_DDFPayback<=15,"PASS","FAIL"),"FAIL")) -> FAIL | Q5: =IF(SA_DDF=0,"N/A",IF(ISNUMBER(SA_DDFPayback),IF(SA_DDFPayback<=15,"PASS","FAIL"),"FAIL")) -> FAIL | R5: error | S5: IRC Sec.42 / QAP deferred-fee standard
B6: Net Rentable SF | C6: 73816 | D6: 71212 | E6: 102104 | F6: 191932 | G6: =SUM(C6:F6) -> 439064 | J6: 4 | K6: FEE-DEV-PCT | L6: Developer fee % <= QAP cap | M6: <= DevFeeCapPct | N6: =IF('Sources & Uses'!C25<=DevFeeCapPct,"PASS","FAIL") -> PASS | O6: =IF('Sources & Uses'!D25<=DevFeeCapPct,"PASS","FAIL") -> PASS | P6: =IF('Sources & Uses'!E25<=DevFeeCapPct,"PASS","FAIL") -> PASS | Q6: =IF('Sources & Uses'!F25<=DevFeeCapPct,"PASS","FAIL") -> PASS | R6: error | S6: QAP fee limits (LA 2025 — PENDING 2026)
B7: Parish | C7: Caddo | D7: Caddo | E7: Vermilion | F7: E. Baton Rouge | J7: 5 | K7: UW-TDC | L7: TDC/unit vs HUD/LHC limit | M7: <= regional limit | N7: =IF(CH_TDCpu<=CH_TDCLimitPU,"PASS","FAIL") -> PASS | O7: =IF(NZ_TDCpu<=NZ_TDCLimitPU,"PASS","FAIL") -> PASS | P7: =IF(LOM_TDCpu<=LOM_TDCLimitPU,"PASS","FAIL") -> PASS | Q7: =IF(SA_TDCpu<=SA_TDCLimitPU,"PASS","FAIL") -> PASS | R7: error | S7: HUD/LHC Unit TDC Limits (2024 vintage)
B8: TDC Region | C8: Shreveport | D8: Shreveport | E8: Lafayette | F8: Baton Rouge | J8: 6 | K8: UW-RENT-CAP | L8: Post-rehab rents <= caps | M8: <= MIN(High HAP, 150% SAFMR) / LIHTC max | N8: =IF(COUNTIF(CH_CapCheck,"FAIL")=0,"PASS","FAIL") -> PASS | O8: =IF(COUNTIF(NZ_CapCheck,"FAIL")=0,"PASS","FAIL") -> PASS | P8: =IF(COUNTIF(LOM_CapCheck,"FAIL")=0,"PASS","FAIL") -> PASS | Q8: =IF(COUNTIF(SA_CapCheck,"FAIL")=0,"PASS","FAIL") -> PASS | R8: error | S8: Sec. 8 renewal policy / SAFMR; spec Sec. 5.2
B9: Building Type | C9: Walkup | D9: Walkup | E9: Walkup | F9: Walkup | J9: 7 | K9: UW-MINREHAB-IRC | L9: Min rehab $/unit (IRC) | M9: >= MinRehabIRC | N9: =IF('Rehab Scope'!C9>=MinRehabIRC,"PASS","FAIL") -> PASS | O9: =IF('Rehab Scope'!D9>=MinRehabIRC,"PASS","FAIL") -> PASS | P9: =IF('Rehab Scope'!E9>=MinRehabIRC,"PASS","FAIL") -> PASS | Q9: =IF('Rehab Scope'!F9>=MinRehabIRC,"PASS","FAIL") -> PASS | R9: error | S9: IRC Sec.42(e)(3)(A)(ii) — indexed min PLACEHOLDER
B10: Credit Type | C10: 4% bond | D10: 4% bond | E10: 4% bond | F10: 4% bond | J10: 8 | K10: UW-MINREHAB-QAP | L10: Min rehab $/unit (LA QAP) | M10: 2026 QAP value unconfirmed | N10: =IF(MinRehabQAP="","PENDING",IF('Rehab Scope'!C9>=MinRehabQAP,"PASS","FAIL")) -> PENDING | O10: =IF(MinRehabQAP="","PENDING",IF('Rehab Scope'!D9>=MinRehabQAP,"PASS","FAIL")) -> PENDING | P10: =IF(MinRehabQAP="","PENDING",IF('Rehab Scope'!E9>=MinRehabQAP,"PASS","FAIL")) -> PENDING | Q10: =IF(MinRehabQAP="","PENDING",IF('Rehab Scope'!F9>=MinRehabQAP,"PASS","FAIL")) -> PENDING | R10: warning | S10: LA QAP rehab standard — PENDING
B11: Basis Boost Eligible | C11: Yes | D11: Yes | E11: Yes | F11: Yes | J11: 9 | K11: ELG-BOND-25 | L11: Tax-exempt bond test | M11: >= 25% of aggregate basis (OBBBA) | N11: =CH_BondTest -> PASS | O11: =NZ_BondTest -> PASS | P11: =LOM_BondTest -> PASS | Q11: =SA_BondTest -> PASS | R11: error | S11: IRC Sec.42(h)(4) as amended (OBBBA P.L. 119-21)
B12: Acquisition Price | C12: 0 | D12: 0 | E12: 3000000 | F12: 500000 | G12: =SUM(C12:F12) -> 3500000 | J12: 10 | K12: UW-VAC-MIN | L12: Underwritten vacancy floor | M12: >= VacancyMin | N12: =IF(CH_VacHAP>=VacancyMin,"PASS","FAIL") -> FAIL | O12: =IF(NZ_VacHAP>=VacancyMin,"PASS","FAIL") -> FAIL | P12: =IF(LOM_VacHAP>=VacancyMin,"PASS","FAIL") -> PASS | Q12: =IF(SA_VacHAP>=VacancyMin,"PASS","FAIL") -> PASS | R12: warning | S12: QAP UW standards
B13: Land % of Acq Price | C13: 0.15 | D13: 0.15 | E13: 0.15 | F13: 0.15 | J13: 11 | K13: UW-OPEX-MIN | L13: Expense PUPA floor | M13: >= OpexMinPU | N13: =IF('Rev+Expenses'!C34>=OpexMinPU,"PASS","FAIL") -> PASS | O13: =IF('Rev+Expenses'!D34>=OpexMinPU,"PASS","FAIL") -> PASS | P13: =IF('Rev+Expenses'!E34>=OpexMinPU,"PASS","FAIL") -> PASS | Q13: =IF('Rev+Expenses'!F34>=OpexMinPU,"PASS","FAIL") -> PASS | R13: warning | S13: QAP UW standards
B14: Acquisition Date | C14: 46357 | D14: 46357 | E14: 46357 | F14: 46357 | J14: 12 | K14: UW-PRICE-COMP | L14: Solved price/unit vs OM comps | M14: sanity: <= comp wtd avg | N14: =IF(CH_MaxPrice=0,"REVIEW",IF(CH_MaxPrice/CH_Units<=60000,"PASS","REVIEW")) -> REVIEW | O14: =IF(NZ_MaxPrice=0,"REVIEW",IF(NZ_MaxPrice/NZ_Units<=60000,"PASS","REVIEW")) -> REVIEW | P14: =IF(LOM_MaxPrice=0,"REVIEW",IF(LOM_MaxPrice/LOM_Units<=60000,"PASS","REVIEW")) -> PASS | Q14: =IF(SA_MaxPrice=0,"REVIEW",IF(SA_MaxPrice/SA_Units<=60000,"PASS","REVIEW")) -> PASS | R14: info | S14: OM sale comps pp.11/18/25/32 (market-rate sales)
B15: Resyndication Close Date | C15: 46753 | D15: 47119 | E15: 47119 | F15: 46357 | J15: 13 | K15: UW-SU-BAL | L15: Sources = Uses w/o unfunded soft gap | M15: required soft funds = 0 | N15: =IF('Sources & Uses'!C12<=SUBalanceTol,"PASS","FAIL") -> FAIL | O15: =IF('Sources & Uses'!D12<=SUBalanceTol,"PASS","FAIL") -> FAIL | P15: =IF('Sources & Uses'!E12<=SUBalanceTol,"PASS","FAIL") -> PASS | Q15: =IF('Sources & Uses'!F12<=SUBalanceTol,"PASS","FAIL") -> PASS | R15: error | S15: arithmetic check; spec Sec. 9.5
B16: Bridge Period (months) | C16: =DATEDIF(C14,C15,"m") -> 13 | D16: =DATEDIF(D14,D15,"m") -> 25 | E16: =DATEDIF(E14,E15,"m") -> 25 | F16: =DATEDIF(F14,F15,"m") -> 0 | J16: 14 | K16: UW-URA | L16: URA applicability | M16: funding stack final? | N16: ="PENDING" -> PENDING | O16: ="PENDING" -> PENDING | P16: ="PENDING" -> PENDING | Q16: ="PENDING" -> PENDING | R16: warning | S16: 49 CFR Part 24; NZ HOME loan in existing stack
B17: Rehab Duration (months) | C17: 12 | D17: 12 | E17: 15 | F17: 18 | J17: 15 | K17: UW-QAP-VINTAGE | L17: QAP vintage (2026 confirm) | M17: register = LA 2025 QAP | N17: ="PENDING" -> PENDING | O17: ="PENDING" -> PENDING | P17: ="PENDING" -> PENDING | Q17: ="PENDING" -> PENDING | R17: warning | S17: spec Gap #6
B18: Hold Period End | C18: 53692 | D18: 53692 | E18: 53692 | F18: 53692
B19: Vintage Inflation Years | C19: =YEAR(C15)-YEAR($C$14) -> 2 | D19: =YEAR(D15)-YEAR($C$14) -> 3 | E19: =YEAR(E15)-YEAR($C$14) -> 3 | F19: =YEAR(F15)-YEAR($C$14) -> 0 | J19: Hard fails | N19: =COUNTIFS($R$3:$R$17,"error",N$3:N$17,"FAIL") -> 3 | O19: =COUNTIFS($R$3:$R$17,"error",O$3:O$17,"FAIL") -> 3 | P19: =COUNTIFS($R$3:$R$17,"error",P$3:P$17,"FAIL") -> 2 | Q19: =COUNTIFS($R$3:$R$17,"error",Q$3:Q$17,"FAIL") -> 2
J20: Warnings failing | N20: =COUNTIFS($R$3:$R$17,"warning",N$3:N$17,"FAIL") -> 2 | O20: =COUNTIFS($R$3:$R$17,"warning",O$3:O$17,"FAIL") -> 1 | P20: =COUNTIFS($R$3:$R$17,"warning",P$3:P$17,"FAIL") -> 0 | Q20: =COUNTIFS($R$3:$R$17,"warning",Q$3:Q$17,"FAIL") -> 0
B21: Global Assumptions | C21: Value | J21: Pending | N21: =COUNTIF(N$3:N$17,"PENDING") -> 3 | O21: =COUNTIF(O$3:O$17,"PENDING") -> 3 | P21: =COUNTIF(P$3:P$17,"PENDING") -> 3 | Q21: =COUNTIF(Q$3:Q$17,"PENDING") -> 3
B22: Target Return Metric | C22: DSCR-constrained | J22: VERDICT | N22: =IF(N19>0,"FAIL",IF((N20+N21)>0,"MARGINAL","PENCILS")) -> FAIL | O22: =IF(O19>0,"FAIL",IF((O20+O21)>0,"MARGINAL","PENCILS")) -> FAIL | P22: =IF(P19>0,"FAIL",IF((P20+P21)>0,"MARGINAL","PENCILS")) -> FAIL | Q22: =IF(Q19>0,"FAIL",IF((Q20+Q21)>0,"MARGINAL","PENCILS")) -> FAIL
B23: Solver DSCR Floor | C23: 1.15 | J23: PORTFOLIO VERDICT | N23: =IF(COUNTIF(N22:Q22,"FAIL")>0,"FAIL",IF(COUNTIF(N22:Q22,"MARGINAL")>0,"MARGINAL","PENCILS")) -> FAIL
B24: OCAF / HAP Rent Growth | C24: 0.025
B25: OCAF Achievement Haircut | C25: 0.75
B26: First-Year LA OCAF (2027) | C26: 0.098
B27: Expense Growth | C27: 0.03
B28: Insurance Growth | C28: 0.06
B29: Post-Rehab Rent Uplift | C29: 0.1
B30: Cost Inflation (vintage $) | C30: 0.04
B31: 4% LIHTC Equity Price | C31: 0.8
B32: Perm Debt Rate (refi) | C32: 0.06
B33: Perm Amortization (yrs) | C33: 35
B34: Perm LTV Cap | C34: 0.9
B35: Debt Strategy (base case) | C35: Refinance
B36: Rehab Hard Cost $/Unit | C36: 40000
B37: Tenant Relocation $/Unit | C37: 2500
B38: Management Fee % | C38: 0.04
B39: SA HAP Renewal (post-4/30/30) | C39: Renew + OCAF trend
B41: KPI register (columns J+) is built with the Model Scorecard step.

Sheet OM Actuals
A1: OM ACTUALS — STATIC REFERENCE DUMP (SVN Offering Memorandum)
B2: Published OM figures only. Per Sec. 9.2 hierarchy, executed DD documents override the OM; variances found in diligence are recorded in the VARIANCE NOTES block at the bottom of this sheet.
B4: CLEAR HORIZONS — INCOME & EXPENSES (OM p.9) | C4: 2024 Audit | D4: 2025 Audit | E4: 2026 Budget | F4: OM Current Rents* | G4: OM Post-Rehab*
B5: Rental Revenue | C5: 882240 | D5: 924973 | E5: 977289 | F5: 1041024 | G5: 1145126
B6: Vacancies & Rent Concessions | C6: -130117 | D6: -76791 | E6: -61743 | F6: -52051 | G6: -57256
B7: Financial Revenue | C7: 1419 | D7: 611 | E7: 0 | F7: 0 | G7: 0
B8: Other Revenue | C8: 9732 | D8: 16458 | E8: 15348 | F8: 13095 | G8: 13095
B9: Total Income | C9: 763274 | D9: 865251 | E9: 930894 | F9: 1002068 | G9: 1100965
B10: Administrative Expenses | C10: 190634 | D10: 233628 | E10: 225894 | F10: 194189 | G10: 201268
B11: Utilities Expense | C11: 105165 | D11: 119952 | E11: 129702 | F11: 129702 | G11: 129702
B12: Operating & Maintenance Expenses | C12: 521839 | D12: 538847 | E12: 428546 | F12: 329597 | G12: 329597
B13: Taxes & Insurance Expenses | C13: 156161 | D13: 158657 | E13: 154121 | F13: 149893 | G13: 149893
B14: Reserves | C14: 18936 | D14: 18937 | E14: 18937 | F14: 25200 | G14: 25200
B15: Gross Expenses | C15: 992735 | D15: 1070021 | E15: 957200 | F15: 828581 | G15: 835660
B16: Net Operating Income | C16: -229461 | D16: -204770 | E16: -26306 | F16: 173487 | G16: 265305
B19: NEW ZION — INCOME & EXPENSES (OM p.16) | C19: 2024 Audit | D19: 2025 Audit | E19: 2026 Budget | F19: OM Current Rents* | G19: OM Post-Rehab*
B20: Rental Revenue | C20: 1055452 | D20: 1088020 | E20: 1127028 | F20: 1250739 | G20: 1375813
B21: Vacancies & Rent Concessions | C21: -152508 | D21: -76003 | E21: -60328 | F21: -62537 | G21: -68791
B22: Financial Revenue | C22: 3296 | D22: 1918 | E22: 0 | F22: 0 | G22: 0
B23: Other Revenue | C23: 10518 | D23: 12095 | E23: 8040 | F23: 11307 | G23: 11307
B24: Total Income | C24: 916758 | D24: 1026030 | E24: 1074740 | F24: 1199509 | G24: 1318329
B25: Administrative Expenses | C25: 245612 | D25: 286194 | E25: 249338 | F25: 216454 | G25: 224959
B26: Utilities Expense | C26: 69411 | D26: 65311 | E26: 66614 | F26: 66614 | G26: 66614
B27: Operating & Maintenance Expenses | C27: 517638 | D27: 511923 | E27: 435741 | F27: 366083 | G27: 366083
B28: Taxes & Insurance Expenses | C28: 184343 | D28: 169930 | E28: 163199 | F28: 157724 | G28: 157724
B29: Reserves | C29: 30480 | D29: 30480 | E29: 30480 | F29: 30000 | G29: 30000
B30: Gross Expenses | C30: 1047484 | D30: 1063838 | E30: 945372 | F30: 836876 | G30: 845381
B31: Net Operating Income | C31: -130726 | D31: -37808 | E31: 129368 | F31: 362633 | G31: 472948
B34: LIVE OAK MANOR — INCOME & EXPENSES (OM p.23) | C34: 2024 Audit | D34: 2025 Audit | E34: 2026 Budget | F34: OM Current Rents* | G34: OM Post-Rehab*
B35: Rental Revenue | C35: 1370464 | D35: 1427333 | E35: 1481844 | F35: 1569468 | G35: 1726415
B36: Vacancies & Rent Concessions | C36: -97424 | D36: -104704 | E36: -60314 | F36: -78473 | G36: -86321
B37: Financial Revenue | C37: 12138 | D37: 1813 | E37: 0 | F37: 0 | G37: 0
B38: Other Revenue | C38: 45461 | D38: 20035 | E38: 18452 | F38: 16003 | G38: 16003
B39: Total Income | C39: 1330639 | D39: 1344477 | E39: 1439982 | F39: 1506998 | G39: 1656097
B40: Administrative Expenses | C40: 266965 | D40: 232329 | E40: 254608 | F40: 220490 | G40: 229593
B41: Utilities Expense | C41: 102940 | D41: 113781 | E41: 122995 | F41: 122995 | G41: 122995
B42: Operating & Maintenance Expenses | C42: 421527 | D42: 494756 | E42: 478216 | F42: 374748 | G42: 374748
B43: Taxes & Insurance Expenses | C43: 330926 | D43: 234200 | E43: 238239 | F43: 215821 | G43: 215821
B44: Reserves | C44: 11589 | D44: 11652 | E44: 11652 | F44: 35700 | G44: 35700
B45: Gross Expenses | C45: 1133947 | D45: 1086718 | E45: 1105710 | F45: 969754 | G45: 978857
B46: Net Operating Income | C46: 196692 | D46: 257759 | E46: 334272 | F46: 537243 | G46: 677240
B49: SPANISH ARMS — INCOME & EXPENSES (OM p.30) | C49: 2024 Audit | D49: 2025 Audit | E49: 2026 Budget | F49: OM Current Rents* | G49: OM Post-Rehab*
B50: Rental Revenue | C50: 1864448 | D50: 1994725 | E50: 2071834 | F50: 2153331 | G50: 2368664
B51: Vacancies & Rent Concessions | C51: -140300 | D51: -169231 | E51: -117058 | F51: -150733 | G51: -165807
B52: Financial Revenue | C52: 1074 | D52: 856 | E52: 0 | F52: 0 | G52: 0
B53: Other Revenue | C53: 48279 | D53: 29757 | E53: 23448 | F53: 34962 | G53: 34962
B54: Total Income | C54: 1773501 | D54: 1856107 | E54: 1978224 | F54: 2037560 | G54: 2237819
B55: Administrative Expenses | C55: 353722 | D55: 347443 | E55: 333357 | F55: 329497 | G55: 343967
B56: Utilities Expense | C56: 300027 | D56: 342111 | E56: 346747 | F56: 346747 | G56: 346747
B57: Operating & Maintenance Expenses | C57: 497706 | D57: 489006 | E57: 442925 | F57: 415840 | G57: 415840
B58: Taxes & Insurance Expenses | C58: 366990 | D58: 354515 | E58: 361325 | F58: 331390 | G58: 331390
B59: Reserves | C59: 69811 | D59: 70312 | E59: 70312 | F59: 61200 | G59: 61200
B60: Gross Expenses | C60: 1588256 | D60: 1603387 | E60: 1554666 | F60: 1484674 | G60: 1499144
B61: Net Operating Income | C61: 185245 | D61: 252720 | E61: 423558 | F61: 552886 | G61: 738675
B64: PORTFOLIO COMBINED — INCOME & EXPENSES (OM p.5) | C64: 2024 Audit | D64: 2025 Audit | E64: 2026 Budget | F64: OM Current Rents* | G64: OM Post-Rehab*
B65: Rental Revenue | C65: 5172604 | D65: 5435051 | E65: 5657995 | F65: 6014562 | G65: 6616019
B66: Vacancies & Rent Concessions | C66: -520349 | D66: -426729 | E66: -299443 | F66: -343795 | G66: -378174
B67: Financial Revenue | C67: 17927 | D67: 5198 | E67: 0 | F67: 0 | G67: 0
B68: Other Revenue | C68: 113990 | D68: 78345 | E68: 65288 | F68: 75366 | G68: 75366
B69: Total Income | C69: 4784172 | D69: 5091865 | E69: 5423840 | F69: 5746134 | G69: 6313210
B70: Administrative Expenses | C70: 1056933 | D70: 1099594 | E70: 1063197 | F70: 960631 | G70: 999788
B71: Utilities Expense | C71: 577543 | D71: 641155 | E71: 666058 | F71: 666058 | G71: 666058
B72: Operating & Maintenance Expenses | C72: 1958710 | D72: 2034532 | E72: 1785428 | F72: 1486268 | G72: 1486268
B73: Taxes & Insurance Expenses | C73: 1038420 | D73: 917302 | E73: 916884 | F73: 854828 | G73: 854828
B74: Reserves | C74: 130816 | D74: 131381 | E74: 131381 | F74: 152100 | G74: 152100
B75: Gross Expenses | C75: 4762422 | D75: 4823964 | E75: 4562948 | F75: 4119885 | G75: 4159042
B76: Net Operating Income | C76: 21750 | D76: 267901 | E76: 860892 | F76: 1626249 | G76: 2154168
B79: OM UNIT MIXES
B80: CLEAR HORIZONS (OM p.10)
B81: Unit Type | C81: Count | D81: SF | E81: Current Rent | F81: Post-Rehab | G81: High HAP | H81: 150% SAFMR
B82: 1BR/1BA - HAP | C82: 8 | D82: 682 | E82: 885 | F82: 974 | G82: 1088 | H82: 1223
B83: 2BR/1BA - HAP | C83: 32 | D83: 750 | E83: 961 | F83: 1057 | G83: 1216 | H83: 1423
B84: 3BR/1BA - HAP | C84: 4 | D84: 990 | E84: 1100 | F84: 1210 | G84: 1422 | H84: 1857
B85: 3BR/1.5BA - HAP | C85: 40 | D85: 1010 | E85: 1113 | F85: 1224 | G85: 1422 | H85: 1861
B86: TOTAL UNITS | C86: =SUM(C82:C85) -> 84
B88: NEW ZION (OM p.17)
B89: Unit Type | C89: Count | D89: SF | E89: Current Rent | F89: Post-Rehab | G89: High HAP | H89: 150% SAFMR
B90: 1BR/1BA - HAP | C90: 12 | D90: 529 | E90: 875 | F90: 1033 | G90: 1088 | H90: 1249
B91: 2BR/1BA - HAP | C91: 64 | D91: 676 | E91: 924 | F91: 1091 | G91: 1216 | H91: 1421
B92: 3BR/1BA - HAP | C92: 24 | D92: 900 | E92: 1144 | F92: 1351 | G92: 1422 | H92: 1882
B93: TOTAL UNITS | C93: =SUM(C90:C92) -> 100
B95: LIVE OAK MANOR (OM p.24)
B96: Unit Type | C96: Count | D96: SF | E96: Current Rent | F96: Post-Rehab | G96: High HAP | H96: 150% SAFMR
B97: 2BR/1BA - HAP | C97: 19 | D97: 716 | E97: 931 | F97: 1024 | G97: 1065 | H97: 1204
B98: 3BR/1BA - HAP | C98: 50 | D98: 822 | E98: 1060 | F98: 1166 | G98: 1326 | H98: 1584
B99: 4BR/1BA - HAP | C99: 50 | D99: 948 | E99: 1202 | F99: 1322 | G99: 1404 | H99: 1587
B100: TOTAL UNITS | C100: =SUM(C97:C99) -> 119
B102: SPANISH ARMS (OM p.31)
B103: Unit Type | C103: Count | D103: SF | E103: Current Rent | F103: Post-Rehab | G103: High HAP | H103: 150% SAFMR | I103: 2026 LIHTC Max
B104: 1BR/1BA - HAP | C104: 49 | D104: 795 | E104: 942 | F104: 1036 | G104: 1176 | H104: 1470 | I104: 1063
B105: 2BR/1BA - HAP | C105: 28 | D105: 975 | E105: 1011 | F105: 1112 | G105: 1321 | H105: 1650 | I105: 1276
B106: 2BR/1.5BA - HAP | C106: 25 | D106: 914 | E106: 1049 | F106: 1154 | G106: 1321 | H106: 1650 | I106: 1276
B107: 3BR/1.5BA - HAP | C107: 21 | D107: 1075 | E107: 1184 | F107: 1302 | G107: 1499 | H107: 2070 | I107: 1474
B108: 1BR/1BA - 50% | C108: 1 | D108: 795 | E108: 560 | F108: 616 | G108: 1176 | H108: 1470 | I108: 886
B109: 1BR/1BA - 60% | C109: 1 | D109: 795 | E109: 560 | F109: 616 | G109: 1176 | H109: 1470 | I109: 1063
B110: 2BR/1BA - 50% | C110: 2 | D110: 975 | E110: 630 | F110: 693 | G110: 1321 | H110: 1650 | I110: 1063
B111: 2BR/1BA - 60% | C111: 18 | D111: 975 | E111: 630 | F111: 693 | G111: 1321 | H111: 1650 | I111: 1276
B112: 2BR/1.5BA - 50% | C112: 3 | D112: 914 | E112: 650 | F112: 715 | G112: 1321 | H112: 1650 | I112: 1063
B113: 2BR/1.5BA - 60% | C113: 20 | D113: 914 | E113: 649 | F113: 714 | G113: 1321 | H113: 1650 | I113: 1276
B114: 3BR/1.5BA - 50% | C114: 5 | D114: 1075 | E114: 705 | F114: 776 | G114: 1499 | H114: 2070 | I114: 1228
...

Sheet Unit Mix+Rents
A1: UNIT MIX + RENTS — HAP RENT ARCHITECTURE
B2: Five rent tiers per unit type (spec Sec. 5.2): current HAP rent (HUD schedule) -> OCAF-trended to resyndication close -> post-rehab (uplift) vs High HAP comp and 150% SAFMR ceilings. Spanish Arms adds the 2026 LIHTC Max column governing its non-HAP units. DD rent schedules govern over OM (Sec. 9.2).
B4: CLEAR HORIZONS — resyndication close: | E4: =CH_ResynDate -> 46753 | G4: (OM p.10)
B5: HUD Rent Schedule effective | C5: 46204 | E5: Year-1 OCAF (published) | G5: =OCAF -> 0.025 | H5: OCAF bumps to close | J5: =ROUNDDOWN(YEARFRAC($C$5,CH_ResynDate),0) -> 1 | K5: Trend factor | M5: =IF($J$5<=0,1,(1+$G$5*OCAFHaircut)*(1+OCAF*OCAFHaircut)^($J$5-1)) -> 1.01875
B6: Unit Type | C6: Count | D6: SF | E6: Current Rent | F6: UA | G6: OCAF-Trended | H6: Post-Rehab | I6: High HAP | J6: 150% SAFMR | K6: LIHTC Max '26 | L6: Cap Check | M6: In-Place 4/26 | N6: Tier
B7: 1BR/1BA - HAP | C7: 8 | D7: 682 | E7: 885 | F7: 127 | G7: =E7*$M$5 -> 901.59375 | H7: =G7*(1+PostRehabUplift) -> 991.75312 | I7: 1088 | J7: 1223 | L7: =IF(H7<=MIN(I7,J7),"PASS","FAIL") -> PASS | M7: 814 | N7: HAP
B8: 2BR/1BA - HAP | C8: 32 | D8: 750 | E8: 961 | F8: 107 | G8: =E8*$M$5 -> 979.01875 | H8: =G8*(1+PostRehabUplift) -> 1076.9206 | I8: 1216 | J8: 1423 | L8: =IF(H8<=MIN(I8,J8),"PASS","FAIL") -> PASS | M8: 884 | N8: HAP
B9: 3BR/1BA - HAP | C9: 4 | D9: 990 | E9: 1100 | F9: 153 | G9: =E9*$M$5 -> 1120.625 | H9: =G9*(1+PostRehabUplift) -> 1232.6875 | I9: 1422 | J9: 1857 | L9: =IF(H9<=MIN(I9,J9),"PASS","FAIL") -> PASS | M9: 1012 | N9: HAP
B10: 3BR/1.5BA - HAP | C10: 40 | D10: 1010 | E10: 1113 | F10: 149 | G10: =E10*$M$5 -> 1133.8688 | H10: =G10*(1+PostRehabUplift) -> 1247.2556 | I10: 1422 | J10: 1861 | L10: =IF(H10<=MIN(I10,J10),"PASS","FAIL") -> PASS | M10: 1024 | N10: HAP
B11: TOTALS / MONTHLY | C11: =SUM(C7:C10) -> 84 | D11: =SUMPRODUCT(C7:C10,D7:D10) -> 73816 | E11: =SUMPRODUCT($C7:$C10,E7:E10) -> 86752 | G11: =SUMPRODUCT($C7:$C10,G7:G10) -> 88378.6 | H11: =SUMPRODUCT($C7:$C10,H7:H10) -> 97216.46 | L11: =IF(COUNTIF(L7:L10,"FAIL")=0,"PASS",COUNTIF(L7:L10,"FAIL")&" FAIL") -> PASS | M11: =SUMPRODUCT($C7:$C10,M7:M10) -> 79808
B12: Units check vs Dashboard | C12: =IF(C11=CH_Units,"OK","MISMATCH") -> OK
B14: NEW ZION — resyndication close: | E14: =NZ_ResynDate -> 47119 | G14: (OM p.17)
B15: HUD Rent Schedule effective | C15: 46023 | E15: Year-1 OCAF (published) | G15: 0.098 | H15: OCAF bumps to close | J15: =ROUNDDOWN(YEARFRAC($C$15,NZ_ResynDate),0) -> 3 | K15: Trend factor | M15: =IF($J$15<=0,1,(1+$G$15*OCAFHaircut)*(1+OCAF*OCAFHaircut)^($J$15-1)) -> 1.1141337
B16: Unit Type | C16: Count | D16: SF | E16: Current Rent | F16: UA | G16: OCAF-Trended | H16: Post-Rehab | I16: High HAP | J16: 150% SAFMR | K16: LIHTC Max '26 | L16: Cap Check | M16: In-Place 4/26 | N16: Tier
B17: 1BR/1BA - HAP | C17: 12 | D17: 529 | E17: 875 | F17: 101 | G17: =E17*$M$15 -> 974.86695 | H17: =G17*(1+PostRehabUplift) -> 1072.3536 | I17: 1088 | J17: 1249 | L17: =IF(H17<=MIN(I17,J17),"PASS","FAIL") -> PASS | M17: 875 | N17: HAP
B18: 2BR/1BA - HAP | C18: 64 | D18: 676 | E18: 924 | F18: 109 | G18: =E18*$M$15 -> 1029.4595 | H18: =G18*(1+PostRehabUplift) -> 1132.4054 | I18: 1216 | J18: 1421 | L18: =IF(H18<=MIN(I18,J18),"PASS","FAIL") -> PASS | M18: 924 | N18: HAP
B19: 3BR/1BA - HAP | C19: 24 | D19: 900 | E19: 1144 | F19: 128 | G19: =E19*$M$15 -> 1274.5689 | H19: =G19*(1+PostRehabUplift) -> 1402.0258 | I19: 1422 | J19: 1882 | L19: =IF(H19<=MIN(I19,J19),"PASS","FAIL") -> PASS | M19: 1144 | N19: HAP
B20: TOTALS / MONTHLY | C20: =SUM(C17:C19) -> 100 | D20: =SUMPRODUCT(C17:C19,D17:D19) -> 71212 | E20: =SUMPRODUCT($C17:$C19,E17:E19) -> 97092 | G20: =SUMPRODUCT($C17:$C19,G17:G19) -> 108173.46 | H20: =SUMPRODUCT($C17:$C19,H17:H19) -> 118990.81 | L20: =IF(COUNTIF(L17:L19,"FAIL")=0,"PASS",COUNTIF(L17:L19,"FAIL")&" FAIL") -> PASS | M20: =SUMPRODUCT($C17:$C19,M17:M19) -> 97092
B21: Units check vs Dashboard | C21: =IF(C20=NZ_Units,"OK","MISMATCH") -> OK
B23: LIVE OAK MANOR — resyndication close: | E23: =LOM_ResynDate -> 47119 | G23: (OM p.24)
B24: HUD Rent Schedule effective | C24: 46113 | E24: Year-1 OCAF (published) | G24: =OCAF -> 0.025 | H24: OCAF bumps to close | J24: =ROUNDDOWN(YEARFRAC($C$24,LOM_ResynDate),0) -> 2 | K24: Trend factor | M24: =IF($J$24<=0,1,(1+$G$24*OCAFHaircut)*(1+OCAF*OCAFHaircut)^($J$24-1)) -> 1.0378516
B25: Unit Type | C25: Count | D25: SF | E25: Current Rent | F25: UA | G25: OCAF-Trended | H25: Post-Rehab | I25: High HAP | J25: 150% SAFMR | K25: LIHTC Max '26 | L25: Cap Check | M25: In-Place 4/26 | N25: Tier
B26: 2BR/1BA - HAP | C26: 19 | D26: 716 | E26: 931 | F26: 71 | G26: =E26*$M$24 -> 966.2398 | H26: =G26*(1+PostRehabUplift) -> 1062.8638 | I26: 1065 | J26: 1204 | L26: =IF(H26<=MIN(I26,J26),"PASS","FAIL") -> PASS | M26: 864 | N26: HAP
B27: 3BR/1BA - HAP | C27: 50 | D27: 822 | E27: 1060 | F27: 96 | G27: =E27*$M$24 -> 1100.1227 | H27: =G27*(1+PostRehabUplift) -> 1210.1349 | I27: 1326 | J27: 1584 | L27: =IF(H27<=MIN(I27,J27),"PASS","FAIL") -> PASS | M27: 984 | N27: HAP
B28: 4BR/1BA - HAP | C28: 50 | D28: 948 | E28: 1202 | F28: 108 | G28: =E28*$M$24 -> 1247.4976 | H28: =G28*(1+PostRehabUplift) -> 1372.2473 | I28: 1404 | J28: 1587 | L28: =IF(H28<=MIN(I28,J28),"PASS","FAIL") -> PASS | M28: 1116 | N28: HAP
B29: TOTALS / MONTHLY | C29: =SUM(C26:C28) -> 119 | D29: =SUMPRODUCT(C26:C28,D26:D28) -> 102104 | E29: =SUMPRODUCT($C26:$C28,E26:E28) -> 130789 | G29: =SUMPRODUCT($C26:$C28,G26:G28) -> 135739.57 | H29: =SUMPRODUCT($C26:$C28,H26:H28) -> 149313.52 | L29: =IF(COUNTIF(L26:L28,"FAIL")=0,"PASS",COUNTIF(L26:L28,"FAIL")&" FAIL") -> PASS | M29: =SUMPRODUCT($C26:$C28,M26:M28) -> 121416
B30: Units check vs Dashboard | C30: =IF(C29=LOM_Units,"OK","MISMATCH") -> OK
B32: SPANISH ARMS — resyndication close: | E32: =SA_ResynDate -> 46357 | G32: (OM p.31)
B33: HUD Rent Schedule effective | C33: 46143 | E33: Year-1 OCAF (published) | G33: =OCAF -> 0.025 | H33: OCAF bumps to close | J33: =ROUNDDOWN(YEARFRAC($C$33,SA_ResynDate),0) -> 0 | K33: Trend factor | M33: =IF($J$33<=0,1,(1+$G$33*OCAFHaircut)*(1+OCAF*OCAFHaircut)^($J$33-1)) -> 1
B34: Unit Type | C34: Count | D34: SF | E34: Current Rent | F34: UA | G34: OCAF-Trended | H34: Post-Rehab | I34: High HAP | J34: 150% SAFMR | K34: LIHTC Max '26 | L34: Cap Check | M34: In-Place 4/26 | N34: Tier
B35: 1BR/1BA - HAP | C35: 49 | D35: 656 | E35: 942 | F35: 0 | G35: =E35*$M$33 -> 942 | H35: =G35*(1+PostRehabUplift) -> 1036.2 | I35: 1176 | J35: 1470 | K35: 1063 | L35: =IF(H35<=MIN(I35,J35),"PASS","FAIL") -> PASS | M35: 875 | N35: HAP
B36: 2BR/1BA - HAP | C36: 28 | D36: 806 | E36: 1011 | F36: 0 | G36: =E36*$M$33 -> 1011 | H36: =G36*(1+PostRehabUplift) -> 1112.1 | I36: 1321 | J36: 1650 | K36: 1276 | L36: =IF(H36<=MIN(I36,J36),"PASS","FAIL") -> PASS | M36: 940 | N36: HAP
B37: 2BR/1.5BA TH - HAP | C37: 25 | D37: 903 | E37: 1049 | F37: 0 | G37: =E37*$M$33 -> 1049 | H37: =G37*(1+PostRehabUplift) -> 1153.9 | I37: 1321 | J37: 1650 | K37: 1276 | L37: =IF(H37<=MIN(I37,J37),"PASS","FAIL") -> PASS | M37: 975 | N37: HAP
B38: 3BR/1.5BA - HAP | C38: 21 | D38: 903 | E38: 1184 | F38: 0 | G38: =E38*$M$33 -> 1184 | H38: =G38*(1+PostRehabUplift) -> 1302.4 | I38: 1499 | J38: 2070 | K38: 1474 | L38: =IF(H38<=MIN(I38,J38),"PASS","FAIL") -> PASS | M38: 1100 | N38: HAP
B39: 1BR/1BA - 50% AMI | C39: 1 | D39: 795 | E39: 769 | F39: 0 | G39: =E39*$M$33 -> 769 | H39: =G39*(1+PostRehabUplift) -> 845.9 | I39: 1176 | J39: 1470 | K39: 886 | L39: =IF(H39<=K39,"PASS","FAIL") -> PASS | M39: 769 | N39: LIHTC
B40: 1BR/1BA - 60% AMI | C40: 1 | D40: 795 | E40: 649 | F40: 0 | G40: =E40*$M$33 -> 649 | H40: =G40*(1+PostRehabUplift) -> 713.9 | I40: 1176 | J40: 1470 | K40: 1063 | L40: =IF(H40<=K40,"PASS","FAIL") -> PASS | M40: 649 | N40: LIHTC
B41: 2BR/1BA - 50% AMI | C41: 2 | D41: 806 | E41: 630 | F41: 0 | G41: =E41*$M$33 -> 630 | H41: =G41*(1+PostRehabUplift) -> 693 | I41: 1321 | J41: 1650 | K41: 1063 | L41: =IF(H41<=K41,"PASS","FAIL") -> PASS | M41: 630 | N41: LIHTC
B42: 2BR/1BA - 60% AMI | C42: 18 | D42: 806 | E42: 647.88 | F42: 0 | G42: =E42*$M$33 -> 647.88 | H42: =G42*(1+PostRehabUplift) -> 712.668 | I42: 1321 | J42: 1650 | K42: 1276 | L42: =IF(H42<=K42,"PASS","FAIL") -> PASS | M42: 647.88 | N42: LIHTC
B43: 2BR/1.5BA TH - 50% AMI | C43: 3 | D43: 903 | E43: 650 | F43: 0 | G43: =E43*$M$33 -> 650 | H43: =G43*(1+PostRehabUplift) -> 715 | I43: 1321 | J43: 1650 | K43: 1063 | L43: =IF(H43<=K43,"PASS","FAIL") -> PASS | M43: 650 | N43: LIHTC
B44: 2BR/1.5BA TH - 60% AMI | C44: 20 | D44: 903 | E44: 668.5 | F44: 0 | G44: =E44*$M$33 -> 668.5 | H44: =G44*(1+PostRehabUplift) -> 735.35 | I44: 1321 | J44: 1650 | K44: 1276 | L44: =IF(H44<=K44,"PASS","FAIL") -> PASS | M44: 668.5 | N44: LIHTC
B45: 3BR/1.5BA - 50% AMI | C45: 5 | D45: 903 | E45: 705 | F45: 0 | G45: =E45*$M$33 -> 705 | H45: =G45*(1+PostRehabUplift) -> 775.5 | I45: 1499 | J45: 2070 | K45: 1228 | L45: =IF(H45<=K45,"PASS","FAIL") -> PASS | M45: 705 | N45: LIHTC
B46: 3BR/1.5BA - 60% AMI | C46: 29 | D46: 903 | E46: 705 | F46: 0 | G46: =E46*$M$33 -> 705 | H46: =G46*(1+PostRehabUplift) -> 775.5 | I46: 1499 | J46: 2070 | K46: 1474 | L46: =IF(H46<=K46,"PASS","FAIL") -> PASS | M46: 705 | N46: LIHTC
B47: 1BR/1BA - Market | C47: 2 | D47: 795 | E47: 672 | F47: 0 | G47: =E47*$M$33 -> 672 | H47: =G47*(1+PostRehabUplift) -> 739.2 | I47: 1176 | J47: 1470 | K47: 1063 | L47: N/A | M47: 672 | N47: MKT
B48: TOTALS / MONTHLY | C48: =SUM(C35:C47) -> 204 | D48: =SUMPRODUCT(C35:C47,D35:D47) -> 167021 | E48: =SUMPRODUCT($C35:$C47,E35:E47) -> 180528.84 | G48: =SUMPRODUCT($C35:$C47,G35:G47) -> 180528.84 | H48: =SUMPRODUCT($C35:$C47,H35:H47) -> 198581.72 | L48: =IF(COUNTIF(L35:L47,"FAIL")=0,"PASS",COUNTIF(L35:L47,"FAIL")&" FAIL") -> PASS | M48: =SUMPRODUCT($C35:$C47,M35:M47) -> 171643.84
B49: Units check vs Dashboard | C49: =IF(C48=SA_Units,"OK","MISMATCH") -> OK

Sheet Rev+Expenses
A1: REVENUE + EXPENSES — STABILIZED YEAR-1 SNAPSHOT (each property's close-year $)
B2: HAP contract-rent revenue engine per spec Sec. 5.3 — not market rents. Each column is stated in that property's resyndication-close-year dollars (rents OCAF-trended on Unit Mix+Rents; expenses trended below). Portfolio column mixes vintages — caveat.
C3: Clear Horizons | D3: New Zion | E3: Live Oak Manor | F3: Spanish Arms | G3: Portfolio (mixed-vintage)
B5: HAP rental income | C5: =SUMPRODUCT((CH_MixTier="HAP")*CH_MixCount*CH_MixPR)*12 -> 1166597.5 | D5: =SUMPRODUCT((NZ_MixTier="HAP")*NZ_MixCount*NZ_MixPR)*12 -> 1427889.7 | E5: =SUMPRODUCT((LOM_MixTier="HAP")*LOM_MixCount*LOM_MixPR)*12 -> 1791762.3 | F5: =SUMPRODUCT((SA_MixTier="HAP")*SA_MixCount*SA_MixPR)*12 -> 1657326 | G5: =SUM(C5:F5) -> 6043575.6
B6: Non-HAP LIHTC income (SA) | C6: =SUMPRODUCT((CH_MixTier="LIHTC")*CH_MixCount*CH_MixPR)*12 -> 0 | D6: =SUMPRODUCT((NZ_MixTier="LIHTC")*NZ_MixCount*NZ_MixPR)*12 -> 0 | E6: =SUMPRODUCT((LOM_MixTier="LIHTC")*LOM_MixCount*LOM_MixPR)*12 -> 0 | F6: =SUMPRODUCT((SA_MixTier="LIHTC")*SA_MixCount*SA_MixPR)*12 -> 707913.89 | G6: =SUM(C6:F6) -> 707913.89
B7: Market income (SA) | C7: =SUMPRODUCT((CH_MixTier="MKT")*CH_MixCount*CH_MixPR)*12 -> 0 | D7: =SUMPRODUCT((NZ_MixTier="MKT")*NZ_MixCount*NZ_MixPR)*12 -> 0 | E7: =SUMPRODUCT((LOM_MixTier="MKT")*LOM_MixCount*LOM_MixPR)*12 -> 0 | F7: =SUMPRODUCT((SA_MixTier="MKT")*SA_MixCount*SA_MixPR)*12 -> 17740.8 | G7: =SUM(C7:F7) -> 17740.8
B8: Gross potential rent | C8: =SUM(C5:C7) -> 1166597.5 | D8: =SUM(D5:D7) -> 1427889.7 | E8: =SUM(E5:E7) -> 1791762.3 | F8: =SUM(F5:F7) -> 2382980.7 | G8: =SUM(C8:F8) -> 6769230.2
B9: Other income | C9: 13095 | D9: 14577 | E9: 12732 | F9: 34962 | G9: =SUM(C9:F9) -> 75366
B11: HAP vacancy % | C11: 0.0357 | D11: 0.02 | E11: 0.0756 | F11: 0.0931
B12: Non-HAP vacancy % | C12: n/a | D12: n/a | E12: n/a | F12: 0.0931
B13: Vacancy adjustment | C13: =-(C5*C11+0) -> -41647.531 | D13: =-(D5*D11+0) -> -28557.795 | E13: =-(E5*E11+0) -> -135457.23 | F13: =-(F5*F11+(F6+F7)*F12) -> -221855.5 | G13: =SUM(C13:F13) -> -427518.06
B15: Effective gross income (EGI) | C15: =SUM(C8:C9)+C13 -> 1138045 | D15: =SUM(D8:D9)+D13 -> 1413908.9 | E15: =SUM(E8:E9)+E13 -> 1669037.1 | F15: =SUM(F8:F9)+F13 -> 2196087.2 | G15: =SUM(C15:F15) -> 6417078.2
B17: Operating Expenses (trended to close year; insurance on its own trend)
B18: Management fee | C18: =MgmtFeePct*C15 -> 45521.8 | D18: =MgmtFeePct*D15 -> 56556.358 | E18: =MgmtFeePct*E15 -> 66761.483 | F18: =MgmtFeePct*F15 -> 87843.487 | G18: =SUM(C18:F18) -> 256683.13
B19: Administrative (ex-mgmt fee) | C19: =(CH_OpexAdmin-CH_MgmtFeeCell)*(1+ExpGrowth)^CH_InflYears -> 163492.12 | D19: =(NZ_OpexAdmin-NZ_MgmtFeeCell)*(1+ExpGrowth)^NZ_InflYears -> 184096.09 | E19: =(LOM_OpexAdmin-LOM_MgmtFeeCell)*(1+ExpGrowth)^LOM_InflYears -> 175065.79 | F19: =(SA_OpexAdmin-SA_MgmtFeeCell)*(1+ExpGrowth)^SA_InflYears -> 247995 | G19: =SUM(C19:F19) -> 770649
B20: Utilities | C20: =CH_OpexUtil*(1+ExpGrowth)^CH_InflYears -> 137600.85 | D20: =NZ_OpexUtil*(1+ExpGrowth)^NZ_InflYears -> 72790.916 | E20: =LOM_OpexUtil*(1+ExpGrowth)^LOM_InflYears -> 134399.96 | F20: =SA_OpexUtil*(1+ExpGrowth)^SA_InflYears -> 346747 | G20: =SUM(C20:F20) -> 691538.73
B21: Operating & maintenance | C21: =CH_OpexOM*(1+ExpGrowth)^CH_InflYears -> 349669.46 | D21: =NZ_OpexOM*(1+ExpGrowth)^NZ_InflYears -> 400028.78 | E21: =LOM_OpexOM*(1+ExpGrowth)^LOM_InflYears -> 409497.26 | F21: =SA_OpexOM*(1+ExpGrowth)^SA_InflYears -> 415840 | G21: =SUM(C21:F21) -> 1575035.5
B22: Taxes (RE & PP) + other T&I (ex-insurance) | C22: =(CH_OpexTI-CH_InsExp)*(1+ExpGrowth)^CH_InflYears -> 74675.69 | D22: =(NZ_OpexTI-NZ_InsExp)*(1+ExpGrowth)^NZ_InflYears -> 84935.484 | E22: =(LOM_OpexTI-LOM_InsExp)*(1+ExpGrowth)^LOM_InflYears -> 64905.798 | F22: =(SA_OpexTI-SA_InsExp)*(1+ExpGrowth)^SA_InflYears -> 100168 | G22: =SUM(C22:F22) -> 324684.97
B23: Property & liability insurance | C23: =CH_InsExp*(1+InsGrowth)^CH_InflYears -> 98737.474 | D23: =NZ_InsExp*(1+InsGrowth)^NZ_InflYears -> 105204.83 | E23: =LOM_InsExp*(1+InsGrowth)^LOM_InflYears -> 205310.91 | F23: =SA_InsExp*(1+InsGrowth)^SA_InflYears -> 272022 | G23: =SUM(C23:F23) -> 681275.21
B24: Total operating expenses | C24: =SUM(C18:C23) -> 869697.39 | D24: =SUM(D18:D23) -> 903612.45 | E24: =SUM(E18:E23) -> 1055941.2 | F24: =SUM(F18:F23) -> 1470615.5 | G24: =SUM(C24:F24) -> 4299866.5
B26: NET OPERATING INCOME | C26: =C15-C24 -> 268347.6 | D26: =D15-D24 -> 510296.49 | E26: =E15-E24 -> 613095.87 | F26: =F15-F24 -> 725471.7 | G26: =SUM(C26:F26) -> 2117211.7
B28: Replacement reserves (below NOI) | C28: =CH_Reserves*(1+ExpGrowth)^CH_InflYears -> 31190.46 | D28: =NZ_Reserves*(1+ExpGrowth)^NZ_InflYears -> 38245.445 | E28: =LOM_Reserves*(1+ExpGrowth)^LOM_InflYears -> 45512.08 | F28: =SA_Reserves*(1+ExpGrowth)^SA_InflYears -> 71400 | G28: =SUM(C28:F28) -> 186347.98
B29: Cash flow before debt service | C29: =C26-C28 -> 237157.14 | D29: =D26-D28 -> 472051.04 | E29: =E26-E28 -> 567583.79 | F29: =F26-F28 -> 654071.7 | G29: =SUM(C29:F29) -> 1930863.7
B31: Ratios
B32: Opex % of EGI | C32: =C24/C15 -> 0.76420299 | D32: =D24/D15 -> 0.63908815 | E32: =E24/E15 -> 0.63266492 | F32: =F24/F15 -> 0.6696526
B33: NOI % of EGI | C33: =C26/C15 -> 0.23579701 | D33: =D26/D15 -> 0.36091185 | E33: =E26/E15 -> 0.36733508 | F33: =F26/F15 -> 0.3303474
B34: Opex PUPA (close-year $) | C34: =C24/CH_Units -> 10353.54 | D34: =D24/NZ_Units -> 9036.1245 | E34: =E24/LOM_Units -> 8873.4555 | F34: =F24/SA_Units -> 7208.8994

Sheet Expense Detail
A1: EXPENSE DETAIL — AUDIT / BUDGET / OM / MODEL COMPARISON
B2: Per spec Sec. 5.4: every line compares 2025 audit | 2026 budget | OM 'market expenses' | model assumption (blue). Insurance carries its own growth rate (InsGrowth) and is never blended into the general trend. Model assumptions follow the OM market-expense basis EXCEPT insurance and taxes, which use DD-documented values (broker figures unsupported — see variance notes on OM Actuals).
B4: CLEAR HORIZONS | C4: 2025 Audit | D4: 2026 Budget | E4: OM Market | F4: Model (UW) | G4: PUPA
B5: ADMINISTRATIVE
B6: Advertising & marketing | C6: 175 | D6: 0 | E6: 865.5 | F6: 866 | G6: =F6/CH_Units -> 10.309524
B7: Other renting expense | C7: 0 | D7: 6226 | E7: 1500 | F7: 1500 | G7: =F7/CH_Units -> 17.857143
B8: Office salaries | C8: 97415 | D8: 97491 | E8: 22963.2 | F8: 22963 | G8: =F8/CH_Units -> 273.36905
B9: Office expenses | C9: 22147 | D9: 19547 | E9: 19547 | F9: 19547 | G9: =F9/CH_Units -> 232.70238
B10: Management fee | C10: 36538 | D10: 35892 | E10: 40082.712 | F10: ='Rev+Expenses'!C18 -> 45521.8 | G10: =F10/CH_Units -> 541.92619
B11: Manager salaries | C11: 0 | D11: 0 | E11: 60500 | F11: 60500 | G11: =F11/CH_Units -> 720.2381
B12: Legal | C12: 6288 | D12: 9368 | E12: 5000 | F12: 5000 | G12: =F12/CH_Units -> 59.52381
B13: Audit | C13: 9900 | D13: 10188 | E13: 7500 | F13: 7500 | G13: =F13/CH_Units -> 89.285714
B14: Bad debts | C14: 32446 | D14: 33552 | E14: 31230.72 | F14: 31231 | G14: =F14/CH_Units -> 371.79762
B15: Misc administrative | C15: 27494 | D15: 9031 | E15: 5000 | F15: 5000 | G15: =F15/CH_Units -> 59.52381
B16: Total administrative | C16: =SUM(C6:C15) -> 232403 | D16: =SUM(D6:D15) -> 221295 | E16: =SUM(E6:E15) -> 194189.13 | F16: =SUM(F6:F15) -> 199628.8 | G16: =F16/CH_Units -> 2376.5333
B17: UTILITIES
B18: Electricity | C18: 19230 | D18: 20100 | E18: 20100 | F18: 20100 | G18: =F18/CH_Units -> 239.28571
B19: Gas | C19: 0 | D19: 0 | E19: 0 | F19: 0 | G19: =F19/CH_Units -> 0
B20: Water | C20: 100722 | D20: 109602 | E20: 109602 | F20: 109602 | G20: =F20/CH_Units -> 1304.7857
B21: Sewer | C21: 0 | D21: 0 | E21: 0 | F21: 0 | G21: =F21/CH_Units -> 0
B22: Total utilities | C22: =SUM(C18:C21) -> 119952 | D22: =SUM(D18:D21) -> 129702 | E22: =SUM(E18:E21) -> 129702 | F22: =SUM(F18:F21) -> 129702 | G22: =F22/CH_Units -> 1544.0714
B23: OPERATING & MAINTENANCE
B24: Maintenance payroll | C24: 139997 | D24: 102132 | E24: 96636.8 | F24: 96637 | G24: =F24/CH_Units -> 1150.4405
B25: Supplies | C25: 79805 | D25: 49224 | E25: 42000 | F25: 42000 | G25: =F25/CH_Units -> 500
B26: Contracts | C26: 176549 | D26: 116549 | E26: 42000 | F26: 42000 | G26: =F26/CH_Units -> 500
B27: Garbage & trash | C27: 28949 | D27: 21372 | E27: 21372 | F27: 21372 | G27: =F27/CH_Units -> 254.42857
B28: Security | C28: 111722 | D28: 120088 | E28: 120088 | F28: 120088 | G28: =F28/CH_Units -> 1429.619
B29: Heating/cooling repairs | C29: 1825 | D29: 18851 | E29: 7500 | F29: 7500 | G29: =F29/CH_Units -> 89.285714
B30: Misc operating & maintenance | C30: 0 | D30: 330 | E30: 0 | F30: 0 | G30: =F30/CH_Units -> 0
B31: Total operating & maintenance | C31: =SUM(C24:C30) -> 538847 | D31: =SUM(D24:D30) -> 428546 | E31: =SUM(E24:E30) -> 329596.8 | F31: =SUM(F24:F30) -> 329597 | G31: =F31/CH_Units -> 3923.7738
B32: TAXES & INSURANCE
B33: Real estate & personal property taxes | C33: 33198 | D33: 30384 | E33: 33198.37 | F33: 33198 | G33: =F33/CH_Units -> 395.21429
B34: Payroll taxes | C34: 18421 | D34: 16333 | E34: 13777.65 | F34: 13778 | G34: =F34/CH_Units -> 164.02381
B35: Property & liability insurance | C35: 92566 | D35: 87876 | E35: 79504 | F35: 87876 | G35: =F35/CH_Units -> 1046.1429
B36: Workers compensation | C36: 677 | D36: 3368 | E36: 5403 | F36: 5403 | G36: =F36/CH_Units -> 64.321429
B37: Health insurance & benefits | C37: 13035 | D37: 16160 | E37: 18010 | F37: 18010 | G37: =F37/CH_Units -> 214.40476
B38: Misc taxes/licenses/insurance | C38: 760 | D38: 0 | E38: 0 | F38: 0 | G38: =F38/CH_Units -> 0
B39: Total taxes & insurance | C39: =SUM(C33:C38) -> 158657 | D39: =SUM(D33:D38) -> 154121 | E39: =SUM(E33:E38) -> 149893.02 | F39: =SUM(F33:F38) -> 158265 | G39: =F39/CH_Units -> 1884.1071
B40: TOTAL OPERATING EXPENSES (before reserves) | C40: =C16+C22+C31+C39 -> 1049859 | D40: =D16+D22+D31+D39 -> 933664 | E40: =E16+E22+E31+E39 -> 803380.95 | F40: =F16+F22+F31+F39 -> 817192.8 | G40: =F40/CH_Units -> 9728.4857
B41: Replacement reserves (below NOI) | C41: 18937 | D41: 18937 | E41: 25200 | F41: =MAX(ReserveFloorFamily*CH_Units,25200) -> 29400 | G41: =F41/CH_Units -> 350
B42: Expense PUPA check (vs OpexMinPU floor) | C42: =IF(G40>=OpexMinPU,"PASS","FAIL") -> PASS
B44: NEW ZION | C44: 2025 Audit | D44: 2026 Budget | E44: OM Market | F44: Model (UW) | G44: PUPA
B45: ADMINISTRATIVE
B46: Advertising & marketing | C46: 767 | D46: 831 | E46: 831 | F46: 831 | G46: =F46/NZ_Units -> 8.31
B47: Other renting expense | C47: 0 | D47: 7639 | E47: 1500 | F47: 1500 | G47: =F47/NZ_Units -> 15
B48: Office salaries | C48: 110511 | D48: 106484 | E48: 26956.8 | F48: 26957 | G48: =F48/NZ_Units -> 269.57
B49: Office expenses | C49: 30878 | D49: 24732 | E49: 24732 | F49: 24732 | G49: =F49/NZ_Units -> 247.32
B50: Management fee | C50: 41719 | D50: 41464 | E50: 47980.347 | F50: ='Rev+Expenses'!D18 -> 56556.358 | G50: =F50/NZ_Units -> 565.56358
B51: Manager salaries | C51: 0 | D51: 0 | E51: 59739.967 | F51: 59740 | G51: =F51/NZ_Units -> 597.4
B52: Legal | C52: 10402 | D52: 4692 | E52: 4692 | F52: 4692 | G52: =F52/NZ_Units -> 46.92
B53: Audit | C53: 9900 | D53: 10188 | E53: 7500 | F53: 7500 | G53: =F53/NZ_Units -> 75
B54: Bad debts | C54: 43022 | D54: 38220 | E54: 37522.174 | F54: 37522 | G54: =F54/NZ_Units -> 375.22
B55: Misc administrative | C55: 31495 | D55: 11584 | E55: 5000 | F55: 5000 | G55: =F55/NZ_Units -> 50
B56: Total administrative | C56: =SUM(C46:C55) -> 278694 | D56: =SUM(D46:D55) -> 245834 | E56: =SUM(E46:E55) -> 216454.29 | F56: =SUM(F46:F55) -> 225030.36 | G56: =F56/NZ_Units -> 2250.3036
B57: UTILITIES
B58: Electricity | C58: 17531 | D58: 17455 | E58: 17455 | F58: 17455 | G58: =F58/NZ_Units -> 174.55
B59: Gas | C59: 0 | D59: 0 | E59: 0 | F59: 0 | G59: =F59/NZ_Units -> 0
B60: Water | C60: 47780 | D60: 49159 | E60: 49159 | F60: 49159 | G60: =F60/NZ_Units -> 491.59
B61: Sewer | C61: 0 | D61: 0 | E61: 0 | F61: 0 | G61: =F61/NZ_Units -> 0
B62: Total utilities | C62: =SUM(C58:C61) -> 65311 | D62: =SUM(D58:D61) -> 66614 | E62: =SUM(E58:E61) -> 66614 | F62: =SUM(F58:F61) -> 66614 | G62: =F62/NZ_Units -> 666.14
B63: OPERATING & MAINTENANCE
B64: Maintenance payroll | C64: 161403 | D64: 123664 | E64: 113443.2 | F64: 113443 | G64: =F64/NZ_Units -> 1134.43
B65: Supplies | C65: 68767 | D65: 49064 | E65: 50000 | F65: 50000 | G65: =F65/NZ_Units -> 500
B66: Contracts | C66: 143289 | D66: 99477 | E66: 50000 | F66: 50000 | G66: =F66/NZ_Units -> 500
B67: Garbage & trash | C67: 22356 | D67: 26832 | E67: 26832 | F67: 26832 | G67: =F67/NZ_Units -> 268.32
B68: Security | C68: 112892 | D68: 118308 | E68: 118308 | F68: 118308 | G68: =F68/NZ_Units -> 1183.08
B69: Heating/cooling repairs | C69: 3059 | D69: 16789 | E69: 7500 | F69: 7500 | G69: =F69/NZ_Units -> 75
B70: Misc operating & maintenance | C70: 0 | D70: 1607 | E70: 0 | F70: 0 | G70: =F70/NZ_Units -> 0
B71: Total operating & maintenance | C71: =SUM(C64:C70) -> 511766 | D71: =SUM(D64:D70) -> 435741 | E71: =SUM(E64:E70) -> 366083.2 | F71: =SUM(F64:F70) -> 366083 | G71: =F71/NZ_Units -> 3660.83
B72: TAXES & INSURANCE
B73: Real estate & personal property taxes | C73: 36503 | D73: 35004 | E73: 36503.15 | F73: 36399 | G73: =F73/NZ_Units -> 363.99
B74: Payroll taxes | C74: 21956 | D74: 18489 | E74: 15310.707 | F74: 15311 | G74: =F74/NZ_Units -> 153.11
B75: Property & liability insurance | C75: 95099 | D75: 88332 | E75: 79892 | F75: 88332 | G75: =F75/NZ_Units -> 883.32
B76: Workers compensation | C76: 7300 | D76: 3902 | E76: 6004.199 | F76: 6004 | G76: =F76/NZ_Units -> 60.04
B77: Health insurance & benefits | C77: 8197 | D77: 17472 | E77: 20013.997 | F77: 20014 | G77: =F77/NZ_Units -> 200.14
B78: Misc taxes/licenses/insurance | C78: 875 | D78: 0 | E78: 0 | F78: 0 | G78: =F78/NZ_Units -> 0
B79: Total taxes & insurance | C79: =SUM(C73:C78) -> 169930 | D79: =SUM(D73:D78) -> 163199 | E79: =SUM(E73:E78) -> 157724.05 | F79: =SUM(F73:F78) -> 166060 | G79: =F79/NZ_Units -> 1660.6
B80: TOTAL OPERATING EXPENSES (before reserves) | C80: =C56+C62+C71+C79 -> 1025701 | D80: =D56+D62+D71+D79 -> 911388 | E80: =E56+E62+E71+E79 -> 806875.54 | F80: =F56+F62+F71+F79 -> 823787.36 | G80: =F80/NZ_Units -> 8237.8736
B81: Replacement reserves (below NOI) | C81: 30480 | D81: 30480 | E81: 30000 | F81: =MAX(ReserveFloorFamily*NZ_Units,30000) -> 35000 | G81: =F81/NZ_Units -> 350
B82: Expense PUPA check (vs OpexMinPU floor) | C82: =IF(G80>=OpexMinPU,"PASS","FAIL") -> PASS
B84: LIVE OAK MANOR | C84: 2025 Audit | D84: 2026 Budget | E84: OM Market | F84: Model (UW) | G84: PUPA
B85: ADMINISTRATIVE
B86: Advertising & marketing | C86: 179 | D86: 250 | E86: 250 | F86: 250 | G86: =F86/LOM_Units -> 2.1008403
B87: Other renting expense | C87: 0 | D87: 8207 | E87: 2000 | F87: 2000 | G87: =F87/LOM_Units -> 16.806723
B88: Office salaries | C88: 69037 | D88: 100146 | E88: 33280 | F88: 33280 | G88: =F88/LOM_Units -> 279.66387
B89: Office expenses | C89: 17433 | D89: 17624 | E89: 17624 | F89: 17624 | G89: =F89/LOM_Units -> 148.10084
B90: Management fee | C90: 53402 | D90: 50128 | E90: 60279.904 | F90: ='Rev+Expenses'!E18 -> 66761.483 | G90: =F90/LOM_Units -> 561.02086
B91: Manager salaries | C91: 0 | D91: 0 | E91: 55166.8 | F91: 55167 | G91: =F91/LOM_Units -> 463.58824
B92: Legal | C92: 3190 | D92: 3000 | E92: 3000 | F92: 3000 | G92: =F92/LOM_Units -> 25.210084
B93: Audit | C93: 9900 | D93: 10188 | E93: 7500 | F93: 7500 | G93: =F93/LOM_Units -> 63.02521
B94: Bad debts | C94: 47870 | D94: 37187 | E94: 31389.36 | F94: 31389 | G94: =F94/LOM_Units -> 263.77311
B95: Misc administrative | C95: 26080 | D95: 24746 | E95: 10000 | F95: 10000 | G95: =F95/LOM_Units -> 84.033613
B96: Total administrative | C96: =SUM(C86:C95) -> 227091 | D96: =SUM(D86:D95) -> 251476 | E96: =SUM(E86:E95) -> 220490.06 | F96: =SUM(F86:F95) -> 226971.48 | G96: =F96/LOM_Units -> 1907.3234
B97: UTILITIES
B98: Electricity | C98: 11491 | D98: 12622 | E98: 12622 | F98: 12622 | G98: =F98/LOM_Units -> 106.06723
B99: Gas | C99: 43693 | D99: 44484 | E99: 44484 | F99: 44484 | G99: =F99/LOM_Units -> 373.81513
B100: Water | C100: 58597 | D100: 65889 | E100: 65889 | F100: 65889 | G100: =F100/LOM_Units -> 553.68908
B101: Sewer | C101: 0 | D101: 0 | E101: 0 | F101: 0 | G101: =F101/LOM_Units -> 0
B102: Total utilities | C102: =SUM(C98:C101) -> 113781 | D102: =SUM(D98:D101) -> 122995 | E102: =SUM(E98:E101) -> 122995 | F102: =SUM(F98:F101) -> 122995 | G102: =F102/LOM_Units -> 1033.5714
B103: OPERATING & MAINTENANCE
...

Sheet Rehab Scope
A1: REHAB SCOPE — $/UNIT BUILD-UP & TENANT RELOCATION
B2: No CNA or rehab budget exists (spec Gap #2) — every hard-cost input on this sheet is a $40,000/unit PLACEHOLDER allocation per user decision 8/6/26. Replace with CNA data.
B3: Hard Costs ($/unit) | C3: Clear Horizons | D3: New Zion | E3: Live Oak Manor | F3: Spanish Arms | G3: Portfolio
B4: Unit interiors | C4: 20000 | D4: 20000 | E4: 20000 | F4: 20000
B5: Roofs | C5: 6000 | D5: 6000 | E5: 6000 | F5: 6000
B6: HVAC | C6: 6000 | D6: 6000 | E6: 6000 | F6: 6000
B7: Plumbing | C7: 4000 | D7: 4000 | E7: 4000 | F7: 4000
B8: Site work | C8: 4000 | D8: 4000 | E8: 4000 | F8: 4000
B9: Base hard cost / unit | C9: =SUM(C4:C8) -> 40000 | D9: =SUM(D4:D8) -> 40000 | E9: =SUM(E4:E8) -> 40000 | F9: =SUM(F4:F8) -> 40000
B10: Check vs Dashboard RehabPerUnit | C10: =IF(C9=RehabPerUnit,"OK","MISMATCH") -> OK | D10: =IF(D9=RehabPerUnit,"OK","MISMATCH") -> OK | E10: =IF(E9=RehabPerUnit,"OK","MISMATCH") -> OK | F10: =IF(F9=RehabPerUnit,"OK","MISMATCH") -> OK
B11: Construction contingency | C11: =C9*ContingencyPct -> 4000 | D11: =D9*ContingencyPct -> 4000 | E11: =E9*ContingencyPct -> 4000 | F11: =F9*ContingencyPct -> 4000
B12: GC fees (gen req + overhead + profit) | C12: =C9*(GenReqPct+BuilderOHPct+BuilderProfitPct) -> 5600 | D12: =D9*(GenReqPct+BuilderOHPct+BuilderProfitPct) -> 5600 | E12: =E9*(GenReqPct+BuilderOHPct+BuilderProfitPct) -> 5600 | F12: =F9*(GenReqPct+BuilderOHPct+BuilderProfitPct) -> 5600
B13: Total rehab cost / unit (2026 $) | C13: =C9+C11+C12 -> 49600 | D13: =D9+D11+D12 -> 49600 | E13: =E9+E11+E12 -> 49600 | F13: =F9+F11+F12 -> 49600
B14: Total rehab cost (2026 $) | C14: =C13*CH_Units -> 4166400 | D14: =D13*NZ_Units -> 4960000 | E14: =E13*LOM_Units -> 5902400 | F14: =F13*SA_Units -> 10118400 | G14: =SUM(C14:F14) -> 25147200
B15: Hard cost / SF | C15: =C14/CH_NRSF -> 56.443048 | D15: =D14/NZ_NRSF -> 69.651182 | E15: =E14/LOM_NRSF -> 57.807725 | F15: =F14/SA_NRSF -> 52.718671
B17: MINIMUM-REHAB TESTS (feed Scorecard)
B18: Base hard cost/unit vs IRC Sec.42(e)(3)(A)(ii) min | C18: =IF(C9>=MinRehabIRC,"PASS","FAIL") -> PASS | D18: =IF(D9>=MinRehabIRC,"PASS","FAIL") -> PASS | E18: =IF(E9>=MinRehabIRC,"PASS","FAIL") -> PASS | F18: =IF(F9>=MinRehabIRC,"PASS","FAIL") -> PASS
B19: Base hard cost/unit vs LA QAP rehab minimum | C19: =IF(MinRehabQAP="","PENDING",IF(C9>=MinRehabQAP,"PASS","FAIL")) -> PENDING | D19: =IF(MinRehabQAP="","PENDING",IF(D9>=MinRehabQAP,"PASS","FAIL")) -> PENDING | E19: =IF(MinRehabQAP="","PENDING",IF(E9>=MinRehabQAP,"PASS","FAIL")) -> PENDING | F19: =IF(MinRehabQAP="","PENDING",IF(F9>=MinRehabQAP,"PASS","FAIL")) -> PENDING
B21: TENANT RELOCATION (properties are 91-98% occupied — spec Sec. 5.5)
B22: Relocation Inputs | C22: Clear Horizons | D22: New Zion | E22: Live Oak Manor | F22: Spanish Arms | G22: Portfolio
B23: Relocation method | C23: In-place phased | D23: In-place phased | E23: In-place phased | F23: In-place phased
B24: Units relocated per month | C24: =ROUNDUP(CH_Units/CH_RehabMonths,0) -> 7 | D24: =ROUNDUP(NZ_Units/NZ_RehabMonths,0) -> 9 | E24: =ROUNDUP(LOM_Units/LOM_RehabMonths,0) -> 8 | F24: =ROUNDUP(SA_Units/SA_RehabMonths,0) -> 12
B25: Downtime per unit (months) | C25: 0.5 | D25: 0.5 | E25: 0.5 | F25: 0.5
B26: Temporary housing / hotel ($/unit) | C26: 800 | D26: 800 | E26: 800 | F26: 800
B27: Moving costs — out ($/unit) | C27: 400 | D27: 400 | E27: 400 | F27: 400
B28: Moving costs — back ($/unit) | C28: 400 | D28: 400 | E28: 400 | F28: 400
B29: Meals / incidentals per-diem ($/unit) | C29: 300 | D29: 300 | E29: 300 | F29: 300
B30: Storage ($/unit) | C30: 200 | D30: 200 | E30: 200 | F30: 200
B31: Staff coordination ($/unit) | C31: 400 | D31: 400 | E31: 400 | F31: 400
B32: Relocation $/unit | C32: =SUM(C26:C31) -> 2500 | D32: =SUM(D26:D31) -> 2500 | E32: =SUM(E26:E31) -> 2500 | F32: =SUM(F26:F31) -> 2500
B33: Check vs Dashboard RelocPerUnit | C33: =IF(C32=RelocPerUnit,"OK","MISMATCH") -> OK | D33: =IF(D32=RelocPerUnit,"OK","MISMATCH") -> OK | E33: =IF(E32=RelocPerUnit,"OK","MISMATCH") -> OK | F33: =IF(F32=RelocPerUnit,"OK","MISMATCH") -> OK
B34: Total tenant relocation (2026 $) | C34: =C32*CH_Units -> 210000 | D34: =D32*NZ_Units -> 250000 | E34: =E32*LOM_Units -> 297500 | F34: =F32*SA_Units -> 510000 | G34: =SUM(C34:F34) -> 1267500
B35: URA applicability: PENDING — if HOME/CDBG or other federal funds enter the stack, Uniform Relocation Act notices/payments apply and costs rise materially. New Zion's existing stack includes a HOME loan (DD folder). Scorecard carries a PENDING flag.
B37: REHAB-PERIOD REVENUE DISRUPTION
B38: Avg units offline during rehab | C38: =C24*C25 -> 3.5 | D38: =D24*D25 -> 4.5 | E38: =E24*E25 -> 4 | F38: =F24*F25 -> 6
B39: Offline vacancy adj (% of GPR, rehab months) | C39: =C38/CH_Units -> 0.041666667 | D39: =D38/NZ_Units -> 0.045 | E39: =E38/LOM_Units -> 0.033613445 | F39: =F38/SA_Units -> 0.029411765
B41: REHAB BURN CURVE — % of rehab cost drawn per month from resyndication close (M1-M18; occupied-rehab curve, spec Sec. 5.12)
B42: Month | C42: Clear Horizons | D42: New Zion | E42: Live Oak Manor | F42: Spanish Arms
B43: 1 | C43: 0.017 | D43: 0.017 | E43: 0.0109 | F43: 0.0076
B44: 2 | C44: 0.05 | D44: 0.05 | E44: 0.0323 | F44: 0.0226
B45: 3 | C45: 0.0795 | D45: 0.0795 | E45: 0.0523 | F45: 0.0368
B46: 4 | C46: 0.1036 | D46: 0.1036 | E46: 0.0699 | F46: 0.05
B47: 5 | C47: 0.1206 | D47: 0.1206 | E47: 0.0846 | F47: 0.0616
B48: 6 | C48: 0.1294 | D48: 0.1294 | E48: 0.0955 | F48: 0.0714
B49: 7 | C49: 0.1294 | D49: 0.1294 | E49: 0.1022 | F49: 0.079
B50: 8 | C50: 0.1206 | D50: 0.1206 | E50: 0.1045 | F50: 0.0842
B51: 9 | C51: 0.1036 | D51: 0.1036 | E51: 0.1022 | F51: 0.0868
B52: 10 | C52: 0.0795 | D52: 0.0795 | E52: 0.0955 | F52: 0.0868
B53: 11 | C53: 0.05 | D53: 0.05 | E53: 0.0846 | F53: 0.0842
B54: 12 | C54: 0.0168 | D54: 0.0168 | E54: 0.0699 | F54: 0.079
... B60: 18 | C60: 0 | D60: 0 | E60: 0 | F60: 0.0076
B61: Total (must = 100%) | C61: =SUM(C43:C60) -> 1 | D61: =SUM(D43:D60) -> 1 | E61: =SUM(E43:E60) -> 1 | F61: =SUM(F43:F60) -> 1
B62: Check | C62: =IF(ABS(C61-1)<0.0001,"OK","MUST = 100%") -> OK | D62: =IF(ABS(D61-1)<0.0001,"OK","MUST = 100%") -> OK | E62: =IF(ABS(E61-1)<0.0001,"OK","MUST = 100%") -> OK | F62: =IF(ABS(F61-1)<0.0001,"OK","MUST = 100%") -> OK

Sheet Sources & Uses
A1: SOURCES AND USES — RESYNDICATION CLOSINGS (each column in its vintage-year dollars)
C3: Clear Horizons | D3: New Zion | E3: Live Oak Manor | F3: Spanish Arms | G3: Portfolio
B4: Resyndication close | C4: =CH_ResynDate -> 46753 | D4: =NZ_ResynDate -> 47119 | E4: =LOM_ResynDate -> 47119 | F4: =SA_ResynDate -> 46357 | G4: mixed vintages
B5: Dollars stated in each column are that close-year's dollars — rehab and fee lines cost-inflated at CostInflation (Dashboard). The Portfolio column sums MIXED-VINTAGE dollars (2026 + 2028 + 2029) — treat as indicative only (spec Sec. 2).
B7: SOURCES
B8: Perm / tax-exempt bond proceeds | C8: =CH_SelProceeds -> 3410352.4 | D8: =NZ_SelProceeds -> 6485211.1 | E8: =LOM_SelProceeds -> 7791658.8 | F8: =SA_SelProceeds -> 9219810.9 | G8: =SUM(C8:F8) -> 26907033
B9: 4% LIHTC equity | C9: =CH_Equity -> 2241868.1 | D9: =NZ_Equity -> 2775646.2 | E9: =LOM_Equity -> 4110859 | F9: =SA_Equity -> 5117769.8 | G9: =SUM(C9:F9) -> 14246143
B10: Deferred developer fee | C10: =MIN(C24,MAX(0,C26-(C8+C9+C11+C12))) -> 816531.21 | D10: =MIN(D24,MAX(0,D26-(D8+D9+D11+D12))) -> 1010943.4 | E10: =MIN(E24,MAX(0,E26-(E8+E9+E11+E12))) -> 1571626.8 | F10: =MIN(F24,MAX(0,F26-(F8+F9+F11+F12))) -> 1799327.9 | G10: =SUM(C10:F10) -> 5198429.2
B11: Bridge-period cash contributed | C11: =MAX(0,CH_BridgeCF) -> 0 | D11: =MAX(0,NZ_BridgeCF) -> 186952.92 | E11: =MAX(0,LOM_BridgeCF) -> 152373.65 | F11: =MAX(0,SA_BridgeCF) -> 0 | G11: =SUM(C11:F11) -> 339326.56
B12: Soft funds REQUIRED (unfunded gap plug) | C12: =MAX(0,C26-(C8+C9+C11+C24)) -> 461898.42 | D12: =MAX(0,D26-(D8+D9+D11+D24)) -> 148039.11 | E12: =MAX(0,E26-(E8+E9+E11+E24)) -> 0 | F12: =MAX(0,F26-(F8+F9+F11+F24)) -> 0 | G12: =SUM(C12:F12) -> 609937.53
B13: TOTAL SOURCES | C13: =SUM(C8:C12) -> 6930650.1 | D13: =SUM(D8:D12) -> 10606793 | E13: =SUM(E8:E12) -> 13626518 | F13: =SUM(F8:F12) -> 16136909 | G13: =SUM(C13:F13) -> 47300870
B15: USES
B16: Acquisition price | C16: =CH_AcqPrice -> 0 | D16: =NZ_AcqPrice -> 0 | E16: =LOM_AcqPrice -> 3000000 | F16: =SA_AcqPrice -> 500000 | G16: =SUM(C16:F16) -> 3500000
B17: NZ HOME loan payoff (principal + accrued) | C17: 0 | D17: =NZ_HOMEPayoff -> 2027484.6 | E17: 0 | F17: 0 | G17: =SUM(C17:F17) -> 2027484.6
B18: Rehab (hard + relocation + soft, vintage $) | C18: =CH_RehabBasis -> 5443541.4 | D18: =NZ_RehabBasis -> 6739622.7 | E18: =LOM_RehabBasis -> 8020151 | F18: =SA_RehabBasis -> 12222660 | G18: =SUM(C18:F18) -> 32425975
B19: Financing fees (perm origination/placement/legal) | C19: =CH_FinFees -> 51155.286 | D19: =NZ_FinFees -> 97278.167 | E19: =LOM_FinFees -> 116874.88 | F19: =SA_FinFees -> 138297.16 | G19: =SUM(C19:F19) -> 403605.5
B20: Bond cost of issuance | C20: 0.02 | D20: 0.02 | E20: 0.02 | F20: 0.02
B21: Bond COI $ | C21: =C20*C8 -> 68207.048 | D21: =D20*D8 -> 129704.22 | E21: =E20*E8 -> 155833.18 | F21: =F20*F8 -> 184396.22 | G21: =SUM(C21:F21) -> 538140.66
B22: Construction-period interest (net) | C22: =CH_ConstrInt -> 116366.47 | D22: =NZ_ConstrInt -> 149953.45 | E22: =LOM_ConstrInt -> 220165.97 | F22: =SA_ConstrInt -> 459098.41 | G22: =SUM(C22:F22) -> 945584.31
B23: Operating reserve | C23: =OpReserveFrac*CH_OpexStab -> 434848.69 | D23: =OpReserveFrac*NZ_OpexStab -> 451806.23 | E23: =OpReserveFrac*LOM_OpexStab -> 527970.6 | F23: =OpReserveFrac*SA_OpexStab -> 735307.74 | G23: =SUM(C23:F23) -> 2149933.3
B24: Developer fee | C24: =C25*(CH_AcqBasis+CH_RehabBasis) -> 816531.21 | D24: =D25*(NZ_AcqBasis+NZ_RehabBasis) -> 1010943.4 | E24: =E25*(LOM_AcqBasis+LOM_RehabBasis) -> 1585522.6 | F24: =F25*(SA_AcqBasis+SA_RehabBasis) -> 1897149 | G24: =SUM(C24:F24) -> 5310146.2
B25: Developer fee % | C25: 0.15 | D25: 0.15 | E25: 0.15 | F25: 0.15
B26: TOTAL USES | C26: =SUM(C16:C18)+C19+SUM(C21:C24) -> 6930650.1 | D26: =SUM(D16:D18)+D19+SUM(D21:D24) -> 10606793 | E26: =SUM(E16:E18)+E19+SUM(E21:E24) -> 13626518 | F26: =SUM(F16:F18)+F19+SUM(F21:F24) -> 16136909 | G26: =SUM(C26:F26) -> 47300870
B28: BALANCE & MEMO
B29: Sources - Uses (surplus / (shortfall)) | C29: =C13-C26 -> 0 | D29: =D13-D26 -> 0 | E29: =E13-E26 -> 0 | F29: =F13-F26 -> 0 | G29: =SUM(C29:F29) -> 0
B30: Balanced? | C30: =IF(ABS(C29)<=SUBalanceTol,"OK",IF(C29<0,"SHORTFALL","SURPLUS")) -> OK | D30: =IF(ABS(D29)<=SUBalanceTol,"OK",IF(D29<0,"SHORTFALL","SURPLUS")) -> OK | E30: =IF(ABS(E29)<=SUBalanceTol,"OK",IF(E29<0,"SHORTFALL","SURPLUS")) -> OK | F30: =IF(ABS(F29)<=SUBalanceTol,"OK",IF(F29<0,"SHORTFALL","SURPLUS")) -> OK
B31: Deferred fee % of developer fee | C31: =IF(C24=0,0,C10/C24) -> 1 | D31: =IF(D24=0,0,D10/D24) -> 1 | E31: =IF(E24=0,0,E10/E24) -> 0.99123578 | F31: =IF(F24=0,0,F10/F24) -> 0.94843781
B32: TDC / unit (vintage $) | C32: =C26/CH_Units -> 82507.739 | D32: =D26/NZ_Units -> 106067.93 | E32: =E26/LOM_Units -> 114508.56 | F32: =F26/SA_Units -> 79102.493
B33: TDC limit / unit (HUD/LHC) | C33: =CH_TDCLimitPU -> 296008.48 | D33: =NZ_TDCLimitPU -> 271516.84 | E33: =LOM_TDCLimitPU -> 367877.08 | F33: =SA_TDCLimitPU -> 269505.86

Sheet S&U Timing
A1: S&U TIMING — MONTHLY DRAWS FROM EACH RESYNDICATION CLOSE (M1-M18)
B2: Sizing engine (spec Sec. 5.12): equity tranches placed by pay-in month (Tax Credit Calc), uses drawn per the Rehab Scope burn curve, perm/bond draws plug the need, construction interest capitalizes on the drawn balance, and max outstanding feeds Financing. Deferred fee is excluded from cash uses.
B4: CLEAR HORIZONS — close: | D4: =CH_ResynDate -> 46753
B5: Month | C5: 1 | D5: 2 | E5: 3 | F5: 4 | G5: 5 | H5: 6 | I5: 7 | J5: 8 | K5: 9 | L5: 10 | M5: 11 | N5: 12 | O5: 13 | P5: 14 | Q5: 15 | R5: 16 | S5: 17 | T5: 18 | U5: TOTAL
B6: Calendar month | C6: =EDATE(CH_ResynDate,0) -> 46753 | D6: =EDATE(CH_ResynDate,1) -> 46784 | E6: =EDATE(CH_ResynDate,2) -> 46813 | F6: =EDATE(CH_ResynDate,3) -> 46844 | G6: =EDATE(CH_ResynDate,4) -> 46874 | H6: =EDATE(CH_ResynDate,5) -> 46905 | I6: =EDATE(CH_ResynDate,6) -> 46935 | J6: =EDATE(CH_ResynDate,7) -> 46966 | K6: =EDATE(CH_ResynDate,8) -> 46997 | L6: =EDATE(CH_ResynDate,9) -> 47027 | M6: =EDATE(CH_ResynDate,10) -> 47058 | N6: =EDATE(CH_ResynDate,11) -> 47088 | O6: =EDATE(CH_ResynDate,12) -> 47119 | P6: =EDATE(CH_ResynDate,13) -> 47150 | Q6: =EDATE(CH_ResynDate,14) -> 47178 | R6: =EDATE(CH_ResynDate,15) -> 47209 | S6: =EDATE(CH_ResynDate,16) -> 47239 | T6: =EDATE(CH_ResynDate,17) -> 47270
B7: Acquisition price (M1) | C7: =IF(C5=1,CH_AcqPrice,0) -> 0 | D7: =IF(D5=1,CH_AcqPrice,0) -> 0 | E7: =IF(E5=1,CH_AcqPrice,0) -> 0 | F7: =IF(F5=1,CH_AcqPrice,0) -> 0 | G7: =IF(G5=1,CH_AcqPrice,0) -> 0 | H7: =IF(H5=1,CH_AcqPrice,0) -> 0 | I7: =IF(I5=1,CH_AcqPrice,0) -> 0 | J7: =IF(J5=1,CH_AcqPrice,0) -> 0 | ... T7: =IF(T5=1,CH_AcqPrice,0) -> 0 | U7: =SUM(C7:T7) -> 0
B8: Other close payments (M1) | C8: 0 | D8: 0 | E8: 0 | F8: 0 | G8: 0 | H8: 0 | I8: 0 | J8: 0 | K8: 0 | L8: 0 | M8: 0 | N8: 0 | O8: 0 | P8: 0 | Q8: 0 | R8: 0 | S8: 0 | T8: 0 | U8: =SUM(C8:T8) -> 0
B9: Rehab draw (burn curve) | C9: =CH_RehabBasis*INDEX(CH_BurnCurve,1) -> 92540.203 | D9: =CH_RehabBasis*INDEX(CH_BurnCurve,2) -> 272177.07 | E9: =CH_RehabBasis*INDEX(CH_BurnCurve,3) -> 432761.54 | F9: =CH_RehabBasis*INDEX(CH_BurnCurve,4) -> 563950.89 | G9: =CH_RehabBasis*INDEX(CH_BurnCurve,5) -> 656491.09 | H9: =CH_RehabBasis*INDEX(CH_BurnCurve,6) -> 704394.25 | I9: =CH_RehabBasis*INDEX(CH_BurnCurve,7) -> 704394.25 | J9: =CH_RehabBasis*INDEX(CH_BurnCurve,8) -> 656491.09 | K9: =CH_RehabBasis*INDEX(CH_BurnCurve,9) -> 563950.89 | L9: =CH_RehabBasis*INDEX(CH_BurnCurve,10) -> 432761.54 | M9: =CH_RehabBasis*INDEX(CH_BurnCurve,11) -> 272177.07 | N9: =CH_RehabBasis*INDEX(CH_BurnCurve,12) -> 91451.495 | O9: =CH_RehabBasis*INDEX(CH_BurnCurve,13) -> 0 | P9: =CH_RehabBasis*INDEX(CH_BurnCurve,14) -> 0 | Q9: =CH_RehabBasis*INDEX(CH_BurnCurve,15) -> 0 | R9: =CH_RehabBasis*INDEX(CH_BurnCurve,16) -> 0 | S9: =CH_RehabBasis*INDEX(CH_BurnCurve,17) -> 0 | T9: =CH_RehabBasis*INDEX(CH_BurnCurve,18) -> 0 | U9: =SUM(C9:T9) -> 5443541.4
B10: Fees + COI + reserves (M1) | C10: =IF(C5=1,CH_FinFees+'Sources & Uses'!C21+'Sources & Uses'!C23,0) -> 554211.03 | D10: =IF(D5=1,CH_FinFees+'Sources & Uses'!C21+'Sources & Uses'!C23,0) -> 0 | E10: =IF(E5=1,CH_FinFees+'Sources & Uses'!C21+'Sources & Uses'!C23,0) -> 0 | F10: =IF(F5=1,CH_FinFees+'Sources & Uses'!C21+'Sources & Uses'!C23,0) -> 0 | G10: =IF(G5=1,CH_FinFees+'Sources & Uses'!C21+'Sources & Uses'!C23,0) -> 0 | H10: =IF(H5=1,CH_FinFees+'Sources & Uses'!C21+'Sources & Uses'!C23,0) -> 0 | I10: =IF(I5=1,CH_FinFees+'Sources & Uses'!C21+'Sources & Uses'!C23,0) -> 0 | J10: =IF(J5=1,CH_FinFees+'Sources & Uses'!C21+'Sources & Uses'!C23,0) -> 0 | K10: =IF(K5=1,CH_FinFees+'Sources & Uses'!C21+'Sources & Uses'!C23,0) -> 0 | L10: =IF(L5=1,CH_FinFees+'Sources & Uses'!C21+'Sources & Uses'!C23,0) -> 0 | M10: =IF(M5=1,CH_FinFees+'Sources & Uses'!C21+'Sources & Uses'!C23,0) -> 0 | N10: =IF(N5=1,CH_FinFees+'Sources & Uses'!C21+'Sources & Uses'!C23,0) -> 0 | O10: =IF(O5=1,CH_FinFees+'Sources & Uses'!C21+'Sources & Uses'!C23,0) -> 0 | P10: =IF(P5=1,CH_FinFees+'Sources & Uses'!C21+'Sources & Uses'!C23,0) -> 0 | Q10: =IF(Q5=1,CH_FinFees+'Sources & Uses'!C21+'Sources & Uses'!C23,0) -> 0 | R10: =IF(R5=1,CH_FinFees+'Sources & Uses'!C21+'Sources & Uses'!C23,0) -> 0 | S10: =IF(S5=1,CH_FinFees+'Sources & Uses'!C21+'Sources & Uses'!C23,0) -> 0 | T10: =IF(T5=1,CH_FinFees+'Sources & Uses'!C21+'Sources & Uses'!C23,0) -> 0 | U10: =SUM(C10:T10) -> 554211.03
B11: Cash developer fee (at stabilization) | C11: =IF(C5=CH_RehabMonths+6,CH_DevFee-CH_DDF,0) -> 0 | D11: =IF(D5=CH_RehabMonths+6,CH_DevFee-CH_DDF,0) -> 0 | E11: =IF(E5=CH_RehabMonths+6,CH_DevFee-CH_DDF,0) -> 0 | F11: =IF(F5=CH_RehabMonths+6,CH_DevFee-CH_DDF,0) -> 0 | G11: =IF(G5=CH_RehabMonths+6,CH_DevFee-CH_DDF,0) -> 0 | H11: =IF(H5=CH_RehabMonths+6,CH_DevFee-CH_DDF,0) -> 0 | I11: =IF(I5=CH_RehabMonths+6,CH_DevFee-CH_DDF,0) -> 0 | J11: =IF(J5=CH_RehabMonths+6,CH_DevFee-CH_DDF,0) -> 0 | ... T11: =IF(T5=CH_RehabMonths+6,CH_DevFee-CH_DDF,0) -> 0 | U11: =SUM(C11:T11) -> 0
B12: TOTAL USES (cash) | C12: =SUM(C7:C11) -> 646751.23 | D12: =SUM(D7:D11) -> 272177.07 | E12: =SUM(E7:E11) -> 432761.54 | F12: =SUM(F7:F11) -> 563950.89 | G12: =SUM(G7:G11) -> 656491.09 | H12: =SUM(H7:H11) -> 704394.25 | I12: =SUM(I7:I11) -> 704394.25 | J12: =SUM(J7:J11) -> 656491.09 | ... T12: =SUM(T7:T11) -> 0 | U12: =SUM(C12:T12) -> 5997752.4
B13: Equity tranches (from pay-in blocks) | C13: =SUMPRODUCT((CH_PayinMonths=C5)*CH_PayinAmts) -> 448373.62 | D13: =SUMPRODUCT((CH_PayinMonths=D5)*CH_PayinAmts) -> 0 | E13: =SUMPRODUCT((CH_PayinMonths=E5)*CH_PayinAmts) -> 0 | F13: =SUMPRODUCT((CH_PayinMonths=F5)*CH_PayinAmts) -> 0 | G13: =SUMPRODUCT((CH_PayinMonths=G5)*CH_PayinAmts) -> 0 | H13: =SUMPRODUCT((CH_PayinMonths=H5)*CH_PayinAmts) -> 0 | I13: =SUMPRODUCT((CH_PayinMonths=I5)*CH_PayinAmts) -> 0 | J13: =SUMPRODUCT((CH_PayinMonths=J5)*CH_PayinAmts) -> 0 | ... T13: =SUMPRODUCT((CH_PayinMonths=T5)*CH_PayinAmts) -> 672560.42 | U13: =SUM(C13:T13) -> 2241868.1
B14: Perm/bond draw (plug to need) | C14: =MAX(0,MIN(CH_SelProceeds-(0),(SUM($C12:C12)+SUM($C15:C15))-(SUM($C13:C13))-(0))) -> 198377.61 | D14: =MAX(0,MIN(CH_SelProceeds-(SUM($C14:C14)),(SUM($C12:D12)+SUM($C15:D15))-(SUM($C13:D13))-(SUM($C14:C14)))) -> 272177.07 | E14: =MAX(0,MIN(CH_SelProceeds-(SUM($C14:D14)),(SUM($C12:E12)+SUM($C15:E15))-(SUM($C13:E13))-(SUM($C14:D14)))) -> 434122.42 | F14: =MAX(0,MIN(CH_SelProceeds-(SUM($C14:E14)),(SUM($C12:F12)+SUM($C15:F15))-(SUM($C13:F13))-(SUM($C14:E14)))) -> 567489.19 | G14: =MAX(0,MIN(CH_SelProceeds-(SUM($C14:F14)),(SUM($C12:G12)+SUM($C15:G15))-(SUM($C13:G13))-(SUM($C14:F14)))) -> 662884.53 | H14: =MAX(0,MIN(CH_SelProceeds-(SUM($C14:G14)),(SUM($C12:H12)+SUM($C15:H15))-(SUM($C13:H13))-(SUM($C14:G14)))) -> 714134.08 | I14: =MAX(0,MIN(CH_SelProceeds-(SUM($C14:H14)),(SUM($C12:I12)+SUM($C15:I15))-(SUM($C13:I13))-(SUM($C14:H14)))) -> 561167.47 | J14: =MAX(0,MIN(CH_SelProceeds-(SUM($C14:I14)),(SUM($C12:J12)+SUM($C15:J15))-(SUM($C13:J13))-(SUM($C14:I14)))) -> 0 | K14: =MAX(0,MIN(CH_SelProceeds-(SUM($C14:J14)),(SUM($C12:K12)+SUM($C15:K15))-(SUM($C13:K13))-(SUM($C14:J14)))) -> 0 | ... T14: =MAX(0,MIN(CH_SelProceeds-(SUM($C14:S14)),(SUM($C12:T12)+SUM($C15:T15))-(SUM($C13:T13))-(SUM($C14:S14)))) -> 0 | U14: =SUM(C14:T14) -> 3410352.4
B15: Construction interest (capitalized) | C15: 0 | D15: =IF(D5<=CH_RehabMonths,MAX(0,C16-$C$16)*PermRate/12,0) -> 0 | E15: =IF(E5<=CH_RehabMonths,MAX(0,D16-$C$16)*PermRate/12,0) -> 1360.8853 | F15: =IF(F5<=CH_RehabMonths,MAX(0,E16-$C$16)*PermRate/12,0) -> 3538.3019 | G15: =IF(G5<=CH_RehabMonths,MAX(0,F16-$C$16)*PermRate/12,0) -> 6393.4393 | H15: =IF(H5<=CH_RehabMonths,MAX(0,G16-$C$16)*PermRate/12,0) -> 9739.8292 | I15: =IF(I5<=CH_RehabMonths,MAX(0,H16-$C$16)*PermRate/12,0) -> 13359.199 | J15: =IF(J5<=CH_RehabMonths,MAX(0,I16-$C$16)*PermRate/12,0) -> 16231.832 | K15: =IF(K5<=CH_RehabMonths,MAX(0,J16-$C$16)*PermRate/12,0) -> 16312.991 | ... T15: =IF(T5<=CH_RehabMonths,MAX(0,S16-$C$16)*PermRate/12,0) -> 0 | U15: =SUM(C15:T15) -> 116366.47
B16: Perm/bond outstanding balance | C16: =0+C14+C15 -> 198377.61 | D16: =C16+D14+D15 -> 470554.68 | E16: =D16+E14+E15 -> 906037.99 | F16: =E16+F14+F15 -> 1477065.5 | G16: =F16+G14+G15 -> 2146343.5 | H16: =G16+H14+H15 -> 2870217.4 | I16: =H16+I14+I15 -> 3444744 | J16: =I16+J14+J15 -> 3460975.9 | K16: =J16+K14+K15 -> 3477288.9 | ... T16: =S16+T14+T15 -> 3526718.8
B17: Cumulative funded (equity + perm) | C17: =SUM($C13:C13)+SUM($C14:C14) -> 646751.23 | D17: =SUM($C13:D13)+SUM($C14:D14) -> 918928.3 | E17: =SUM($C13:E13)+SUM($C14:E14) -> 1353050.7 | F17: =SUM($C13:F13)+SUM($C14:F14) -> 1920539.9 | G17: =SUM($C13:G13)+SUM($C14:G14) -> 2583424.4 | H17: =SUM($C13:H13)+SUM($C14:H14) -> 3297558.5 | I17: =SUM($C13:I13)+SUM($C14:I14) -> 3858726 | J17: =SUM($C13:J13)+SUM($C14:J14) -> 3858726 | ... T17: =SUM($C13:T13)+SUM($C14:T14) -> 5652220.5
B18: Max outstanding perm/bond balance | U18: =MAX(C16:T16) -> 3526718.8
B21: NEW ZION — close: | D21: =NZ_ResynDate -> 47119
B22: Month | C22: 1 | D22: 2 | E22: 3 | F22: 4 | G22: 5 | H22: 6 | I22: 7 | J22: 8 | K22: 9 | L22: 10 | M22: 11 | N22: 12 | O22: 13 | P22: 14 | Q22: 15 | R22: 16 | S22: 17 | T22: 18 | U22: TOTAL
B23: Calendar month | C23: =EDATE(NZ_ResynDate,0) -> 47119 | D23: =EDATE(NZ_ResynDate,1) -> 47150 | E23: =EDATE(NZ_ResynDate,2) -> 47178 | F23: =EDATE(NZ_ResynDate,3) -> 47209 | G23: =EDATE(NZ_ResynDate,4) -> 47239 | H23: =EDATE(NZ_ResynDate,5) -> 47270 | I23: =EDATE(NZ_ResynDate,6) -> 47300 | J23: =EDATE(NZ_ResynDate,7) -> 47331 | K23: =EDATE(NZ_ResynDate,8) -> 47362 | L23: =EDATE(NZ_ResynDate,9) -> 47392 | M23: =EDATE(NZ_ResynDate,10) -> 47423 | N23: =EDATE(NZ_ResynDate,11) -> 47453 | O23: =EDATE(NZ_ResynDate,12) -> 47484 | P23: =EDATE(NZ_ResynDate,13) -> 47515 | Q23: =EDATE(NZ_ResynDate,14) -> 47543 | R23: =EDATE(NZ_ResynDate,15) -> 47574 | S23: =EDATE(NZ_ResynDate,16) -> 47604 | T23: =EDATE(NZ_ResynDate,17) -> 47635
B24: Acquisition price (M1) | C24: =IF(C22=1,NZ_AcqPrice,0) -> 0 | D24: =IF(D22=1,NZ_AcqPrice,0) -> 0 | E24: =IF(E22=1,NZ_AcqPrice,0) -> 0 | F24: =IF(F22=1,NZ_AcqPrice,0) -> 0 | G24: =IF(G22=1,NZ_AcqPrice,0) -> 0 | H24: =IF(H22=1,NZ_AcqPrice,0) -> 0 | I24: =IF(I22=1,NZ_AcqPrice,0) -> 0 | J24: =IF(J22=1,NZ_AcqPrice,0) -> 0 | ... T24: =IF(T22=1,NZ_AcqPrice,0) -> 0 | U24: =SUM(C24:T24) -> 0
B25: NZ HOME payoff (M1) | C25: =IF(C22=1,NZ_HOMEPayoff,0) -> 2027484.6 | D25: =IF(D22=1,NZ_HOMEPayoff,0) -> 0 | E25: =IF(E22=1,NZ_HOMEPayoff,0) -> 0 | F25: =IF(F22=1,NZ_HOMEPayoff,0) -> 0 | G25: =IF(G22=1,NZ_HOMEPayoff,0) -> 0 | H25: =IF(H22=1,NZ_HOMEPayoff,0) -> 0 | I25: =IF(I22=1,NZ_HOMEPayoff,0) -> 0 | J25: =IF(J22=1,NZ_HOMEPayoff,0) -> 0 | ... T25: =IF(T22=1,NZ_HOMEPayoff,0) -> 0 | U25: =SUM(C25:T25) -> 2027484.6
B26: Rehab draw (burn curve) | C26: =NZ_RehabBasis*INDEX(NZ_BurnCurve,1) -> 114573.59 | D26: =NZ_RehabBasis*INDEX(NZ_BurnCurve,2) -> 336981.13 | E26: =NZ_RehabBasis*INDEX(NZ_BurnCurve,3) -> 535800 | F26: =NZ_RehabBasis*INDEX(NZ_BurnCurve,4) -> 698224.91 | G26: =NZ_RehabBasis*INDEX(NZ_BurnCurve,5) -> 812798.49 | H26: =NZ_RehabBasis*INDEX(NZ_BurnCurve,6) -> 872107.17 | I26: =NZ_RehabBasis*INDEX(NZ_BurnCurve,7) -> 872107.17 | J26: =NZ_RehabBasis*INDEX(NZ_BurnCurve,8) -> 812798.49 | K26: =NZ_RehabBasis*INDEX(NZ_BurnCurve,9) -> 698224.91 | L26: =NZ_RehabBasis*INDEX(NZ_BurnCurve,10) -> 535800 | M26: =NZ_RehabBasis*INDEX(NZ_BurnCurve,11) -> 336981.13 | N26: =NZ_RehabBasis*INDEX(NZ_BurnCurve,12) -> 113225.66 | O26: =NZ_RehabBasis*INDEX(NZ_BurnCurve,13) -> 0 | P26: =NZ_RehabBasis*INDEX(NZ_BurnCurve,14) -> 0 | Q26: =NZ_RehabBasis*INDEX(NZ_BurnCurve,15) -> 0 | R26: =NZ_RehabBasis*INDEX(NZ_BurnCurve,16) -> 0 | S26: =NZ_RehabBasis*INDEX(NZ_BurnCurve,17) -> 0 | T26: =NZ_RehabBasis*INDEX(NZ_BurnCurve,18) -> 0 | U26: =SUM(C26:T26) -> 6739622.7
B27: Fees + COI + reserves (M1) | C27: =IF(C22=1,NZ_FinFees+'Sources & Uses'!D21+'Sources & Uses'!D23,0) -> 678788.61 | D27: =IF(D22=1,NZ_FinFees+'Sources & Uses'!D21+'Sources & Uses'!D23,0) -> 0 | E27: =IF(E22=1,NZ_FinFees+'Sources & Uses'!D21+'Sources & Uses'!D23,0) -> 0 | F27: =IF(F22=1,NZ_FinFees+'Sources & Uses'!D21+'Sources & Uses'!D23,0) -> 0 | G27: =IF(G22=1,NZ_FinFees+'Sources & Uses'!D21+'Sources & Uses'!D23,0) -> 0 | H27: =IF(H22=1,NZ_FinFees+'Sources & Uses'!D21+'Sources & Uses'!D23,0) -> 0 | I27: =IF(I22=1,NZ_FinFees+'Sources & Uses'!D21+'Sources & Uses'!D23,0) -> 0 | J27: =IF(J22=1,NZ_FinFees+'Sources & Uses'!D21+'Sources & Uses'!D23,0) -> 0 | K27: =IF(K22=1,NZ_FinFees+'Sources & Uses'!D21+'Sources & Uses'!D23,0) -> 0 | L27: =IF(L22=1,NZ_FinFees+'Sources & Uses'!D21+'Sources & Uses'!D23,0) -> 0 | M27: =IF(M22=1,NZ_FinFees+'Sources & Uses'!D21+'Sources & Uses'!D23,0) -> 0 | N27: =IF(N22=1,NZ_FinFees+'Sources & Uses'!D21+'Sources & Uses'!D23,0) -> 0 | O27: =IF(O22=1,NZ_FinFees+'Sources & Uses'!D21+'Sources & Uses'!D23,0) -> 0 | P27: =IF(P22=1,NZ_FinFees+'Sources & Uses'!D21+'Sources & Uses'!D23,0) -> 0 | Q27: =IF(Q22=1,NZ_FinFees+'Sources & Uses'!D21+'Sources & Uses'!D23,0) -> 0 | R27: =IF(R22=1,NZ_FinFees+'Sources & Uses'!D21+'Sources & Uses'!D23,0) -> 0 | S27: =IF(S22=1,NZ_FinFees+'Sources & Uses'!D21+'Sources & Uses'!D23,0) -> 0 | T27: =IF(T22=1,NZ_FinFees+'Sources & Uses'!D21+'Sources & Uses'!D23,0) -> 0 | U27: =SUM(C27:T27) -> 678788.61
B28: Cash developer fee (at stabilization) | C28: =IF(C22=NZ_RehabMonths+6,NZ_DevFee-NZ_DDF,0) -> 0 | D28: =IF(D22=NZ_RehabMonths+6,NZ_DevFee-NZ_DDF,0) -> 0 | E28: =IF(E22=NZ_RehabMonths+6,NZ_DevFee-NZ_DDF,0) -> 0 | F28: =IF(F22=NZ_RehabMonths+6,NZ_DevFee-NZ_DDF,0) -> 0 | G28: =IF(G22=NZ_RehabMonths+6,NZ_DevFee-NZ_DDF,0) -> 0 | H28: =IF(H22=NZ_RehabMonths+6,NZ_DevFee-NZ_DDF,0) -> 0 | I28: =IF(I22=NZ_RehabMonths+6,NZ_DevFee-NZ_DDF,0) -> 0 | J28: =IF(J22=NZ_RehabMonths+6,NZ_DevFee-NZ_DDF,0) -> 0 | ... T28: =IF(T22=NZ_RehabMonths+6,NZ_DevFee-NZ_DDF,0) -> 0 | U28: =SUM(C28:T28) -> 0
B29: TOTAL USES (cash) | C29: =SUM(C24:C28) -> 2820846.8 | D29: =SUM(D24:D28) -> 336981.13 | E29: =SUM(E24:E28) -> 535800 | F29: =SUM(F24:F28) -> 698224.91 | G29: =SUM(G24:G28) -> 812798.49 | H29: =SUM(H24:H28) -> 872107.17 | I29: =SUM(I24:I28) -> 872107.17 | J29: =SUM(J24:J28) -> 812798.49 | ... T29: =SUM(T24:T28) -> 0 | U29: =SUM(C29:T29) -> 9445895.9
B30: Equity tranches (from pay-in blocks) | C30: =SUMPRODUCT((NZ_PayinMonths=C22)*NZ_PayinAmts) -> 555129.24 | D30: =SUMPRODUCT((NZ_PayinMonths=D22)*NZ_PayinAmts) -> 0 | E30: =SUMPRODUCT((NZ_PayinMonths=E22)*NZ_PayinAmts) -> 0 | F30: =SUMPRODUCT((NZ_PayinMonths=F22)*NZ_PayinAmts) -> 0 | G30: =SUMPRODUCT((NZ_PayinMonths=G22)*NZ_PayinAmts) -> 0 | H30: =SUMPRODUCT((NZ_PayinMonths=H22)*NZ_PayinAmts) -> 0 | I30: =SUMPRODUCT((NZ_PayinMonths=I22)*NZ_PayinAmts) -> 0 | J30: =SUMPRODUCT((NZ_PayinMonths=J22)*NZ_PayinAmts) -> 0 | ... T30: =SUMPRODUCT((NZ_PayinMonths=T22)*NZ_PayinAmts) -> 832693.86 | U30: =SUM(C30:T30) -> 2775646.2
B31: Perm/bond draw (plug to need) | C31: =MAX(0,MIN(NZ_SelProceeds-(0),(SUM($C29:C29)+SUM($C32:C32))-(SUM($C30:C30))-(0))) -> 2265717.6 | D31: =MAX(0,MIN(NZ_SelProceeds-(SUM($C31:C31)),(SUM($C29:D29)+SUM($C32:D32))-(SUM($C30:D30))-(SUM($C31:C31)))) -> 336981.13 | E31: =MAX(0,MIN(NZ_SelProceeds-(SUM($C31:D31)),(SUM($C29:E29)+SUM($C32:E32))-(SUM($C30:E30))-(SUM($C31:D31)))) -> 537484.91 | F31: =MAX(0,MIN(NZ_SelProceeds-(SUM($C31:E31)),(SUM($C29:F29)+SUM($C32:F32))-(SUM($C30:F30))-(SUM($C31:E31)))) -> 702605.66 | G31: =MAX(0,MIN(NZ_SelProceeds-(SUM($C31:F31)),(SUM($C29:G29)+SUM($C32:G32))-(SUM($C30:G30))-(SUM($C31:F31)))) -> 820714.18 | H31: =MAX(0,MIN(NZ_SelProceeds-(SUM($C31:G31)),(SUM($C29:H29)+SUM($C32:H32))-(SUM($C30:H30))-(SUM($C31:G31)))) -> 884166.01 | I31: =MAX(0,MIN(NZ_SelProceeds-(SUM($C31:H31)),(SUM($C29:I29)+SUM($C32:I32))-(SUM($C30:I30))-(SUM($C31:H31)))) -> 888647.13 | J31: =MAX(0,MIN(NZ_SelProceeds-(SUM($C31:I31)),(SUM($C29:J29)+SUM($C32:J32))-(SUM($C30:J30))-(SUM($C31:I31)))) -> 48894.514 | K31: =MAX(0,MIN(NZ_SelProceeds-(SUM($C31:J31)),(SUM($C29:K29)+SUM($C32:K32))-(SUM($C30:K30))-(SUM($C31:J31)))) -> 0 | ... T31: =MAX(0,MIN(NZ_SelProceeds-(SUM($C31:S31)),(SUM($C29:T29)+SUM($C32:T32))-(SUM($C30:T30))-(SUM($C31:S31)))) -> 0 | U31: =SUM(C31:T31) -> 6485211.1
B32: Construction interest (capitalized) | C32: 0 | D32: =IF(D22<=NZ_RehabMonths,MAX(0,C33-$C$33)*PermRate/12,0) -> 0 | E32: =IF(E22<=NZ_RehabMonths,MAX(0,D33-$C$33)*PermRate/12,0) -> 1684.9057 | F32: =IF(F22<=NZ_RehabMonths,MAX(0,E33-$C$33)*PermRate/12,0) -> 4380.7547 | G32: =IF(G22<=NZ_RehabMonths,MAX(0,F33-$C$33)*PermRate/12,0) -> 7915.6868 | H32: =IF(H22<=NZ_RehabMonths,MAX(0,G33-$C$33)*PermRate/12,0) -> 12058.836 | I32: =IF(I22<=NZ_RehabMonths,MAX(0,H33-$C$33)*PermRate/12,0) -> 16539.96 | J32: =IF(J22<=NZ_RehabMonths,MAX(0,I33-$C$33)*PermRate/12,0) -> 21065.896 | K32: =IF(K22<=NZ_RehabMonths,MAX(0,J33-$C$33)*PermRate/12,0) -> 21415.698 | ... T32: =IF(T22<=NZ_RehabMonths,MAX(0,S33-$C$33)*PermRate/12,0) -> 0 | U32: =SUM(C32:T32) -> 149953.45
B33: Perm/bond outstanding balance | C33: =0+C31+C32 -> 2265717.6 | D33: =C33+D31+D32 -> 2602698.7 | E33: =D33+E31+E32 -> 3141868.5 | F33: =E33+F31+F32 -> 3848854.9 | G33: =F33+G31+G32 -> 4677484.8 | H33: =G33+H31+H32 -> 5573709.7 | I33: =H33+I31+I32 -> 6478896.7 | J33: =I33+J31+J32 -> 6548857.2 | K33: =J33+K31+K32 -> 6570272.9 | ... T33: =S33+T31+T32 -> 6635164.6
B34: Cumulative funded (equity + perm) | C34: =SUM($C30:C30)+SUM($C31:C31) -> 2820846.8 | D34: =SUM($C30:D30)+SUM($C31:D31) -> 3157828 | E34: =SUM($C30:E30)+SUM($C31:E31) -> 3695312.9 | F34: =SUM($C30:F30)+SUM($C31:F31) -> 4397918.5 | G34: =SUM($C30:G30)+SUM($C31:G31) -> 5218632.7 | H34: =SUM($C30:H30)+SUM($C31:H31) -> 6102798.7 | I34: =SUM($C30:I30)+SUM($C31:I31) -> 6991445.8 | J34: =SUM($C30:J30)+SUM($C31:J31) -> 7040340.4 | ... T34: =SUM($C30:T30)+SUM($C31:T31) -> 9260857.3
B35: Max outstanding perm/bond balance | U35: =MAX(C33:T33) -> 6635164.6
B38: LIVE OAK MANOR — close: | D38: =LOM_ResynDate -> 47119
B39: Month | C39: 1 | D39: 2 | E39: 3 | F39: 4 | G39: 5 | H39: 6 | I39: 7 | J39: 8 | K39: 9 | L39: 10 | M39: 11 | N39: 12 | O39: 13 | P39: 14 | Q39: 15 | R39: 16 | S39: 17 | T39: 18 | U39: TOTAL
B40: Calendar month | C40: =EDATE(LOM_ResynDate,0) -> 47119 | D40: =EDATE(LOM_ResynDate,1) -> 47150 | E40: =EDATE(LOM_ResynDate,2) -> 47178 | F40: =EDATE(LOM_ResynDate,3) -> 47209 | G40: =EDATE(LOM_ResynDate,4) -> 47239 | H40: =EDATE(LOM_ResynDate,5) -> 47270 | I40: =EDATE(LOM_ResynDate,6) -> 47300 | J40: =EDATE(LOM_ResynDate,7) -> 47331 | K40: =EDATE(LOM_ResynDate,8) -> 47362 | L40: =EDATE(LOM_ResynDate,9) -> 47392 | M40: =EDATE(LOM_ResynDate,10) -> 47423 | N40: =EDATE(LOM_ResynDate,11) -> 47453 | O40: =EDATE(LOM_ResynDate,12) -> 47484 | P40: =EDATE(LOM_ResynDate,13) -> 47515 | Q40: =EDATE(LOM_ResynDate,14) -> 47543 | R40: =EDATE(LOM_ResynDate,15) -> 47574 | S40: =EDATE(LOM_ResynDate,16) -> 47604 | T40: =EDATE(LOM_ResynDate,17) -> 47635
B41: Acquisition price (M1) | C41: =IF(C39=1,LOM_AcqPrice,0) -> 3000000 | D41: =IF(D39=1,LOM_AcqPrice,0) -> 0 | E41: =IF(E39=1,LOM_AcqPrice,0) -> 0 | F41: =IF(F39=1,LOM_AcqPrice,0) -> 0 | G41: =IF(G39=1,LOM_AcqPrice,0) -> 0 | H41: =IF(H39=1,LOM_AcqPrice,0) -> 0 | I41: =IF(I39=1,LOM_AcqPrice,0) -> 0 | J41: =IF(J39=1,LOM_AcqPrice,0) -> 0 | ... T41: =IF(T39=1,LOM_AcqPrice,0) -> 0 | U41: =SUM(C41:T41) -> 3000000
B42: Other close payments (M1) | C42: 0 | D42: 0 | E42: 0 | F42: 0 | G42: 0 | H42: 0 | I42: 0 | J42: 0 | K42: 0 | L42: 0 | M42: 0 | N42: 0 | O42: 0 | P42: 0 | Q42: 0 | R42: 0 | S42: 0 | T42: 0 | U42: =SUM(C42:T42) -> 0
B43: Rehab draw (burn curve) | C43: =LOM_RehabBasis*INDEX(LOM_BurnCurve,1) -> 87419.645 | D43: =LOM_RehabBasis*INDEX(LOM_BurnCurve,2) -> 259050.88 | E43: =LOM_RehabBasis*INDEX(LOM_BurnCurve,3) -> 419453.9 | F43: =LOM_RehabBasis*INDEX(LOM_BurnCurve,4) -> 560608.55 | G43: =LOM_RehabBasis*INDEX(LOM_BurnCurve,5) -> 678504.77 | H43: =LOM_RehabBasis*INDEX(LOM_BurnCurve,6) -> 765924.42 | I43: =LOM_RehabBasis*INDEX(LOM_BurnCurve,7) -> 819659.43 | J43: =LOM_RehabBasis*INDEX(LOM_BurnCurve,8) -> 838105.78 | K43: =LOM_RehabBasis*INDEX(LOM_BurnCurve,9) -> 819659.43 | L43: =LOM_RehabBasis*INDEX(LOM_BurnCurve,10) -> 765924.42 | M43: =LOM_RehabBasis*INDEX(LOM_BurnCurve,11) -> 678504.77 | N43: =LOM_RehabBasis*INDEX(LOM_BurnCurve,12) -> 560608.55 | O43: =LOM_RehabBasis*INDEX(LOM_BurnCurve,13) -> 419453.9 | P43: =LOM_RehabBasis*INDEX(LOM_BurnCurve,14) -> 259050.88 | Q43: =LOM_RehabBasis*INDEX(LOM_BurnCurve,15) -> 88221.661 | R43: =LOM_RehabBasis*INDEX(LOM_BurnCurve,16) -> 0 | S43: =LOM_RehabBasis*INDEX(LOM_BurnCurve,17) -> 0 | T43: =LOM_RehabBasis*INDEX(LOM_BurnCurve,18) -> 0 | U43: =SUM(C43:T43) -> 8020151
B44: Fees + COI + reserves (M1) | C44: =IF(C39=1,LOM_FinFees+'Sources & Uses'!E21+'Sources & Uses'!E23,0) -> 800678.66 | D44: =IF(D39=1,LOM_FinFees+'Sources & Uses'!E21+'Sources & Uses'!E23,0) -> 0 | E44: =IF(E39=1,LOM_FinFees+'Sources & Uses'!E21+'Sources & Uses'!E23,0) -> 0 | F44: =IF(F39=1,LOM_FinFees+'Sources & Uses'!E21+'Sources & Uses'!E23,0) -> 0 | G44: =IF(G39=1,LOM_FinFees+'Sources & Uses'!E21+'Sources & Uses'!E23,0) -> 0 | H44: =IF(H39=1,LOM_FinFees+'Sources & Uses'!E21+'Sources & Uses'!E23,0) -> 0 | I44: =IF(I39=1,LOM_FinFees+'Sources & Uses'!E21+'Sources & Uses'!E23,0) -> 0 | J44: =IF(J39=1,LOM_FinFees+'Sources & Uses'!E21+'Sources & Uses'!E23,0) -> 0 | K44: =IF(K39=1,LOM_FinFees+'Sources & Uses'!E21+'Sources & Uses'!E23,0) -> 0 | L44: =IF(L39=1,LOM_FinFees+'Sources & Uses'!E21+'Sources & Uses'!E23,0) -> 0 | M44: =IF(M39=1,LOM_FinFees+'Sources & Uses'!E21+'Sources & Uses'!E23,0) -> 0 | N44: =IF(N39=1,LOM_FinFees+'Sources & Uses'!E21+'Sources & Uses'!E23,0) -> 0 | O44: =IF(O39=1,LOM_FinFees+'Sources & Uses'!E21+'Sources & Uses'!E23,0) -> 0 | P44: =IF(P39=1,LOM_FinFees+'Sources & Uses'!E21+'Sources & Uses'!E23,0) -> 0 | Q44: =IF(Q39=1,LOM_FinFees+'Sources & Uses'!E21+'Sources & Uses'!E23,0) -> 0 | R44: =IF(R39=1,LOM_FinFees+'Sources & Uses'!E21+'Sources & Uses'!E23,0) -> 0 | S44: =IF(S39=1,LOM_FinFees+'Sources & Uses'!E21+'Sources & Uses'!E23,0) -> 0 | T44: =IF(T39=1,LOM_FinFees+'Sources & Uses'!E21+'Sources & Uses'!E23,0) -> 0 | U44: =SUM(C44:T44) -> 800678.66
B45: Cash developer fee (at stabilization) | C45: =IF(C39=LOM_RehabMonths+6,LOM_DevFee-LOM_DDF,0) -> 0 | D45: =IF(D39=LOM_RehabMonths+6,LOM_DevFee-LOM_DDF,0) -> 0 | E45: =IF(E39=LOM_RehabMonths+6,LOM_DevFee-LOM_DDF,0) -> 0 | F45: =IF(F39=LOM_RehabMonths+6,LOM_DevFee-LOM_DDF,0) -> 0 | G45: =IF(G39=LOM_RehabMonths+6,LOM_DevFee-LOM_DDF,0) -> 0 | H45: =IF(H39=LOM_RehabMonths+6,LOM_DevFee-LOM_DDF,0) -> 0 | I45: =IF(I39=LOM_RehabMonths+6,LOM_DevFee-LOM_DDF,0) -> 0 | J45: =IF(J39=LOM_RehabMonths+6,LOM_DevFee-LOM_DDF,0) -> 0 | ... T45: =IF(T39=LOM_RehabMonths+6,LOM_DevFee-LOM_DDF,0) -> 0 | U45: =SUM(C45:T45) -> 0
B46: TOTAL USES (cash) | C46: =SUM(C41:C45) -> 3888098.3 | D46: =SUM(D41:D45) -> 259050.88 | E46: =SUM(E41:E45) -> 419453.9 | F46: =SUM(F41:F45) -> 560608.55 | G46: =SUM(G41:G45) -> 678504.77 | H46: =SUM(H41:H45) -> 765924.42 | I46: =SUM(I41:I45) -> 819659.43 | J46: =SUM(J41:J45) -> 838105.78 | ... T46: =SUM(T41:T45) -> 0 | U46: =SUM(C46:T46) -> 11820830
B47: Equity tranches (from pay-in blocks) | C47: =SUMPRODUCT((LOM_PayinMonths=C39)*LOM_PayinAmts) -> 822171.79 | D47: =SUMPRODUCT((LOM_PayinMonths=D39)*LOM_PayinAmts) -> 0 | E47: =SUMPRODUCT((LOM_PayinMonths=E39)*LOM_PayinAmts) -> 0 | F47: =SUMPRODUCT((LOM_PayinMonths=F39)*LOM_PayinAmts) -> 0 | G47: =SUMPRODUCT((LOM_PayinMonths=G39)*LOM_PayinAmts) -> 0 | H47: =SUMPRODUCT((LOM_PayinMonths=H39)*LOM_PayinAmts) -> 0 | I47: =SUMPRODUCT((LOM_PayinMonths=I39)*LOM_PayinAmts) -> 0 | J47: =SUMPRODUCT((LOM_PayinMonths=J39)*LOM_PayinAmts) -> 0 | ... T47: =SUMPRODUCT((LOM_PayinMonths=T39)*LOM_PayinAmts) -> 0 | U47: =SUM(C47:T47) -> 2877601.3
B48: Perm/bond draw (plug to need) | C48: =MAX(0,MIN(LOM_SelProceeds-(0),(SUM($C46:C46)+SUM($C49:C49))-(SUM($C47:C47))-(0))) -> 3065926.5 | D48: =MAX(0,MIN(LOM_SelProceeds-(SUM($C48:C48)),(SUM($C46:D46)+SUM($C49:D49))-(SUM($C47:D47))-(SUM($C48:C48)))) -> 259050.88 | E48: =MAX(0,MIN(LOM_SelProceeds-(SUM($C48:D48)),(SUM($C46:E46)+SUM($C49:E49))-(SUM($C47:E47))-(SUM($C48:D48)))) -> 420749.15 | F48: =MAX(0,MIN(LOM_SelProceeds-(SUM($C48:E48)),(SUM($C46:F46)+SUM($C49:F49))-(SUM($C47:F47))-(SUM($C48:E48)))) -> 564014.03 | G48: =MAX(0,MIN(LOM_SelProceeds-(SUM($C48:F48)),(SUM($C46:G46)+SUM($C49:G49))-(SUM($C47:G47))-(SUM($C48:F48)))) -> 684747.35 | H48: =MAX(0,MIN(LOM_SelProceeds-(SUM($C48:G48)),(SUM($C46:H46)+SUM($C49:H49))-(SUM($C47:H47))-(SUM($C48:G48)))) -> 775621.94 | I48: =MAX(0,MIN(LOM_SelProceeds-(SUM($C48:H48)),(SUM($C46:I46)+SUM($C49:I49))-(SUM($C47:I47))-(SUM($C48:H48)))) -> 833283.55 | J48: =MAX(0,MIN(LOM_SelProceeds-(SUM($C48:I48)),(SUM($C46:J46)+SUM($C49:J49))-(SUM($C47:J47))-(SUM($C48:I48)))) -> 855964.43 | K48: =MAX(0,MIN(LOM_SelProceeds-(SUM($C48:J48)),(SUM($C46:K46)+SUM($C49:K49))-(SUM($C47:K47))-(SUM($C48:J48)))) -> 332301.01 | ... T48: =MAX(0,MIN(LOM_SelProceeds-(SUM($C48:S48)),(SUM($C46:T46)+SUM($C49:T49))-(SUM($C47:T47))-(SUM($C48:S48)))) -> 0 | U48: =SUM(C48:T48) -> 7791658.8
B49: Construction interest (capitalized) | C49: 0 | D49: =IF(D39<=LOM_RehabMonths,MAX(0,C50-$C$50)*PermRate/12,0) -> 0 | E49: =IF(E39<=LOM_RehabMonths,MAX(0,D50-$C$50)*PermRate/12,0) -> 1295.2544 | F49: =IF(F39<=LOM_RehabMonths,MAX(0,E50-$C$50)*PermRate/12,0) -> 3405.4764 | G49: =IF(G39<=LOM_RehabMonths,MAX(0,F50-$C$50)*PermRate/12,0) -> 6242.5739 | H49: =IF(H39<=LOM_RehabMonths,MAX(0,G50-$C$50)*PermRate/12,0) -> 9697.5235 | I49: =IF(I39<=LOM_RehabMonths,MAX(0,H50-$C$50)*PermRate/12,0) -> 13624.121 | J49: =IF(J39<=LOM_RehabMonths,MAX(0,I50-$C$50)*PermRate/12,0) -> 17858.659 | K49: =IF(K39<=LOM_RehabMonths,MAX(0,J50-$C$50)*PermRate/12,0) -> 22227.775 | ... T49: =IF(T39<=LOM_RehabMonths,MAX(0,S50-$C$50)*PermRate/12,0) -> 0 | U49: =SUM(C49:T49) -> 220165.97
B50: Perm/bond outstanding balance | C50: =0+C48+C49 -> 3065926.5 | D50: =C50+D48+D49 -> 3324977.4 | E50: =D50+E48+E49 -> 3747021.8 | F50: =E50+F48+F49 -> 4314441.3 | G50: =F50+G48+G49 -> 5005431.2 | H50: =G50+H48+H49 -> 5790750.7 | I50: =H50+I48+I49 -> 6637658.3 | J50: =I50+J48+J49 -> 7511481.4 | K50: =J50+K48+K49 -> 7866010.2 | ... T50: =S50+T48+T49 -> 8011824.8
B51: Cumulative funded (equity + perm) | C51: =SUM($C47:C47)+SUM($C48:C48) -> 3888098.3 | D51: =SUM($C47:D47)+SUM($C48:D48) -> 4147149.2 | E51: =SUM($C47:E47)+SUM($C48:E48) -> 4567898.3 | F51: =SUM($C47:F47)+SUM($C48:F48) -> 5131912.4 | G51: =SUM($C47:G47)+SUM($C48:G48) -> 5816659.7 | H51: =SUM($C47:H47)+SUM($C48:H48) -> 6592281.6 | I51: =SUM($C47:I47)+SUM($C48:I48) -> 7425565.2 | J51: =SUM($C47:J47)+SUM($C48:J48) -> 8281529.6 | ... T51: =SUM($C47:T47)+SUM($C48:T48) -> 10669260
B52: Max outstanding perm/bond balance | U52: =MAX(C50:T50) -> 8011824.8
B55: SPANISH ARMS — close: | D55: =SA_ResynDate -> 46357
B56: Month | C56: 1 | D56: 2 | E56: 3 | F56: 4 | G56: 5 | H56: 6 | I56: 7 | J56: 8 | K56: 9 | L56: 10 | M56: 11 | N56: 12 | O56: 13 | P56: 14 | Q56: 15 | R56: 16 | S56: 17 | T56: 18 | U56: TOTAL
B57: Calendar month | C57: =EDATE(SA_ResynDate,0) -> 46357 | D57: =EDATE(SA_ResynDate,1) -> 46388 | E57: =EDATE(SA_ResynDate,2) -> 46419 | F57: =EDATE(SA_ResynDate,3) -> 46447 | G57: =EDATE(SA_ResynDate,4) -> 46478 | H57: =EDATE(SA_ResynDate,5) -> 46508 | I57: =EDATE(SA_ResynDate,6) -> 46539 | J57: =EDATE(SA_ResynDate,7) -> 46569 | K57: =EDATE(SA_ResynDate,8) -> 46600 | L57: =EDATE(SA_ResynDate,9) -> 46631 | M57: =EDATE(SA_ResynDate,10) -> 46661 | N57: =EDATE(SA_ResynDate,11) -> 46692 | O57: =EDATE(SA_ResynDate,12) -> 46722 | P57: =EDATE(SA_ResynDate,13) -> 46753 | Q57: =EDATE(SA_ResynDate,14) -> 46784 | R57: =EDATE(SA_ResynDate,15) -> 46813 | S57: =EDATE(SA_ResynDate,16) -> 46844 | T57: =EDATE(SA_ResynDate,17) -> 46874
B58: Acquisition price (M1) | C58: =IF(C56=1,SA_AcqPrice,0) -> 500000 | D58: =IF(D56=1,SA_AcqPrice,0) -> 0 | E58: =IF(E56=1,SA_AcqPrice,0) -> 0 | F58: =IF(F56=1,SA_AcqPrice,0) -> 0 | G58: =IF(G56=1,SA_AcqPrice,0) -> 0 | H58: =IF(H56=1,SA_AcqPrice,0) -> 0 | I58: =IF(I56=1,SA_AcqPrice,0) -> 0 | J58: =IF(J56=1,SA_AcqPrice,0) -> 0 | ... T58: =IF(T56=1,SA_AcqPrice,0) -> 0 | U58: =SUM(C58:T58) -> 500000
B59: Other close payments (M1) | C59: 0 | D59: 0 | E59: 0 | F59: 0 | G59: 0 | H59: 0 | I59: 0 | J59: 0 | K59: 0 | L59: 0 | M59: 0 | N59: 0 | O59: 0 | P59: 0 | Q59: 0 | R59: 0 | S59: 0 | T59: 0 | U59: =SUM(C59:T59) -> 0
B60: Rehab draw (burn curve) | C60: =SA_RehabBasis*INDEX(SA_BurnCurve,1) -> 92892.216 | D60: =SA_RehabBasis*INDEX(SA_BurnCurve,2) -> 276232.12 | E60: =SA_RehabBasis*INDEX(SA_BurnCurve,3) -> 449793.89 | F60: =SA_RehabBasis*INDEX(SA_BurnCurve,4) -> 611133 | G60: =SA_RehabBasis*INDEX(SA_BurnCurve,5) -> 752915.86 | H60: =SA_RehabBasis*INDEX(SA_BurnCurve,6) -> 872697.92 | I60: =SA_RehabBasis*INDEX(SA_BurnCurve,7) -> 965590.14 | J60: =SA_RehabBasis*INDEX(SA_BurnCurve,8) -> 1029148 | K60: =SA_RehabBasis*INDEX(SA_BurnCurve,9) -> 1060926.9 | L60: =SA_RehabBasis*INDEX(SA_BurnCurve,10) -> 1060926.9 | M60: =SA_RehabBasis*INDEX(SA_BurnCurve,11) -> 1029148 | N60: =SA_RehabBasis*INDEX(SA_BurnCurve,12) -> 965590.14 | O60: =SA_RehabBasis*INDEX(SA_BurnCurve,13) -> 872697.92 | P60: =SA_RehabBasis*INDEX(SA_BurnCurve,14) -> 752915.86 | Q60: =SA_RehabBasis*INDEX(SA_BurnCurve,15) -> 611133 | R60: =SA_RehabBasis*INDEX(SA_BurnCurve,16) -> 449793.89 | S60: =SA_RehabBasis*INDEX(SA_BurnCurve,17) -> 276232.12 | T60: =SA_RehabBasis*INDEX(SA_BurnCurve,18) -> 92892.216 | U60: =SUM(C60:T60) -> 12222660
B61: Fees + COI + reserves (M1) | C61: =IF(C56=1,SA_FinFees+'Sources & Uses'!F21+'Sources & Uses'!F23,0) -> 1058001.1 | D61: =IF(D56=1,SA_FinFees+'Sources & Uses'!F21+'Sources & Uses'!F23,0) -> 0 | E61: =IF(E56=1,SA_FinFees+'Sources & Uses'!F21+'Sources & Uses'!F23,0) -> 0 | F61: =IF(F56=1,SA_FinFees+'Sources & Uses'!F21+'Sources & Uses'!F23,0) -> 0 | G61: =IF(G56=1,SA_FinFees+'Sources & Uses'!F21+'Sources & Uses'!F23,0) -> 0 | H61: =IF(H56=1,SA_FinFees+'Sources & Uses'!F21+'Sources & Uses'!F23,0) -> 0 | I61: =IF(I56=1,SA_FinFees+'Sources & Uses'!F21+'Sources & Uses'!F23,0) -> 0 | J61: =IF(J56=1,SA_FinFees+'Sources & Uses'!F21+'Sources & Uses'!F23,0) -> 0 | K61: =IF(K56=1,SA_FinFees+'Sources & Uses'!F21+'Sources & Uses'!F23,0) -> 0 | L61: =IF(L56=1,SA_FinFees+'Sources & Uses'!F21+'Sources & Uses'!F23,0) -> 0 | M61: =IF(M56=1,SA_FinFees+'Sources & Uses'!F21+'Sources & Uses'!F23,0) -> 0 | N61: =IF(N56=1,SA_FinFees+'Sources & Uses'!F21+'Sources & Uses'!F23,0) -> 0 | O61: =IF(O56=1,SA_FinFees+'Sources & Uses'!F21+'Sources & Uses'!F23,0) -> 0 | P61: =IF(P56=1,SA_FinFees+'Sources & Uses'!F21+'Sources & Uses'!F23,0) -> 0 | Q61: =IF(Q56=1,SA_FinFees+'Sources & Uses'!F21+'Sources & Uses'!F23,0) -> 0 | R61: =IF(R56=1,SA_FinFees+'Sources & Uses'!F21+'Sources & Uses'!F23,0) -> 0 | S61: =IF(S56=1,SA_FinFees+'Sources & Uses'!F21+'Sources & Uses'!F23,0) -> 0 | T61: =IF(T56=1,SA_FinFees+'Sources & Uses'!F21+'Sources & Uses'!F23,0) -> 0 | U61: =SUM(C61:T61) -> 1058001.1
B62: Cash developer fee (at stabilization) | C62: =IF(C56=SA_RehabMonths+6,SA_DevFee-SA_DDF,0) -> 0 | D62: =IF(D56=SA_RehabMonths+6,SA_DevFee-SA_DDF,0) -> 0 | E62: =IF(E56=SA_RehabMonths+6,SA_DevFee-SA_DDF,0) -> 0 | F62: =IF(F56=SA_RehabMonths+6,SA_DevFee-SA_DDF,0) -> 0 | G62: =IF(G56=SA_RehabMonths+6,SA_DevFee-SA_DDF,0) -> 0 | H62: =IF(H56=SA_RehabMonths+6,SA_DevFee-SA_DDF,0) -> 0 | I62: =IF(I56=SA_RehabMonths+6,SA_DevFee-SA_DDF,0) -> 0 | J62: =IF(J56=SA_RehabMonths+6,SA_DevFee-SA_DDF,0) -> 0 | ... T62: =IF(T56=SA_RehabMonths+6,SA_DevFee-SA_DDF,0) -> 0 | U62: =SUM(C62:T62) -> 0
B63: TOTAL USES (cash) | C63: =SUM(C58:C62) -> 1650893.3 | D63: =SUM(D58:D62) -> 276232.12 | E63: =SUM(E58:E62) -> 449793.89 | F63: =SUM(F58:F62) -> 611133 | G63: =SUM(G58:G62) -> 752915.86 | H63: =SUM(H58:H62) -> 872697.92 | I63: =SUM(I58:I62) -> 965590.14 | J63: =SUM(J58:J62) -> 1029148 | ... T63: =SUM(T58:T62) -> 92892.216 | U63: =SUM(C63:T63) -> 13780661
B64: Equity tranches (from pay-in blocks) | C64: =SUMPRODUCT((SA_PayinMonths=C56)*SA_PayinAmts) -> 1023554 | D64: =SUMPRODUCT((SA_PayinMonths=D56)*SA_PayinAmts) -> 0 | E64: =SUMPRODUCT((SA_PayinMonths=E56)*SA_PayinAmts) -> 0 | F64: =SUMPRODUCT((SA_PayinMonths=F56)*SA_PayinAmts) -> 0 | G64: =SUMPRODUCT((SA_PayinMonths=G56)*SA_PayinAmts) -> 0 | H64: =SUMPRODUCT((SA_PayinMonths=H56)*SA_PayinAmts) -> 0 | I64: =SUMPRODUCT((SA_PayinMonths=I56)*SA_PayinAmts) -> 0 | J64: =SUMPRODUCT((SA_PayinMonths=J56)*SA_PayinAmts) -> 0 | ... T64: =SUMPRODUCT((SA_PayinMonths=T56)*SA_PayinAmts) -> 2558884.9 | U64: =SUM(C64:T64) -> 3582438.8
B65: Perm/bond draw (plug to need) | C65: =MAX(0,MIN(SA_SelProceeds-(0),(SUM($C63:C63)+SUM($C66:C66))-(SUM($C64:C64))-(0))) -> 627339.39 | D65: =MAX(0,MIN(SA_SelProceeds-(SUM($C65:C65)),(SUM($C63:D63)+SUM($C66:D66))-(SUM($C64:D64))-(SUM($C65:C65)))) -> 276232.12 | E65: =MAX(0,MIN(SA_SelProceeds-(SUM($C65:D65)),(SUM($C63:E63)+SUM($C66:E66))-(SUM($C64:E64))-(SUM($C65:D65)))) -> 451175.05 | F65: =MAX(0,MIN(SA_SelProceeds-(SUM($C65:E65)),(SUM($C63:F63)+SUM($C66:F66))-(SUM($C64:F64))-(SUM($C65:E65)))) -> 614776.94 | G65: =MAX(0,MIN(SA_SelProceeds-(SUM($C65:F65)),(SUM($C63:G63)+SUM($C66:G66))-(SUM($C64:G64))-(SUM($C65:F65)))) -> 759651.9 | H65: =MAX(0,MIN(SA_SelProceeds-(SUM($C65:G65)),(SUM($C63:H63)+SUM($C66:H66))-(SUM($C64:H64))-(SUM($C65:G65)))) -> 883265.91 | I65: =MAX(0,MIN(SA_SelProceeds-(SUM($C65:H65)),(SUM($C63:I63)+SUM($C66:I66))-(SUM($C64:I64))-(SUM($C65:H65)))) -> 980627.3 | J65: =MAX(0,MIN(SA_SelProceeds-(SUM($C65:I65)),(SUM($C63:J63)+SUM($C66:J66))-(SUM($C64:J64))-(SUM($C65:I65)))) -> 1049163.4 | K65: =MAX(0,MIN(SA_SelProceeds-(SUM($C65:J65)),(SUM($C63:K63)+SUM($C66:K66))-(SUM($C64:K64))-(SUM($C65:J65)))) -> 1086288.3 | ... T65: =MAX(0,MIN(SA_SelProceeds-(SUM($C65:S65)),(SUM($C63:T63)+SUM($C66:T66))-(SUM($C64:T64))-(SUM($C65:S65)))) -> 0 | U65: =SUM(C65:T65) -> 9219810.9
B66: Construction interest (capitalized) | C66: 0 | D66: =IF(D56<=SA_RehabMonths,MAX(0,C67-$C$67)*PermRate/12,0) -> 0 | E66: =IF(E56<=SA_RehabMonths,MAX(0,D67-$C$67)*PermRate/12,0) -> 1381.1606 | F66: =IF(F56<=SA_RehabMonths,MAX(0,E67-$C$67)*PermRate/12,0) -> 3643.9416 | G66: =IF(G56<=SA_RehabMonths,MAX(0,F67-$C$67)*PermRate/12,0) -> 6736.046 | H66: =IF(H56<=SA_RehabMonths,MAX(0,G67-$C$67)*PermRate/12,0) -> 10567.986 | I66: =IF(I56<=SA_RehabMonths,MAX(0,H67-$C$67)*PermRate/12,0) -> 15037.155 | J66: =IF(J56<=SA_RehabMonths,MAX(0,I67-$C$67)*PermRate/12,0) -> 20015.478 | K66: =IF(K56<=SA_RehabMonths,MAX(0,J67-$C$67)*PermRate/12,0) -> 25361.372 | ... T66: =IF(T56<=SA_RehabMonths,MAX(0,S67-$C$67)*PermRate/12,0) -> 45032.686 | U66: =SUM(C66:T66) -> 459098.41
B67: Perm/bond outstanding balance | C67: =0+C65+C66 -> 627339.39 | D67: =C67+D65+D66 -> 903571.5 | E67: =D67+E65+E66 -> 1356127.7 | F67: =E67+F65+F66 -> 1974548.6 | G67: =F67+G65+G66 -> 2740936.5 | H67: =G67+H65+H66 -> 3634770.4 | I67: =H67+I65+I66 -> 4630434.9 | J67: =I67+J65+J66 -> 5699613.8 | K67: =J67+K65+K66 -> 6811263.4 | ... T67: =S67+T65+T66 -> 9678909.3
B68: Cumulative funded (equity + perm) | C68: =SUM($C64:C64)+SUM($C65:C65) -> 1650893.3 | D68: =SUM($C64:D64)+SUM($C65:D65) -> 1927125.5 | E68: =SUM($C64:E64)+SUM($C65:E65) -> 2378300.5 | F68: =SUM($C64:F64)+SUM($C65:F65) -> 2993077.4 | G68: =SUM($C64:G64)+SUM($C65:G65) -> 3752729.3 | H68: =SUM($C64:H64)+SUM($C65:H65) -> 4635995.3 | I68: =SUM($C64:I64)+SUM($C65:I65) -> 5616622.6 | J68: =SUM($C64:J64)+SUM($C65:J65) -> 6665786 | ... T68: =SUM($C64:T64)+SUM($C65:T65) -> 12802250
B69: Max outstanding perm/bond balance | U69: =MAX(C67:T67) -> 9678909.3
B72: PORTFOLIO ROLL-UP — calendar quarters (flows summed by each property's actual close date; exposure = quarter-end total outstanding)
B73: Quarter beginning | C73: =EDATE(DATE(2026,10,1),0) -> 46296 | D73: =EDATE(DATE(2026,10,1),3) -> 46388 | E73: =EDATE(DATE(2026,10,1),6) -> 46478 | F73: =EDATE(DATE(2026,10,1),9) -> 46569 | G73: =EDATE(DATE(2026,10,1),12) -> 46661 | H73: =EDATE(DATE(2026,10,1),15) -> 46753 | I73: =EDATE(DATE(2026,10,1),18) -> 46844 | J73: =EDATE(DATE(2026,10,1),21) -> 46935 | K73: =EDATE(DATE(2026,10,1),24) -> 47027 | L73: =EDATE(DATE(2026,10,1),27) -> 47119 | M73: =EDATE(DATE(2026,10,1),30) -> 47209 | N73: =EDATE(DATE(2026,10,1),33) -> 47300 | O73: =EDATE(DATE(2026,10,1),36) -> 47392 | P73: =EDATE(DATE(2026,10,1),39) -> 47484 | Q73: =EDATE(DATE(2026,10,1),42) -> 47574 | R73: =EDATE(DATE(2026,10,1),45) -> 47665 | S73: =EDATE(DATE(2026,10,1),48) -> 47757 | T73: =EDATE(DATE(2026,10,1),51) -> 47849 | U73: =EDATE(DATE(2026,10,1),54) -> 47939 | V73: =EDATE(DATE(2026,10,1),57) -> 48030 | W73: =EDATE(DATE(2026,10,1),60) -> 48122
B74: Total equity draws | C74: =SUMPRODUCT(($C$6:$T$6>=C$73)*($C$6:$T$6<EDATE(C$73,3))*$C$13:$T$13)+SUMPRODUCT(($C$23:$T$23>=C$73)*($C$23:$T$23<EDATE(C$73,3))*$C$30:$T$30)+SUMPRODUCT(($C$40:$T$40>=C$73)*($C$40:$T$40<EDATE(C$73,3))*$C$47:$T$47)+SUMPRODUCT(($C$57:$T$57>=C$73)*($C$57:$T$57<EDATE(C$73,3))*$C$64:$T$64) -> 1023554 | D74: =SUMPRODUCT(($C$6:$T$6>=D$73)*($C$6:$T$6<EDATE(D$73,3))*$C$13:$T$13)+SUMPRODUCT(($C$23:$T$23>=D$73)*($C$23:$T$23<EDATE(D$73,3))*$C$30:$T$30)+SUMPRODUCT(($C$40:$T$40>=D$73)*($C$40:$T$40<EDATE(D$73,3))*$C$47:$T$47)+SUMPRODUCT(($C$57:$T$57>=D$73)*($C$57:$T$57<EDATE(D$73,3))*$C$64:$T$64) -> 0 | E74: =SUMPRODUCT(($C$6:$T$6>=E$73)*($C$6:$T$6<EDATE(E$73,3))*$C$13:$T$13)+SUMPRODUCT(($C$23:$T$23>=E$73)*($C$23:$T$23<EDATE(E$73,3))*$C$30:$T$30)+SUMPRODUCT(($C$40:$T$40>=E$73)*($C$40:$T$40<EDATE(E$73,3))*$C$47:$T$47)+SUMPRODUCT(($C$57:$T$57>=E$73)*($C$57:$T$57<EDATE(E$73,3))*$C$64:$T$64) -> 0 | F74: =SUMPRODUCT(($C$6:$T$6>=F$73)*($C$6:$T$6<EDATE(F$73,3))*$C$13:$T$13)+SUMPRODUCT(($C$23:$T$23>=F$73)*($C$23:$T$23<EDATE(F$73,3))*$C$30:$T$30)+SUMPRODUCT(($C$40:$T$40>=F$73)*($C$40:$T$40<EDATE(F$73,3))*$C$47:$T$47)+SUMPRODUCT(($C$57:$T$57>=F$73)*($C$57:$T$57<EDATE(F$73,3))*$C$64:$T$64) -> 0 | G74: =SUMPRODUCT(($C$6:$T$6>=G$73)*($C$6:$T$6<EDATE(G$73,3))*$C$13:$T$13)+SUMPRODUCT(($C$23:$T$23>=G$73)*($C$23:$T$23<EDATE(G$73,3))*$C$30:$T$30)+SUMPRODUCT(($C$40:$T$40>=G$73)*($C$40:$T$40<EDATE(G$73,3))*$C$47:$T$47)+SUMPRODUCT(($C$57:$T$57>=G$73)*($C$57:$T$57<EDATE(G$73,3))*$C$64:$T$64) -> 0 | H74: =SUMPRODUCT(($C$6:$T$6>=H$73)*($C$6:$T$6<EDATE(H$73,3))*$C$13:$T$13)+SUMPRODUCT(($C$23:$T$23>=H$73)*($C$23:$T$23<EDATE(H$73,3))*$C$30:$T$30)+SUMPRODUCT(($C$40:$T$40>=H$73)*($C$40:$T$40<EDATE(H$73,3))*$C$47:$T$47)+SUMPRODUCT(($C$57:$T$57>=H$73)*($C$57:$T$57<EDATE(H$73,3))*$C$64:$T$64) -> 448373.62 | I74: =SUMPRODUCT(($C$6:$T$6>=I$73)*($C$6:$T$6<EDATE(I$73,3))*$C$13:$T$13)+SUMPRODUCT(($C$23:$T$23>=I$73)*($C$23:$T$23<EDATE(I$73,3))*$C$30:$T$30)+SUMPRODUCT(($C$40:$T$40>=I$73)*($C$40:$T$40<EDATE(I$73,3))*$C$47:$T$47)+SUMPRODUCT(($C$57:$T$57>=I$73)*($C$57:$T$57<EDATE(I$73,3))*$C$64:$T$64) -> 2558884.9 | J74: =SUMPRODUCT(($C$6:$T$6>=J$73)*($C$6:$T$6<EDATE(J$73,3))*$C$13:$T$13)+SUMPRODUCT(($C$23:$T$23>=J$73)*($C$23:$T$23<EDATE(J$73,3))*$C$30:$T$30)+SUMPRODUCT(($C$40:$T$40>=J$73)*($C$40:$T$40<EDATE(J$73,3))*$C$47:$T$47)+SUMPRODUCT(($C$57:$T$57>=J$73)*($C$57:$T$57<EDATE(J$73,3))*$C$64:$T$64) -> 0 | ... W74: =SUMPRODUCT(($C$6:$T$6>=W$73)*($C$6:$T$6<EDATE(W$73,3))*$C$13:$T$13)+SUMPRODUCT(($C$23:$T$23>=W$73)*($C$23:$T$23<EDATE(W$73,3))*$C$30:$T$30)+SUMPRODUCT(($C$40:$T$40>=W$73)*($C$40:$T$40<EDATE(W$73,3))*$C$47:$T$47)+SUMPRODUCT(($C$57:$T$57>=W$73)*($C$57:$T$57<EDATE(W$73,3))*$C$64:$T$64) -> 0
B75: Total debt draws | C75: =SUMPRODUCT(($C$6:$T$6>=C$73)*($C$6:$T$6<EDATE(C$73,3))*$C$14:$T$14)+SUMPRODUCT(($C$23:$T$23>=C$73)*($C$23:$T$23<EDATE(C$73,3))*$C$31:$T$31)+SUMPRODUCT(($C$40:$T$40>=C$73)*($C$40:$T$40<EDATE(C$73,3))*$C$48:$T$48)+SUMPRODUCT(($C$57:$T$57>=C$73)*($C$57:$T$57<EDATE(C$73,3))*$C$65:$T$65) -> 627339.39 | D75: =SUMPRODUCT(($C$6:$T$6>=D$73)*($C$6:$T$6<EDATE(D$73,3))*$C$14:$T$14)+SUMPRODUCT(($C$23:$T$23>=D$73)*($C$23:$T$23<EDATE(D$73,3))*$C$31:$T$31)+SUMPRODUCT(($C$40:$T$40>=D$73)*($C$40:$T$40<EDATE(D$73,3))*$C$48:$T$48)+SUMPRODUCT(($C$57:$T$57>=D$73)*($C$57:$T$57<EDATE(D$73,3))*$C$65:$T$65) -> 1342184.1 | E75: =SUMPRODUCT(($C$6:$T$6>=E$73)*($C$6:$T$6<EDATE(E$73,3))*$C$14:$T$14)+SUMPRODUCT(($C$23:$T$23>=E$73)*($C$23:$T$23<EDATE(E$73,3))*$C$31:$T$31)+SUMPRODUCT(($C$40:$T$40>=E$73)*($C$40:$T$40<EDATE(E$73,3))*$C$48:$T$48)+SUMPRODUCT(($C$57:$T$57>=E$73)*($C$57:$T$57<EDATE(E$73,3))*$C$65:$T$65) -> 2623545.1 | F75: =SUMPRODUCT(($C$6:$T$6>=F$73)*($C$6:$T$6<EDATE(F$73,3))*$C$14:$T$14)+SUMPRODUCT(($C$23:$T$23>=F$73)*($C$23:$T$23<EDATE(F$73,3))*$C$31:$T$31)+SUMPRODUCT(($C$40:$T$40>=F$73)*($C$40:$T$40<EDATE(F$73,3))*$C$48:$T$48)+SUMPRODUCT(($C$57:$T$57>=F$73)*($C$57:$T$57<EDATE(F$73,3))*$C$65:$T$65) -> 3227298.2 | G75: =SUMPRODUCT(($C$6:$T$6>=G$73)*($C$6:$T$6<EDATE(G$73,3))*$C$14:$T$14)+SUMPRODUCT(($C$23:$T$23>=G$73)*($C$23:$T$23<EDATE(G$73,3))*$C$31:$T$31)+SUMPRODUCT(($C$40:$T$40>=G$73)*($C$40:$T$40<EDATE(G$73,3))*$C$48:$T$48)+SUMPRODUCT(($C$57:$T$57>=G$73)*($C$57:$T$57<EDATE(G$73,3))*$C$65:$T$65) -> 1399444.1 | H75: =SUMPRODUCT(($C$6:$T$6>=H$73)*($C$6:$T$6<EDATE(H$73,3))*$C$14:$T$14)+SUMPRODUCT(($C$23:$T$23>=H$73)*($C$23:$T$23<EDATE(H$73,3))*$C$31:$T$31)+SUMPRODUCT(($C$40:$T$40>=H$73)*($C$40:$T$40<EDATE(H$73,3))*$C$48:$T$48)+SUMPRODUCT(($C$57:$T$57>=H$73)*($C$57:$T$57<EDATE(H$73,3))*$C$65:$T$65) -> 904677.11 | I75: =SUMPRODUCT(($C$6:$T$6>=I$73)*($C$6:$T$6<EDATE(I$73,3))*$C$14:$T$14)+SUMPRODUCT(($C$23:$T$23>=I$73)*($C$23:$T$23<EDATE(I$73,3))*$C$31:$T$31)+SUMPRODUCT(($C$40:$T$40>=I$73)*($C$40:$T$40<EDATE(I$73,3))*$C$48:$T$48)+SUMPRODUCT(($C$57:$T$57>=I$73)*($C$57:$T$57<EDATE(I$73,3))*$C$65:$T$65) -> 1944507.8 | J75: =SUMPRODUCT(($C$6:$T$6>=J$73)*($C$6:$T$6<EDATE(J$73,3))*$C$14:$T$14)+SUMPRODUCT(($C$23:$T$23>=J$73)*($C$23:$T$23<EDATE(J$73,3))*$C$31:$T$31)+SUMPRODUCT(($C$40:$T$40>=J$73)*($C$40:$T$40<EDATE(J$73,3))*$C$48:$T$48)+SUMPRODUCT(($C$57:$T$57>=J$73)*($C$57:$T$57<EDATE(J$73,3))*$C$65:$T$65) -> 561167.47 | ... W75: =SUMPRODUCT(($C$6:$T$6>=W$73)*($C$6:$T$6<EDATE(W$73,3))*$C$14:$T$14)+SUMPRODUCT(($C$23:$T$23>=W$73)*($C$23:$T$23<EDATE(W$73,3))*$C$31:$T$31)+SUMPRODUCT(($C$40:$T$40>=W$73)*($C$40:$T$40<EDATE(W$73,3))*$C$48:$T$48)+SUMPRODUCT(($C$57:$T$57>=W$73)*($C$57:$T$57<EDATE(W$73,3))*$C$65:$T$65) -> 0
B76: Total uses (cash) | C76: =SUMPRODUCT(($C$6:$T$6>=C$73)*($C$6:$T$6<EDATE(C$73,3))*$C$12:$T$12)+SUMPRODUCT(($C$23:$T$23>=C$73)*($C$23:$T$23<EDATE(C$73,3))*$C$29:$T$29)+SUMPRODUCT(($C$40:$T$40>=C$73)*($C$40:$T$40<EDATE(C$73,3))*$C$46:$T$46)+SUMPRODUCT(($C$57:$T$57>=C$73)*($C$57:$T$57<EDATE(C$73,3))*$C$63:$T$63) -> 1650893.3 | D76: =SUMPRODUCT(($C$6:$T$6>=D$73)*($C$6:$T$6<EDATE(D$73,3))*$C$12:$T$12)+SUMPRODUCT(($C$23:$T$23>=D$73)*($C$23:$T$23<EDATE(D$73,3))*$C$29:$T$29)+SUMPRODUCT(($C$40:$T$40>=D$73)*($C$40:$T$40<EDATE(D$73,3))*$C$46:$T$46)+SUMPRODUCT(($C$57:$T$57>=D$73)*($C$57:$T$57<EDATE(D$73,3))*$C$63:$T$63) -> 1337159 | E76: =SUMPRODUCT(($C$6:$T$6>=E$73)*($C$6:$T$6<EDATE(E$73,3))*$C$12:$T$12)+SUMPRODUCT(($C$23:$T$23>=E$73)*($C$23:$T$23<EDATE(E$73,3))*$C$29:$T$29)+SUMPRODUCT(($C$40:$T$40>=E$73)*($C$40:$T$40<EDATE(E$73,3))*$C$46:$T$46)+SUMPRODUCT(($C$57:$T$57>=E$73)*($C$57:$T$57<EDATE(E$73,3))*$C$63:$T$63) -> 2591203.9 | F76: =SUMPRODUCT(($C$6:$T$6>=F$73)*($C$6:$T$6<EDATE(F$73,3))*$C$12:$T$12)+SUMPRODUCT(($C$23:$T$23>=F$73)*($C$23:$T$23<EDATE(F$73,3))*$C$29:$T$29)+SUMPRODUCT(($C$40:$T$40>=F$73)*($C$40:$T$40<EDATE(F$73,3))*$C$46:$T$46)+SUMPRODUCT(($C$57:$T$57>=F$73)*($C$57:$T$57<EDATE(F$73,3))*$C$63:$T$63) -> 3151001.7 | G76: =SUMPRODUCT(($C$6:$T$6>=G$73)*($C$6:$T$6<EDATE(G$73,3))*$C$12:$T$12)+SUMPRODUCT(($C$23:$T$23>=G$73)*($C$23:$T$23<EDATE(G$73,3))*$C$29:$T$29)+SUMPRODUCT(($C$40:$T$40>=G$73)*($C$40:$T$40<EDATE(G$73,3))*$C$46:$T$46)+SUMPRODUCT(($C$57:$T$57>=G$73)*($C$57:$T$57<EDATE(G$73,3))*$C$63:$T$63) -> 2867436 | H76: =SUMPRODUCT(($C$6:$T$6>=H$73)*($C$6:$T$6<EDATE(H$73,3))*$C$12:$T$12)+SUMPRODUCT(($C$23:$T$23>=H$73)*($C$23:$T$23<EDATE(H$73,3))*$C$29:$T$29)+SUMPRODUCT(($C$40:$T$40>=H$73)*($C$40:$T$40<EDATE(H$73,3))*$C$46:$T$46)+SUMPRODUCT(($C$57:$T$57>=H$73)*($C$57:$T$57<EDATE(H$73,3))*$C$63:$T$63) -> 3165532.6 | I76: =SUMPRODUCT(($C$6:$T$6>=I$73)*($C$6:$T$6<EDATE(I$73,3))*$C$12:$T$12)+SUMPRODUCT(($C$23:$T$23>=I$73)*($C$23:$T$23<EDATE(I$73,3))*$C$29:$T$29)+SUMPRODUCT(($C$40:$T$40>=I$73)*($C$40:$T$40<EDATE(I$73,3))*$C$46:$T$46)+SUMPRODUCT(($C$57:$T$57>=I$73)*($C$57:$T$57<EDATE(I$73,3))*$C$63:$T$63) -> 2293960.6 | J76: =SUMPRODUCT(($C$6:$T$6>=J$73)*($C$6:$T$6<EDATE(J$73,3))*$C$12:$T$12)+SUMPRODUCT(($C$23:$T$23>=J$73)*($C$23:$T$23<EDATE(J$73,3))*$C$29:$T$29)+SUMPRODUCT(($C$40:$T$40>=J$73)*($C$40:$T$40<EDATE(J$73,3))*$C$46:$T$46)+SUMPRODUCT(($C$57:$T$57>=J$73)*($C$57:$T$57<EDATE(J$73,3))*$C$63:$T$63) -> 1924836.2 | ... W76: =SUMPRODUCT(($C$6:$T$6>=W$73)*($C$6:$T$6<EDATE(W$73,3))*$C$12:$T$12)+SUMPRODUCT(($C$23:$T$23>=W$73)*($C$23:$T$23<EDATE(W$73,3))*$C$29:$T$29)+SUMPRODUCT(($C$40:$T$40>=W$73)*($C$40:$T$40<EDATE(W$73,3))*$C$46:$T$46)+SUMPRODUCT(($C$57:$T$57>=W$73)*($C$57:$T$57<EDATE(W$73,3))*$C$63:$T$63) -> 0
B77: Cumulative capital deployed | C77: =C74+C75 -> 1650893.3 | D77: =D74+D75+C77 -> 2993077.4 | E77: =E74+E75+D77 -> 5616622.6 | F77: =F74+F75+E77 -> 8843920.8 | G77: =G74+G75+F77 -> 10243365 | H77: =H74+H75+G77 -> 11596416 | I77: =I74+I75+H77 -> 16099808 | J77: =J74+J75+I77 -> 16660976 | K77: =K74+K75+J77 -> 17781910 | ... W77: =W74+W75+V77 -> 38384588
B78: Total outstanding at quarter-end | C78: {=IFERROR(INDEX($C$16:$T$16,MATCH(MAX(IF(($C$6:$T$6>=C$73)*($C$6:$T$6<EDATE(C$73,3)),$C$6:$T$6)),$C$6:$T$6,0)),0)+IFERROR(INDEX($C$33:$T$33,MATCH(MAX(IF(($C$23:$T$23>=C$73)*($C$23:$T$23<EDATE(C$73,3)),$C$23:$T$23)),$C$23:$T$23,0)),0)+IFERROR(INDEX($C$50:$T$50,MATCH(MAX(IF(($C$40:$T$40>=C$73)*($C$40:$T$40<EDATE(C$73,3)),$C$40:$T$40)),$C$40:$T$40,0)),0)+IFERROR(INDEX($C$67:$T$67,MATCH(MAX(IF(($C$57:$T$57>=C$73)*($C$57:$T$57<EDATE(C$73,3)),$C$57:$T$57)),$C$57:$T$57,0)),0)} -> 627339.39 | D78: {=IFERROR(INDEX($C$16:$T$16,MATCH(MAX(IF(($C$6:$T$6>=D$73)*($C$6:$T$6<EDATE(D$73,3)),$C$6:$T$6)),$C$6:$T$6,0)),0)+IFERROR(INDEX($C$33:$T$33,MATCH(MAX(IF(($C$23:$T$23>=D$73)*($C$23:$T$23<EDATE(D$73,3)),$C$23:$T$23)),$C$23:$T$23,0)),0)+IFERROR(INDEX($C$50:$T$50,MATCH(MAX(IF(($C$40:$T$40>=D$73)*($C$40:$T$40<EDATE(D$73,3)),$C$40:$T$40)),$C$40:$T$40,0)),0)+IFERROR(INDEX($C$67:$T$67,MATCH(MAX(IF(($C$57:$T$57>=D$73)*($C$57:$T$57<EDATE(D$73,3)),$C$57:$T$57)),$C$57:$T$57,0)),0)} -> 1974548.6 | E78: {=IFERROR(INDEX($C$16:$T$16,MATCH(MAX(IF(($C$6:$T$6>=E$73)*($C$6:$T$6<EDATE(E$73,3)),$C$6:$T$6)),$C$6:$T$6,0)),0)+IFERROR(INDEX($C$33:$T$33,MATCH(MAX(IF(($C$23:$T$23>=E$73)*($C$23:$T$23<EDATE(E$73,3)),$C$23:$T$23)),$C$23:$T$23,0)),0)+IFERROR(INDEX($C$50:$T$50,MATCH(MAX(IF(($C$40:$T$40>=E$73)*($C$40:$T$40<EDATE(E$73,3)),$C$40:$T$40)),$C$40:$T$40,0)),0)+IFERROR(INDEX($C$67:$T$67,MATCH(MAX(IF(($C$57:$T$57>=E$73)*($C$57:$T$57<EDATE(E$73,3)),$C$57:$T$57)),$C$57:$T$57,0)),0)} -> 4630434.9 | F78: {=IFERROR(INDEX($C$16:$T$16,MATCH(MAX(IF(($C$6:$T$6>=F$73)*($C$6:$T$6<EDATE(F$73,3)),$C$6:$T$6)),$C$6:$T$6,0)),0)+IFERROR(INDEX($C$33:$T$33,MATCH(MAX(IF(($C$23:$T$23>=F$73)*($C$23:$T$23<EDATE(F$73,3)),$C$23:$T$23)),$C$23:$T$23,0)),0)+IFERROR(INDEX($C$50:$T$50,MATCH(MAX(IF(($C$40:$T$40>=F$73)*($C$40:$T$40<EDATE(F$73,3)),$C$40:$T$40)),$C$40:$T$40,0)),0)+IFERROR(INDEX($C$67:$T$67,MATCH(MAX(IF(($C$57:$T$57>=F$73)*($C$57:$T$57<EDATE(F$73,3)),$C$57:$T$57)),$C$57:$T$57,0)),0)} -> 7934029.6 | G78: {=IFERROR(INDEX($C$16:$T$16,MATCH(MAX(IF(($C$6:$T$6>=G$73)*($C$6:$T$6<EDATE(G$73,3)),$C$6:$T$6)),$C$6:$T$6,0)),0)+IFERROR(INDEX($C$33:$T$33,MATCH(MAX(IF(($C$23:$T$23>=G$73)*($C$23:$T$23<EDATE(G$73,3)),$C$23:$T$23)),$C$23:$T$23,0)),0)+IFERROR(INDEX($C$50:$T$50,MATCH(MAX(IF(($C$40:$T$40>=G$73)*($C$40:$T$40<EDATE(G$73,3)),$C$40:$T$40)),$C$40:$T$40,0)),0)+IFERROR(INDEX($C$67:$T$67,MATCH(MAX(IF(($C$57:$T$57>=G$73)*($C$57:$T$57<EDATE(G$73,3)),$C$57:$T$57)),$C$57:$T$57,0)),0)} -> 9455975.2 | H78: {=IFERROR(INDEX($C$16:$T$16,MATCH(MAX(IF(($C$6:$T$6>=H$73)*($C$6:$T$6<EDATE(H$73,3)),$C$6:$T$6)),$C$6:$T$6,0)),0)+IFERROR(INDEX($C$33:$T$33,MATCH(MAX(IF(($C$23:$T$23>=H$73)*($C$23:$T$23<EDATE(H$73,3)),$C$23:$T$23)),$C$23:$T$23,0)),0)+IFERROR(INDEX($C$50:$T$50,MATCH(MAX(IF(($C$40:$T$40>=H$73)*($C$40:$T$40<EDATE(H$73,3)),$C$40:$T$40)),$C$40:$T$40,0)),0)+IFERROR(INDEX($C$67:$T$67,MATCH(MAX(IF(($C$57:$T$57>=H$73)*($C$57:$T$57<EDATE(H$73,3)),$C$57:$T$57)),$C$57:$T$57,0)),0)} -> 10495106 | I78: {=IFERROR(INDEX($C$16:$T$16,MATCH(MAX(IF(($C$6:$T$6>=I$73)*($C$6:$T$6<EDATE(I$73,3)),$C$6:$T$6)),$C$6:$T$6,0)),0)+IFERROR(INDEX($C$33:$T$33,MATCH(MAX(IF(($C$23:$T$23>=I$73)*($C$23:$T$23<EDATE(I$73,3)),$C$23:$T$23)),$C$23:$T$23,0)),0)+IFERROR(INDEX($C$50:$T$50,MATCH(MAX(IF(($C$40:$T$40>=I$73)*($C$40:$T$40<EDATE(I$73,3)),$C$40:$T$40)),$C$40:$T$40,0)),0)+IFERROR(INDEX($C$67:$T$67,MATCH(MAX(IF(($C$57:$T$57>=I$73)*($C$57:$T$57<EDATE(I$73,3)),$C$57:$T$57)),$C$57:$T$57,0)),0)} -> 12549127 | J78: {=IFERROR(INDEX($C$16:$T$16,MATCH(MAX(IF(($C$6:$T$6>=J$73)*($C$6:$T$6<EDATE(J$73,3)),$C$6:$T$6)),$C$6:$T$6,0)),0)+IFERROR(INDEX($C$33:$T$33,MATCH(MAX(IF(($C$23:$T$23>=J$73)*($C$23:$T$23<EDATE(J$73,3)),$C$23:$T$23)),$C$23:$T$23,0)),0)+IFERROR(INDEX($C$50:$T$50,MATCH(MAX(IF(($C$40:$T$40>=J$73)*($C$40:$T$40<EDATE(J$73,3)),$C$40:$T$40)),$C$40:$T$40,0)),0)+IFERROR(INDEX($C$67:$T$67,MATCH(MAX(IF(($C$57:$T$57>=J$73)*($C$57:$T$57<EDATE(J$73,3)),$C$57:$T$57)),$C$57:$T$57,0)),0)} -> 3477288.9 | ... W78: {=IFERROR(INDEX($C$16:$T$16,MATCH(MAX(IF(($C$6:$T$6>=W$73)*($C$6:$T$6<EDATE(W$73,3)),$C$6:$T$6)),$C$6:$T$6,0)),0)+IFERROR(INDEX($C$33:$T$33,MATCH(MAX(IF(($C$23:$T$23>=W$73)*($C$23:$T$23<EDATE(W$73,3)),$C$23:$T$23)),$C$23:$T$23,0)),0)+IFERROR(INDEX($C$50:$T$50,MATCH(MAX(IF(($C$40:$T$40>=W$73)*($C$40:$T$40<EDATE(W$73,3)),$C$40:$T$40)),$C$40:$T$40,0)),0)+IFERROR(INDEX($C$67:$T$67,MATCH(MAX(IF(($C$57:$T$57>=W$73)*($C$57:$T$57<EDATE(W$73,3)),$C$57:$T$57)),$C$57:$T$57,0)),0)} -> 0
B79: Peak concurrent exposure | C79: =MAX(C78:W78) -> 14891179

Sheet Tax Credit Calc
A1: LIHTC CREDIT CALCULATIONS — ACQUISITION / REHAB RESYNDICATION
C2: Clear Horizons | D2: New Zion | E2: Live Oak Manor | F2: Spanish Arms | G2: Portfolio (mixed-vintage)
B4: Tax credit equity price | C4: =EquityPrice -> 0.8
B5: GP credit share | C5: 0.01
B7: ACQUISITION CREDITS (no basis boost — IRC Sec.42(d)(5)(B) boost applies to new construction/rehab basis only)
B8: Acquisition price | C8: =CH_AcqPrice -> 0 | D8: =NZ_AcqPrice -> 0 | E8: =LOM_AcqPrice -> 3000000 | F8: =SA_AcqPrice -> 500000 | G8: =SUM(C8:F8) -> 3500000
B9: Less: land (allocation input) | C9: =-C8*CH_LandPct -> 0 | D9: =-D8*NZ_LandPct -> 0 | E9: =-E8*LOM_LandPct -> -450000 | F9: =-F8*SA_LandPct -> -75000
B10: Building acquisition basis | C10: =C8+C9 -> 0 | D10: =D8+D9 -> 0 | E10: =E8+E9 -> 2550000 | F10: =F8+F9 -> 425000
B11: 10-year rule / prior-credit flag | C11: OK — confirm transfers | D11: OK — confirm transfers | E11: OK — confirm transfers | F11: OK — confirm transfers
B12: Applicable fraction | C12: 1 | D12: 1 | E12: 1 | F12: 0.9902
B13: Credit rate — 4% floor | C13: =LIHTCRate4 -> 0.04 | D13: =LIHTCRate4 -> 0.04 | E13: =LIHTCRate4 -> 0.04 | F13: =LIHTCRate4 -> 0.04
B14: Annual acquisition credits | C14: =C10*C12*C13 -> 0 | D14: =D10*D12*D13 -> 0 | E14: =E10*E12*E13 -> 102000 | F14: =F10*F12*F13 -> 16833.4 | G14: =SUM(C14:F14) -> 118833.4
B16: REHAB CREDITS (130% QCT boost)
B17: Rehab cost incl. contingency/GC (vintage $) | C17: =CH_RehabTotal*(1+CostInflation)^CH_InflYears -> 4506378.2 | D17: =NZ_RehabTotal*(1+CostInflation)^NZ_InflYears -> 5579325.4 | E17: =LOM_RehabTotal*(1+CostInflation)^LOM_InflYears -> 6639397.3 | F17: =SA_RehabTotal*(1+CostInflation)^SA_InflYears -> 10118400
B18: Tenant relocation in basis (vintage $) | C18: =CH_RelocTotal*(1+CostInflation)^CH_InflYears -> 227136 | D18: =NZ_RelocTotal*(1+CostInflation)^NZ_InflYears -> 281216 | E18: =LOM_RelocTotal*(1+CostInflation)^LOM_InflYears -> 334647.04 | F18: =SA_RelocTotal*(1+CostInflation)^SA_InflYears -> 510000
B19: Soft costs in basis (% of rehab) | C19: 0.15 | D19: 0.15 | E19: 0.15 | F19: 0.15
B20: Rehab eligible basis | C20: =(C17+C18)*(1+C19) -> 5443541.4 | D20: =(D17+D18)*(1+D19) -> 6739622.7 | E20: =(E17+E18)*(1+E19) -> 8020151 | F20: =(F17+F18)*(1+F19) -> 12222660
B21: QCT basis boost | C21: =IF('Dashboard Calc'!C11="Yes",BoostCapPct,0) -> 0.3 | D21: =IF('Dashboard Calc'!D11="Yes",BoostCapPct,0) -> 0.3 | E21: =IF('Dashboard Calc'!E11="Yes",BoostCapPct,0) -> 0.3 | F21: =IF('Dashboard Calc'!F11="Yes",BoostCapPct,0) -> 0.3
B22: Boosted rehab basis | C22: =C20*(1+C21) -> 7076603.8 | D22: =D20*(1+D21) -> 8761509.5 | E22: =E20*(1+E21) -> 10426196 | F22: =F20*(1+F21) -> 15889458
B23: Annual rehab credits | C23: =C22*C12*C13 -> 283064.15 | D23: =D22*D12*D13 -> 350460.38 | E23: =E22*E12*E13 -> 417047.85 | F23: =F22*F12*F13 -> 629349.65 | G23: =SUM(C23:F23) -> 1679922
B25: TOTAL ANNUAL CREDITS | C25: =C14+C23 -> 283064.15 | D25: =D14+D23 -> 350460.38 | E25: =E14+E23 -> 519047.85 | F25: =F14+F23 -> 646183.05 | G25: =SUM(C25:F25) -> 1798755.4
B26: 10-year credit total | C26: =C25*10 -> 2830641.5 | D26: =D25*10 -> 3504603.8 | E26: =E25*10 -> 5190478.5 | F26: =F25*10 -> 6461830.5
B27: LP share of credits | C27: =1-$C$5 -> 0.99 | D27: =1-$C$5 -> 0.99 | E27: =1-$C$5 -> 0.99 | F27: =1-$C$5 -> 0.99
B28: TAX CREDIT EQUITY (LP) | C28: =C26*C27*EquityPrice -> 2241868.1 | D28: =D26*D27*EquityPrice -> 2775646.2 | E28: =E26*E27*EquityPrice -> 4110859 | F28: =F26*F27*EquityPrice -> 5117769.8 | G28: =SUM(C28:F28) -> 14246143
B30: TAX-EXEMPT BOND FINANCING TEST (25% aggregate-basis minimum — OBBBA; was 50% for pre-2026 PIS)
B31: Tax-exempt bond proceeds | C31: =CH_SelProceeds -> 3410352.4 | D31: =NZ_SelProceeds -> 6485211.1 | E31: =LOM_SelProceeds -> 7791658.8 | F31: =SA_SelProceeds -> 9219810.9
B32: Aggregate basis (bldg acq + rehab, unboosted, + land) | C32: =C10+C20-C9 -> 5443541.4 | D32: =D10+D20-D9 -> 6739622.7 | E32: =E10+E20-E9 -> 11020151 | F32: =F10+F20-F9 -> 12722660
B33: Bond % of aggregate basis | C33: =C31/C32 -> 0.62649517 | D33: =D31/D32 -> 0.96225137 | E33: =E31/E32 -> 0.7070374 | F33: =F31/F32 -> 0.72467636
B34: Minimum required | C34: =Bond50Min -> 0.25 | D34: =Bond50Min -> 0.25 | E34: =Bond50Min -> 0.25 | F34: =Bond50Min -> 0.25
B35: Bond test result | C35: =IF(C33>=C34,"PASS","FAIL") -> PASS | D35: =IF(D33>=D34,"PASS","FAIL") -> PASS | E35: =IF(E33>=E34,"PASS","FAIL") -> PASS | F35: =IF(F33>=F34,"PASS","FAIL") -> PASS
B38: EQUITY PAY-IN SCHEDULES — month # measured from THAT property's resyndication close; single source of truth for the Pro Formas and S&U Timing (spec Sec. 5.8)
B39: CLEAR HORIZONS — equity pay-in (close: | D39: =CH_ResynDate -> 46753 | E39: Total equity: | F39: =C28 -> 2241868.1
B40: Milestone | C40: Month # | D40: % of Equity | E40: $ Amount
B41: Closing | C41: 1 | D41: 0.2 | E41: =D41*$C$28 -> 448373.62
B42: Construction completion | C42: 12 | D42: 0.5 | E42: =D42*$C$28 -> 1120934
B43: Stabilization / 8609s | C43: 18 | D43: 0.3 | E43: =D43*$C$28 -> 672560.42
B44: (spare) | D44: 0 | E44: =D44*$C$28 -> 0
B45: (spare) | D45: 0 | E45: =D45*$C$28 -> 0
B46: (spare) | D46: 0 | E46: =D46*$C$28 -> 0
B47: Total | C47: =IF(ABS(D47-1)<0.0001,"OK","MUST = 100%") -> OK | D47: =SUM(D41:D46) -> 1 | E47: =SUM(E41:E46) -> 2241868.1
B49: NEW ZION — equity pay-in (close: | D49: =NZ_ResynDate -> 47119 | E49: Total equity: | F49: =D28 -> 2775646.2
B50: Milestone | C50: Month # | D50: % of Equity | E50: $ Amount
B51: Closing | C51: 1 | D51: 0.2 | E51: =D51*$D$28 -> 555129.24
B52: Construction completion | C52: 12 | D52: 0.5 | E52: =D52*$D$28 -> 1387823.1
B53: Stabilization / 8609s | C53: 18 | D53: 0.3 | E53: =D53*$D$28 -> 832693.86
B54: (spare) | D54: 0 | E54: =D54*$D$28 -> 0
B55: (spare) | D55: 0 | E55: =D55*$D$28 -> 0
B56: (spare) | D56: 0 | E56: =D56*$D$28 -> 0
B57: Total | C57: =IF(ABS(D57-1)<0.0001,"OK","MUST = 100%") -> OK | D57: =SUM(D51:D56) -> 1 | E57: =SUM(E51:E56) -> 2775646.2
B59: LIVE OAK MANOR — equity pay-in (close: | D59: =LOM_ResynDate -> 47119 | E59: Total equity: | F59: =E28 -> 4110859
B60: Milestone | C60: Month # | D60: % of Equity | E60: $ Amount
B61: Closing | C61: 1 | D61: 0.2 | E61: =D61*$E$28 -> 822171.79
B62: Construction completion | C62: 15 | D62: 0.5 | E62: =D62*$E$28 -> 2055429.5
B63: Stabilization / 8609s | C63: 21 | D63: 0.3 | E63: =D63*$E$28 -> 1233257.7
B64: (spare) | D64: 0 | E64: =D64*$E$28 -> 0
B65: (spare) | D65: 0 | E65: =D65*$E$28 -> 0
B66: (spare) | D66: 0 | E66: =D66*$E$28 -> 0
B67: Total | C67: =IF(ABS(D67-1)<0.0001,"OK","MUST = 100%") -> OK | D67: =SUM(D61:D66) -> 1 | E67: =SUM(E61:E66) -> 4110859
B69: SPANISH ARMS — equity pay-in (close: | D69: =SA_ResynDate -> 46357 | E69: Total equity: | F69: =F28 -> 5117769.8
B70: Milestone | C70: Month # | D70: % of Equity | E70: $ Amount
B71: Closing | C71: 1 | D71: 0.2 | E71: =D71*$F$28 -> 1023554
B72: Construction completion | C72: 18 | D72: 0.5 | E72: =D72*$F$28 -> 2558884.9
B73: Stabilization / 8609s | C73: 24 | D73: 0.3 | E73: =D73*$F$28 -> 1535330.9
B74: (spare) | D74: 0 | E74: =D74*$F$28 -> 0
B75: (spare) | D75: 0 | E75: =D75*$F$28 -> 0
B76: (spare) | D76: 0 | E76: =D76*$F$28 -> 0
B77: Total | C77: =IF(ABS(D77-1)<0.0001,"OK","MUST = 100%") -> OK | D77: =SUM(D71:D76) -> 1 | E77: =SUM(E71:E76) -> 5117769.8

Sheet Bridge Period
A1: BRIDGE PERIOD — ACQUISITION TO RESYNDICATION CLOSE (assumed debt, current rents + OCAF)
B2: Cumulative bridge cash flow can be NEGATIVE (Clear Horizons runs negative at current NOI) — it feeds the Max Price Solver as carry cost (spec Sec. 5.7). Revenue at executed HUD schedule rents with OCAF anniversaries; expenses at actual 2026-budget basis trended; reserves deposited; debt service at note terms. | K2: Portfolio bridge CF: | L2: =SUM(CH_BridgeCF,NZ_BridgeCF,LOM_BridgeCF,SA_BridgeCF) -> 292087.4
B4: CLEAR HORIZONS — acquisition to close | H4: =CH_AcqDate -> 46357 | I4: =CH_ResynDate -> 46753 | J4: P&I/mo: | K4: 8496.64
B5: Quarter | C5: Q1 | D5: Q2 | E5: Q3 | F5: Q4 | G5: Q5 | H5: Q6 | I5: Q7 | J5: Q8 | K5: Q9 | L5: TOTAL
B6: Quarter start | C6: =EDATE(CH_AcqDate,0) -> 46357 | D6: =EDATE(CH_AcqDate,3) -> 46447 | E6: =EDATE(CH_AcqDate,6) -> 46539 | F6: =EDATE(CH_AcqDate,9) -> 46631 | G6: =EDATE(CH_AcqDate,12) -> 46722 | H6: =EDATE(CH_AcqDate,15) -> 46813 | I6: =EDATE(CH_AcqDate,18) -> 46905 | J6: =EDATE(CH_AcqDate,21) -> 46997 | K6: =EDATE(CH_AcqDate,24) -> 47088
B7: Months in quarter (to close) | C7: =MAX(0,MIN(3,CH_BridgeMonths-0)) -> 3 | D7: =MAX(0,MIN(3,CH_BridgeMonths-3)) -> 3 | E7: =MAX(0,MIN(3,CH_BridgeMonths-6)) -> 3 | F7: =MAX(0,MIN(3,CH_BridgeMonths-9)) -> 3 | G7: =MAX(0,MIN(3,CH_BridgeMonths-12)) -> 1 | H7: =MAX(0,MIN(3,CH_BridgeMonths-15)) -> 0 | I7: =MAX(0,MIN(3,CH_BridgeMonths-18)) -> 0 | J7: =MAX(0,MIN(3,CH_BridgeMonths-21)) -> 0 | K7: =MAX(0,MIN(3,CH_BridgeMonths-24)) -> 0 | L7: =SUM(C7:K7) -> 13
B8: OCAF anniversaries since schedule | C8: =ROUNDDOWN(YEARFRAC(CH_SchedDate,C6),0) -> 0 | D8: =ROUNDDOWN(YEARFRAC(CH_SchedDate,D6),0) -> 0 | E8: =ROUNDDOWN(YEARFRAC(CH_SchedDate,E6),0) -> 0 | F8: =ROUNDDOWN(YEARFRAC(CH_SchedDate,F6),0) -> 1 | G8: =ROUNDDOWN(YEARFRAC(CH_SchedDate,G6),0) -> 1 | H8: =ROUNDDOWN(YEARFRAC(CH_SchedDate,H6),0) -> 1 | I8: =ROUNDDOWN(YEARFRAC(CH_SchedDate,I6),0) -> 1 | J8: =ROUNDDOWN(YEARFRAC(CH_SchedDate,J6),0) -> 2 | K8: =ROUNDDOWN(YEARFRAC(CH_SchedDate,K6),0) -> 2
B9: GPR / month (schedule + OCAF) | C9: =(CH_CurMonthly)*IF(C8<=0,1,(1+CH_Y1OCAF*OCAFHaircut)*(1+OCAF*OCAFHaircut)^(C8-1)) -> 86752 | D9: =(CH_CurMonthly)*IF(D8<=0,1,(1+CH_Y1OCAF*OCAFHaircut)*(1+OCAF*OCAFHaircut)^(D8-1)) -> 86752 | E9: =(CH_CurMonthly)*IF(E8<=0,1,(1+CH_Y1OCAF*OCAFHaircut)*(1+OCAF*OCAFHaircut)^(E8-1)) -> 86752 | F9: =(CH_CurMonthly)*IF(F8<=0,1,(1+CH_Y1OCAF*OCAFHaircut)*(1+OCAF*OCAFHaircut)^(F8-1)) -> 88378.6 | G9: =(CH_CurMonthly)*IF(G8<=0,1,(1+CH_Y1OCAF*OCAFHaircut)*(1+OCAF*OCAFHaircut)^(G8-1)) -> 88378.6 | H9: =(CH_CurMonthly)*IF(H8<=0,1,(1+CH_Y1OCAF*OCAFHaircut)*(1+OCAF*OCAFHaircut)^(H8-1)) -> 88378.6 | I9: =(CH_CurMonthly)*IF(I8<=0,1,(1+CH_Y1OCAF*OCAFHaircut)*(1+OCAF*OCAFHaircut)^(I8-1)) -> 88378.6 | J9: =(CH_CurMonthly)*IF(J8<=0,1,(1+CH_Y1OCAF*OCAFHaircut)*(1+OCAF*OCAFHaircut)^(J8-1)) -> 90035.699 | K9: =(CH_CurMonthly)*IF(K8<=0,1,(1+CH_Y1OCAF*OCAFHaircut)*(1+OCAF*OCAFHaircut)^(K8-1)) -> 90035.699
B10: Revenue (net of vacancy + other inc) | C10: =(C9*(1-CH_VacHAP)+CH_OtherInc/12)*C7 -> 254238.61 | D10: =(D9*(1-CH_VacHAP)+CH_OtherInc/12)*D7 -> 254238.61 | E10: =(E9*(1-CH_VacHAP)+CH_OtherInc/12)*E7 -> 254238.61 | F10: =(F9*(1-CH_VacHAP)+CH_OtherInc/12)*F7 -> 258944.2 | G10: =(G9*(1-CH_VacHAP)+CH_OtherInc/12)*G7 -> 86314.734 | H10: =(H9*(1-CH_VacHAP)+CH_OtherInc/12)*H7 -> 0 | I10: =(I9*(1-CH_VacHAP)+CH_OtherInc/12)*I7 -> 0 | J10: =(J9*(1-CH_VacHAP)+CH_OtherInc/12)*J7 -> 0 | K10: =(K9*(1-CH_VacHAP)+CH_OtherInc/12)*K7 -> 0 | L10: =SUM(C10:K10) -> 1107974.8
B11: Operating expenses (actual basis) | C11: =-'Expense Detail'!$D$40/12*C7*(1+ExpGrowth)^(0/12) -> -233416 | D11: =-'Expense Detail'!$D$40/12*D7*(1+ExpGrowth)^(3/12) -> -235147.26 | E11: =-'Expense Detail'!$D$40/12*E7*(1+ExpGrowth)^(6/12) -> -236891.37 | F11: =-'Expense Detail'!$D$40/12*F7*(1+ExpGrowth)^(9/12) -> -238648.41 | G11: =-'Expense Detail'!$D$40/12*G7*(1+ExpGrowth)^(12/12) -> -80139.493 | H11: =-'Expense Detail'!$D$40/12*H7*(1+ExpGrowth)^(15/12) -> 0 | I11: =-'Expense Detail'!$D$40/12*I7*(1+ExpGrowth)^(18/12) -> 0 | J11: =-'Expense Detail'!$D$40/12*J7*(1+ExpGrowth)^(21/12) -> 0 | K11: =-'Expense Detail'!$D$40/12*K7*(1+ExpGrowth)^(24/12) -> 0 | L11: =SUM(C11:K11) -> -1024242.5
B12: Replacement reserve deposits | C12: =-'Expense Detail'!$D$41/12*C7 -> -4734.25 | D12: =-'Expense Detail'!$D$41/12*D7 -> -4734.25 | E12: =-'Expense Detail'!$D$41/12*E7 -> -4734.25 | F12: =-'Expense Detail'!$D$41/12*F7 -> -4734.25 | G12: =-'Expense Detail'!$D$41/12*G7 -> -1578.0833 | H12: =-'Expense Detail'!$D$41/12*H7 -> 0 | I12: =-'Expense Detail'!$D$41/12*I7 -> 0 | J12: =-'Expense Detail'!$D$41/12*J7 -> 0 | K12: =-'Expense Detail'!$D$41/12*K7 -> 0 | L12: =SUM(C12:K12) -> -20515.083
B13: NOI (after reserves) | C13: =SUM(C10:C12) -> 16088.361 | D13: =SUM(D10:D12) -> 14357.098 | E13: =SUM(E10:E12) -> 12612.993 | F13: =SUM(F10:F12) -> 15561.544 | G13: =SUM(G10:G12) -> 4597.1573 | H13: =SUM(H10:H12) -> 0 | I13: =SUM(I10:I12) -> 0 | J13: =SUM(J10:J12) -> 0 | K13: =SUM(K10:K12) -> 0 | L13: =SUM(C13:K13) -> 63217.153
B14: Assumed debt service | C14: =-CH_NotePI*C7 -> -25489.92 | D14: =-CH_NotePI*D7 -> -25489.92 | E14: =-CH_NotePI*E7 -> -25489.92 | F14: =-CH_NotePI*F7 -> -25489.92 | G14: =-CH_NotePI*G7 -> -8496.64 | H14: =-CH_NotePI*H7 -> 0 | I14: =-CH_NotePI*I7 -> 0 | J14: =-CH_NotePI*J7 -> 0 | K14: =-CH_NotePI*K7 -> 0 | L14: =SUM(C14:K14) -> -110456.32
B15: Net cash flow | C15: =C13+C14 -> -9401.5592 | D15: =D13+D14 -> -11132.822 | E15: =E13+E14 -> -12876.927 | F15: =F13+F14 -> -9928.3757 | G15: =G13+G14 -> -3899.4827 | H15: =H13+H14 -> 0 | I15: =I13+I14 -> 0 | J15: =J13+J14 -> 0 | K15: =K13+K14 -> 0 | L15: =SUM(C15:K15) -> -47239.167
B16: Cumulative cash flow | C16: =C15 -> -9401.5592 | D16: =D15+C16 -> -20534.382 | E16: =E15+D16 -> -33411.308 | F16: =F15+E16 -> -43339.684 | G16: =G15+F16 -> -47239.167 | H16: =H15+G16 -> -47239.167 | I16: =I15+H16 -> -47239.167 | J16: =J15+I16 -> -47239.167 | K16: =K15+J16 -> -47239.167
B17: Bridge DSCR (period total) | L17: =IF(L14=0,"n/a",-L13/L14) -> 0.57232717
B20: NEW ZION — acquisition to close | H20: =NZ_AcqDate -> 46357 | I20: =NZ_ResynDate -> 47119 | J20: P&I/mo: | K20: 15212.08
B21: Quarter | C21: Q1 | D21: Q2 | E21: Q3 | F21: Q4 | G21: Q5 | H21: Q6 | I21: Q7 | J21: Q8 | K21: Q9 | L21: TOTAL
B22: Quarter start | C22: =EDATE(NZ_AcqDate,0) -> 46357 | D22: =EDATE(NZ_AcqDate,3) -> 46447 | E22: =EDATE(NZ_AcqDate,6) -> 46539 | F22: =EDATE(NZ_AcqDate,9) -> 46631 | G22: =EDATE(NZ_AcqDate,12) -> 46722 | H22: =EDATE(NZ_AcqDate,15) -> 46813 | I22: =EDATE(NZ_AcqDate,18) -> 46905 | J22: =EDATE(NZ_AcqDate,21) -> 46997 | K22: =EDATE(NZ_AcqDate,24) -> 47088
B23: Months in quarter (to close) | C23: =MAX(0,MIN(3,NZ_BridgeMonths-0)) -> 3 | D23: =MAX(0,MIN(3,NZ_BridgeMonths-3)) -> 3 | E23: =MAX(0,MIN(3,NZ_BridgeMonths-6)) -> 3 | F23: =MAX(0,MIN(3,NZ_BridgeMonths-9)) -> 3 | G23: =MAX(0,MIN(3,NZ_BridgeMonths-12)) -> 3 | H23: =MAX(0,MIN(3,NZ_BridgeMonths-15)) -> 3 | I23: =MAX(0,MIN(3,NZ_BridgeMonths-18)) -> 3 | J23: =MAX(0,MIN(3,NZ_BridgeMonths-21)) -> 3 | K23: =MAX(0,MIN(3,NZ_BridgeMonths-24)) -> 1 | L23: =SUM(C23:K23) -> 25
B24: OCAF anniversaries since schedule | C24: =ROUNDDOWN(YEARFRAC(NZ_SchedDate,C22),0) -> 0 | D24: =ROUNDDOWN(YEARFRAC(NZ_SchedDate,D22),0) -> 1 | E24: =ROUNDDOWN(YEARFRAC(NZ_SchedDate,E22),0) -> 1 | F24: =ROUNDDOWN(YEARFRAC(NZ_SchedDate,F22),0) -> 1 | G24: =ROUNDDOWN(YEARFRAC(NZ_SchedDate,G22),0) -> 1 | H24: =ROUNDDOWN(YEARFRAC(NZ_SchedDate,H22),0) -> 2 | I24: =ROUNDDOWN(YEARFRAC(NZ_SchedDate,I22),0) -> 2 | J24: =ROUNDDOWN(YEARFRAC(NZ_SchedDate,J22),0) -> 2 | K24: =ROUNDDOWN(YEARFRAC(NZ_SchedDate,K22),0) -> 2
B25: GPR / month (schedule + OCAF) | C25: =(NZ_CurMonthly)*IF(C24<=0,1,(1+NZ_Y1OCAF*OCAFHaircut)*(1+OCAF*OCAFHaircut)^(C24-1)) -> 97092 | D25: =(NZ_CurMonthly)*IF(D24<=0,1,(1+NZ_Y1OCAF*OCAFHaircut)*(1+OCAF*OCAFHaircut)^(D24-1)) -> 104228.26 | E25: =(NZ_CurMonthly)*IF(E24<=0,1,(1+NZ_Y1OCAF*OCAFHaircut)*(1+OCAF*OCAFHaircut)^(E24-1)) -> 104228.26 | F25: =(NZ_CurMonthly)*IF(F24<=0,1,(1+NZ_Y1OCAF*OCAFHaircut)*(1+OCAF*OCAFHaircut)^(F24-1)) -> 104228.26 | G25: =(NZ_CurMonthly)*IF(G24<=0,1,(1+NZ_Y1OCAF*OCAFHaircut)*(1+OCAF*OCAFHaircut)^(G24-1)) -> 104228.26 | H25: =(NZ_CurMonthly)*IF(H24<=0,1,(1+NZ_Y1OCAF*OCAFHaircut)*(1+OCAF*OCAFHaircut)^(H24-1)) -> 106182.54 | I25: =(NZ_CurMonthly)*IF(I24<=0,1,(1+NZ_Y1OCAF*OCAFHaircut)*(1+OCAF*OCAFHaircut)^(I24-1)) -> 106182.54 | J25: =(NZ_CurMonthly)*IF(J24<=0,1,(1+NZ_Y1OCAF*OCAFHaircut)*(1+OCAF*OCAFHaircut)^(J24-1)) -> 106182.54 | K25: =(NZ_CurMonthly)*IF(K24<=0,1,(1+NZ_Y1OCAF*OCAFHaircut)*(1+OCAF*OCAFHaircut)^(K24-1)) -> 106182.54
B26: Revenue (net of vacancy + other inc) | C26: =(C25*(1-NZ_VacHAP)+NZ_OtherInc/12)*C23 -> 289094.73 | D26: =(D25*(1-NZ_VacHAP)+NZ_OtherInc/12)*D23 -> 310075.34 | E26: =(E25*(1-NZ_VacHAP)+NZ_OtherInc/12)*E23 -> 310075.34 | F26: =(F25*(1-NZ_VacHAP)+NZ_OtherInc/12)*F23 -> 310075.34 | G26: =(G25*(1-NZ_VacHAP)+NZ_OtherInc/12)*G23 -> 310075.34 | H26: =(H25*(1-NZ_VacHAP)+NZ_OtherInc/12)*H23 -> 315820.92 | I26: =(I25*(1-NZ_VacHAP)+NZ_OtherInc/12)*I23 -> 315820.92 | J26: =(J25*(1-NZ_VacHAP)+NZ_OtherInc/12)*J23 -> 315820.92 | K26: =(K25*(1-NZ_VacHAP)+NZ_OtherInc/12)*K23 -> 105273.64 | L26: =SUM(C26:K26) -> 2582132.5
B27: Operating expenses (actual basis) | C27: =-'Expense Detail'!$D$80/12*C23*(1+ExpGrowth)^(0/12) -> -227847 | D27: =-'Expense Detail'!$D$80/12*D23*(1+ExpGrowth)^(3/12) -> -229536.96 | E27: =-'Expense Detail'!$D$80/12*E23*(1+ExpGrowth)^(6/12) -> -231239.45 | F27: =-'Expense Detail'!$D$80/12*F23*(1+ExpGrowth)^(9/12) -> -232954.57 | G27: =-'Expense Detail'!$D$80/12*G23*(1+ExpGrowth)^(12/12) -> -234682.41 | H27: =-'Expense Detail'!$D$80/12*H23*(1+ExpGrowth)^(15/12) -> -236423.07 | I27: =-'Expense Detail'!$D$80/12*I23*(1+ExpGrowth)^(18/12) -> -238176.63 | J27: =-'Expense Detail'!$D$80/12*J23*(1+ExpGrowth)^(21/12) -> -239943.21 | K27: =-'Expense Detail'!$D$80/12*K23*(1+ExpGrowth)^(24/12) -> -80574.294 | L27: =SUM(C27:K27) -> -1951377.6
B28: Replacement reserve deposits | C28: =-'Expense Detail'!$D$81/12*C23 -> -7620 | D28: =-'Expense Detail'!$D$81/12*D23 -> -7620 | E28: =-'Expense Detail'!$D$81/12*E23 -> -7620 | F28: =-'Expense Detail'!$D$81/12*F23 -> -7620 | G28: =-'Expense Detail'!$D$81/12*G23 -> -7620 | H28: =-'Expense Detail'!$D$81/12*H23 -> -7620 | I28: =-'Expense Detail'!$D$81/12*I23 -> -7620 | J28: =-'Expense Detail'!$D$81/12*J23 -> -7620 | K28: =-'Expense Detail'!$D$81/12*K23 -> -2540 | L28: =SUM(C28:K28) -> -63500
B29: NOI (after reserves) | C29: =SUM(C26:C28) -> 53627.73 | D29: =SUM(D26:D28) -> 72918.383 | E29: =SUM(E26:E28) -> 71215.891 | F29: =SUM(F26:F28) -> 69500.771 | G29: =SUM(G26:G28) -> 67772.93 | H29: =SUM(H26:H28) -> 71777.857 | I29: =SUM(I26:I28) -> 70024.29 | J29: =SUM(J26:J28) -> 68257.717 | K29: =SUM(K26:K28) -> 22159.347 | L29: =SUM(C29:K29) -> 567254.92
B30: Assumed debt service | C30: =-NZ_NotePI*C23 -> -45636.24 | D30: =-NZ_NotePI*D23 -> -45636.24 | E30: =-NZ_NotePI*E23 -> -45636.24 | F30: =-NZ_NotePI*F23 -> -45636.24 | G30: =-NZ_NotePI*G23 -> -45636.24 | H30: =-NZ_NotePI*H23 -> -45636.24 | I30: =-NZ_NotePI*I23 -> -45636.24 | J30: =-NZ_NotePI*J23 -> -45636.24 | K30: =-NZ_NotePI*K23 -> -15212.08 | L30: =SUM(C30:K30) -> -380302
B31: Net cash flow | C31: =C29+C30 -> 7991.49 | D31: =D29+D30 -> 27282.143 | E31: =E29+E30 -> 25579.651 | F31: =F29+F30 -> 23864.531 | G31: =G29+G30 -> 22136.69 | H31: =H29+H30 -> 26141.617 | I31: =I29+I30 -> 24388.05 | J31: =J29+J30 -> 22621.477 | K31: =K29+K30 -> 6947.267 | L31: =SUM(C31:K31) -> 186952.92
B32: Cumulative cash flow | C32: =C31 -> 7991.49 | D32: =D31+C32 -> 35273.633 | E32: =E31+D32 -> 60853.283 | F32: =F31+E32 -> 84717.814 | G32: =G31+F32 -> 106854.5 | H32: =H31+G32 -> 132996.12 | I32: =I31+H32 -> 157384.17 | J32: =J31+I32 -> 180005.65 | K32: =K31+J32 -> 186952.92
B33: Bridge DSCR (period total) | L33: =IF(L30=0,"n/a",-L29/L30) -> 1.4915907
B36: LIVE OAK MANOR — acquisition to close | H36: =LOM_AcqDate -> 46357 | I36: =LOM_ResynDate -> 47119 | J36: P&I/mo: | K36: 23834.39
B37: Quarter | C37: Q1 | D37: Q2 | E37: Q3 | F37: Q4 | G37: Q5 | H37: Q6 | I37: Q7 | J37: Q8 | K37: Q9 | L37: TOTAL
B38: Quarter start | C38: =EDATE(LOM_AcqDate,0) -> 46357 | D38: =EDATE(LOM_AcqDate,3) -> 46447 | E38: =EDATE(LOM_AcqDate,6) -> 46539 | F38: =EDATE(LOM_AcqDate,9) -> 46631 | G38: =EDATE(LOM_AcqDate,12) -> 46722 | H38: =EDATE(LOM_AcqDate,15) -> 46813 | I38: =EDATE(LOM_AcqDate,18) -> 46905 | J38: =EDATE(LOM_AcqDate,21) -> 46997 | K38: =EDATE(LOM_AcqDate,24) -> 47088
B39: Months in quarter (to close) | C39: =MAX(0,MIN(3,LOM_BridgeMonths-0)) -> 3 | D39: =MAX(0,MIN(3,LOM_BridgeMonths-3)) -> 3 | E39: =MAX(0,MIN(3,LOM_BridgeMonths-6)) -> 3 | F39: =MAX(0,MIN(3,LOM_BridgeMonths-9)) -> 3 | G39: =MAX(0,MIN(3,LOM_BridgeMonths-12)) -> 3 | H39: =MAX(0,MIN(3,LOM_BridgeMonths-15)) -> 3 | I39: =MAX(0,MIN(3,LOM_BridgeMonths-18)) -> 3 | J39: =MAX(0,MIN(3,LOM_BridgeMonths-21)) -> 3 | K39: =MAX(0,MIN(3,LOM_BridgeMonths-24)) -> 1 | L39: =SUM(C39:K39) -> 25
B40: OCAF anniversaries since schedule | C40: =ROUNDDOWN(YEARFRAC(LOM_SchedDate,C38),0) -> 0 | D40: =ROUNDDOWN(YEARFRAC(LOM_SchedDate,D38),0) -> 0 | E40: =ROUNDDOWN(YEARFRAC(LOM_SchedDate,E38),0) -> 1 | F40: =ROUNDDOWN(YEARFRAC(LOM_SchedDate,F38),0) -> 1 | G40: =ROUNDDOWN(YEARFRAC(LOM_SchedDate,G38),0) -> 1 | H40: =ROUNDDOWN(YEARFRAC(LOM_SchedDate,H38),0) -> 1 | I40: =ROUNDDOWN(YEARFRAC(LOM_SchedDate,I38),0) -> 2 | J40: =ROUNDDOWN(YEARFRAC(LOM_SchedDate,J38),0) -> 2 | K40: =ROUNDDOWN(YEARFRAC(LOM_SchedDate,K38),0) -> 2
B41: GPR / month (schedule + OCAF) | C41: =(LOM_CurMonthly)*IF(C40<=0,1,(1+LOM_Y1OCAF*OCAFHaircut)*(1+OCAF*OCAFHaircut)^(C40-1)) -> 130789 | D41: =(LOM_CurMonthly)*IF(D40<=0,1,(1+LOM_Y1OCAF*OCAFHaircut)*(1+OCAF*OCAFHaircut)^(D40-1)) -> 130789 | E41: =(LOM_CurMonthly)*IF(E40<=0,1,(1+LOM_Y1OCAF*OCAFHaircut)*(1+OCAF*OCAFHaircut)^(E40-1)) -> 133241.29 | F41: =(LOM_CurMonthly)*IF(F40<=0,1,(1+LOM_Y1OCAF*OCAFHaircut)*(1+OCAF*OCAFHaircut)^(F40-1)) -> 133241.29 | G41: =(LOM_CurMonthly)*IF(G40<=0,1,(1+LOM_Y1OCAF*OCAFHaircut)*(1+OCAF*OCAFHaircut)^(G40-1)) -> 133241.29 | H41: =(LOM_CurMonthly)*IF(H40<=0,1,(1+LOM_Y1OCAF*OCAFHaircut)*(1+OCAF*OCAFHaircut)^(H40-1)) -> 133241.29 | I41: =(LOM_CurMonthly)*IF(I40<=0,1,(1+LOM_Y1OCAF*OCAFHaircut)*(1+OCAF*OCAFHaircut)^(I40-1)) -> 135739.57 | J41: =(LOM_CurMonthly)*IF(J40<=0,1,(1+LOM_Y1OCAF*OCAFHaircut)*(1+OCAF*OCAFHaircut)^(J40-1)) -> 135739.57 | K41: =(LOM_CurMonthly)*IF(K40<=0,1,(1+LOM_Y1OCAF*OCAFHaircut)*(1+OCAF*OCAFHaircut)^(K40-1)) -> 135739.57
B42: Revenue (net of vacancy + other inc) | C42: =(C41*(1-LOM_VacHAP)+LOM_OtherInc/12)*C39 -> 365887.05 | D42: =(D41*(1-LOM_VacHAP)+LOM_OtherInc/12)*D39 -> 365887.05 | E42: =(E41*(1-LOM_VacHAP)+LOM_OtherInc/12)*E39 -> 372687.76 | F42: =(F41*(1-LOM_VacHAP)+LOM_OtherInc/12)*F39 -> 372687.76 | G42: =(G41*(1-LOM_VacHAP)+LOM_OtherInc/12)*G39 -> 372687.76 | H42: =(H41*(1-LOM_VacHAP)+LOM_OtherInc/12)*H39 -> 372687.76 | I42: =(I41*(1-LOM_VacHAP)+LOM_OtherInc/12)*I39 -> 379615.97 | J42: =(J41*(1-LOM_VacHAP)+LOM_OtherInc/12)*J39 -> 379615.97 | K42: =(K41*(1-LOM_VacHAP)+LOM_OtherInc/12)*K39 -> 126538.66 | L42: =SUM(C42:K42) -> 3108295.7
B43: Operating expenses (actual basis) | C43: =-'Expense Detail'!$D$120/12*C39*(1+ExpGrowth)^(0/12) -> -272731.5 | D43: =-'Expense Detail'!$D$120/12*D39*(1+ExpGrowth)^(3/12) -> -274754.37 | E43: =-'Expense Detail'!$D$120/12*E39*(1+ExpGrowth)^(6/12) -> -276792.24 | F43: =-'Expense Detail'!$D$120/12*F39*(1+ExpGrowth)^(9/12) -> -278845.23 | G43: =-'Expense Detail'!$D$120/12*G39*(1+ExpGrowth)^(12/12) -> -280913.45 | H43: =-'Expense Detail'!$D$120/12*H39*(1+ExpGrowth)^(15/12) -> -282997 | I43: =-'Expense Detail'!$D$120/12*I39*(1+ExpGrowth)^(18/12) -> -285096.01 | J43: =-'Expense Detail'!$D$120/12*J39*(1+ExpGrowth)^(21/12) -> -287210.59 | K43: =-'Expense Detail'!$D$120/12*K39*(1+ExpGrowth)^(24/12) -> -96446.949 | L43: =SUM(C43:K43) -> -2335787.3
B44: Replacement reserve deposits | C44: =-'Expense Detail'!$D$121/12*C39 -> -2913 | D44: =-'Expense Detail'!$D$121/12*D39 -> -2913 | E44: =-'Expense Detail'!$D$121/12*E39 -> -2913 | F44: =-'Expense Detail'!$D$121/12*F39 -> -2913 | G44: =-'Expense Detail'!$D$121/12*G39 -> -2913 | H44: =-'Expense Detail'!$D$121/12*H39 -> -2913 | I44: =-'Expense Detail'!$D$121/12*I39 -> -2913 | J44: =-'Expense Detail'!$D$121/12*J39 -> -2913 | K44: =-'Expense Detail'!$D$121/12*K39 -> -971 | L44: =SUM(C44:K44) -> -24275
B45: NOI (after reserves) | C45: =SUM(C42:C44) -> 90242.555 | D45: =SUM(D42:D44) -> 88219.686 | E45: =SUM(E42:E44) -> 92982.514 | F45: =SUM(F42:F44) -> 90929.526 | G45: =SUM(G42:G44) -> 88861.311 | H45: =SUM(H42:H44) -> 86777.756 | I45: =SUM(I42:I44) -> 91606.961 | J45: =SUM(J42:J44) -> 89492.383 | K45: =SUM(K42:K44) -> 29120.707 | L45: =SUM(C45:K45) -> 748233.4
B46: Assumed debt service | C46: =-LOM_NotePI*C39 -> -71503.17 | D46: =-LOM_NotePI*D39 -> -71503.17 | E46: =-LOM_NotePI*E39 -> -71503.17 | F46: =-LOM_NotePI*F39 -> -71503.17 | G46: =-LOM_NotePI*G39 -> -71503.17 | H46: =-LOM_NotePI*H39 -> -71503.17 | I46: =-LOM_NotePI*I39 -> -71503.17 | J46: =-LOM_NotePI*J39 -> -71503.17 | K46: =-LOM_NotePI*K39 -> -23834.39 | L46: =SUM(C46:K46) -> -595859.75
B47: Net cash flow | C47: =C45+C46 -> 18739.385 | D47: =D45+D46 -> 16716.516 | E47: =E45+E46 -> 21479.344 | F47: =F45+F46 -> 19426.356 | G47: =G45+G46 -> 17358.141 | H47: =H45+H46 -> 15274.586 | I47: =I45+I46 -> 20103.791 | J47: =J45+J46 -> 17989.213 | K47: =K45+K46 -> 5286.3172 | L47: =SUM(C47:K47) -> 152373.65
B48: Cumulative cash flow | C48: =C47 -> 18739.385 | D48: =D47+C48 -> 35455.9 | E48: =E47+D48 -> 56935.244 | F48: =F47+E48 -> 76361.6 | G48: =G47+F48 -> 93719.741 | H48: =H47+G48 -> 108994.33 | I48: =I47+H48 -> 129098.12 | J48: =J47+I48 -> 147087.33 | K48: =K47+J48 -> 152373.65
B49: Bridge DSCR (period total) | L49: =IF(L46=0,"n/a",-L45/L46) -> 1.2557207
B52: SPANISH ARMS — acquisition to close | H52: =SA_AcqDate -> 46357 | I52: =SA_ResynDate -> 46357 | J52: P&I/mo: | K52: 44732.88
B53: Quarter | C53: Q1 | D53: Q2 | E53: Q3 | F53: Q4 | G53: Q5 | H53: Q6 | I53: Q7 | J53: Q8 | K53: Q9 | L53: TOTAL
B54: Quarter start | C54: =EDATE(SA_AcqDate,0) -> 46357 | D54: =EDATE(SA_AcqDate,3) -> 46447 | E54: =EDATE(SA_AcqDate,6) -> 46539 | F54: =EDATE(SA_AcqDate,9) -> 46631 | G54: =EDATE(SA_AcqDate,12) -> 46722 | H54: =EDATE(SA_AcqDate,15) -> 46813 | I54: =EDATE(SA_AcqDate,18) -> 46905 | J54: =EDATE(SA_AcqDate,21) -> 46997 | K54: =EDATE(SA_AcqDate,24) -> 47088
B55: Months in quarter (to close) | C55: =MAX(0,MIN(3,SA_BridgeMonths-0)) -> 0 | D55: =MAX(0,MIN(3,SA_BridgeMonths-3)) -> 0 | E55: =MAX(0,MIN(3,SA_BridgeMonths-6)) -> 0 | F55: =MAX(0,MIN(3,SA_BridgeMonths-9)) -> 0 | G55: =MAX(0,MIN(3,SA_BridgeMonths-12)) -> 0 | H55: =MAX(0,MIN(3,SA_BridgeMonths-15)) -> 0 | I55: =MAX(0,MIN(3,SA_BridgeMonths-18)) -> 0 | J55: =MAX(0,MIN(3,SA_BridgeMonths-21)) -> 0 | K55: =MAX(0,MIN(3,SA_BridgeMonths-24)) -> 0 | L55: =SUM(C55:K55) -> 0
B56: OCAF anniversaries since schedule | C56: =ROUNDDOWN(YEARFRAC(SA_SchedDate,C54),0) -> 0 | D56: =ROUNDDOWN(YEARFRAC(SA_SchedDate,D54),0) -> 0 | E56: =ROUNDDOWN(YEARFRAC(SA_SchedDate,E54),0) -> 1 | F56: =ROUNDDOWN(YEARFRAC(SA_SchedDate,F54),0) -> 1 | G56: =ROUNDDOWN(YEARFRAC(SA_SchedDate,G54),0) -> 1 | H56: =ROUNDDOWN(YEARFRAC(SA_SchedDate,H54),0) -> 1 | I56: =ROUNDDOWN(YEARFRAC(SA_SchedDate,I54),0) -> 2 | J56: =ROUNDDOWN(YEARFRAC(SA_SchedDate,J54),0) -> 2 | K56: =ROUNDDOWN(YEARFRAC(SA_SchedDate,K54),0) -> 2
B57: GPR / month (schedule + OCAF) | C57: =(SA_CurMonthly)*IF(C56<=0,1,(1+SA_Y1OCAF*OCAFHaircut)*(1+OCAF*OCAFHaircut)^(C56-1)) -> 180528.84 | D57: =(SA_CurMonthly)*IF(D56<=0,1,(1+SA_Y1OCAF*OCAFHaircut)*(1+OCAF*OCAFHaircut)^(D56-1)) -> 180528.84 | E57: =(SA_CurMonthly)*IF(E56<=0,1,(1+SA_Y1OCAF*OCAFHaircut)*(1+OCAF*OCAFHaircut)^(E56-1)) -> 183913.76 | F57: =(SA_CurMonthly)*IF(F56<=0,1,(1+SA_Y1OCAF*OCAFHaircut)*(1+OCAF*OCAFHaircut)^(F56-1)) -> 183913.76 | G57: =(SA_CurMonthly)*IF(G56<=0,1,(1+SA_Y1OCAF*OCAFHaircut)*(1+OCAF*OCAFHaircut)^(G56-1)) -> 183913.76 | H57: =(SA_CurMonthly)*IF(H56<=0,1,(1+SA_Y1OCAF*OCAFHaircut)*(1+OCAF*OCAFHaircut)^(H56-1)) -> 183913.76 | I57: =(SA_CurMonthly)*IF(I56<=0,1,(1+SA_Y1OCAF*OCAFHaircut)*(1+OCAF*OCAFHaircut)^(I56-1)) -> 187362.14 | J57: =(SA_CurMonthly)*IF(J56<=0,1,(1+SA_Y1OCAF*OCAFHaircut)*(1+OCAF*OCAFHaircut)^(J56-1)) -> 187362.14 | K57: =(SA_CurMonthly)*IF(K56<=0,1,(1+SA_Y1OCAF*OCAFHaircut)*(1+OCAF*OCAFHaircut)^(K56-1)) -> 187362.14
B58: Revenue (net of vacancy + other inc) | C58: =(C57*(1-SA_VacHAP)+SA_OtherInc/12)*C55 -> 0 | D58: =(D57*(1-SA_VacHAP)+SA_OtherInc/12)*D55 -> 0 | E58: =(E57*(1-SA_VacHAP)+SA_OtherInc/12)*E55 -> 0 | F58: =(F57*(1-SA_VacHAP)+SA_OtherInc/12)*F55 -> 0 | G58: =(G57*(1-SA_VacHAP)+SA_OtherInc/12)*G55 -> 0 | H58: =(H57*(1-SA_VacHAP)+SA_OtherInc/12)*H55 -> 0 | I58: =(I57*(1-SA_VacHAP)+SA_OtherInc/12)*I55 -> 0 | J58: =(J57*(1-SA_VacHAP)+SA_OtherInc/12)*J55 -> 0 | K58: =(K57*(1-SA_VacHAP)+SA_OtherInc/12)*K55 -> 0 | L58: =SUM(C58:K58) -> 0
B59: Operating expenses (actual basis) | C59: =-'Expense Detail'!$D$160/12*C55*(1+ExpGrowth)^(0/12) -> 0 | D59: =-'Expense Detail'!$D$160/12*D55*(1+ExpGrowth)^(3/12) -> 0 | E59: =-'Expense Detail'!$D$160/12*E55*(1+ExpGrowth)^(6/12) -> 0 | F59: =-'Expense Detail'!$D$160/12*F55*(1+ExpGrowth)^(9/12) -> 0 | G59: =-'Expense Detail'!$D$160/12*G55*(1+ExpGrowth)^(12/12) -> 0 | H59: =-'Expense Detail'!$D$160/12*H55*(1+ExpGrowth)^(15/12) -> 0 | I59: =-'Expense Detail'!$D$160/12*I55*(1+ExpGrowth)^(18/12) -> 0 | J59: =-'Expense Detail'!$D$160/12*J55*(1+ExpGrowth)^(21/12) -> 0 | K59: =-'Expense Detail'!$D$160/12*K55*(1+ExpGrowth)^(24/12) -> 0 | L59: =SUM(C59:K59) -> 0
B60: Replacement reserve deposits | C60: =-'Expense Detail'!$D$161/12*C55 -> 0 | D60: =-'Expense Detail'!$D$161/12*D55 -> 0 | E60: =-'Expense Detail'!$D$161/12*E55 -> 0 | F60: =-'Expense Detail'!$D$161/12*F55 -> 0 | G60: =-'Expense Detail'!$D$161/12*G55 -> 0 | H60: =-'Expense Detail'!$D$161/12*H55 -> 0 | I60: =-'Expense Detail'!$D$161/12*I55 -> 0 | J60: =-'Expense Detail'!$D$161/12*J55 -> 0 | K60: =-'Expense Detail'!$D$161/12*K55 -> 0 | L60: =SUM(C60:K60) -> 0
B61: NOI (after reserves) | C61: =SUM(C58:C60) -> 0 | D61: =SUM(D58:D60) -> 0 | E61: =SUM(E58:E60) -> 0 | F61: =SUM(F58:F60) -> 0 | G61: =SUM(G58:G60) -> 0 | H61: =SUM(H58:H60) -> 0 | I61: =SUM(I58:I60) -> 0 | J61: =SUM(J58:J60) -> 0 | K61: =SUM(K58:K60) -> 0 | L61: =SUM(C61:K61) -> 0
B62: Assumed debt service | C62: =-SA_NotePI*C55 -> 0 | D62: =-SA_NotePI*D55 -> 0 | E62: =-SA_NotePI*E55 -> 0 | F62: =-SA_NotePI*F55 -> 0 | G62: =-SA_NotePI*G55 -> 0 | H62: =-SA_NotePI*H55 -> 0 | I62: =-SA_NotePI*I55 -> 0 | J62: =-SA_NotePI*J55 -> 0 | K62: =-SA_NotePI*K55 -> 0 | L62: =SUM(C62:K62) -> 0
B63: Net cash flow | C63: =C61+C62 -> 0 | D63: =D61+D62 -> 0 | E63: =E61+E62 -> 0 | F63: =F61+F62 -> 0 | G63: =G61+G62 -> 0 | H63: =H61+H62 -> 0 | I63: =I61+I62 -> 0 | J63: =J61+J62 -> 0 | K63: =K61+K62 -> 0 | L63: =SUM(C63:K63) -> 0
B64: Cumulative cash flow | C64: =C63 -> 0 | D64: =D63+C64 -> 0 | E64: =E63+D64 -> 0 | F64: =F63+E64 -> 0 | G64: =G63+F64 -> 0 | H64: =H63+G64 -> 0 | I64: =I63+H64 -> 0 | J64: =J63+I64 -> 0 | K64: =K63+J64 -> 0
B65: Bridge DSCR (period total) | L65: =IF(L62=0,"n/a",-L61/L62) -> n/a
B66: Spanish Arms resyndicates at acquisition — 0-month bridge by design.

Sheet Financing Assumptions
A1: FINANCING ASSUMPTIONS — ASSUMED DEBT & RESYNDICATION PERM
B2: Module A: actual note terms per DD loan documents (Gap #3 resolved). Module B: refi perm sizing at TargetReturn DSCR and LTV cap. Module C: strategy toggle — the assumable-rate arbitrage is shown side-by-side, not buried (spec Sec. 5.9).
B3: MODULE A — ASSUMED 221(d)(4) DEBT | C3: Clear Horizons | D3: New Zion | E3: Live Oak Manor | F3: Spanish Arms
B4: Lender / program | C4: Centerline / FHA 221(d)(4) | D4: Highland / FHA 221(d)(4) | E4: Highland / FHA 221(d)(4) (bond-funded) | F4: Prudential Huntoon Paige / FHA (2007 bonds)
B5: Original principal | C5: 2450000 | D5: 4200000 | E5: 6500000 | F5: 8770000
B6: Note rate (current) | C6: 0.027 | D6: 0.0289 | E6: 0.0315 | F6: 0.0564
B7: Monthly P&I | C7: =CH_NotePI -> 8496.64 | D7: =NZ_NotePI -> 15212.08 | E7: =LOM_NotePI -> 23834.39 | F7: =SA_NotePI -> 44732.88
B8: Maturity | C8: 56189 | D8: 56615 | E8: 56340 | F8: 54483
B9: Balance per 5/31/26 balance sheet | C9: 1977565.4 | D9: 3555182.8 | E9: 4755915.1 | F9: 6554391.7
B10: Est. balance at acquisition (12/1/26) | C10: =FV(C6/12,6,C7,-C9) -> 1953145.7 | D10: =FV(D6/12,6,D7,-D9) -> 3515041.7 | E10: =FV(E6/12,6,E7,-E9) -> 4687365.9 | F10: =FV(F6/12,6,F7,-F9) -> 6469840.3
B11: Est. balance at resyndication close | C11: =FV(C6/12,CH_BridgeMonths,C7,-C10) -> 1899093.1 | D11: =FV(D6/12,NZ_BridgeMonths,D7,-D10) -> 3341408.8 | E11: =FV(E6/12,LOM_BridgeMonths,E7,-E10) -> 4389849.3 | F11: =FV(F6/12,SA_BridgeMonths,F7,-F10) -> 6469840.3
B12: Annual assumed debt service | C12: =12*C7 -> 101959.68 | D12: =12*D7 -> 182544.96 | E12: =12*E7 -> 286012.68 | F12: =12*F7 -> 536794.56
B13: Prepayment terms | C13: 6% premium through 3/31/27, declining 1%/yr; 0% from 4/1/2032 | D13: 6% premium through 2/28/27, declining 1%/yr; 0% from 3/1/2032 | E13: Freely prepayable now (premiums ended 5/1/2024), 30 days notice | F13: Freely prepayable now (premiums ended 2/28/2017), 30 days notice
B14: Assumption | C14: HUD TPA approval required | D14: HUD TPA approval required | E14: HUD TPA approval required | F14: HUD TPA approval required
B16: NZ HOME loan (subordinate soft debt) | D16: 1476484.6
B17: NZ HOME accrued interest (est. at close) | D17: 551000
B18: NZ HOME treatment at resyndication | D18: Repay at close
B20: MODULE B — RESYNDICATION PERM DEBT (refi)
B21: Stabilized Yr-1 NOI (close-year $) | C21: =CH_NOI -> 268347.6 | D21: =NZ_NOI -> 510296.49 | E21: =LOM_NOI -> 613095.87 | F21: =SA_NOI -> 725471.7
B22: Sizing DSCR | C22: =TargetReturn -> 1.15 | D22: =TargetReturn -> 1.15 | E22: =TargetReturn -> 1.15 | F22: =TargetReturn -> 1.15
B23: Mortgage constant | C23: =-PMT(PermRate/12,PermAmort*12,1)*12 -> 0.068422765 | D23: =-PMT(PermRate/12,PermAmort*12,1)*12 -> 0.068422765 | E23: =-PMT(PermRate/12,PermAmort*12,1)*12 -> 0.068422765 | F23: =-PMT(PermRate/12,PermAmort*12,1)*12 -> 0.068422765
B24: Max loan by DSCR | C24: =C21/(C22*C23) -> 3410352.4 | D24: =D21/(D22*D23) -> 6485211.1 | E24: =E21/(E22*E23) -> 7791658.8 | F24: =F21/(F22*F23) -> 9219810.9
B25: LTV cap $ (LTVCap x TDC proxy) | C25: =LTVCap*'Sources & Uses'!C26 -> 6237585.1 | D25: =LTVCap*'Sources & Uses'!D26 -> 9546113.5 | E25: =LTVCap*'Sources & Uses'!E26 -> 12263866 | F25: =LTVCap*'Sources & Uses'!F26 -> 14523218
B26: Perm loan (refi) | C26: =IF(C25="",C24,MIN(C24,C25)) -> 3410352.4 | D26: =IF(D25="",D24,MIN(D24,D25)) -> 6485211.1 | E26: =IF(E25="",E24,MIN(E24,E25)) -> 7791658.8 | F26: =IF(F25="",F24,MIN(F24,F25)) -> 9219810.9
B27: Perm annual debt service | C27: =C26*C23 -> 233345.74 | D27: =D26*D23 -> 443736.08 | E27: =E26*E23 -> 533126.84 | F27: =F26*F23 -> 630844.96
B28: Perm DSCR check | C28: =C21/C27 -> 1.15 | D28: =D21/D27 -> 1.15 | E28: =E21/E27 -> 1.15 | F28: =F21/F27 -> 1.15
B29: Financing fees % (orig + placement + legal) | C29: 0.015 | D29: 0.015 | E29: 0.015 | F29: 0.015
B30: Financing fees $ | C30: =C26*C29 -> 51155.286 | D30: =D26*D29 -> 97278.167 | E30: =E26*E29 -> 116874.88 | F30: =F26*F29 -> 138297.16
B32: MODULE C — STRATEGY TOGGLE & SIDE-BY-SIDE
B33: Debt strategy (Dashboard toggle) | C33: =DebtStrategy -> Refinance | D33: =DebtStrategy -> Refinance | E33: =DebtStrategy -> Refinance | F33: =DebtStrategy -> Refinance
B34: Proceeds — refinance | C34: =C26 -> 3410352.4 | D34: =D26 -> 6485211.1 | E34: =E26 -> 7791658.8 | F34: =F26 -> 9219810.9
B35: Proceeds — assume & hold (balance at close) | C35: =C11 -> 1899093.1 | D35: =D11 -> 3341408.8 | E35: =E11 -> 4389849.3 | F35: =F11 -> 6469840.3
B36: DSCR — refinance | C36: =C28 -> 1.15 | D36: =D28 -> 1.15 | E36: =E28 -> 1.15 | F36: =F28 -> 1.15
B37: DSCR — assume & hold | C37: =C21/C12 -> 2.6318992 | D37: =D21/D12 -> 2.7954565 | E37: =E21/E12 -> 2.1435968 | F37: =F21/F12 -> 1.3514885
B38: SELECTED perm proceeds at close | C38: =IF(DebtStrategy="Refinance",C34,C35) -> 3410352.4 | D38: =IF(DebtStrategy="Refinance",D34,D35) -> 6485211.1 | E38: =IF(DebtStrategy="Refinance",E34,E35) -> 7791658.8 | F38: =IF(DebtStrategy="Refinance",F34,F35) -> 9219810.9
B39: SELECTED annual debt service | C39: =IF(DebtStrategy="Refinance",C27,C12) -> 233345.74 | D39: =IF(DebtStrategy="Refinance",D27,D12) -> 443736.08 | E39: =IF(DebtStrategy="Refinance",E27,E12) -> 533126.84 | F39: =IF(DebtStrategy="Refinance",F27,F12) -> 630844.96
B40: SELECTED DSCR | C40: =C21/C39 -> 1.15 | D40: =D21/D39 -> 1.15 | E40: =E21/E39 -> 1.15 | F40: =F21/F39 -> 1.15
B42: Rate arbitrage note: CH/NZ/LOM notes carry 2.70%-3.15% vs ~6% market — assuming preserves cheap debt but yields lower proceeds; SA's documented 5.64% note rate offers NO arbitrage vs the OM's 4.01% claim.

Sheet CH - Pro Forma
A1: CASH FLOW FORECAST — CLEAR HORIZONS
B2: 20 years from this property's resyndication close. Rehab-period offline disruption per Rehab Scope; debt service per the amortization block below (strategy toggle on Dashboard). Equity pay-ins reference the Tax Credit Calc block — single source of truth.
B3: Year | D3: Yr 1 | E3: Yr 2 | F3: Yr 3 | G3: Yr 4 | H3: Yr 5 | I3: Yr 6 | J3: Yr 7 | K3: Yr 8 | L3: Yr 9 | M3: Yr 10 | N3: Yr 11 | O3: Yr 12 | P3: Yr 13 | Q3: Yr 14 | R3: Yr 15 | S3: Yr 16 | T3: Yr 17 | U3: Yr 18 | V3: Yr 19 | W3: Yr 20 | X3: TOTAL
B4: Calendar year | D4: =YEAR(CH_ResynDate)+0 -> 2028 | E4: =YEAR(CH_ResynDate)+1 -> 2029 | F4: =YEAR(CH_ResynDate)+2 -> 2030 | G4: =YEAR(CH_ResynDate)+3 -> 2031 | H4: =YEAR(CH_ResynDate)+4 -> 2032 | I4: =YEAR(CH_ResynDate)+5 -> 2033 | J4: =YEAR(CH_ResynDate)+6 -> 2034 | K4: =YEAR(CH_ResynDate)+7 -> 2035 | L4: =YEAR(CH_ResynDate)+8 -> 2036 | M4: =YEAR(CH_ResynDate)+9 -> 2037 | N4: =YEAR(CH_ResynDate)+10 -> 2038 | O4: =YEAR(CH_ResynDate)+11 -> 2039 | P4: =YEAR(CH_ResynDate)+12 -> 2040 | Q4: =YEAR(CH_ResynDate)+13 -> 2041 | R4: =YEAR(CH_ResynDate)+14 -> 2042 | S4: =YEAR(CH_ResynDate)+15 -> 2043 | T4: =YEAR(CH_ResynDate)+16 -> 2044 | U4: =YEAR(CH_ResynDate)+17 -> 2045 | V4: =YEAR(CH_ResynDate)+18 -> 2046 | W4: =YEAR(CH_ResynDate)+19 -> 2047
B6: Gross rental income | D6: =CH_GPR -> 1166597.5 | E6: =D6*(1+$D$50) -> 1188471.2 | F6: =E6*(1+$D$50) -> 1210755.1 | G6: =F6*(1+$D$50) -> 1233456.7 | H6: =G6*(1+$D$50) -> 1256584 | I6: =H6*(1+$D$50) -> 1280145 | J6: =I6*(1+$D$50) -> 1304147.7 | K6: =J6*(1+$D$50) -> 1328600.5 | L6: =K6*(1+$D$50) -> 1353511.7 | ... W6: =V6*(1+$D$50) -> 1660373.8
B7: Other income | D7: =CH_OtherInc -> 13095 | E7: =D7*(1+$D$50) -> 13340.531 | F7: =E7*(1+$D$50) -> 13590.666 | G7: =F7*(1+$D$50) -> 13845.491 | H7: =G7*(1+$D$50) -> 14105.094 | I7: =H7*(1+$D$50) -> 14369.565 | J7: =I7*(1+$D$50) -> 14638.994 | K7: =J7*(1+$D$50) -> 14913.475 | L7: =K7*(1+$D$50) -> 15193.103 | ... W7: =V7*(1+$D$50) -> 18637.614
B9: Gross revenue | D9: =SUM(D6:D7) -> 1179692.5 | E9: =SUM(E6:E7) -> 1201811.8 | F9: =SUM(F6:F7) -> 1224345.7 | G9: =SUM(G6:G7) -> 1247302.2 | H9: =SUM(H6:H7) -> 1270689.1 | I9: =SUM(I6:I7) -> 1294514.5 | J9: =SUM(J6:J7) -> 1318786.7 | K9: =SUM(K6:K7) -> 1343513.9 | ... W9: =SUM(W6:W7) -> 1679011.4 | X9: =SUM(D9:W9) -> 28309350
B10: Vacancy | D10: =-CH_VacHAP*D9 -> -42115.023 | E10: =-CH_VacHAP*E9 -> -42904.68 | F10: =-CH_VacHAP*F9 -> -43709.142 | G10: =-CH_VacHAP*G9 -> -44528.689 | H10: =-CH_VacHAP*H9 -> -45363.602 | I10: =-CH_VacHAP*I9 -> -46214.169 | J10: =-CH_VacHAP*J9 -> -47080.685 | K10: =-CH_VacHAP*K9 -> -47963.448 | ... W10: =-CH_VacHAP*W9 -> -59940.706
B11: Rehab offline adjustment | D11: =-D9*CH_OfflinePct*MAX(0,MIN(CH_RehabMonths-0,12))/12 -> -49153.855 | E11: =-E9*CH_OfflinePct*MAX(0,MIN(CH_RehabMonths-12,12))/12 -> 0 | F11: =-F9*CH_OfflinePct*MAX(0,MIN(CH_RehabMonths-24,12))/12 -> 0 | G11: =-G9*CH_OfflinePct*MAX(0,MIN(CH_RehabMonths-36,12))/12 -> 0 | H11: =-H9*CH_OfflinePct*MAX(0,MIN(CH_RehabMonths-48,12))/12 -> 0 | I11: =-I9*CH_OfflinePct*MAX(0,MIN(CH_RehabMonths-60,12))/12 -> 0 | J11: =-J9*CH_OfflinePct*MAX(0,MIN(CH_RehabMonths-72,12))/12 -> 0 | K11: =-K9*CH_OfflinePct*MAX(0,MIN(CH_RehabMonths-84,12))/12 -> 0 | L11: =-L9*CH_OfflinePct*MAX(0,MIN(CH_RehabMonths-96,12))/12 -> 0 | M11: =-M9*CH_OfflinePct*MAX(0,MIN(CH_RehabMonths-108,12))/12 -> 0 | N11: =-N9*CH_OfflinePct*MAX(0,MIN(CH_RehabMonths-120,12))/12 -> 0 | O11: =-O9*CH_OfflinePct*MAX(0,MIN(CH_RehabMonths-132,12))/12 -> 0 | P11: =-P9*CH_OfflinePct*MAX(0,MIN(CH_RehabMonths-144,12))/12 -> 0 | Q11: =-Q9*CH_OfflinePct*MAX(0,MIN(CH_RehabMonths-156,12))/12 -> 0 | R11: =-R9*CH_OfflinePct*MAX(0,MIN(CH_RehabMonths-168,12))/12 -> 0 | S11: =-S9*CH_OfflinePct*MAX(0,MIN(CH_RehabMonths-180,12))/12 -> 0 | T11: =-T9*CH_OfflinePct*MAX(0,MIN(CH_RehabMonths-192,12))/12 -> 0 | U11: =-U9*CH_OfflinePct*MAX(0,MIN(CH_RehabMonths-204,12))/12 -> 0 | V11: =-V9*CH_OfflinePct*MAX(0,MIN(CH_RehabMonths-216,12))/12 -> 0 | W11: =-W9*CH_OfflinePct*MAX(0,MIN(CH_RehabMonths-228,12))/12 -> 0
B13: Net revenue | D13: =D9+D10+D11 -> 1088423.6 | E13: =E9+E10+E11 -> 1158907.1 | F13: =F9+F10+F11 -> 1180636.6 | G13: =G9+G10+G11 -> 1202773.5 | H13: =H9+H10+H11 -> 1225325.5 | I13: =I9+I10+I11 -> 1248300.4 | J13: =J9+J10+J11 -> 1271706 | K13: =K9+K10+K11 -> 1295550.5 | ... W13: =W9+W10+W11 -> 1619070.7 | X13: =SUM(D13:W13) -> 27249553
B15: Operating Expenses
B16: Management fee | D16: =MgmtFeePct*D13 -> 43536.946 | E16: =MgmtFeePct*E13 -> 46356.283 | F16: =MgmtFeePct*F13 -> 47225.463 | G16: =MgmtFeePct*G13 -> 48110.941 | H16: =MgmtFeePct*H13 -> 49013.021 | I16: =MgmtFeePct*I13 -> 49932.015 | J16: =MgmtFeePct*J13 -> 50868.24 | K16: =MgmtFeePct*K13 -> 51822.02 | ... W16: =MgmtFeePct*W13 -> 64762.827
B17: Administrative (ex-mgmt) | D17: ='Rev+Expenses'!C19 -> 163492.12 | E17: =D17*(1+$D$51) -> 168396.88 | F17: =E17*(1+$D$51) -> 173448.79 | G17: =F17*(1+$D$51) -> 178652.25 | H17: =G17*(1+$D$51) -> 184011.82 | I17: =H17*(1+$D$51) -> 189532.17 | J17: =I17*(1+$D$51) -> 195218.14 | K17: =J17*(1+$D$51) -> 201074.68 | L17: =K17*(1+$D$51) -> 207106.92 | ... W17: =V17*(1+$D$51) -> 286684.42
B18: Utilities | D18: ='Rev+Expenses'!C20 -> 137600.85 | E18: =D18*(1+$D$51) -> 141728.88 | F18: =E18*(1+$D$51) -> 145980.74 | G18: =F18*(1+$D$51) -> 150360.17 | H18: =G18*(1+$D$51) -> 154870.97 | I18: =H18*(1+$D$51) -> 159517.1 | J18: =I18*(1+$D$51) -> 164302.61 | K18: =J18*(1+$D$51) -> 169231.69 | L18: =K18*(1+$D$51) -> 174308.64 | ... W18: =V18*(1+$D$51) -> 241283.93
B19: Operating & maintenance | D19: ='Rev+Expenses'!C21 -> 349669.46 | E19: =D19*(1+$D$51) -> 360159.54 | F19: =E19*(1+$D$51) -> 370964.33 | G19: =F19*(1+$D$51) -> 382093.26 | H19: =G19*(1+$D$51) -> 393556.05 | I19: =H19*(1+$D$51) -> 405362.74 | J19: =I19*(1+$D$51) -> 417523.62 | K19: =J19*(1+$D$51) -> 430049.33 | L19: =K19*(1+$D$51) -> 442950.81 | ... W19: =V19*(1+$D$51) -> 613147.51
B20: Taxes + other T&I (ex-insurance) | D20: ='Rev+Expenses'!C22 -> 74675.69 | E20: =D20*(1+$D$51) -> 76915.961 | F20: =E20*(1+$D$51) -> 79223.44 | G20: =F20*(1+$D$51) -> 81600.143 | H20: =G20*(1+$D$51) -> 84048.147 | I20: =H20*(1+$D$51) -> 86569.592 | J20: =I20*(1+$D$51) -> 89166.679 | K20: =J20*(1+$D$51) -> 91841.68 | L20: =K20*(1+$D$51) -> 94596.93 | ... W20: =V20*(1+$D$51) -> 130944.27
B21: Property insurance | D21: ='Rev+Expenses'!C23 -> 98737.474 | E21: =D21*(1+InsGrowth) -> 104661.72 | F21: =E21*(1+InsGrowth) -> 110941.43 | G21: =F21*(1+InsGrowth) -> 117597.91 | H21: =G21*(1+InsGrowth) -> 124653.79 | I21: =H21*(1+InsGrowth) -> 132133.01 | J21: =I21*(1+InsGrowth) -> 140060.99 | K21: =J21*(1+InsGrowth) -> 148464.65 | L21: =K21*(1+InsGrowth) -> 157372.53 | ... W21: =V21*(1+InsGrowth) -> 298740.05
B23: Total operating expenses | D23: =SUM(D16:D21) -> 867712.53 | E23: =SUM(E16:E21) -> 898219.26 | F23: =SUM(F16:F21) -> 927784.19 | G23: =SUM(G16:G21) -> 958414.67 | H23: =SUM(H16:H21) -> 990153.8 | I23: =SUM(I16:I21) -> 1023046.6 | J23: =SUM(J16:J21) -> 1057140.3 | K23: =SUM(K16:K21) -> 1092484.1 | ... W23: =SUM(W16:W21) -> 1635563 | X23: =SUM(D23:W23) -> 24214892
B25: NET OPERATING INCOME | D25: =D13-D23 -> 220711.11 | E25: =E13-E23 -> 260687.81 | F25: =F13-F23 -> 252852.4 | G25: =G13-G23 -> 244358.85 | H25: =H13-H23 -> 235171.73 | I25: =I13-I23 -> 225253.75 | J25: =J13-J23 -> 214565.73 | K25: =K13-K23 -> 203066.44 | ... W25: =W13-W23 -> -16492.334 | X25: =SUM(D25:W25) -> 3034660.5
B27: Replacement reserves | D27: =CH_ReservesStab -> 31190.46 | E27: =D27*(1+$D$51) -> 32126.174 | F27: =E27*(1+$D$51) -> 33089.959 | G27: =F27*(1+$D$51) -> 34082.658 | H27: =G27*(1+$D$51) -> 35105.138 | I27: =H27*(1+$D$51) -> 36158.292 | J27: =I27*(1+$D$51) -> 37243.04 | K27: =J27*(1+$D$51) -> 38360.332 | L27: =K27*(1+$D$51) -> 39511.142 | ... W27: =V27*(1+$D$51) -> 54692.66
B29: Debt service — interest | D29: =D59 -> 204621.14 | E29: =E59 -> 202897.67 | F29: =F59 -> 201070.78 | G29: =G59 -> 199134.28 | H29: =H59 -> 197081.6 | I29: =I59 -> 194905.75 | J29: =J59 -> 192599.35 | K29: =K59 -> 190154.57 | ... W29: =W59 -> 146436.61
B30: Debt service — principal | D30: =D60 -> 28724.597 | E30: =E60 -> 30448.072 | F30: =F60 -> 32274.957 | G30: =G60 -> 34211.454 | H30: =H60 -> 36264.141 | I30: =I60 -> 38439.99 | J30: =J60 -> 40746.389 | K30: =K60 -> 43191.173 | ... W30: =W60 -> 86909.125
B32: Cash flow after debt service | D32: =D25-D27-D29-D30 -> -43825.092 | E32: =E25-E27-E29-E30 -> -4784.1017 | F32: =F25-F27-F29-F30 -> -13583.301 | G32: =G25-G27-G29-G30 -> -23069.545 | H32: =H25-H27-H29-H30 -> -33279.151 | I32: =I25-I27-I29-I30 -> -44250.282 | J32: =J25-J27-J29-J30 -> -56023.053 | K32: =K25-K27-K29-K30 -> -68639.627 | ... W32: =W25-W27-W29-W30 -> -304530.73
B34: Asset management fee | D34: =IF((CashFlowCeilPct*D32)<=0,0,CashFlowCeilPct*D32) -> 0 | E34: =IF((CashFlowCeilPct*E32)<=0,0,CashFlowCeilPct*E32) -> 0 | F34: =IF((CashFlowCeilPct*F32)<=0,0,CashFlowCeilPct*F32) -> 0 | G34: =IF((CashFlowCeilPct*G32)<=0,0,CashFlowCeilPct*G32) -> 0 | H34: =IF((CashFlowCeilPct*H32)<=0,0,CashFlowCeilPct*H32) -> 0 | I34: =IF((CashFlowCeilPct*I32)<=0,0,CashFlowCeilPct*I32) -> 0 | J34: =IF((CashFlowCeilPct*J32)<=0,0,CashFlowCeilPct*J32) -> 0 | K34: =IF((CashFlowCeilPct*K32)<=0,0,CashFlowCeilPct*K32) -> 0 | ... W34: =IF((CashFlowCeilPct*W32)<=0,0,CashFlowCeilPct*W32) -> 0
B36: CASH AVAILABLE AFTER FEES | D36: =D32-D34 -> -43825.092 | E36: =E32-E34 -> -4784.1017 | F36: =F32-F34 -> -13583.301 | G36: =G32-G34 -> -23069.545 | H36: =H32-H34 -> -33279.151 | I36: =I32-I34 -> -44250.282 | J36: =J32-J34 -> -56023.053 | K36: =K32-K34 -> -68639.627 | ... W36: =W32-W34 -> -304530.73 | X36: =SUM(D36:W36) -> -2470353.7
B37: Surplus cash distribution — see the Waterfall tab
B39: DSCR | D39: =IF((D29+D30)=0,0,D25/(D29+D30)) -> 0.94585446 | E39: =IF((E29+E30)=0,0,E25/(E29+E30)) -> 1.1171741 | F39: =IF((F29+F30)=0,0,F25/(F29+F30)) -> 1.0835955 | G39: =IF((G29+G30)=0,0,G25/(G29+G30)) -> 1.0471965 | H39: =IF((H29+H30)=0,0,H25/(H29+H30)) -> 1.0078252 | I39: =IF((I29+I30)=0,0,I25/(I29+I30)) -> 0.96532188 | J39: =IF((J29+J30)=0,0,J25/(J29+J30)) -> 0.91951851 | K39: =IF((K29+K30)=0,0,K25/(K29+K30)) -> 0.87023849 | ... W39: =IF((W29+W30)=0,0,W25/(W29+W30)) -> -0.070677672
B41: Equity pay-ins received (memo) | D41: =SUMPRODUCT((ROUNDUP(CH_PayinMonths/12,0)=1)*CH_PayinAmts) -> 1569307.7 | E41: =SUMPRODUCT((ROUNDUP(CH_PayinMonths/12,0)=2)*CH_PayinAmts) -> 672560.42 | F41: =SUMPRODUCT((ROUNDUP(CH_PayinMonths/12,0)=3)*CH_PayinAmts) -> 0 | G41: =SUMPRODUCT((ROUNDUP(CH_PayinMonths/12,0)=4)*CH_PayinAmts) -> 0 | H41: =SUMPRODUCT((ROUNDUP(CH_PayinMonths/12,0)=5)*CH_PayinAmts) -> 0 | I41: =SUMPRODUCT((ROUNDUP(CH_PayinMonths/12,0)=6)*CH_PayinAmts) -> 0 | J41: =SUMPRODUCT((ROUNDUP(CH_PayinMonths/12,0)=7)*CH_PayinAmts) -> 0 | K41: =SUMPRODUCT((ROUNDUP(CH_PayinMonths/12,0)=8)*CH_PayinAmts) -> 0 | L41: =SUMPRODUCT((ROUNDUP(CH_PayinMonths/12,0)=9)*CH_PayinAmts) -> 0 | M41: =SUMPRODUCT((ROUNDUP(CH_PayinMonths/12,0)=10)*CH_PayinAmts) -> 0 | N41: =SUMPRODUCT((ROUNDUP(CH_PayinMonths/12,0)=11)*CH_PayinAmts) -> 0 | O41: =SUMPRODUCT((ROUNDUP(CH_PayinMonths/12,0)=12)*CH_PayinAmts) -> 0 | P41: =SUMPRODUCT((ROUNDUP(CH_PayinMonths/12,0)=13)*CH_PayinAmts) -> 0 | Q41: =SUMPRODUCT((ROUNDUP(CH_PayinMonths/12,0)=14)*CH_PayinAmts) -> 0 | R41: =SUMPRODUCT((ROUNDUP(CH_PayinMonths/12,0)=15)*CH_PayinAmts) -> 0 | S41: =SUMPRODUCT((ROUNDUP(CH_PayinMonths/12,0)=16)*CH_PayinAmts) -> 0 | T41: =SUMPRODUCT((ROUNDUP(CH_PayinMonths/12,0)=17)*CH_PayinAmts) -> 0 | U41: =SUMPRODUCT((ROUNDUP(CH_PayinMonths/12,0)=18)*CH_PayinAmts) -> 0 | V41: =SUMPRODUCT((ROUNDUP(CH_PayinMonths/12,0)=19)*CH_PayinAmts) -> 0 | W41: =SUMPRODUCT((ROUNDUP(CH_PayinMonths/12,0)=20)*CH_PayinAmts) -> 0 | X41: =SUM(D41:W41) -> 2241868.1
B49: Ratios & Assumptions
B50: Revenue growth (OCAF x haircut) | D50: =OCAF*OCAFHaircut -> 0.01875
B51: Expense growth | D51: =ExpGrowth -> 0.03
B56: LOAN AMORTIZATION (selected strategy)
B57: Rate | C57: =IF(DebtStrategy="Refinance",PermRate,CH_NoteRate) -> 0.06
B58: Beginning balance | D58: =CH_SelProceeds -> 3410352.4 | E58: =D61 -> 3381627.8 | F58: =E61 -> 3351179.7 | G58: =F61 -> 3318904.7 | H58: =G61 -> 3284693.3 | I58: =H61 -> 3248429.2 | J58: =I61 -> 3209989.2 | K58: =J61 -> 3169242.8 | L58: =K61 -> 3126051.6 | ... W58: =V61 -> 2440610.2
B59: Interest | D59: =D58*$C$57 -> 204621.14 | E59: =E58*$C$57 -> 202897.67 | F59: =F58*$C$57 -> 201070.78 | G59: =G58*$C$57 -> 199134.28 | H59: =H58*$C$57 -> 197081.6 | I59: =I58*$C$57 -> 194905.75 | J59: =J58*$C$57 -> 192599.35 | K59: =K58*$C$57 -> 190154.57 | ... W59: =W58*$C$57 -> 146436.61
B60: Principal | D60: =MAX(0,MIN(D58,$C$62-D59)) -> 28724.597 | E60: =MAX(0,MIN(E58,$C$62-E59)) -> 30448.072 | F60: =MAX(0,MIN(F58,$C$62-F59)) -> 32274.957 | G60: =MAX(0,MIN(G58,$C$62-G59)) -> 34211.454 | H60: =MAX(0,MIN(H58,$C$62-H59)) -> 36264.141 | I60: =MAX(0,MIN(I58,$C$62-I59)) -> 38439.99 | J60: =MAX(0,MIN(J58,$C$62-J59)) -> 40746.389 | K60: =MAX(0,MIN(K58,$C$62-K59)) -> 43191.173 | ... W60: =MAX(0,MIN(W58,$C$62-W59)) -> 86909.125
B61: Ending balance | D61: =D58-D60 -> 3381627.8 | E61: =E58-E60 -> 3351179.7 | F61: =F58-F60 -> 3318904.7 | G61: =G58-G60 -> 3284693.3 | H61: =H58-H60 -> 3248429.2 | I61: =I58-I60 -> 3209989.2 | J61: =J58-J60 -> 3169242.8 | K61: =K58-K60 -> 3126051.6 | ... W61: =W58-W60 -> 2353701.1
B62: Annual payment | C62: =IF(DebtStrategy="Refinance",CH_PermLoan*(-PMT(PermRate/12,PermAmort*12,1)*12),12*CH_NotePI) -> 233345.74

Sheet CH - Waterfall
A1: SURPLUS CASH-RESERVE WATERFALL — CLEAR HORIZONS
B3: Year | C3: ="Yr "&1 -> Yr 1 | D3: ="Yr "&2 -> Yr 2 | E3: ="Yr "&3 -> Yr 3 | F3: ="Yr "&4 -> Yr 4 | G3: ="Yr "&5 -> Yr 5 | H3: ="Yr "&6 -> Yr 6 | I3: ="Yr "&7 -> Yr 7 | J3: ="Yr "&8 -> Yr 8 | K3: ="Yr "&9 -> Yr 9 | L3: ="Yr "&10 -> Yr 10 | M3: ="Yr "&11 -> Yr 11 | N3: ="Yr "&12 -> Yr 12 | O3: ="Yr "&13 -> Yr 13 | P3: ="Yr "&14 -> Yr 14 | Q3: ="Yr "&15 -> Yr 15 | R3: ="Yr "&16 -> Yr 16 | S3: ="Yr "&17 -> Yr 17 | T3: ="Yr "&18 -> Yr 18 | U3: ="Yr "&19 -> Yr 19 | V3: ="Yr "&20 -> Yr 20
B5: SURPLUS CASH AVAILABLE | C5: ='CH - Pro Forma'!D36 -> -43825.092 | D5: ='CH - Pro Forma'!E36 -> -4784.1017 | E5: ='CH - Pro Forma'!F36 -> -13583.301 | F5: ='CH - Pro Forma'!G36 -> -23069.545 | G5: ='CH - Pro Forma'!H36 -> -33279.151 | H5: ='CH - Pro Forma'!I36 -> -44250.282 | I5: ='CH - Pro Forma'!J36 -> -56023.053 | J5: ='CH - Pro Forma'!K36 -> -68639.627 | ... V5: ='CH - Pro Forma'!W36 -> -304530.73
B7: Less: deferred developer fee payment | C7: =MIN(C17,MAX(0,C5)) -> 0 | D7: =MIN(D17,MAX(0,D5)) -> 0 | E7: =MIN(E17,MAX(0,E5)) -> 0 | F7: =MIN(F17,MAX(0,F5)) -> 0 | G7: =MIN(G17,MAX(0,G5)) -> 0 | H7: =MIN(H17,MAX(0,H5)) -> 0 | I7: =MIN(I17,MAX(0,I5)) -> 0 | J7: =MIN(J17,MAX(0,J5)) -> 0 | ... V7: =MIN(V17,MAX(0,V5)) -> 0
B8: Less: soft-loan payment | C8: =MIN(C23,MAX(0,C5)-C7) -> 0 | D8: =MIN(D23,MAX(0,D5)-D7) -> 0 | E8: =MIN(E23,MAX(0,E5)-E7) -> 0 | F8: =MIN(F23,MAX(0,F5)-F7) -> 0 | G8: =MIN(G23,MAX(0,G5)-G7) -> 0 | H8: =MIN(H23,MAX(0,H5)-H7) -> 0 | I8: =MIN(I23,MAX(0,I5)-I7) -> 0 | J8: =MIN(J23,MAX(0,J5)-J7) -> 0 | ... V8: =MIN(V23,MAX(0,V5)-V7) -> 0
B9: Less: reserve top-up | C9: =MIN(MAX(0,C33-C29),MAX(0,C5)-C7-C8) -> 0 | D9: =MIN(MAX(0,D33-D29),MAX(0,D5)-D7-D8) -> 0 | E9: =MIN(MAX(0,E33-E29),MAX(0,E5)-E7-E8) -> 0 | F9: =MIN(MAX(0,F33-F29),MAX(0,F5)-F7-F8) -> 0 | G9: =MIN(MAX(0,G33-G29),MAX(0,G5)-G7-G8) -> 0 | H9: =MIN(MAX(0,H33-H29),MAX(0,H5)-H7-H8) -> 0 | I9: =MIN(MAX(0,I33-I29),MAX(0,I5)-I7-I8) -> 0 | J9: =MIN(MAX(0,J33-J29),MAX(0,J5)-J7-J8) -> 0 | ... V9: =MIN(MAX(0,V33-V29),MAX(0,V5)-V7-V8) -> 0
B11: Total distributed | C11: =C7+C8+C9 -> 0 | D11: =D7+D8+D9 -> 0 | E11: =E7+E8+E9 -> 0 | F11: =F7+F8+F9 -> 0 | G11: =G7+G8+G9 -> 0 | H11: =H7+H8+H9 -> 0 | I11: =I7+I8+I9 -> 0 | J11: =J7+J8+J9 -> 0 | ... V11: =V7+V8+V9 -> 0
B13: Undistributed surplus / (deficit) | C13: =C5-C11 -> -43825.092 | D13: =D5-D11 -> -4784.1017 | E13: =E5-E11 -> -13583.301 | F13: =F5-F11 -> -23069.545 | G13: =G5-G11 -> -33279.151 | H13: =H5-H11 -> -44250.282 | I13: =I5-I11 -> -56023.053 | J13: =J5-J11 -> -68639.627 | ... V13: =V5-V11 -> -304530.73
B16: DEFERRED DEVELOPER FEE PAYDOWN
B17: Beginning balance | C17: ='Sources & Uses'!C10 -> 816531.21 | D17: =C19 -> 816531.21 | E17: =D19 -> 816531.21 | F17: =E19 -> 816531.21 | G17: =F19 -> 816531.21 | H17: =G19 -> 816531.21 | I17: =H19 -> 816531.21 | J17: =I19 -> 816531.21 | K17: =J19 -> 816531.21 | ... V17: =U19 -> 816531.21
B18: Less: payment | C18: =C7 -> 0 | D18: =D7 -> 0 | E18: =E7 -> 0 | F18: =F7 -> 0 | G18: =G7 -> 0 | H18: =H7 -> 0 | I18: =I7 -> 0 | J18: =J7 -> 0 | ... V18: =V7 -> 0
B19: Ending balance | C19: =C17-C18 -> 816531.21 | D19: =D17-D18 -> 816531.21 | E19: =E17-E18 -> 816531.21 | F19: =F17-F18 -> 816531.21 | G19: =G17-G18 -> 816531.21 | H19: =H17-H18 -> 816531.21 | I19: =I17-I18 -> 816531.21 | J19: =J17-J18 -> 816531.21 | ... V19: =V17-V18 -> 816531.21
B22: SOFT LOAN PAYDOWN
B23: Beginning balance | C23: ='Sources & Uses'!C12 -> 461898.42 | D23: =C25 -> 461898.42 | E23: =D25 -> 461898.42 | F23: =E25 -> 461898.42 | G23: =F25 -> 461898.42 | H23: =G25 -> 461898.42 | I23: =H25 -> 461898.42 | J23: =I25 -> 461898.42 | K23: =J25 -> 461898.42 | ... V23: =U25 -> 461898.42
B24: Less: payment | C24: =C8 -> 0 | D24: =D8 -> 0 | E24: =E8 -> 0 | F24: =F8 -> 0 | G24: =G8 -> 0 | H24: =H8 -> 0 | I24: =I8 -> 0 | J24: =J8 -> 0 | ... V24: =V8 -> 0
B25: Ending balance | C25: =C23-C24 -> 461898.42 | D25: =D23-D24 -> 461898.42 | E25: =E23-E24 -> 461898.42 | F25: =F23-F24 -> 461898.42 | G25: =G23-G24 -> 461898.42 | H25: =H23-H24 -> 461898.42 | I25: =I23-I24 -> 461898.42 | J25: =J23-J24 -> 461898.42 | ... V25: =V23-V24 -> 461898.42
B28: RESERVE ACCOUNT
B29: Beginning balance | C29: ='Sources & Uses'!C23 -> 434848.69 | D29: =C32 -> 391023.6 | E29: =D32 -> 386239.5 | F29: =E32 -> 372656.2 | G29: =F32 -> 349586.65 | H29: =G32 -> 316307.5 | I29: =H32 -> 272057.22 | J29: =I32 -> 216034.17 | K29: =J32 -> 147394.54 | ... V29: =U32 -> 0
B30: Plus: reserve funding | C30: =C9 -> 0 | D30: =D9 -> 0 | E30: =E9 -> 0 | F30: =F9 -> 0 | G30: =G9 -> 0 | H30: =H9 -> 0 | I30: =I9 -> 0 | J30: =J9 -> 0 | ... V30: =V9 -> 0
B31: Less: operating-deficit draw | C31: =MIN(C29,MAX(0,-C5)) -> 43825.092 | D31: =MIN(D29,MAX(0,-D5)) -> 4784.1017 | E31: =MIN(E29,MAX(0,-E5)) -> 13583.301 | F31: =MIN(F29,MAX(0,-F5)) -> 23069.545 | G31: =MIN(G29,MAX(0,-G5)) -> 33279.151 | H31: =MIN(H29,MAX(0,-H5)) -> 44250.282 | I31: =MIN(I29,MAX(0,-I5)) -> 56023.053 | J31: =MIN(J29,MAX(0,-J5)) -> 68639.627 | ... V31: =MIN(V29,MAX(0,-V5)) -> 0
B32: Ending balance | C32: =C29+C30-C31 -> 391023.6 | D32: =D29+D30-D31 -> 386239.5 | E32: =E29+E30-E31 -> 372656.2 | F32: =F29+F30-F31 -> 349586.65 | G32: =G29+G30-G31 -> 316307.5 | H32: =H29+H30-H31 -> 272057.22 | I32: =I29+I30-I31 -> 216034.17 | J32: =J29+J30-J31 -> 147394.54 | ... V32: =V29+V30-V31 -> 0
B33: Target (operating reserve) | C33: ='Sources & Uses'!C23 -> 434848.69 | D33: ='Sources & Uses'!C23 -> 434848.69 | E33: ='Sources & Uses'!C23 -> 434848.69 | F33: ='Sources & Uses'!C23 -> 434848.69 | G33: ='Sources & Uses'!C23 -> 434848.69 | H33: ='Sources & Uses'!C23 -> 434848.69 | I33: ='Sources & Uses'!C23 -> 434848.69 | J33: ='Sources & Uses'!C23 -> 434848.69 | K33: ='Sources & Uses'!C23 -> 434848.69 | L33: ='Sources & Uses'!C23 -> 434848.69 | M33: ='Sources & Uses'!C23 -> 434848.69 | N33: ='Sources & Uses'!C23 -> 434848.69 | O33: ='Sources & Uses'!C23 -> 434848.69 | P33: ='Sources & Uses'!C23 -> 434848.69 | Q33: ='Sources & Uses'!C23 -> 434848.69 | R33: ='Sources & Uses'!C23 -> 434848.69 | S33: ='Sources & Uses'!C23 -> 434848.69 | T33: ='Sources & Uses'!C23 -> 434848.69 | U33: ='Sources & Uses'!C23 -> 434848.69 | V33: ='Sources & Uses'!C23 -> 434848.69
B35: DDF fully repaid in year | C35: =IFERROR(MATCH(0,C19:V19,0),"NOT REPAID") -> NOT REPAID

Sheet NZ - Pro Forma
A1: CASH FLOW FORECAST — NEW ZION
B2: 20 years from this property's resyndication close. Rehab-period offline disruption per Rehab Scope; debt service per the amortization block below (strategy toggle on Dashboard). Equity pay-ins reference the Tax Credit Calc block — single source of truth.
B3: Year | D3: Yr 1 | E3: Yr 2 | F3: Yr 3 | G3: Yr 4 | H3: Yr 5 | I3: Yr 6 | J3: Yr 7 | K3: Yr 8 | L3: Yr 9 | M3: Yr 10 | N3: Yr 11 | O3: Yr 12 | P3: Yr 13 | Q3: Yr 14 | R3: Yr 15 | S3: Yr 16 | T3: Yr 17 | U3: Yr 18 | V3: Yr 19 | W3: Yr 20 | X3: TOTAL
B4: Calendar year | D4: =YEAR(NZ_ResynDate)+0 -> 2029 | E4: =YEAR(NZ_ResynDate)+1 -> 2030 | F4: =YEAR(NZ_ResynDate)+2 -> 2031 | G4: =YEAR(NZ_ResynDate)+3 -> 2032 | H4: =YEAR(NZ_ResynDate)+4 -> 2033 | I4: =YEAR(NZ_ResynDate)+5 -> 2034 | J4: =YEAR(NZ_ResynDate)+6 -> 2035 | K4: =YEAR(NZ_ResynDate)+7 -> 2036 | L4: =YEAR(NZ_ResynDate)+8 -> 2037 | M4: =YEAR(NZ_ResynDate)+9 -> 2038 | N4: =YEAR(NZ_ResynDate)+10 -> 2039 | O4: =YEAR(NZ_ResynDate)+11 -> 2040 | P4: =YEAR(NZ_ResynDate)+12 -> 2041 | Q4: =YEAR(NZ_ResynDate)+13 -> 2042 | R4: =YEAR(NZ_ResynDate)+14 -> 2043 | S4: =YEAR(NZ_ResynDate)+15 -> 2044 | T4: =YEAR(NZ_ResynDate)+16 -> 2045 | U4: =YEAR(NZ_ResynDate)+17 -> 2046 | V4: =YEAR(NZ_ResynDate)+18 -> 2047 | W4: =YEAR(NZ_ResynDate)+19 -> 2048
B6: Gross rental income | D6: =NZ_GPR -> 1427889.7 | E6: =D6*(1+$D$50) -> 1454662.7 | F6: =E6*(1+$D$50) -> 1481937.6 | G6: =F6*(1+$D$50) -> 1509723.9 | H6: =G6*(1+$D$50) -> 1538031.2 | I6: =H6*(1+$D$50) -> 1566869.3 | J6: =I6*(1+$D$50) -> 1596248.1 | K6: =J6*(1+$D$50) -> 1626177.8 | L6: =K6*(1+$D$50) -> 1656668.6 | ... W6: =V6*(1+$D$50) -> 2032261
B7: Other income | D7: =NZ_OtherInc -> 14577 | E7: =D7*(1+$D$50) -> 14850.319 | F7: =E7*(1+$D$50) -> 15128.762 | G7: =F7*(1+$D$50) -> 15412.427 | H7: =G7*(1+$D$50) -> 15701.41 | I7: =H7*(1+$D$50) -> 15995.811 | J7: =I7*(1+$D$50) -> 16295.732 | K7: =J7*(1+$D$50) -> 16601.277 | L7: =K7*(1+$D$50) -> 16912.551 | ... W7: =V7*(1+$D$50) -> 20746.888
B9: Gross revenue | D9: =SUM(D6:D7) -> 1442466.7 | E9: =SUM(E6:E7) -> 1469513 | F9: =SUM(F6:F7) -> 1497066.4 | G9: =SUM(G6:G7) -> 1525136.3 | H9: =SUM(H6:H7) -> 1553732.7 | I9: =SUM(I6:I7) -> 1582865.1 | J9: =SUM(J6:J7) -> 1612543.9 | K9: =SUM(K6:K7) -> 1642779.1 | ... W9: =SUM(W6:W7) -> 2053007.9 | X9: =SUM(D9:W9) -> 34615203
B10: Vacancy | D10: =-NZ_VacHAP*D9 -> -28849.335 | E10: =-NZ_VacHAP*E9 -> -29390.26 | F10: =-NZ_VacHAP*F9 -> -29941.327 | G10: =-NZ_VacHAP*G9 -> -30502.727 | H10: =-NZ_VacHAP*H9 -> -31074.653 | I10: =-NZ_VacHAP*I9 -> -31657.303 | J10: =-NZ_VacHAP*J9 -> -32250.877 | K10: =-NZ_VacHAP*K9 -> -32855.581 | ... W10: =-NZ_VacHAP*W9 -> -41060.158
B11: Rehab offline adjustment | D11: =-D9*NZ_OfflinePct*MAX(0,MIN(NZ_RehabMonths-0,12))/12 -> -64911.003 | E11: =-E9*NZ_OfflinePct*MAX(0,MIN(NZ_RehabMonths-12,12))/12 -> 0 | F11: =-F9*NZ_OfflinePct*MAX(0,MIN(NZ_RehabMonths-24,12))/12 -> 0 | G11: =-G9*NZ_OfflinePct*MAX(0,MIN(NZ_RehabMonths-36,12))/12 -> 0 | H11: =-H9*NZ_OfflinePct*MAX(0,MIN(NZ_RehabMonths-48,12))/12 -> 0 | I11: =-I9*NZ_OfflinePct*MAX(0,MIN(NZ_RehabMonths-60,12))/12 -> 0 | J11: =-J9*NZ_OfflinePct*MAX(0,MIN(NZ_RehabMonths-72,12))/12 -> 0 | K11: =-K9*NZ_OfflinePct*MAX(0,MIN(NZ_RehabMonths-84,12))/12 -> 0 | L11: =-L9*NZ_OfflinePct*MAX(0,MIN(NZ_RehabMonths-96,12))/12 -> 0 | M11: =-M9*NZ_OfflinePct*MAX(0,MIN(NZ_RehabMonths-108,12))/12 -> 0 | N11: =-N9*NZ_OfflinePct*MAX(0,MIN(NZ_RehabMonths-120,12))/12 -> 0 | O11: =-O9*NZ_OfflinePct*MAX(0,MIN(NZ_RehabMonths-132,12))/12 -> 0 | P11: =-P9*NZ_OfflinePct*MAX(0,MIN(NZ_RehabMonths-144,12))/12 -> 0 | Q11: =-Q9*NZ_OfflinePct*MAX(0,MIN(NZ_RehabMonths-156,12))/12 -> 0 | R11: =-R9*NZ_OfflinePct*MAX(0,MIN(NZ_RehabMonths-168,12))/12 -> 0 | S11: =-S9*NZ_OfflinePct*MAX(0,MIN(NZ_RehabMonths-180,12))/12 -> 0 | T11: =-T9*NZ_OfflinePct*MAX(0,MIN(NZ_RehabMonths-192,12))/12 -> 0 | U11: =-U9*NZ_OfflinePct*MAX(0,MIN(NZ_RehabMonths-204,12))/12 -> 0 | V11: =-V9*NZ_OfflinePct*MAX(0,MIN(NZ_RehabMonths-216,12))/12 -> 0 | W11: =-W9*NZ_OfflinePct*MAX(0,MIN(NZ_RehabMonths-228,12))/12 -> 0
B13: Net revenue | D13: =D9+D10+D11 -> 1348706.4 | E13: =E9+E10+E11 -> 1440122.7 | F13: =F9+F10+F11 -> 1467125 | G13: =G9+G10+G11 -> 1494633.6 | H13: =H9+H10+H11 -> 1522658 | I13: =I9+I10+I11 -> 1551207.8 | J13: =J9+J10+J11 -> 1580293 | K13: =K9+K10+K11 -> 1609923.5 | ... W13: =W9+W10+W11 -> 2011947.7 | X13: =SUM(D13:W13) -> 33857988
B15: Operating Expenses
B16: Management fee | D16: =MgmtFeePct*D13 -> 53948.256 | E16: =MgmtFeePct*E13 -> 57604.909 | F16: =MgmtFeePct*F13 -> 58685.001 | G16: =MgmtFeePct*G13 -> 59785.345 | H16: =MgmtFeePct*H13 -> 60906.32 | I16: =MgmtFeePct*I13 -> 62048.313 | J16: =MgmtFeePct*J13 -> 63211.719 | K16: =MgmtFeePct*K13 -> 64396.939 | ... W16: =MgmtFeePct*W13 -> 80477.909
B17: Administrative (ex-mgmt) | D17: ='Rev+Expenses'!D19 -> 184096.09 | E17: =D17*(1+$D$51) -> 189618.97 | F17: =E17*(1+$D$51) -> 195307.54 | G17: =F17*(1+$D$51) -> 201166.77 | H17: =G17*(1+$D$51) -> 207201.77 | I17: =H17*(1+$D$51) -> 213417.82 | J17: =I17*(1+$D$51) -> 219820.36 | K17: =J17*(1+$D$51) -> 226414.97 | L17: =K17*(1+$D$51) -> 233207.42 | ... W17: =V17*(1+$D$51) -> 322813.61
B18: Utilities | D18: ='Rev+Expenses'!D20 -> 72790.916 | E18: =D18*(1+$D$51) -> 74974.644 | F18: =E18*(1+$D$51) -> 77223.883 | G18: =F18*(1+$D$51) -> 79540.6 | H18: =G18*(1+$D$51) -> 81926.818 | I18: =H18*(1+$D$51) -> 84384.622 | J18: =I18*(1+$D$51) -> 86916.161 | K18: =J18*(1+$D$51) -> 89523.646 | L18: =K18*(1+$D$51) -> 92209.355 | ... W18: =V18*(1+$D$51) -> 127639.31
B19: Operating & maintenance | D19: ='Rev+Expenses'!D21 -> 400028.78 | E19: =D19*(1+$D$51) -> 412029.64 | F19: =E19*(1+$D$51) -> 424390.53 | G19: =F19*(1+$D$51) -> 437122.25 | H19: =G19*(1+$D$51) -> 450235.91 | I19: =H19*(1+$D$51) -> 463742.99 | J19: =I19*(1+$D$51) -> 477655.28 | K19: =J19*(1+$D$51) -> 491984.94 | L19: =K19*(1+$D$51) -> 506744.49 | ... W19: =V19*(1+$D$51) -> 701452.88
B20: Taxes + other T&I (ex-insurance) | D20: ='Rev+Expenses'!D22 -> 84935.484 | E20: =D20*(1+$D$51) -> 87483.549 | F20: =E20*(1+$D$51) -> 90108.055 | G20: =F20*(1+$D$51) -> 92811.297 | H20: =G20*(1+$D$51) -> 95595.636 | I20: =H20*(1+$D$51) -> 98463.505 | J20: =I20*(1+$D$51) -> 101417.41 | K20: =J20*(1+$D$51) -> 104459.93 | L20: =K20*(1+$D$51) -> 107593.73 | ... W20: =V20*(1+$D$51) -> 148934.89
B21: Property insurance | D21: ='Rev+Expenses'!D23 -> 105204.83 | E21: =D21*(1+InsGrowth) -> 111517.11 | F21: =E21*(1+InsGrowth) -> 118208.14 | G21: =F21*(1+InsGrowth) -> 125300.63 | H21: =G21*(1+InsGrowth) -> 132818.67 | I21: =H21*(1+InsGrowth) -> 140787.79 | J21: =I21*(1+InsGrowth) -> 149235.06 | K21: =J21*(1+InsGrowth) -> 158189.16 | L21: =K21*(1+InsGrowth) -> 167680.51 | ... W21: =V21*(1+InsGrowth) -> 318307.67
B23: Total operating expenses | D23: =SUM(D16:D21) -> 901004.35 | E23: =SUM(E16:E21) -> 933228.83 | F23: =SUM(F16:F21) -> 963923.15 | G23: =SUM(G16:G21) -> 995726.89 | H23: =SUM(H16:H21) -> 1028685.1 | I23: =SUM(I16:I21) -> 1062845 | J23: =SUM(J16:J21) -> 1098256 | K23: =SUM(K16:K21) -> 1134969.6 | ... W23: =SUM(W16:W21) -> 1699626.3 | X23: =SUM(D23:W23) -> 25158163
B25: NET OPERATING INCOME | D25: =D13-D23 -> 447702.05 | E25: =E13-E23 -> 506893.89 | F25: =F13-F23 -> 503201.87 | G25: =G13-G23 -> 498906.73 | H25: =H13-H23 -> 493972.87 | I25: =I13-I23 -> 488362.79 | J25: =J13-J23 -> 482037 | K25: =K13-K23 -> 474953.89 | ... W25: =W13-W23 -> 312321.47 | X25: =SUM(D25:W25) -> 8699825.5
B27: Replacement reserves | D27: =NZ_ReservesStab -> 38245.445 | E27: =D27*(1+$D$51) -> 39392.808 | F27: =E27*(1+$D$51) -> 40574.593 | G27: =F27*(1+$D$51) -> 41791.83 | H27: =G27*(1+$D$51) -> 43045.585 | I27: =H27*(1+$D$51) -> 44336.953 | J27: =I27*(1+$D$51) -> 45667.061 | K27: =J27*(1+$D$51) -> 47037.073 | L27: =K27*(1+$D$51) -> 48448.185 | ... W27: =V27*(1+$D$51) -> 67063.619
B29: Debt service — interest | D29: =D59 -> 389112.67 | E29: =E59 -> 385835.26 | F29: =F59 -> 382361.21 | G29: =G59 -> 378678.72 | H29: =H59 -> 374775.28 | I29: =I59 -> 370637.63 | J29: =J59 -> 366251.73 | K29: =K59 -> 361602.67 | ... W29: =W59 -> 278467.52
B30: Debt service — principal | D30: =D60 -> 54623.409 | E30: =E60 -> 57900.814 | F30: =F60 -> 61374.862 | G30: =G60 -> 65057.354 | H30: =H60 -> 68960.795 | I30: =I60 -> 73098.443 | J30: =J60 -> 77484.35 | K30: =K60 -> 82133.411 | ... W30: =W60 -> 165268.56
B32: Cash flow after debt service | D32: =D25-D27-D29-D30 -> -34279.475 | E32: =E25-E27-E29-E30 -> 23765.01 | F32: =F25-F27-F29-F30 -> 18891.204 | G32: =G25-G27-G29-G30 -> 13378.828 | H32: =H25-H27-H29-H30 -> 7191.213 | I32: =I25-I27-I29-I30 -> 289.7652 | J32: =J25-J27-J29-J30 -> -7366.1378 | K32: =K25-K27-K29-K30 -> -15819.256 | ... W32: =W25-W27-W29-W30 -> -198478.22
B34: Asset management fee | D34: =IF((CashFlowCeilPct*D32)<=0,0,CashFlowCeilPct*D32) -> 0 | E34: =IF((CashFlowCeilPct*E32)<=0,0,CashFlowCeilPct*E32) -> 2376.501 | F34: =IF((CashFlowCeilPct*F32)<=0,0,CashFlowCeilPct*F32) -> 1889.1204 | G34: =IF((CashFlowCeilPct*G32)<=0,0,CashFlowCeilPct*G32) -> 1337.8828 | H34: =IF((CashFlowCeilPct*H32)<=0,0,CashFlowCeilPct*H32) -> 719.1213 | I34: =IF((CashFlowCeilPct*I32)<=0,0,CashFlowCeilPct*I32) -> 28.97652 | J34: =IF((CashFlowCeilPct*J32)<=0,0,CashFlowCeilPct*J32) -> 0 | K34: =IF((CashFlowCeilPct*K32)<=0,0,CashFlowCeilPct*K32) -> 0 | ... W34: =IF((CashFlowCeilPct*W32)<=0,0,CashFlowCeilPct*W32) -> 0
B36: CASH AVAILABLE AFTER FEES | D36: =D32-D34 -> -34279.475 | E36: =E32-E34 -> 21388.509 | F36: =F32-F34 -> 17002.084 | G36: =G32-G34 -> 12040.945 | H36: =H32-H34 -> 6472.0917 | I36: =I32-I34 -> 260.78868 | J36: =J32-J34 -> -7366.1378 | K36: =K32-K34 -> -15819.256 | ... W36: =W32-W34 -> -198478.22 | X36: =SUM(D36:W36) -> -1208917.1
B37: Surplus cash distribution — see the Waterfall tab
B39: DSCR | D39: =IF((D29+D30)=0,0,D25/(D29+D30)) -> 1.0089377 | E39: =IF((E29+E30)=0,0,E25/(E29+E30)) -> 1.1423319 | F39: =IF((F29+F30)=0,0,F25/(F29+F30)) -> 1.1340116 | G39: =IF((G29+G30)=0,0,G25/(G29+G30)) -> 1.1243321 | H39: =IF((H29+H30)=0,0,H25/(H29+H30)) -> 1.1132132 | I39: =IF((I29+I30)=0,0,I25/(I29+I30)) -> 1.1005704 | J39: =IF((J29+J30)=0,0,J25/(J29+J30)) -> 1.0863146 | K39: =IF((K29+K30)=0,0,K25/(K29+K30)) -> 1.0703522 | ... W39: =IF((W29+W30)=0,0,W25/(W29+W30)) -> 0.70384512
B41: Equity pay-ins received (memo) | D41: =SUMPRODUCT((ROUNDUP(NZ_PayinMonths/12,0)=1)*NZ_PayinAmts) -> 1942952.3 | E41: =SUMPRODUCT((ROUNDUP(NZ_PayinMonths/12,0)=2)*NZ_PayinAmts) -> 832693.86 | F41: =SUMPRODUCT((ROUNDUP(NZ_PayinMonths/12,0)=3)*NZ_PayinAmts) -> 0 | G41: =SUMPRODUCT((ROUNDUP(NZ_PayinMonths/12,0)=4)*NZ_PayinAmts) -> 0 | H41: =SUMPRODUCT((ROUNDUP(NZ_PayinMonths/12,0)=5)*NZ_PayinAmts) -> 0 | I41: =SUMPRODUCT((ROUNDUP(NZ_PayinMonths/12,0)=6)*NZ_PayinAmts) -> 0 | J41: =SUMPRODUCT((ROUNDUP(NZ_PayinMonths/12,0)=7)*NZ_PayinAmts) -> 0 | K41: =SUMPRODUCT((ROUNDUP(NZ_PayinMonths/12,0)=8)*NZ_PayinAmts) -> 0 | L41: =SUMPRODUCT((ROUNDUP(NZ_PayinMonths/12,0)=9)*NZ_PayinAmts) -> 0 | M41: =SUMPRODUCT((ROUNDUP(NZ_PayinMonths/12,0)=10)*NZ_PayinAmts) -> 0 | N41: =SUMPRODUCT((ROUNDUP(NZ_PayinMonths/12,0)=11)*NZ_PayinAmts) -> 0 | O41: =SUMPRODUCT((ROUNDUP(NZ_PayinMonths/12,0)=12)*NZ_PayinAmts) -> 0 | P41: =SUMPRODUCT((ROUNDUP(NZ_PayinMonths/12,0)=13)*NZ_PayinAmts) -> 0 | Q41: =SUMPRODUCT((ROUNDUP(NZ_PayinMonths/12,0)=14)*NZ_PayinAmts) -> 0 | R41: =SUMPRODUCT((ROUNDUP(NZ_PayinMonths/12,0)=15)*NZ_PayinAmts) -> 0 | S41: =SUMPRODUCT((ROUNDUP(NZ_PayinMonths/12,0)=16)*NZ_PayinAmts) -> 0 | T41: =SUMPRODUCT((ROUNDUP(NZ_PayinMonths/12,0)=17)*NZ_PayinAmts) -> 0 | U41: =SUMPRODUCT((ROUNDUP(NZ_PayinMonths/12,0)=18)*NZ_PayinAmts) -> 0 | V41: =SUMPRODUCT((ROUNDUP(NZ_PayinMonths/12,0)=19)*NZ_PayinAmts) -> 0 | W41: =SUMPRODUCT((ROUNDUP(NZ_PayinMonths/12,0)=20)*NZ_PayinAmts) -> 0 | X41: =SUM(D41:W41) -> 2775646.2
B49: Ratios & Assumptions
B50: Revenue growth (OCAF x haircut) | D50: =OCAF*OCAFHaircut -> 0.01875
B51: Expense growth | D51: =ExpGrowth -> 0.03
B56: LOAN AMORTIZATION (selected strategy)
B57: Rate | C57: =IF(DebtStrategy="Refinance",PermRate,NZ_NoteRate) -> 0.06
B58: Beginning balance | D58: =NZ_SelProceeds -> 6485211.1 | E58: =D61 -> 6430587.7 | F58: =E61 -> 6372686.9 | G58: =F61 -> 6311312 | H58: =G61 -> 6246254.7 | I58: =H61 -> 6177293.9 | J58: =I61 -> 6104195.4 | K58: =J61 -> 6026711.1 | L58: =K61 -> 5944577.7 | ... W58: =V61 -> 4641125.3
B59: Interest | D59: =D58*$C$57 -> 389112.67 | E59: =E58*$C$57 -> 385835.26 | F59: =F58*$C$57 -> 382361.21 | G59: =G58*$C$57 -> 378678.72 | H59: =H58*$C$57 -> 374775.28 | I59: =I58*$C$57 -> 370637.63 | J59: =J58*$C$57 -> 366251.73 | K59: =K58*$C$57 -> 361602.67 | ... W59: =W58*$C$57 -> 278467.52
B60: Principal | D60: =MAX(0,MIN(D58,$C$62-D59)) -> 54623.409 | E60: =MAX(0,MIN(E58,$C$62-E59)) -> 57900.814 | F60: =MAX(0,MIN(F58,$C$62-F59)) -> 61374.862 | G60: =MAX(0,MIN(G58,$C$62-G59)) -> 65057.354 | H60: =MAX(0,MIN(H58,$C$62-H59)) -> 68960.795 | I60: =MAX(0,MIN(I58,$C$62-I59)) -> 73098.443 | J60: =MAX(0,MIN(J58,$C$62-J59)) -> 77484.35 | K60: =MAX(0,MIN(K58,$C$62-K59)) -> 82133.411 | ... W60: =MAX(0,MIN(W58,$C$62-W59)) -> 165268.56
B61: Ending balance | D61: =D58-D60 -> 6430587.7 | E61: =E58-E60 -> 6372686.9 | F61: =F58-F60 -> 6311312 | G61: =G58-G60 -> 6246254.7 | H61: =H58-H60 -> 6177293.9 | I61: =I58-I60 -> 6104195.4 | J61: =J58-J60 -> 6026711.1 | K61: =K58-K60 -> 5944577.7 | ... W61: =W58-W60 -> 4475856.7
B62: Annual payment | C62: =IF(DebtStrategy="Refinance",NZ_PermLoan*(-PMT(PermRate/12,PermAmort*12,1)*12),12*NZ_NotePI) -> 443736.08

Sheet NZ - Waterfall
A1: SURPLUS CASH-RESERVE WATERFALL — NEW ZION
B3: Year | C3: ="Yr "&1 -> Yr 1 | D3: ="Yr "&2 -> Yr 2 | E3: ="Yr "&3 -> Yr 3 | F3: ="Yr "&4 -> Yr 4 | G3: ="Yr "&5 -> Yr 5 | H3: ="Yr "&6 -> Yr 6 | I3: ="Yr "&7 -> Yr 7 | J3: ="Yr "&8 -> Yr 8 | K3: ="Yr "&9 -> Yr 9 | L3: ="Yr "&10 -> Yr 10 | M3: ="Yr "&11 -> Yr 11 | N3: ="Yr "&12 -> Yr 12 | O3: ="Yr "&13 -> Yr 13 | P3: ="Yr "&14 -> Yr 14 | Q3: ="Yr "&15 -> Yr 15 | R3: ="Yr "&16 -> Yr 16 | S3: ="Yr "&17 -> Yr 17 | T3: ="Yr "&18 -> Yr 18 | U3: ="Yr "&19 -> Yr 19 | V3: ="Yr "&20 -> Yr 20
B5: SURPLUS CASH AVAILABLE | C5: ='NZ - Pro Forma'!D36 -> -34279.475 | D5: ='NZ - Pro Forma'!E36 -> 21388.509 | E5: ='NZ - Pro Forma'!F36 -> 17002.084 | F5: ='NZ - Pro Forma'!G36 -> 12040.945 | G5: ='NZ - Pro Forma'!H36 -> 6472.0917 | H5: ='NZ - Pro Forma'!I36 -> 260.78868 | I5: ='NZ - Pro Forma'!J36 -> -7366.1378 | J5: ='NZ - Pro Forma'!K36 -> -15819.256 | ... V5: ='NZ - Pro Forma'!W36 -> -198478.22
B7: Less: deferred developer fee payment | C7: =MIN(C17,MAX(0,C5)) -> 0 | D7: =MIN(D17,MAX(0,D5)) -> 21388.509 | E7: =MIN(E17,MAX(0,E5)) -> 17002.084 | F7: =MIN(F17,MAX(0,F5)) -> 12040.945 | G7: =MIN(G17,MAX(0,G5)) -> 6472.0917 | H7: =MIN(H17,MAX(0,H5)) -> 260.78868 | I7: =MIN(I17,MAX(0,I5)) -> 0 | J7: =MIN(J17,MAX(0,J5)) -> 0 | ... V7: =MIN(V17,MAX(0,V5)) -> 0
B8: Less: soft-loan payment | C8: =MIN(C23,MAX(0,C5)-C7) -> 0 | D8: =MIN(D23,MAX(0,D5)-D7) -> 0 | E8: =MIN(E23,MAX(0,E5)-E7) -> 0 | F8: =MIN(F23,MAX(0,F5)-F7) -> 0 | G8: =MIN(G23,MAX(0,G5)-G7) -> 0 | H8: =MIN(H23,MAX(0,H5)-H7) -> 0 | I8: =MIN(I23,MAX(0,I5)-I7) -> 0 | J8: =MIN(J23,MAX(0,J5)-J7) -> 0 | ... V8: =MIN(V23,MAX(0,V5)-V7) -> 0
B9: Less: reserve top-up | C9: =MIN(MAX(0,C33-C29),MAX(0,C5)-C7-C8) -> 0 | D9: =MIN(MAX(0,D33-D29),MAX(0,D5)-D7-D8) -> 0 | E9: =MIN(MAX(0,E33-E29),MAX(0,E5)-E7-E8) -> 0 | F9: =MIN(MAX(0,F33-F29),MAX(0,F5)-F7-F8) -> 0 | G9: =MIN(MAX(0,G33-G29),MAX(0,G5)-G7-G8) -> 0 | H9: =MIN(MAX(0,H33-H29),MAX(0,H5)-H7-H8) -> 0 | I9: =MIN(MAX(0,I33-I29),MAX(0,I5)-I7-I8) -> 0 | J9: =MIN(MAX(0,J33-J29),MAX(0,J5)-J7-J8) -> 0 | ... V9: =MIN(MAX(0,V33-V29),MAX(0,V5)-V7-V8) -> 0
B11: Total distributed | C11: =C7+C8+C9 -> 0 | D11: =D7+D8+D9 -> 21388.509 | E11: =E7+E8+E9 -> 17002.084 | F11: =F7+F8+F9 -> 12040.945 | G11: =G7+G8+G9 -> 6472.0917 | H11: =H7+H8+H9 -> 260.78868 | I11: =I7+I8+I9 -> 0 | J11: =J7+J8+J9 -> 0 | ... V11: =V7+V8+V9 -> 0
B13: Undistributed surplus / (deficit) | C13: =C5-C11 -> -34279.475 | D13: =D5-D11 -> 0 | E13: =E5-E11 -> 0 | F13: =F5-F11 -> 0 | G13: =G5-G11 -> 0 | H13: =H5-H11 -> 0 | I13: =I5-I11 -> -7366.1378 | J13: =J5-J11 -> -15819.256 | ... V13: =V5-V11 -> -198478.22
B16: DEFERRED DEVELOPER FEE PAYDOWN
B17: Beginning balance | C17: ='Sources & Uses'!D10 -> 1010943.4 | D17: =C19 -> 1010943.4 | E17: =D19 -> 989554.89 | F17: =E19 -> 972552.81 | G17: =F19 -> 960511.86 | H17: =G19 -> 954039.77 | I17: =H19 -> 953778.98 | J17: =I19 -> 953778.98 | K17: =J19 -> 953778.98 | ... V17: =U19 -> 953778.98
B18: Less: payment | C18: =C7 -> 0 | D18: =D7 -> 21388.509 | E18: =E7 -> 17002.084 | F18: =F7 -> 12040.945 | G18: =G7 -> 6472.0917 | H18: =H7 -> 260.78868 | I18: =I7 -> 0 | J18: =J7 -> 0 | ... V18: =V7 -> 0
B19: Ending balance | C19: =C17-C18 -> 1010943.4 | D19: =D17-D18 -> 989554.89 | E19: =E17-E18 -> 972552.81 | F19: =F17-F18 -> 960511.86 | G19: =G17-G18 -> 954039.77 | H19: =H17-H18 -> 953778.98 | I19: =I17-I18 -> 953778.98 | J19: =J17-J18 -> 953778.98 | ... V19: =V17-V18 -> 953778.98
B22: SOFT LOAN PAYDOWN
B23: Beginning balance | C23: ='Sources & Uses'!D12 -> 148039.11 | D23: =C25 -> 148039.11 | E23: =D25 -> 148039.11 | F23: =E25 -> 148039.11 | G23: =F25 -> 148039.11 | H23: =G25 -> 148039.11 | I23: =H25 -> 148039.11 | J23: =I25 -> 148039.11 | K23: =J25 -> 148039.11 | ... V23: =U25 -> 148039.11
B24: Less: payment | C24: =C8 -> 0 | D24: =D8 -> 0 | E24: =E8 -> 0 | F24: =F8 -> 0 | G24: =G8 -> 0 | H24: =H8 -> 0 | I24: =I8 -> 0 | J24: =J8 -> 0 | ... V24: =V8 -> 0
B25: Ending balance | C25: =C23-C24 -> 148039.11 | D25: =D23-D24 -> 148039.11 | E25: =E23-E24 -> 148039.11 | F25: =F23-F24 -> 148039.11 | G25: =G23-G24 -> 148039.11 | H25: =H23-H24 -> 148039.11 | I25: =I23-I24 -> 148039.11 | J25: =J23-J24 -> 148039.11 | ... V25: =V23-V24 -> 148039.11
B28: RESERVE ACCOUNT
B29: Beginning balance | C29: ='Sources & Uses'!D23 -> 451806.23 | D29: =C32 -> 417526.75 | E29: =D32 -> 417526.75 | F29: =E32 -> 417526.75 | G29: =F32 -> 417526.75 | H29: =G32 -> 417526.75 | I29: =H32 -> 417526.75 | J29: =I32 -> 410160.61 | K29: =J32 -> 394341.36 | ... V29: =U32 -> 0
B30: Plus: reserve funding | C30: =C9 -> 0 | D30: =D9 -> 0 | E30: =E9 -> 0 | F30: =F9 -> 0 | G30: =G9 -> 0 | H30: =H9 -> 0 | I30: =I9 -> 0 | J30: =J9 -> 0 | ... V30: =V9 -> 0
B31: Less: operating-deficit draw | C31: =MIN(C29,MAX(0,-C5)) -> 34279.475 | D31: =MIN(D29,MAX(0,-D5)) -> 0 | E31: =MIN(E29,MAX(0,-E5)) -> 0 | F31: =MIN(F29,MAX(0,-F5)) -> 0 | G31: =MIN(G29,MAX(0,-G5)) -> 0 | H31: =MIN(H29,MAX(0,-H5)) -> 0 | I31: =MIN(I29,MAX(0,-I5)) -> 7366.1378 | J31: =MIN(J29,MAX(0,-J5)) -> 15819.256 | ... V31: =MIN(V29,MAX(0,-V5)) -> 0
B32: Ending balance | C32: =C29+C30-C31 -> 417526.75 | D32: =D29+D30-D31 -> 417526.75 | E32: =E29+E30-E31 -> 417526.75 | F32: =F29+F30-F31 -> 417526.75 | G32: =G29+G30-G31 -> 417526.75 | H32: =H29+H30-H31 -> 417526.75 | I32: =I29+I30-I31 -> 410160.61 | J32: =J29+J30-J31 -> 394341.36 | ... V32: =V29+V30-V31 -> 0
B33: Target (operating reserve) | C33: ='Sources & Uses'!D23 -> 451806.23 | D33: ='Sources & Uses'!D23 -> 451806.23 | E33: ='Sources & Uses'!D23 -> 451806.23 | F33: ='Sources & Uses'!D23 -> 451806.23 | G33: ='Sources & Uses'!D23 -> 451806.23 | H33: ='Sources & Uses'!D23 -> 451806.23 | I33: ='Sources & Uses'!D23 -> 451806.23 | J33: ='Sources & Uses'!D23 -> 451806.23 | K33: ='Sources & Uses'!D23 -> 451806.23 | L33: ='Sources & Uses'!D23 -> 451806.23 | M33: ='Sources & Uses'!D23 -> 451806.23 | N33: ='Sources & Uses'!D23 -> 451806.23 | O33: ='Sources & Uses'!D23 -> 451806.23 | P33: ='Sources & Uses'!D23 -> 451806.23 | Q33: ='Sources & Uses'!D23 -> 451806.23 | R33: ='Sources & Uses'!D23 -> 451806.23 | S33: ='Sources & Uses'!D23 -> 451806.23 | T33: ='Sources & Uses'!D23 -> 451806.23 | U33: ='Sources & Uses'!D23 -> 451806.23 | V33: ='Sources & Uses'!D23 -> 451806.23
B35: DDF fully repaid in year | C35: =IFERROR(MATCH(0,C19:V19,0),"NOT REPAID") -> NOT REPAID
B36: NZ HOME loan is repaid at the resyndication close (see Financing) — the soft-loan block above is for any future soft money.

Sheet LOM - Pro Forma
A1: CASH FLOW FORECAST — LIVE OAK MANOR
B2: 20 years from this property's resyndication close. Rehab-period offline disruption per Rehab Scope; debt service per the amortization block below (strategy toggle on Dashboard). Equity pay-ins reference the Tax Credit Calc block — single source of truth.
B3: Year | D3: Yr 1 | E3: Yr 2 | F3: Yr 3 | G3: Yr 4 | H3: Yr 5 | I3: Yr 6 | J3: Yr 7 | K3: Yr 8 | L3: Yr 9 | M3: Yr 10 | N3: Yr 11 | O3: Yr 12 | P3: Yr 13 | Q3: Yr 14 | R3: Yr 15 | S3: Yr 16 | T3: Yr 17 | U3: Yr 18 | V3: Yr 19 | W3: Yr 20 | X3: TOTAL
B4: Calendar year | D4: =YEAR(LOM_ResynDate)+0 -> 2029 | E4: =YEAR(LOM_ResynDate)+1 -> 2030 | F4: =YEAR(LOM_ResynDate)+2 -> 2031 | G4: =YEAR(LOM_ResynDate)+3 -> 2032 | H4: =YEAR(LOM_ResynDate)+4 -> 2033 | I4: =YEAR(LOM_ResynDate)+5 -> 2034 | J4: =YEAR(LOM_ResynDate)+6 -> 2035 | K4: =YEAR(LOM_ResynDate)+7 -> 2036 | L4: =YEAR(LOM_ResynDate)+8 -> 2037 | M4: =YEAR(LOM_ResynDate)+9 -> 2038 | N4: =YEAR(LOM_ResynDate)+10 -> 2039 | O4: =YEAR(LOM_ResynDate)+11 -> 2040 | P4: =YEAR(LOM_ResynDate)+12 -> 2041 | Q4: =YEAR(LOM_ResynDate)+13 -> 2042 | R4: =YEAR(LOM_ResynDate)+14 -> 2043 | S4: =YEAR(LOM_ResynDate)+15 -> 2044 | T4: =YEAR(LOM_ResynDate)+16 -> 2045 | U4: =YEAR(LOM_ResynDate)+17 -> 2046 | V4: =YEAR(LOM_ResynDate)+18 -> 2047 | W4: =YEAR(LOM_ResynDate)+19 -> 2048
B6: Gross rental income | D6: =LOM_GPR -> 1791762.3 | E6: =D6*(1+$D$50) -> 1825357.8 | F6: =E6*(1+$D$50) -> 1859583.3 | G6: =F6*(1+$D$50) -> 1894450.5 | H6: =G6*(1+$D$50) -> 1929971.4 | I6: =H6*(1+$D$50) -> 1966158.4 | J6: =I6*(1+$D$50) -> 2003023.9 | K6: =J6*(1+$D$50) -> 2040580.6 | L6: =K6*(1+$D$50) -> 2078841.5 | ... W6: =V6*(1+$D$50) -> 2550147
B7: Other income | D7: =LOM_OtherInc -> 12732 | E7: =D7*(1+$D$50) -> 12970.725 | F7: =E7*(1+$D$50) -> 13213.926 | G7: =F7*(1+$D$50) -> 13461.687 | H7: =G7*(1+$D$50) -> 13714.094 | I7: =H7*(1+$D$50) -> 13971.233 | J7: =I7*(1+$D$50) -> 14233.194 | K7: =J7*(1+$D$50) -> 14500.066 | L7: =K7*(1+$D$50) -> 14771.942 | ... W7: =V7*(1+$D$50) -> 18120.97
B9: Gross revenue | D9: =SUM(D6:D7) -> 1804494.3 | E9: =SUM(E6:E7) -> 1838328.6 | F9: =SUM(F6:F7) -> 1872797.2 | G9: =SUM(G6:G7) -> 1907912.2 | H9: =SUM(H6:H7) -> 1943685.5 | I9: =SUM(I6:I7) -> 1980129.6 | J9: =SUM(J6:J7) -> 2017257.1 | K9: =SUM(K6:K7) -> 2055080.6 | ... W9: =SUM(W6:W7) -> 2568267.9 | X9: =SUM(D9:W9) -> 43302861
B10: Vacancy | D10: =-LOM_VacHAP*D9 -> -136419.77 | E10: =-LOM_VacHAP*E9 -> -138977.64 | F10: =-LOM_VacHAP*F9 -> -141583.47 | G10: =-LOM_VacHAP*G9 -> -144238.16 | H10: =-LOM_VacHAP*H9 -> -146942.63 | I10: =-LOM_VacHAP*I9 -> -149697.8 | J10: =-LOM_VacHAP*J9 -> -152504.63 | K10: =-LOM_VacHAP*K9 -> -155364.1 | ... W10: =-LOM_VacHAP*W9 -> -194161.05
B11: Rehab offline adjustment | D11: =-D9*LOM_OfflinePct*MAX(0,MIN(LOM_RehabMonths-0,12))/12 -> -60655.271 | E11: =-E9*LOM_OfflinePct*MAX(0,MIN(LOM_RehabMonths-12,12))/12 -> -15448.139 | F11: =-F9*LOM_OfflinePct*MAX(0,MIN(LOM_RehabMonths-24,12))/12 -> 0 | G11: =-G9*LOM_OfflinePct*MAX(0,MIN(LOM_RehabMonths-36,12))/12 -> 0 | H11: =-H9*LOM_OfflinePct*MAX(0,MIN(LOM_RehabMonths-48,12))/12 -> 0 | I11: =-I9*LOM_OfflinePct*MAX(0,MIN(LOM_RehabMonths-60,12))/12 -> 0 | J11: =-J9*LOM_OfflinePct*MAX(0,MIN(LOM_RehabMonths-72,12))/12 -> 0 | K11: =-K9*LOM_OfflinePct*MAX(0,MIN(LOM_RehabMonths-84,12))/12 -> 0 | L11: =-L9*LOM_OfflinePct*MAX(0,MIN(LOM_RehabMonths-96,12))/12 -> 0 | M11: =-M9*LOM_OfflinePct*MAX(0,MIN(LOM_RehabMonths-108,12))/12 -> 0 | N11: =-N9*LOM_OfflinePct*MAX(0,MIN(LOM_RehabMonths-120,12))/12 -> 0 | O11: =-O9*LOM_OfflinePct*MAX(0,MIN(LOM_RehabMonths-132,12))/12 -> 0 | P11: =-P9*LOM_OfflinePct*MAX(0,MIN(LOM_RehabMonths-144,12))/12 -> 0 | Q11: =-Q9*LOM_OfflinePct*MAX(0,MIN(LOM_RehabMonths-156,12))/12 -> 0 | R11: =-R9*LOM_OfflinePct*MAX(0,MIN(LOM_RehabMonths-168,12))/12 -> 0 | S11: =-S9*LOM_OfflinePct*MAX(0,MIN(LOM_RehabMonths-180,12))/12 -> 0 | T11: =-T9*LOM_OfflinePct*MAX(0,MIN(LOM_RehabMonths-192,12))/12 -> 0 | U11: =-U9*LOM_OfflinePct*MAX(0,MIN(LOM_RehabMonths-204,12))/12 -> 0 | V11: =-V9*LOM_OfflinePct*MAX(0,MIN(LOM_RehabMonths-216,12))/12 -> 0 | W11: =-W9*LOM_OfflinePct*MAX(0,MIN(LOM_RehabMonths-228,12))/12 -> 0
B13: Net revenue | D13: =D9+D10+D11 -> 1607419.3 | E13: =E9+E10+E11 -> 1683902.8 | F13: =F9+F10+F11 -> 1731213.8 | G13: =G9+G10+G11 -> 1763674 | H13: =H9+H10+H11 -> 1796742.9 | I13: =I9+I10+I11 -> 1830431.8 | J13: =J9+J10+J11 -> 1864752.4 | K13: =K9+K10+K11 -> 1899716.5 | ... W13: =W9+W10+W11 -> 2374106.9 | X13: =SUM(D13:W13) -> 39953061
B15: Operating Expenses
B16: Management fee | D16: =MgmtFeePct*D13 -> 64296.77 | E16: =MgmtFeePct*E13 -> 67356.111 | F16: =MgmtFeePct*F13 -> 69248.55 | G16: =MgmtFeePct*G13 -> 70546.961 | H16: =MgmtFeePct*H13 -> 71869.716 | I16: =MgmtFeePct*I13 -> 73217.273 | J16: =MgmtFeePct*J13 -> 74590.097 | K16: =MgmtFeePct*K13 -> 75988.661 | ... W16: =MgmtFeePct*W13 -> 94964.275
B17: Administrative (ex-mgmt) | D17: ='Rev+Expenses'!E19 -> 175065.79 | E17: =D17*(1+$D$51) -> 180317.77 | F17: =E17*(1+$D$51) -> 185727.3 | G17: =F17*(1+$D$51) -> 191299.12 | H17: =G17*(1+$D$51) -> 197038.09 | I17: =H17*(1+$D$51) -> 202949.23 | J17: =I17*(1+$D$51) -> 209037.71 | K17: =J17*(1+$D$51) -> 215308.84 | L17: =K17*(1+$D$51) -> 221768.11 | ... W17: =V17*(1+$D$51) -> 306978.93
B18: Utilities | D18: ='Rev+Expenses'!E20 -> 134399.96 | E18: =D18*(1+$D$51) -> 138431.96 | F18: =E18*(1+$D$51) -> 142584.91 | G18: =F18*(1+$D$51) -> 146862.46 | H18: =G18*(1+$D$51) -> 151268.34 | I18: =H18*(1+$D$51) -> 155806.39 | J18: =I18*(1+$D$51) -> 160480.58 | K18: =J18*(1+$D$51) -> 165295 | L18: =K18*(1+$D$51) -> 170253.84 | ... W18: =V18*(1+$D$51) -> 235671.14
B19: Operating & maintenance | D19: ='Rev+Expenses'!E21 -> 409497.26 | E19: =D19*(1+$D$51) -> 421782.18 | F19: =E19*(1+$D$51) -> 434435.64 | G19: =F19*(1+$D$51) -> 447468.71 | H19: =G19*(1+$D$51) -> 460892.77 | I19: =H19*(1+$D$51) -> 474719.55 | J19: =I19*(1+$D$51) -> 488961.14 | K19: =J19*(1+$D$51) -> 503629.98 | L19: =K19*(1+$D$51) -> 518738.87 | ... W19: =V19*(1+$D$51) -> 718055.92
B20: Taxes + other T&I (ex-insurance) | D20: ='Rev+Expenses'!E22 -> 64905.798 | E20: =D20*(1+$D$51) -> 66852.972 | F20: =E20*(1+$D$51) -> 68858.561 | G20: =F20*(1+$D$51) -> 70924.318 | H20: =G20*(1+$D$51) -> 73052.048 | I20: =H20*(1+$D$51) -> 75243.609 | J20: =I20*(1+$D$51) -> 77500.918 | K20: =J20*(1+$D$51) -> 79825.945 | L20: =K20*(1+$D$51) -> 82220.723 | ... W20: =V20*(1+$D$51) -> 113812.71
B21: Property insurance | D21: ='Rev+Expenses'!E23 -> 205310.91 | E21: =D21*(1+InsGrowth) -> 217629.57 | F21: =E21*(1+InsGrowth) -> 230687.34 | G21: =F21*(1+InsGrowth) -> 244528.58 | H21: =G21*(1+InsGrowth) -> 259200.29 | I21: =H21*(1+InsGrowth) -> 274752.31 | J21: =I21*(1+InsGrowth) -> 291237.45 | K21: =J21*(1+InsGrowth) -> 308711.7 | L21: =K21*(1+InsGrowth) -> 327234.4 | ... W21: =V21*(1+InsGrowth) -> 621188.59
B23: Total operating expenses | D23: =SUM(D16:D21) -> 1053476.5 | E23: =SUM(E16:E21) -> 1092370.5 | F23: =SUM(F16:F21) -> 1131542.3 | G23: =SUM(G16:G21) -> 1171630.1 | H23: =SUM(H16:H21) -> 1213321.3 | I23: =SUM(I16:I21) -> 1256688.4 | J23: =SUM(J16:J21) -> 1301807.9 | K23: =SUM(K16:K21) -> 1348760.1 | ... W23: =SUM(W16:W21) -> 2090671.6 | X23: =SUM(D23:W23) -> 30213454
B25: NET OPERATING INCOME | D25: =D13-D23 -> 553942.77 | E25: =E13-E23 -> 591532.24 | F25: =F13-F23 -> 599671.45 | G25: =G13-G23 -> 592043.86 | H25: =H13-H23 -> 583421.64 | I25: =I13-I23 -> 573743.46 | J25: =J13-J23 -> 562944.53 | K25: =K13-K23 -> 550956.42 | ... W25: =W13-W23 -> 283435.3 | X25: =SUM(D25:W25) -> 9739607.4
B27: Replacement reserves | D27: =LOM_ReservesStab -> 45512.08 | E27: =D27*(1+$D$51) -> 46877.442 | F27: =E27*(1+$D$51) -> 48283.765 | G27: =F27*(1+$D$51) -> 49732.278 | H27: =G27*(1+$D$51) -> 51224.246 | I27: =H27*(1+$D$51) -> 52760.974 | J27: =I27*(1+$D$51) -> 54343.803 | K27: =J27*(1+$D$51) -> 55974.117 | L27: =K27*(1+$D$51) -> 57653.341 | ... W27: =V27*(1+$D$51) -> 79805.707
B29: Debt service — interest | D29: =D59 -> 467499.53 | E29: =E59 -> 463561.89 | F29: =F59 -> 459387.99 | G29: =G59 -> 454963.66 | H29: =H59 -> 450273.87 | I29: =I59 -> 445302.7 | J29: =J59 -> 440033.25 | K29: =K59 -> 434447.63 | ... W29: =W59 -> 334564.88
B30: Debt service — principal | D30: =D60 -> 65627.311 | E30: =E60 -> 69564.95 | F30: =F60 -> 73738.847 | G30: =G60 -> 78163.178 | H30: =H60 -> 82852.968 | I30: =I60 -> 87824.146 | J30: =J60 -> 93093.595 | K30: =K60 -> 98679.211 | ... W30: =W60 -> 198561.96
B32: Cash flow after debt service | D32: =D25-D27-D29-D30 -> -24696.151 | E32: =E25-E27-E29-E30 -> 11527.956 | F32: =F25-F27-F29-F30 -> 18260.843 | G32: =G25-G27-G29-G30 -> 9184.7445 | H32: =H25-H27-H29-H30 -> -929.44469 | I32: =I25-I27-I29-I30 -> -12144.355 | J32: =J25-J27-J29-J30 -> -24526.114 | K32: =K25-K27-K29-K30 -> -38144.541 | ... W32: =W25-W27-W29-W30 -> -329497.24
B34: Asset management fee | D34: =IF((CashFlowCeilPct*D32)<=0,0,CashFlowCeilPct*D32) -> 0 | E34: =IF((CashFlowCeilPct*E32)<=0,0,CashFlowCeilPct*E32) -> 1152.7956 | F34: =IF((CashFlowCeilPct*F32)<=0,0,CashFlowCeilPct*F32) -> 1826.0843 | G34: =IF((CashFlowCeilPct*G32)<=0,0,CashFlowCeilPct*G32) -> 918.47445 | H34: =IF((CashFlowCeilPct*H32)<=0,0,CashFlowCeilPct*H32) -> 0 | I34: =IF((CashFlowCeilPct*I32)<=0,0,CashFlowCeilPct*I32) -> 0 | J34: =IF((CashFlowCeilPct*J32)<=0,0,CashFlowCeilPct*J32) -> 0 | K34: =IF((CashFlowCeilPct*K32)<=0,0,CashFlowCeilPct*K32) -> 0 | ... W34: =IF((CashFlowCeilPct*W32)<=0,0,CashFlowCeilPct*W32) -> 0
B36: CASH AVAILABLE AFTER FEES | D36: =D32-D34 -> -24696.151 | E36: =E32-E34 -> 10375.16 | F36: =F32-F34 -> 16434.758 | G36: =G32-G34 -> 8266.27 | H36: =H32-H34 -> -929.44469 | I36: =I32-I34 -> -12144.355 | J36: =J32-J34 -> -24526.114 | K36: =K32-K34 -> -38144.541 | ... W36: =W32-W34 -> -329497.24 | X36: =SUM(D36:W36) -> -2149753.4
B37: Surplus cash distribution — see the Waterfall tab
B39: DSCR | D39: =IF((D29+D30)=0,0,D25/(D29+D30)) -> 1.039045 | E39: =IF((E29+E30)=0,0,E25/(E29+E30)) -> 1.1095525 | F39: =IF((F29+F30)=0,0,F25/(F29+F30)) -> 1.1248195 | G39: =IF((G29+G30)=0,0,G25/(G29+G30)) -> 1.1105122 | H39: =IF((H29+H30)=0,0,H25/(H29+H30)) -> 1.0943393 | I39: =IF((I29+I30)=0,0,I25/(I29+I30)) -> 1.0761857 | J39: =IF((J29+J30)=0,0,J25/(J29+J30)) -> 1.0559298 | K39: =IF((K29+K30)=0,0,K25/(K29+K30)) -> 1.0334434 | ... W39: =IF((W29+W30)=0,0,W25/(W29+W30)) -> 0.53164703
