Workbook
Name AMFeeCap: QAP_Rule_Register!$H$23
Name ArchPct: QAP_Rule_Register!$H$16
Name BoostCapPct: QAP_Rule_Register!$H$10
Name BoostEligible: 'Dashboard Calc'!$B$6
Name BuilderOHPct: QAP_Rule_Register!$H$18
Name BuilderProfitPct: QAP_Rule_Register!$H$17
Name BuildingType: 'Dashboard Calc'!$B$10
Name CashFlowCeilPct: QAP_Rule_Register!$H$36
Name checks_paid: #N/A
Name ContingencyPct: QAP_Rule_Register!$H$20
Name CreditType: 'Dashboard Calc'!$B$5
Name DeferredFee: 'Dashboard Calc'!$B$13
Name DevFeeCapAbs: QAP_Rule_Register!$B$48
Name DevFeeCapPct: QAP_Rule_Register!$B$49
Name DSCR15Floor: QAP_Rule_Register!$B$54
Name DSCRCeil: QAP_Rule_Register!$B$53
Name DSCRFloor: QAP_Rule_Register!$B$52
Name EXP: #N/A
Name ExpTrendMin: QAP_Rule_Register!$H$30
Name GenReqPct: QAP_Rule_Register!$H$19
Name HUDTDCLimit: 'Dashboard Calc'!$B$12
Name MEMORANDUM: "memo1"
Name MGMT: #N/A
Name OpexMinPU: QAP_Rule_Register!$H$21
Name OpReserveFrac: QAP_Rule_Register!$H$22
Name Pool: 'Dashboard Calc'!$B$9
Name PoolCapMetro: QAP_Rule_Register!$B$44
Name PoolCapReproc: QAP_Rule_Register!$B$47
Name PoolCapRural: QAP_Rule_Register!$B$45
Name PoolCapRuralQNP: QAP_Rule_Register!$B$46
Name ProjectName: 'Dashboard Calc'!$B$3
Name ProjectType: 'Dashboard Calc'!$B$4
Name RDHUD: 'Dashboard Calc'!$B$7
Name RENT: #N/A
Name RentTrendMax: QAP_Rule_Register!$H$28
Name ReserveFloorFamily: QAP_Rule_Register!$B$42
Name ReserveFloorRehab: QAP_Rule_Register!$B$43
Name ReserveFloorSenior: QAP_Rule_Register!$B$41
Name SUBalanceTol: QAP_Rule_Register!$H$32
Name SyndCapPriv: QAP_Rule_Register!$B$50
Name SyndCapPub: QAP_Rule_Register!$B$51
Name Syndication: 'Dashboard Calc'!$B$8
Name VAC: #N/A
Name VacancyMin: QAP_Rule_Register!$H$26

Sheet Model Scorecard
A1: ='Dashboard Calc'!B3&" Scorecard" -> Westbend Scorecard
A2: Metric | B2: Value | C2: Test | D2: Threshold | E2: Status | F2: Severity
A3: DSCR
A4: ='Dashboard Calc'!M9 -> Annual DSCR band (Yr2-17) | B4: ='Dashboard Calc'!N9 -> 1.2459969 | C4: band | D4: ='Dashboard Calc'!O9 -> 1.15-1.40 | E4: ='Dashboard Calc'!P9 -> FAIL | F4: =IF('Dashboard Calc'!P9<>"FAIL","",IF('Dashboard Calc'!Q9="error","Hard fail",IF('Dashboard Calc'!Q9="warning","Warning","Info"))) -> Hard fail
A5: ='Dashboard Calc'!M10 -> 15-yr projected DSCR (y5/10/15) | B5: ='Dashboard Calc'!N10 -> 1.2640715 | C5: band | D5: ='Dashboard Calc'!O10 -> 1.00-1.40 | E5: ='Dashboard Calc'!P10 -> FAIL | F5: =IF('Dashboard Calc'!P10<>"FAIL","",IF('Dashboard Calc'!Q10="error","Hard fail",IF('Dashboard Calc'!Q10="warning","Warning","Info"))) -> Hard fail
A6: CASH FLOW & DEFERRED FEE
A7: ='Dashboard Calc'!M29 -> Year-1 cash-flow ceiling | B7: ='Dashboard Calc'!N29 -> 274844.28 | C7: ≤ | D7: ='Dashboard Calc'!O29 -> 133198.81 | E7: ='Dashboard Calc'!P29 -> FAIL | F7: =IF('Dashboard Calc'!P29<>"FAIL","",IF('Dashboard Calc'!Q29="error","Hard fail",IF('Dashboard Calc'!Q29="warning","Warning","Info"))) -> Warning
A8: ='Dashboard Calc'!M30 -> Deferred dev-fee payoff by Yr15 | B8: ='Dashboard Calc'!N30 -> 3865332.1 | C8: ≥ | D8: ='Dashboard Calc'!O30 -> 2131813.1 | E8: ='Dashboard Calc'!P30 -> PASS | F8: =IF('Dashboard Calc'!P30<>"FAIL","",IF('Dashboard Calc'!Q30="error","Hard fail",IF('Dashboard Calc'!Q30="warning","Warning","Info")))
A9: COST & TDC
A10: ='Dashboard Calc'!M35 -> Per-unit TDC vs QAP max | B10: ='Dashboard Calc'!N35 -> 181600.1 | C10: ≤ | D10: ='Dashboard Calc'!O35 -> 247226.11 | E10: ='Dashboard Calc'!P35 -> PASS | F10: =IF('Dashboard Calc'!P35<>"FAIL","",IF('Dashboard Calc'!Q35="error","Hard fail",IF('Dashboard Calc'!Q35="warning","Warning","Info")))
A11: ='Dashboard Calc'!M36 -> Total TDC vs QAP max | B11: ='Dashboard Calc'!N36 -> 50848028 | C11: ≤ | D11: ='Dashboard Calc'!O36 -> 69223310 | E11: ='Dashboard Calc'!P36 -> PASS | F11: =IF('Dashboard Calc'!P36<>"FAIL","",IF('Dashboard Calc'!Q36="error","Hard fail",IF('Dashboard Calc'!Q36="warning","Warning","Info")))
A12: ='Dashboard Calc'!M26 -> HUD Total Dev Cost limit | B12: ='Dashboard Calc'!N26 -> 50848028 | C12: ≤ | D12: ='Dashboard Calc'!O26 -> 69223310 | E12: ='Dashboard Calc'!P26 -> PASS | F12: =IF('Dashboard Calc'!P26<>"FAIL","",IF('Dashboard Calc'!Q26="error","Hard fail",IF('Dashboard Calc'!Q26="warning","Warning","Info")))
A13: FEE LIMITS
A14: ='Dashboard Calc'!M11 -> Developer fee | B14: ='Dashboard Calc'!N11 -> 5921703 | C14: ≤ | D14: ='Dashboard Calc'!O11 -> No cap (4% bond) | E14: ='Dashboard Calc'!P11 -> PASS | F14: =IF('Dashboard Calc'!P11<>"FAIL","",IF('Dashboard Calc'!Q11="error","Hard fail",IF('Dashboard Calc'!Q11="warning","Warning","Info")))
A15: ='Dashboard Calc'!M12 -> Architect / design fee | B15: ='Dashboard Calc'!N12 -> 750000 | C15: ≤ | D15: ='Dashboard Calc'!O12 -> 2440288.8 | E15: ='Dashboard Calc'!P12 -> PASS | F15: =IF('Dashboard Calc'!P12<>"FAIL","",IF('Dashboard Calc'!Q12="error","Hard fail",IF('Dashboard Calc'!Q12="warning","Warning","Info")))
A16: ='Dashboard Calc'!M13 -> Builder profit | B16: ='Dashboard Calc'!N13 -> 1834803.6 | C16: ≤ | D16: ='Dashboard Calc'!O13 -> 1834803.6 | E16: ='Dashboard Calc'!P13 -> PASS | F16: =IF('Dashboard Calc'!P13<>"FAIL","",IF('Dashboard Calc'!Q13="error","Hard fail",IF('Dashboard Calc'!Q13="warning","Warning","Info")))
A17: ='Dashboard Calc'!M14 -> Builder overhead | B17: ='Dashboard Calc'!N14 -> 611601.21 | C17: ≤ | D17: ='Dashboard Calc'!O14 -> 611601.21 | E17: ='Dashboard Calc'!P14 -> PASS | F17: =IF('Dashboard Calc'!P14<>"FAIL","",IF('Dashboard Calc'!Q14="error","Hard fail",IF('Dashboard Calc'!Q14="warning","Warning","Info")))
A18: ='Dashboard Calc'!M15 -> General requirements | B18: ='Dashboard Calc'!N15 -> 1834803.6 | C18: ≤ | D18: ='Dashboard Calc'!O15 -> 1834803.6 | E18: ='Dashboard Calc'!P15 -> PASS | F18: =IF('Dashboard Calc'!P15<>"FAIL","",IF('Dashboard Calc'!Q15="error","Hard fail",IF('Dashboard Calc'!Q15="warning","Warning","Info")))
A19: ='Dashboard Calc'!M16 -> Construction contingency | B19: ='Dashboard Calc'!N16 -> 1660060.4 | C19: ≤ | D19: ='Dashboard Calc'!O16 -> 3486126.9 | E19: ='Dashboard Calc'!P16 -> PASS | F19: =IF('Dashboard Calc'!P16<>"FAIL","",IF('Dashboard Calc'!Q16="error","Hard fail",IF('Dashboard Calc'!Q16="warning","Warning","Info")))
A20: OPERATING & RESERVES
A21: ='Dashboard Calc'!M17 -> Minimum operating expenses | B21: ='Dashboard Calc'!N17 -> 1331988.1 | C21: ≥ | D21: ='Dashboard Calc'!O17 -> 1260000 | E21: ='Dashboard Calc'!P17 -> PASS | F21: =IF('Dashboard Calc'!P17<>"FAIL","",IF('Dashboard Calc'!Q17="error","Hard fail",IF('Dashboard Calc'!Q17="warning","Warning","Info")))
A22: ='Dashboard Calc'!M18 -> Operating reserve (6 mo) | B22: ='Dashboard Calc'!N18 -> 665994.03 | C22: ≥ | D22: ='Dashboard Calc'!O18 -> 665994.03 | E22: ='Dashboard Calc'!P18 -> PASS | F22: =IF('Dashboard Calc'!P18<>"FAIL","",IF('Dashboard Calc'!Q18="error","Hard fail",IF('Dashboard Calc'!Q18="warning","Warning","Info")))
A23: ='Dashboard Calc'!M20 -> Repl-reserve adequacy (all yrs) | B23: ='Dashboard Calc'!N20 -> 500 | C23: ≥ | D23: ='Dashboard Calc'!O20 -> 350 | E23: ='Dashboard Calc'!P20 -> PASS | F23: =IF('Dashboard Calc'!P20<>"FAIL","",IF('Dashboard Calc'!Q20="error","Hard fail",IF('Dashboard Calc'!Q20="warning","Warning","Info")))
A24: VACANCY & TRENDING
A25: ='Dashboard Calc'!M21 -> Vacancy, years 1-3 | B25: ='Dashboard Calc'!N21 -> 0.07 | C25: ≥ | D25: ='Dashboard Calc'!O21 -> 0.07 | E25: ='Dashboard Calc'!P21 -> PASS | F25: =IF('Dashboard Calc'!P21<>"FAIL","",IF('Dashboard Calc'!Q21="error","Hard fail",IF('Dashboard Calc'!Q21="warning","Warning","Info")))
A26: ='Dashboard Calc'!M22 -> Vacancy, years 4+ | B26: ='Dashboard Calc'!N22 -> 0.07 | C26: ≥ | D26: ='Dashboard Calc'!O22 -> 0.07 | E26: ='Dashboard Calc'!P22 -> PASS | F26: =IF('Dashboard Calc'!P22<>"FAIL","",IF('Dashboard Calc'!Q22="error","Hard fail",IF('Dashboard Calc'!Q22="warning","Warning","Info")))
A27: ='Dashboard Calc'!M23 -> Rent inflation, years 1-3 | B27: ='Dashboard Calc'!N23 -> 0.02 | C27: ≤ | D27: ='Dashboard Calc'!O23 -> 0.02 | E27: ='Dashboard Calc'!P23 -> PASS | F27: =IF('Dashboard Calc'!P23<>"FAIL","",IF('Dashboard Calc'!Q23="error","Hard fail",IF('Dashboard Calc'!Q23="warning","Warning","Info")))
A28: ='Dashboard Calc'!M24 -> Rent inflation, years 4-15 | B28: ='Dashboard Calc'!N24 -> 0.02 | C28: ≤ | D28: ='Dashboard Calc'!O24 -> 0.02 | E28: ='Dashboard Calc'!P24 -> PASS | F28: =IF('Dashboard Calc'!P24<>"FAIL","",IF('Dashboard Calc'!Q24="error","Hard fail",IF('Dashboard Calc'!Q24="warning","Warning","Info")))
A29: ='Dashboard Calc'!M25 -> Expense inflation (payroll YoY) | B29: ='Dashboard Calc'!N25 -> 0.03 | C29: ≥ | D29: ='Dashboard Calc'!O25 -> 0.028 | E29: ='Dashboard Calc'!P25 -> PASS | F29: =IF('Dashboard Calc'!P25<>"FAIL","",IF('Dashboard Calc'!Q25="error","Hard fail",IF('Dashboard Calc'!Q25="warning","Warning","Info")))
A30: CREDIT STRUCTURE & SIZING
A31: ='Dashboard Calc'!M3 -> 4% credit requires bonds | B31: ='Dashboard Calc'!N3 -> 26629504 | C31: > | D31: ='Dashboard Calc'!O3 -> Bonds > $0 | E31: ='Dashboard Calc'!P3 -> PASS | F31: =IF('Dashboard Calc'!P3<>"FAIL","",IF('Dashboard Calc'!Q3="error","Hard fail",IF('Dashboard Calc'!Q3="warning","Warning","Info")))
A32: ='Dashboard Calc'!M4 -> 9% + bonds mutually exclusive | B32: ='Dashboard Calc'!N4 -> n/a | C32: = | D32: ='Dashboard Calc'!O4 -> Bonds = $0 | E32: ='Dashboard Calc'!P4 -> N/A | F32: =IF('Dashboard Calc'!P4<>"FAIL","",IF('Dashboard Calc'!Q4="error","Hard fail",IF('Dashboard Calc'!Q4="warning","Warning","Info")))
A33: ='Dashboard Calc'!M5 -> Construction basis boost cap | B33: ='Dashboard Calc'!N5 -> 0 | C33: ≤ | D33: ='Dashboard Calc'!O5 -> 0.3 | E33: ='Dashboard Calc'!P5 -> PASS | F33: =IF('Dashboard Calc'!P5<>"FAIL","",IF('Dashboard Calc'!Q5="error","Hard fail",IF('Dashboard Calc'!Q5="warning","Warning","Info")))
A34: ='Dashboard Calc'!M6 -> Basis-boost geo eligibility | B34: ='Dashboard Calc'!N6 -> No | C34: req | D34: ='Dashboard Calc'!O6 -> Qualifying geo | E34: ='Dashboard Calc'!P6 -> PASS | F34: =IF('Dashboard Calc'!P6<>"FAIL","",IF('Dashboard Calc'!Q6="error","Hard fail",IF('Dashboard Calc'!Q6="warning","Warning","Info")))
A35: ='Dashboard Calc'!M7 -> Per-project pool cap | B35: ='Dashboard Calc'!N7 -> n/a | C35: ≤ | D35: ='Dashboard Calc'!O7 -> N/A (PAB cap) | E35: ='Dashboard Calc'!P7 -> N/A | F35: =IF('Dashboard Calc'!P7<>"FAIL","",IF('Dashboard Calc'!Q7="error","Hard fail",IF('Dashboard Calc'!Q7="warning","Warning","Info")))
A36: ='Dashboard Calc'!M8 -> Maximum allowable credit | B36: ='Dashboard Calc'!N8 -> 1841756.5 | C36: ≤ | D36: ='Dashboard Calc'!O8 -> 1841756.5 | E36: ='Dashboard Calc'!P8 -> PASS | F36: =IF('Dashboard Calc'!P8<>"FAIL","",IF('Dashboard Calc'!Q8="error","Hard fail",IF('Dashboard Calc'!Q8="warning","Warning","Info")))
A38: VERDICT KEY
A39: FAIL — one or more hard fails present
A40: MARGINAL — no hard fails, but ≥1 warning or pending item
A41: PENCILS — fully clean: no hard fails, warnings, or pending items

Sheet Unit Mix+Rents
A1: UNIT MIX
A3: # BRs | B3: # Baths | C3: Sqft | D3: # Units | E3: LIHTC | F3: Staff Unit | G3: Subsidy | H3: PSH | I3: % AMI | J3: Net Rent | K3: Gr Rent | L3: UA | O3: Unit Ratio
A4: 1 | B4: 1 | C4: 900 | D4: 0 | E4: Yes | F4: No | G4: No | H4: No | I4: 0.2 | J4: =+K4-L4 -> 270 | K4: =+VLOOKUP(I4,$A$20:$F$27,A4+2,FALSE) -> 337 | L4: =HLOOKUP(A4,$B$32:$F$37,6,TRUE) -> 67 | O4: =+D4/$D$14 -> 0
A5: 1 | B5: 1 | C5: 900 | D5: 0 | E5: Yes | F5: No | G5: No | H5: No | I5: 0.3 | J5: =+K5-L5 -> 431 | K5: =+VLOOKUP(I5,$A$20:$F$27,A5+2,FALSE) -> 498 | L5: =HLOOKUP(A5,$B$32:$F$37,6,TRUE) -> 67 | O5: =+D5/$D$14 -> 0
A6: 1 | B6: 1 | C6: 900 | D6: 0 | E6: Yes | F6: No | G6: No | H6: No | I6: 0.4 | J6: =+K6-L6 -> 607 | K6: =+VLOOKUP(I6,$A$20:$F$27,A6+2,FALSE) -> 674 | L6: =HLOOKUP(A6,$B$32:$F$37,6,TRUE) -> 67 | O6: =+D6/$D$14 -> 0
A7: 1 | B7: 1 | C7: 900 | D7: 0 | E7: Yes | F7: No | G7: No | H7: No | I7: 0.5 | J7: =+K7-L7 -> 764 | K7: =+VLOOKUP(I7,$A$20:$F$27,A7+2,FALSE) -> 831 | L7: =HLOOKUP(A7,$B$32:$F$37,6,TRUE) -> 67 | O7: =+D7/$D$14 -> 0
A8: 1 | B8: 1 | C8: 900 | D8: 110 | E8: Yes | F8: No | G8: No | H8: No | I8: 0.6 | J8: =+K8-L8 -> 930 | K8: =+VLOOKUP(I8,$A$20:$F$27,A8+2,FALSE) -> 997 | L8: =HLOOKUP(A8,$B$32:$F$37,6,TRUE) -> 67 | O8: =+D8/$D$14 -> 0.39285714
A9: 2 | B9: 2 | C9: 1100 | D9: 0 | E9: Yes | F9: No | G9: No | H9: No | I9: 0.2 | J9: =+K9-L9 -> 315 | K9: =+VLOOKUP(I9,$A$20:$F$27,A9+2,FALSE) -> 404 | L9: =HLOOKUP(A9,$B$32:$F$37,6,TRUE) -> 89 | O9: =+D9/$D$14 -> 0
A10: 2 | B10: 2 | C10: 1100 | D10: 0 | E10: Yes | F10: No | G10: No | H10: No | I10: 0.3 | J10: =+K10-L10 -> 509 | K10: =+VLOOKUP(I10,$A$20:$F$27,A10+2,FALSE) -> 598 | L10: =HLOOKUP(A10,$B$32:$F$37,6,TRUE) -> 89 | O10: =+D10/$D$14 -> 0
A11: 2 | B11: 2 | C11: 1100 | D11: 0 | E11: Yes | F11: No | G11: No | H11: No | I11: 0.4 | J11: =+K11-L11 -> 720 | K11: =+VLOOKUP(I11,$A$20:$F$27,A11+2,FALSE) -> 809 | L11: =HLOOKUP(A11,$B$32:$F$37,6,TRUE) -> 89 | O11: =+D11/$D$14 -> 0
A12: 2 | B12: 2 | C12: 1100 | D12: 0 | E12: Yes | F12: No | G12: No | H12: No | I12: 0.5 | J12: =+K12-L12 -> 908 | K12: =+VLOOKUP(I12,$A$20:$F$27,A12+2,FALSE) -> 997 | L12: =HLOOKUP(A12,$B$32:$F$37,6,TRUE) -> 89 | O12: =+D12/$D$14 -> 0
A13: 2 | B13: 2 | C13: 1100 | D13: 170 | E13: Yes | F13: No | G13: No | H13: No | I13: 0.6 | J13: =+K13-L13 -> 1108 | K13: =+VLOOKUP(I13,$A$20:$F$27,A13+2,FALSE) -> 1197 | L13: =HLOOKUP(A13,$B$32:$F$37,6,TRUE) -> 89 | O13: =+D13/$D$14 -> 0.60714286
A14: TOTAL | C14: =+SUMPRODUCT(C4:C13,D4:D13) -> 286000 | D14: =+SUM(D4:D13) -> 280 | I14: =+SUMPRODUCT(I4:I13,O4:O13) -> 0.6 | J14: =+SUMPRODUCT(D4:D13,J4:J13) -> 290660 | K14: =+SUMPRODUCT(D4:D13,K4:K13) -> 313160 | L14: =+SUMPRODUCT(D4:D13,L4:L13) -> 22500
A16: 2025 New Orleans-Metairie MSA Gross Rent Limits
A17: Source: HUD FY2025 MTSP Income Limits (Orleans Parish)
B19: 0 | C19: 1 | D19: 2 | E19: 3 | F19: 4
A20: 1.2 | B20: 1887 | C20: 2022 | D20: 2427 | E20: 2802 | F20: 3126
A21: 0.2 | B21: 314 | C21: 337 | D21: 404 | E21: 467 | F21: 521
A22: 0.3 | B22: 471 | C22: 498 | D22: 598 | E22: 691 | F22: 781
A23: 0.4 | B23: 629 | C23: 674 | D23: 809 | E23: 934 | F23: 1042
A24: 0.5 | B24: 786 | C24: 831 | D24: 997 | E24: 1151 | F24: 1302
A25: 0.6 | B25: 943 | C25: 997 | D25: 1197 | E25: 1382 | F25: 1563
A26: 0.7 | B26: 1100 | C26: 1163 | D26: 1396 | E26: 1612 | F26: 1823
A27: 0.8 | B27: 1258 | C27: 1348 | D27: 1618 | E27: 1868 | F27: 2084
A29: New Orleans Utility Allowances
A30: Source: HANO Utility Allowance Schedule, eff. 09/01/2025 (Apartment, all-electric)
B32: 0 | C32: 1 | D32: 2 | E32: 3 | F32: 4
A33: Electricity | B33: =8+5+18+15+11 -> 57 | C33: =9+6+21+18+13 -> 67 | D33: =11+8+30+24+16 -> 89 | E33: =12+11+38+31+19 -> 111 | F33: =14+13+46+38+23 -> 134
A34: Water | B34: 0 | C34: 0 | D34: 0 | E34: 0 | F34: 0
A35: Sewer | B35: 0 | C35: 0 | D35: 0 | E35: 0 | F35: 0
A36: Trash | B36: 0 | C36: 0 | D36: 0 | E36: 0 | F36: 0
A37: Total | B37: =+SUM(B33:B36) -> 57 | C37: =+SUM(C33:C36) -> 67 | D37: =+SUM(D33:D36) -> 89 | E37: =+SUM(E33:E36) -> 111 | F37: =+SUM(F33:F36) -> 134
A40: Checks
A42: % of Rental Subsidy Units in the project:
A43: % of Low-Income Units in the project:
A44: Total square feet for LIHTC units:
A45: PSH Units:
A46: Non-PSH Units Under 30% AMI:
A47: Units under 30% AMI:
A48: Units under 20% AMI:
A49: Units under 50% AMI:
A50: Units between 31% and 50% AMI:
A51: Units under 80% AMI:
A52: Units Not AMI Restricted
... A54: Staff Units

Sheet Expense Detail
A1: EXPENSE DETAIL
A4: Staff Payroll
D5: # | E5: $/hr | F5: Per Year | G5: PUPA
B6: Property Manager | D6: 1 | E6: 24 | F6: =+D6*E6*2080 -> 49920 | G6: =+F6/'Unit Mix+Rents'!$D$14 -> 178.28571
B7: Leasing Agent | D7: 1 | E7: 18 | F7: =+D7*E7*2080 -> 37440 | G7: =+F7/'Unit Mix+Rents'!$D$14 -> 133.71429
B8: Maintenance Staff | D8: 2 | E8: 20 | F8: =+D8*E8*2080 -> 83200 | G8: =+F8/'Unit Mix+Rents'!$D$14 -> 297.14286
B10: Tax Burden | E10: 0.1 | F10: =+E10*SUM(F6:F8) -> 17056 | G10: =+F10/'Unit Mix+Rents'!$D$14 -> 60.914286
B11: Benefits Burden | E11: 0 | F11: =+E11*SUM(F6:F8) -> 0 | G11: =+F11/'Unit Mix+Rents'!$D$14 -> 0
A13: Total Payroll | F13: =+SUM(F6:F12) -> 187616 | G13: =+SUM(G6:G12) -> 670.05714
A15: Maintenance + Make Ready
D16: #/Mo | E16: $/Turn | F16: Per Year | G16: PUPA
B17: Make Ready | C17: 0.4 | D17: =+('Unit Mix+Rents'!D14*C17/12) -> 9.3333333 | E17: 400 | F17: =+D17*E17*12 -> 44800 | G17: =+F17/'Unit Mix+Rents'!$D$14 -> 160
E18: $/Unit/Mo | F18: Per Year | G18: PUPA
B19: Maintenance | E19: 50 | F19: =+E19*'Unit Mix+Rents'!D14*12 -> 168000 | G19: =+F19/'Unit Mix+Rents'!$D$14 -> 600
A20: Total Maintenance + Make Ready | F20: =+F17+F19 -> 212800 | G20: =+G17+G19 -> 760
A22: Utilities
E23: $/Unit/Mo | F23: Per Year | G23: PUPA
B24: Units
B25: Water | E25: 20 | F25: =+E25*'Unit Mix+Rents'!$D$14*12 -> 67200 | G25: =+F25/'Unit Mix+Rents'!$D$14 -> 240
B26: Sewer | C26: 2 | E26: =+E25*C26 -> 40 | F26: =+E26*'Unit Mix+Rents'!$D$14*12 -> 134400 | G26: =+F26/'Unit Mix+Rents'!$D$14 -> 480
B27: Gas | E27: 0 | F27: =+E27*'Unit Mix+Rents'!$D$14*12 -> 0 | G27: =+F27/'Unit Mix+Rents'!$D$14 -> 0
B28: Electricty | E28: 0 | F28: =+E28*'Unit Mix+Rents'!$D$14*12 -> 0 | G28: =+F28/'Unit Mix+Rents'!$D$14 -> 0
B29: Clubhouse
B30: Water | E30: 20 | F30: =+E30*12 -> 240 | G30: =+F30/'Unit Mix+Rents'!$D$14 -> 0.85714286
B31: Sewer | E31: =+E30*C26 -> 40 | F31: =+E31*12 -> 480 | G31: =+F31/'Unit Mix+Rents'!$D$14 -> 1.7142857
B32: Gas | E32: 0 | F32: =+E32*12 -> 0 | G32: =+F32/'Unit Mix+Rents'!$D$14 -> 0
B33: Electricty | E33: 300 | F33: =+E33*12 -> 3600 | G33: =+F33/'Unit Mix+Rents'!$D$14 -> 12.857143
B34: Property
B35: Water | E35: 50 | F35: =+E35*12 -> 600 | G35: =+F35/'Unit Mix+Rents'!$D$14 -> 2.1428571
B36: Sewer | E36: =+E35*C26 -> 100 | F36: =+E36*12 -> 1200 | G36: =+F36/'Unit Mix+Rents'!$D$14 -> 4.2857143
B37: Gas | E37: 0 | F37: =+E37*12 -> 0 | G37: =+F37/'Unit Mix+Rents'!$D$14 -> 0
B38: Electricty | E38: 200 | F38: =+E38*12 -> 2400 | G38: =+F38/'Unit Mix+Rents'!$D$14 -> 8.5714286
A39: Total Utilities | E39: =+F39/12/'Unit Mix+Rents'!D14 -> 62.535714 | F39: =+SUM(F25:F38) -> 210120 | G39: =+SUM(G25:G38) -> 750.42857
A41: Contract Services
E42: $/Mo | F42: Per Year | G42: PUPA
B43: Landscaping | E43: 1500 | F43: =+E43*12 -> 18000 | G43: =+F43/'Unit Mix+Rents'!$D$14 -> 64.285714
B44: Elevator Maintenance | E44: 0 | F44: =+E44*12 -> 0 | G44: =+F44/'Unit Mix+Rents'!$D$14 -> 0
B45: Pest Control | E45: 500 | F45: =+E45*12 -> 6000 | G45: =+F45/'Unit Mix+Rents'!$D$14 -> 21.428571
B46: Janitorial | E46: 500 | F46: =+E46*12 -> 6000 | G46: =+F46/'Unit Mix+Rents'!$D$14 -> 21.428571
B47: Security | E47: 500 | F47: =+E47*12 -> 6000 | G47: =+F47/'Unit Mix+Rents'!$D$14 -> 21.428571
B48: Waste Collection | E48: 1500 | F48: =+E48*12 -> 18000 | G48: =+F48/'Unit Mix+Rents'!$D$14 -> 64.285714
B49: Pool Maintenance | E49: 500 | F49: =+E49*12 -> 6000 | G49: =+F49/'Unit Mix+Rents'!$D$14 -> 21.428571
A50: Total Contract Services | E50: =F50/12 -> 5000 | F50: =+SUM(F43:F49) -> 60000 | G50: =+SUM(G43:G49) -> 214.28571
A52: Property Taxes | G52: PUPA
B53: Net Operating Income | F53: =+'NOI Calc'!J29 -> 1979252.1 | G53: =+F53/'Unit Mix+Rents'!$D$14 -> 7068.7576
B54: Cap Rate | F54: 0.08
B55: Stabilized Value | F55: =+F53/F54 -> 24740652 | G55: =+F55/'Unit Mix+Rents'!$D$14 -> 88359.47
B56: Millage Factor | F56: 0.017
B57: Calculated Property Tax | F57: =+F55*F56 -> 420591.08
B58: PILOT in place? (Yes/No) | F58: Yes
B59: PILOT term (years) | F59: 10
B60: PILOT Annual Payment ($) | F60: 50000 | G60: =+F60/'Unit Mix+Rents'!$D$14 -> 178.57143
A61: Total Property Tax | F61: =IF(F58="Yes",F60,F57) -> 50000 | G61: =+F61/'Unit Mix+Rents'!$D$14 -> 178.57143
A63: Property Insurance
F64: Per Year | G64: PUPA
A65: Total Property Insurance | F65: =+G65*'Unit Mix+Rents'!D14 -> 420000 | G65: 1500

Sheet Construction Estimates
A1: Construction Cost Estimates
A3: Category | D3: Unit Type | E3: Unit Cost | F3: Units | G3: Estimate
A4: Sitework | D4: lump sum | E4: 500000 | F4: 1 | G4: =E4*F4 -> 500000
A5: Abatement | D5: lump sum | E5: 0 | F5: 1 | G5: =E5*F5 -> 0
A6: Demolition | D6: $/unit | E6: 1500 | F6: =+'Unit Mix+Rents'!D14 -> 280 | G6: =E6*F6 -> 420000
A7: Construction Cost - Units | D7: $/unit | E7: 100000 | F7: =+'Unit Mix+Rents'!D14 -> 280 | G7: =(E7*F7)-G8-G10-G11-G12 -> 27575000
A8: Construction Cost - Clubhouse | D8: lump sum | E8: 200000 | F8: 1 | G8: =E8*F8 -> 200000
A9: Elevators | D9: $/shaft | E9: 0 | F9: 0 | G9: =E9*F9 -> 0
A10: Pool | D10: lump sum | E10: 100000 | F10: 1 | G10: =E10*F10 -> 100000
A11: Sports Courts | D11: lump sum | E11: 25000 | F11: 1 | G11: =E11*F11 -> 25000
A12: Playground | D12: lump sum | E12: 100000 | F12: 1 | G12: =E12*F12 -> 100000
A13: Total Vertical Construction Cost | G13: =SUM(G4:G12) -> 28920000
A14: General Requirements | D14: $/sf | G14: ='Sources & Uses'!I38 -> 1834803.6
A15: Overhead | D15: $/sf | G15: ='Sources & Uses'!I39 -> 611601.21
A16: Profit | D16: $/sf | G16: ='Sources & Uses'!I40 -> 1834803.6
A17: Contigency | D17: $/sf | G17: ='Sources & Uses'!I41 -> 1660060.4
A18: Total Hard Construction Cost | G18: =SUM(G13:G17) -> 34861269
A19: *Acquisition/Rehab: $110,000/unit direct hard cost; GC fees & contingency layered on top
A21: Vertical Cost per Unit | G21: =G13/'Unit Mix+Rents'!D14 -> 103285.71
A22: Hard Cost per Unit | G22: =+G18/'Unit Mix+Rents'!D14 -> 124504.53
A23: Vertical Cost per SF | G23: N/A
A24: Hard Cost per SF | G24: N/A
A26: Construction Cash Burn % by month
B28: Cumul | C28: Monthly
A29: M0 | B29: 0 | C29: =+B29 -> 0
A30: M1 | B30: =+B29+C30 -> 0.02 | C30: 0.02
A31: M2 | B31: =+B30+C31 -> 0.055 | C31: 0.035
A32: M3 | B32: =+B31+C32 -> 0.105 | C32: 0.05
A33: M4 | B33: =+B32+C33 -> 0.17 | C33: 0.065
A34: M5 | B34: =+B33+C34 -> 0.24 | C34: 0.07
A35: M6 | B35: =+B34+C35 -> 0.315 | C35: 0.075
A36: M7 | B36: =+B35+C36 -> 0.39 | C36: 0.075
A37: M8 | B37: =+B36+C37 -> 0.465 | C37: 0.075
A38: M9 | B38: =+B37+C38 -> 0.54 | C38: 0.075
A39: M10 | B39: =+B38+C39 -> 0.615 | C39: 0.075
A40: M11 | B40: =+B39+C40 -> 0.685 | C40: 0.07
A41: M12 | B41: =+B40+C41 -> 0.755 | C41: 0.07
... A47: M18 | B47: =+B46+C47 -> 1 | C47: 0.02

Sheet Sources & Uses
A1: SOURCES AND USES
A4: Debt/Equity Ratio | G4: Debt | I4: Equity
G6: =+I12/I26 -> 0.52370769 | I6: =+SUM(I14,I19,I24)/I26 -> 0.47629231
A8: Sources of Funds | E8: % of Tot Sources
B10: Series 2026 Permanent Bonds | E10: =+I10/$I$26 -> 0.52370769 | G10: =+I10/'Unit Mix+Rents'!$D$14 -> 95105.37 | I10: =+'S&U Timing'!D10 -> 26629504
B12: Total Loan/Bond Par Amount | E12: =+I12/$I$26 -> 0.52370769 | G12: =+I12/'Unit Mix+Rents'!$D$14 -> 95105.37 | I12: =+SUM(I10:I10) -> 26629504
B14: Tax Credit Equity | E14: =+I14/$I$26 -> 0.28686877 | G14: =+I14/'Unit Mix+Rents'!$D$14 -> 52095.398 | I14: =+'Tax Credit Calc'!F41 -> 14586712
B16: CDBG | E16: =+I16/$I$26 -> 0.14749834 | G16: =+I16/'Unit Mix+Rents'!$D$14 -> 26785.714 | I16: 7500000
B17: LHC HOME | E17: =+I17/$I$26 -> 0 | G17: =+I17/'Unit Mix+Rents'!$D$14 -> 0 | I17: 0
B19: Total Soft Money | E19: =+I19/$I$26 -> 0.14749834 | G19: =+I19/'Unit Mix+Rents'!$D$14 -> 26785.714 | I19: =+SUM(I16:I17) -> 7500000
B21: Deferred GC Fee | E21: =+I21/$I$26 -> 0 | G21: =+I21/'Unit Mix+Rents'!$D$14 -> 0 | I21: 0
B22: Deferred Developer Fee | D22: 0.36 | E22: =+I22/$I$26 -> 0.041925187 | G22: =+I22/'Unit Mix+Rents'!$D$14 -> 7613.6181 | I22: =+D22*I65 -> 2131813.1
B24: Total Deferred Fees | E24: =+I24/$I$26 -> 0.041925187 | G24: =+I24/'Unit Mix+Rents'!$D$14 -> 7613.6181 | I24: =+SUM(I21:I22) -> 2131813.1
A26: Total Sources of Funds | E26: =+I26/$I$26 -> 1 | G26: =+I26/'Unit Mix+Rents'!$D$14 -> 181600.1 | I26: =+SUM(I12,I14,I19,I24) -> 50848028
A28: Uses of Funds | E28: % of Tot Uses | G28: Per Unit | I28: Total
B30: Land/Building Acquisition Cost | E30: =+I30/$I$78 -> 0.078665784 | G30: =+I30/'Unit Mix+Rents'!$D$14 -> 14285.714 | I30: 4000000
B32: Construction Costs | E32: =+I32/$I$78 -> 0
B34: On-Site Improvements | E34: =+I34/$I$78 -> 0.009833223 | G34: =+I34/'Unit Mix+Rents'!$D$14 -> 1785.7143 | I34: ='Construction Estimates'!G4 -> 500000
B35: Special Site Conditions | E35: =+I35/$I$78 -> 0 | G35: =+I35/'Unit Mix+Rents'!$D$14 -> 0 | I35: =+'Construction Estimates'!G5 -> 0
B36: Residential Structures | E36: =+I36/$I$78 -> 0.55056215 | G36: =+I36/'Unit Mix+Rents'!$D$14 -> 99982.143 | I36: =+SUM('Construction Estimates'!G6,'Construction Estimates'!G7) -> 27995000
B37: Community Facilities | E37: =+I37/$I$78 -> 0.0083582395 | G37: =+I37/'Unit Mix+Rents'!$D$14 -> 1517.8571 | I37: =+SUM('Construction Estimates'!G8,'Construction Estimates'!G10,'Construction Estimates'!G11,'Construction Estimates'!G12) -> 425000
B38: General Requirements | D38: 0.06 | E38: =+I38/$I$78 -> 0.036084066 | G38: =+I38/'Unit Mix+Rents'!$D$14 -> 6552.8701 | I38: =+D38*I81 -> 1834803.6
B39: GC Overhead | D39: 0.02 | E39: =+I39/$I$78 -> 0.012028022 | G39: =+I39/'Unit Mix+Rents'!$D$14 -> 2184.29 | I39: =+D39*I81 -> 611601.21
B40: GC Profit | D40: 0.06 | E40: =+I40/$I$78 -> 0.036084066 | G40: =+I40/'Unit Mix+Rents'!$D$14 -> 6552.8701 | I40: =+D40*I81 -> 1834803.6
B41: Contingency (belongs to the GC) | D41: 0.05 | E41: =+I41/$I$78 -> 0.032647489 | G41: =+I41/'Unit Mix+Rents'!$D$14 -> 5928.7872 | I41: =+D41*SUM(I34:I40) -> 1660060.4
B43: Total Hard Costs | E43: =+I43/$I$78 -> 0.68559726 | G43: =SUM(G34:G42) -> 124504.53 | I43: =SUM(I34:I42) -> 34861269
B45: Market Analysis | E45: =+I45/$I$78 -> 0.00011799868 | G45: =+I45/'Unit Mix+Rents'!$D$14 -> 21.428571 | I45: 6000
B46: Architect & Engineering | E46: =+I46/$I$78 -> 0.014749834 | G46: =+I46/'Unit Mix+Rents'!$D$14 -> 2678.5714 | I46: 750000
B47: Plan Review Fees | E47: =+I47/$I$78 -> 0.00068559726 | G47: =+I47/'Unit Mix+Rents'!$D$14 -> 124.50453 | I47: =MAX(60,0.001*I43) -> 34861.269
B48: Permit, ROW and Impact Fees | E48: =+I48/$I$78 -> 0.0034291663 | G48: =+I48/'Unit Mix+Rents'!$D$14 -> 622.73694 | I48: =60+0.005*I43 -> 174366.34
B49: Environmental Study and Geotech | E49: =+I49/$I$78 -> 0.00078665784 | G49: =+I49/'Unit Mix+Rents'!$D$14 -> 142.85714 | I49: 40000
B50: Construction/Builder's Risk | E50: =+I50/$I$78 -> 0.0024583057 | G50: =+I50/'Unit Mix+Rents'!$D$14 -> 446.42857 | I50: 125000
B51: Accounting Fees | E51: =+I51/$I$78 -> 0.00078665784 | G51: =+I51/'Unit Mix+Rents'!$D$14 -> 142.85714 | I51: 40000
B52: LHC Fees | E52: =+I52/$I$78 -> 0.0040055762 | G52: =+I52/'Unit Mix+Rents'!$D$14 -> 727.41304 | I52: =4000+6000+6000+3000+500+0.1*'Tax Credit Calc'!F22 -> 203675.65
B53: Appraisal | E53: =+I53/$I$78 -> 0.00049166115 | G53: =+I53/'Unit Mix+Rents'!$D$14 -> 89.285714 | I53: 25000
B54: Title & Recording | E54: =+I54/$I$78 -> 0.0024583057 | G54: =+I54/'Unit Mix+Rents'!$D$14 -> 446.42857 | I54: 125000
B55: RE Taxes During Construction | E55: =+I55/$I$78 -> 0 | G55: =+I55/'Unit Mix+Rents'!$D$14 -> 0 | I55: 0
B56: Survey | E56: =+I56/$I$78 -> 0.00013766512 | G56: =+I56/'Unit Mix+Rents'!$D$14 -> 25 | I56: 7000
B57: Marketing/Lease-Up | E57: =+I57/$I$78 -> 0.0014749834 | G57: =+I57/'Unit Mix+Rents'!$D$14 -> 267.85714 | I57: 75000
B58: FF&E (Common Areas) | E58: =+I58/$I$78 -> 0.00078665784 | G58: =+I58/'Unit Mix+Rents'!$D$14 -> 142.85714 | I58: 40000
B59: Owner's Counsel | E59: =+I59/$I$78 -> 0.0019666446 | G59: =+I59/'Unit Mix+Rents'!$D$14 -> 357.14286 | I59: 100000
B61: Total Soft Costs | E61: =+I61/$I$78 -> 0.034335712 | G61: =+SUM(G45:G59) -> 6235.3688 | I61: =+SUM(I45:I59) -> 1745903.3
B63: Total Construction Costs | E63: =+I63/$I$78 -> 0.71993297 | G63: =+G43+G61 -> 130739.9 | I63: =+I43+I61 -> 36607172
B65: Developer Fee | E65: =+I65/$I$78 -> 0.11645885 | G65: =+I65/'Unit Mix+Rents'!$D$14 -> 21148.939 | I65: =0.15*I82 -> 5921703
B67: Operating Deficit Guarantee Reserve | E67: =+I67/$I$78 -> 0.013097736 | G67: =+I67/'Unit Mix+Rents'!$D$14 -> 2378.5501 | I67: ='Surplus Cash-Reserve Waterfall'!B46 -> 665994.03
B68: Interest Expense Reserves | E68: =+I68/$I$78 -> 0.014401962 | G68: =+I68/'Unit Mix+Rents'!$D$14 -> 2615.3977 | I68: ='Surplus Cash-Reserve Waterfall'!B47 -> 732311.35
B69: Replacement Reserve Deposit | E69: =+I69/$I$78 -> 0 | G69: =+I69/'Unit Mix+Rents'!$D$14 -> 0 | I69: 0
B70: Insurance Reserves | E70: =+I70/$I$78 -> 0 | G70: =+I70/'Unit Mix+Rents'!$D$14 -> 0 | I70: 0
B72: Total Reserves | E72: =+I72/$I$78 -> 0.027499697 | G72: =+I72/'Unit Mix+Rents'!$D$14 -> 4993.9478 | I72: =+SUM(I67:I71) -> 1398305.4
B74: Capitalized Construction Interest | E74: =+I74/$I$78 -> 0.038153644 | G74: =+I74/'Unit Mix+Rents'!$D$14 -> 6928.7055 | I74: =+'S&U Timing'!D44 -> 1940037.6
B76: Financing Fees | E76: =+I76/$I$78 -> 0.019289051 | G76: =+I76/'Unit Mix+Rents'!$D$14 -> 3502.8937 | I76: =+'Financing Assumptions'!D53 -> 980810.23
A78: Total Uses of Funds | E78: =+I78/$I$78 -> 1 | G78: =+SUM(G30,G63,G65,G72,G74,G76) -> 181600.1 | I78: =+SUM(I30,I63,I65,I72,I74,I76) -> 50848028
B80: Sources/Uses Balance | I80: =+I78-I26 -> 1.1943281e-05
B81: Builder Profit Fee Base | I81: =+I43-I38-I39-I40 -> 30580060
B82: Developer Fee Base | I82: =+I78-I30-I65-I72-'Financing Assumptions'!D49 -> 39478020
B83: Developer Fee Limit | I83: 9999999 | J83: * from 2025 QAP
B84: $/SF Construction Cost | I84: =+I63/'Unit Mix+Rents'!C14 -> 127.99711
B85: Max TDC/Unit | I85: =H99 -> 247226.11 | J85: * HUD 2024 Region VI
B86: Max TDC | I86: =+I85*'Unit Mix+Rents'!$D$14 -> 69223310
A88: New Orleans TDC Limits | B88: Source: HUD FY2024 Unit TDC Limits, Region VI – Midsouth, New Orleans row (hud.gov)
G89: BRs | H89: Detached/Semi | I89: Row House | J89: Walkup | K89: Elevator
G90: 0 | H90: 199618 | I90: 172976 | J90: 156737 | K90: 161035
G91: 1 | H91: 258890 | I91: 227077 | J91: 213098 | K91: 225448
G92: 2 | H92: 310326 | I92: 276477 | J92: 269309 | K92: 289862
G93: 3 | H93: 370970 | I93: 339946 | J93: 354388 | K93: 386483
G94: 4 | H94: 437537 | I94: 404791 | J94: 438588 | K94: 483104
G96: Building type: | H96: Walkup
G97: 1BR TDC/unit: | H97: =INDEX($H$90:$K$94,MATCH(1,$G$90:$G$94,0),MATCH($H$96,$H$89:$K$89,0)) -> 213098
G98: 2BR TDC/unit: | H98: =INDEX($H$90:$K$94,MATCH(2,$G$90:$G$94,0),MATCH($H$96,$H$89:$K$89,0)) -> 269309
G99: Weighted TDC/unit: | H99: {=(SUMPRODUCT(('Unit Mix+Rents'!$A$4:$A$13=0)*'Unit Mix+Rents'!$D$4:$D$13)*INDEX($H$90:$K$94,MATCH(0,$G$90:$G$94,0),MATCH($H$96,$H$89:$K$89,0))+SUMPRODUCT(('Unit Mix+Rents'!$A$4:$A$13=1)*'Unit Mix+Rents'!$D$4:$D$13)*H97+SUMPRODUCT(('Unit Mix+Rents'!$A$4:$A$13=2)*'Unit Mix+Rents'!$D$4:$D$13)*H98+SUMPRODUCT(('Unit Mix+Rents'!$A$4:$A$13=3)*'Unit Mix+Rents'!$D$4:$D$13)*INDEX($H$90:$K$94,MATCH(3,$G$90:$G$94,0),MATCH($H$96,$H$89:$K$89,0))+SUMPRODUCT(('Unit Mix+Rents'!$A$4:$A$13=4)*'Unit Mix+Rents'!$D$4:$D$13)*INDEX($H$90:$K$94,MATCH(4,$G$90:$G$94,0),MATCH($H$96,$H$89:$K$89,0)))/'Unit Mix+Rents'!$D$14} -> 247226.11
G100: Total TDC limit: | H100: =H99*'Unit Mix+Rents'!$D$14 -> 69223310

Sheet S&U Timing
A1: SOURCES AND USES TIMING
D4: TOTAL DEV COSTS | E4: Check | G4: Closings | H4: Preconstruction | M4: Construction Period | AE4: Stabilize
G5: 46229 | H5: =G5+30 -> 46259 | I5: =H5+30 -> 46289 | J5: =I5+30 -> 46319 | K5: =J5+30 -> 46349 | L5: =K5+30 -> 46379 | M5: =L5+30 -> 46409 | N5: =M5+30 -> 46439 | O5: =N5+30 -> 46469 | ... AD5: =AC5+30 -> 46919 | AE5: =AD5+360 -> 47279
G6: 1 | H6: =G6+1 -> 2 | I6: =H6+1 -> 3 | J6: =I6+1 -> 4 | K6: =J6+1 -> 5 | L6: =K6+1 -> 6 | M6: =L6+1 -> 7 | N6: =M6+1 -> 8 | O6: =N6+1 -> 9 | ... AD6: =AC6+1 -> 24 | AE6: YR1
A8: Sources of Funds
B10: Series 2026 Permanent Bonds | D10: =+SUM(G10:AD10) -> 26629504 | G10: =G50 -> 3126643.1 | H10: =H50 -> 156085.91 | I10: =I50 -> 156870.26 | J10: =J50 -> 157658.55 | K10: =K50 -> 158450.8 | L10: =L50 -> 410503.32 | M10: =+M50 -> 408677.17 | N10: =+N50 -> 702709.71 | O10: =+O50 -> 999099.39 | P10: =+P50 -> 1297858.1 | Q10: =+Q50 -> 1405126.9 | R10: =+R50 -> 1513228 | S10: =+S50 -> 1525230.2 | T10: =+T50 -> 1537292.7 | ... AD10: =+AD50 -> 1937968.8 | AE10: 0
B11: Tax Equity Bridge Loan | D11: =+SUM(G11:AE11) -> 11669369 | M11: =+$L$52*'Construction Estimates'!$C$30 -> 233387.38 | N11: =+$L$52*'Construction Estimates'!$C$31 -> 408427.92 | O11: =+$L$52*'Construction Estimates'!$C$32 -> 583468.46 | P11: =+$L$52*'Construction Estimates'!$C$33 -> 758509 | Q11: =+$L$52*'Construction Estimates'!$C$34 -> 816855.85 | R11: =+$L$52*'Construction Estimates'!$C$35 -> 875202.69 | S11: =+$L$52*'Construction Estimates'!$C$36 -> 875202.69 | T11: =+$L$52*'Construction Estimates'!$C37 -> 875202.69 | U11: =+$L$52*'Construction Estimates'!$C$38 -> 875202.69 | V11: =+$L$52*'Construction Estimates'!$C$39 -> 875202.69 | W11: =+$L$52*'Construction Estimates'!$C$40 -> 816855.85 | X11: =+$L$52*'Construction Estimates'!$C$41 -> 816855.85 | Y11: =+$L$52*'Construction Estimates'!$C$42 -> 758509 | Z11: =+$L$52*'Construction Estimates'!$C$43 -> 641815.31 | AA11: =+$L$52*'Construction Estimates'!$C$44 -> 525121.62 | AB11: =+$L$52*'Construction Estimates'!$C$45 -> 408427.92 | AC11: =+$L$52*'Construction Estimates'!$C$46 -> 291734.23 | AD11: =+$L$52*'Construction Estimates'!$C$47 -> 233387.38
B12: Bridge Loan Payback | D12: =+SUM(G12:AE12) -> -11669369 | M12: =-M16 -> 0 | N12: =-N16 -> 0 | O12: =-O16 -> 0 | P12: =-P16 -> 0 | Q12: =-Q16 -> 0 | R12: =-R16 -> 0 | S12: =-S16 -> 0 | T12: =-T16 -> 0 | ... W12: =-W16 -> 0 | Z12: =-Z16 -> -7293355.8 | AD12: =-AD16 -> 0 | AE12: =-AE16 -> -4376013.5
B14: Total Loan/Bond Par Amount | D14: =SUM(D10:D12) -> 26629504 | G14: =SUM(G10:G12) -> 3126643.1 | H14: =SUM(H10:H12) -> 156085.91 | I14: =SUM(I10:I12) -> 156870.26 | J14: =SUM(J10:J12) -> 157658.55 | K14: =SUM(K10:K12) -> 158450.8 | L14: =SUM(L10:L12) -> 410503.32 | M14: =SUM(M10:M12) -> 642064.56 | N14: =SUM(N10:N12) -> 1111137.6 | ... AE14: =SUM(AE10:AE12) -> -4376013.5
B16: Tax Equity Proceeds | D16: ='Sources & Uses'!I14 -> 14586712 | E16: =D16-SUM(G16:AE16) -> -2.7753413e-06 | G16: =0.2*$D$16 -> 2917342.3 | Z16: =0.5*$D$16 -> 7293355.8 | AD16: 0 | AE16: =+D16-SUM(G16:AD16) -> 4376013.5
B18: CDBG | D18: ='Sources & Uses'!I16 -> 7500000 | E18: =D18-SUM(G18:AE18) -> 0 | M18: =($D$18-SUM($G$18:$L$18))*'Construction Estimates'!$C30 -> 150000 | N18: =($D$18-SUM($G$18:$L$18))*'Construction Estimates'!$C31 -> 262500 | O18: =($D$18-SUM($G$18:$L$18))*'Construction Estimates'!$C32 -> 375000 | P18: =($D$18-SUM($G$18:$L$18))*'Construction Estimates'!$C33 -> 487500 | Q18: =($D$18-SUM($G$18:$L$18))*'Construction Estimates'!$C34 -> 525000 | R18: =($D$18-SUM($G$18:$L$18))*'Construction Estimates'!$C35 -> 562500 | S18: =($D$18-SUM($G$18:$L$18))*'Construction Estimates'!$C36 -> 562500 | T18: =($D$18-SUM($G$18:$L$18))*'Construction Estimates'!$C37 -> 562500 | U18: =($D$18-SUM($G$18:$L$18))*'Construction Estimates'!$C38 -> 562500 | V18: =($D$18-SUM($G$18:$L$18))*'Construction Estimates'!$C39 -> 562500 | W18: =($D$18-SUM($G$18:$L$18))*'Construction Estimates'!$C40 -> 525000 | X18: =($D$18-SUM($G$18:$L$18))*'Construction Estimates'!$C41 -> 525000 | Y18: =($D$18-SUM($G$18:$L$18))*'Construction Estimates'!$C42 -> 487500 | Z18: =($D$18-SUM($G$18:$L$18))*'Construction Estimates'!$C43 -> 412500 | AA18: =($D$18-SUM($G$18:$L$18))*'Construction Estimates'!$C44 -> 337500 | AB18: =($D$18-SUM($G$18:$L$18))*'Construction Estimates'!$C45 -> 262500 | AC18: =($D$18-SUM($G$18:$L$18))*'Construction Estimates'!$C46 -> 187500 | AD18: =($D$18-SUM($G$18:$L$18))*'Construction Estimates'!$C47 -> 150000 | AE18: 0
B19: LHC HOME | D19: ='Sources & Uses'!I17 -> 0 | E19: =D19-SUM(G19:AE19) -> 0 | M19: =($D$19-SUM($G$19:$L$19))*'Construction Estimates'!$C30 -> 0 | N19: =($D$19-SUM($G$19:$L$19))*'Construction Estimates'!$C31 -> 0 | O19: =($D$19-SUM($G$19:$L$19))*'Construction Estimates'!$C32 -> 0 | P19: =($D$19-SUM($G$19:$L$19))*'Construction Estimates'!$C33 -> 0 | Q19: =($D$19-SUM($G$19:$L$19))*'Construction Estimates'!$C34 -> 0 | R19: =($D$19-SUM($G$19:$L$19))*'Construction Estimates'!$C35 -> 0 | S19: =($D$19-SUM($G$19:$L$19))*'Construction Estimates'!$C36 -> 0 | T19: =($D$19-SUM($G$19:$L$19))*'Construction Estimates'!$C37 -> 0 | U19: =($D$19-SUM($G$19:$L$19))*'Construction Estimates'!$C38 -> 0 | V19: =($D$19-SUM($G$19:$L$19))*'Construction Estimates'!$C39 -> 0 | W19: =($D$19-SUM($G$19:$L$19))*'Construction Estimates'!$C40 -> 0 | AD19: =($D$19-SUM($G$19:$L$19))*'Construction Estimates'!$C41 -> 0 | AE19: 0
B21: Total Soft Money | D21: =SUM(D18:D19) -> 7500000 | E21: =D21-SUM(G21:AE21) -> 0 | G21: =SUM(G18:G19) -> 0 | H21: =SUM(H18:H19) -> 0 | I21: =SUM(I18:I19) -> 0 | J21: =SUM(J18:J19) -> 0 | K21: =SUM(K18:K19) -> 0 | L21: =SUM(L18:L19) -> 0 | M21: =SUM(M18:M19) -> 150000 | N21: =SUM(N18:N19) -> 262500 | ... AE21: =SUM(AE18:AE19) -> 0
B23: Deferred GC Fee | D23: 0 | E23: =D23-SUM(G23:AE23) -> 0
B24: Deferred Developer Fee | D24: =+'Sources & Uses'!I22 -> 2131813.1 | E24: =D24-SUM(G24:AE24) -> -4.6566129e-09 | G24: 0 | H24: 0 | I24: 0 | J24: 0 | K24: 0 | L24: 0 | M24: =+$D$24*'Construction Estimates'!$C$30 -> 42636.262 | N24: =+$D$24*'Construction Estimates'!$C$31 -> 74613.458 | O24: =+$D$24*'Construction Estimates'!$C$32 -> 106590.65 | P24: =+$D$24*'Construction Estimates'!$C$33 -> 138567.85 | Q24: =+$D$24*'Construction Estimates'!$C$34 -> 149226.92 | R24: =+$D$24*'Construction Estimates'!$C$35 -> 159885.98 | S24: =+$D$24*'Construction Estimates'!$C$36 -> 159885.98 | T24: =+$D$24*'Construction Estimates'!$C$37 -> 159885.98 | U24: =+$D$24*'Construction Estimates'!$C$38 -> 159885.98 | V24: =+$D$24*'Construction Estimates'!$C$39 -> 159885.98 | W24: =+$D$24*'Construction Estimates'!$C$40 -> 149226.92 | X24: =+$D$24*'Construction Estimates'!$C$41 -> 149226.92 | Y24: =+$D$24*'Construction Estimates'!$C$42 -> 138567.85 | Z24: =+$D$24*'Construction Estimates'!$C$43 -> 117249.72 | AA24: =+$D$24*'Construction Estimates'!$C$44 -> 95931.588 | AB24: =+$D$24*'Construction Estimates'!$C$45 -> 74613.458 | AC24: =+$D$24*'Construction Estimates'!$C$46 -> 53295.327 | AD24: =+$D$24*'Construction Estimates'!$C$47 -> 42636.262
E25: =D25-SUM(G25:AE25) -> 0
B26: Total Deferred Fees | D26: =D23+D24 -> 2131813.1 | G26: =G23+G24 -> 0 | H26: =H23+H24 -> 0 | I26: =I23+I24 -> 0 | J26: =J23+J24 -> 0 | K26: =K23+K24 -> 0 | L26: =L23+L24 -> 0 | M26: =M23+M24 -> 42636.262 | N26: =N23+N24 -> 74613.458 | ... AE26: =AE23+AE24 -> 0
A28: Total Sources of Funds | D28: =D14+D16+D21+D26 -> 50848028 | E28: =D28-SUM(G28:AE28) -> -2.7865171e-06 | G28: =G14+G16+G21+G26 -> 6043985.4 | H28: =H14+H16+H21+H26 -> 156085.91 | I28: =I14+I16+I21+I26 -> 156870.26 | J28: =J14+J16+J21+J26 -> 157658.55 | K28: =K14+K16+K21+K26 -> 158450.8 | L28: =L14+L16+L21+L26 -> 410503.32 | M28: =M14+M16+M21+M26 -> 834700.82 | N28: =N14+N16+N21+N26 -> 1448251.1 | ... AE28: =AE14+AE16+AE21+AE26 -> -8.3260238e-07
A30: Uses of Funds
B32: Land/Building Acquisition Cost | D32: ='Sources & Uses'!I30 -> 4000000 | E32: =D32-SUM(G32:AE32) -> 0 | G32: =D32 -> 4000000
B33: Total Hard Costs | D33: ='Sources & Uses'!I43 -> 34861269 | E33: =D33-SUM(G33:AE33) -> 0 | L33: 250000 | M33: =($D$33-$L$33)*'Construction Estimates'!$C30 -> 692225.38 | N33: =($D$33-$L$33)*'Construction Estimates'!$C31 -> 1211394.4 | O33: =($D$33-$L$33)*'Construction Estimates'!$C32 -> 1730563.4 | P33: =($D$33-$L$33)*'Construction Estimates'!$C33 -> 2249732.5 | Q33: =($D$33-$L$33)*'Construction Estimates'!$C34 -> 2422788.8 | R33: =($D$33-$L$33)*'Construction Estimates'!$C35 -> 2595845.2 | S33: =($D$33-$L$33)*'Construction Estimates'!$C36 -> 2595845.2 | T33: =($D$33-$L$33)*'Construction Estimates'!$C37 -> 2595845.2 | U33: =($D$33-$L$33)*'Construction Estimates'!$C38 -> 2595845.2 | V33: =($D$33-$L$33)*'Construction Estimates'!$C39 -> 2595845.2 | W33: =($D$33-$L$33)*'Construction Estimates'!$C40 -> 2422788.8 | X33: =($D$33-$L$33)*'Construction Estimates'!$C41 -> 2422788.8 | Y33: =($D$33-$L$33)*'Construction Estimates'!$C42 -> 2249732.5 | Z33: =($D$33-$L$33)*'Construction Estimates'!$C43 -> 1903619.8 | AA33: =($D$33-$L$33)*'Construction Estimates'!$C44 -> 1557507.1 | AB33: =($D$33-$L$33)*'Construction Estimates'!$C45 -> 1211394.4 | AC33: =($D$33-$L$33)*'Construction Estimates'!$C46 -> 865281.72 | AD33: =($D$33-$L$33)*'Construction Estimates'!$C47 -> 692225.38 | AE33: 0
B34: Total Soft Costs | D34: ='Sources & Uses'!I61 -> 1745903.3 | E34: =D34-SUM(G34:AE34) -> -3.4458935e-08 | G34: =D34*0.6 -> 1047542 | H34: =(D34-G34)/5 -> 139672.26 | I34: =H34 -> 139672.26 | J34: =I34 -> 139672.26 | K34: =J34 -> 139672.26 | L34: =K34 -> 139672.26
B35: Developer Fee | D35: =+'Sources & Uses'!I65 -> 5921703 | E35: =D35-SUM(G35:AE35) -> 6.2491745e-07 | M35: =$D$35*'Construction Estimates'!$C30 -> 118434.06 | N35: =$D$35*'Construction Estimates'!$C31 -> 207259.6 | O35: =$D$35*'Construction Estimates'!$C32 -> 296085.15 | P35: =$D$35*'Construction Estimates'!$C33 -> 384910.69 | Q35: =$D$35*'Construction Estimates'!$C34 -> 414519.21 | R35: =$D$35*'Construction Estimates'!$C35 -> 444127.72 | S35: =$D$35*'Construction Estimates'!$C36 -> 444127.72 | T35: =$D$35*'Construction Estimates'!$C37 -> 444127.72 | U35: =$D$35*'Construction Estimates'!$C38 -> 444127.72 | V35: =$D$35*'Construction Estimates'!$C39 -> 444127.72 | W35: =$D$35*'Construction Estimates'!$C40 -> 414519.21 | X35: =$D$35*'Construction Estimates'!$C41 -> 414519.21 | Y35: =$D$35*'Construction Estimates'!$C42 -> 384910.69 | Z35: =$D$35*'Construction Estimates'!$C43 -> 325693.66 | AA35: =$D$35*'Construction Estimates'!$C44 -> 266476.63 | AB35: =$D$35*'Construction Estimates'!$C45 -> 207259.6 | AC35: =$D$35*'Construction Estimates'!$C46 -> 148042.57 | AD35: =$D$35*'Construction Estimates'!$C47 -> 118434.06 | AE35: 0
B37: Total Construction Cost | D37: =+SUM(D32:D35) -> 46528875 | E37: =D37-SUM(G37:AE37) -> 5.8859587e-07 | G37: =+SUM(G32:G35) -> 5047542 | H37: =+SUM(H32:H35) -> 139672.26 | I37: =+SUM(I32:I35) -> 139672.26 | J37: =+SUM(J32:J35) -> 139672.26 | K37: =+SUM(K32:K35) -> 139672.26 | L37: =+SUM(L32:L35) -> 389672.26 | M37: =+SUM(M32:M35) -> 810659.44 | N37: =+SUM(N32:N35) -> 1418654 | ... AE37: =+SUM(AE32:AE35) -> 0
B39: Total Reserves | D39: ='Sources & Uses'!I72 -> 1398305.4 | E39: =D39-SUM(G39:AD39) -> -9.3830749e-08 | AD39: =+D39 -> 1398305.4 | AE39: =-AE41-AE42 -> -1860331
B41: Capitalized Construction Interest | D41: =+SUM(G41:AD41) -> 1507979.2 | G41: =+'Loan Amortization'!C11 -> 15633.215 | H41: =+'Loan Amortization'!D11 -> 16413.645 | I41: =+'Loan Amortization'!E11 -> 17197.996 | J41: =+'Loan Amortization'!F11 -> 17986.289 | K41: =+'Loan Amortization'!G11 -> 18778.543 | L41: =+'Loan Amortization'!H11 -> 20831.06 | M41: =+'Loan Amortization'!I11 -> 22874.446 | N41: =+'Loan Amortization'!J11 -> 26387.994 | ... AE41: =+'Loan Amortization'!AA11 -> 1597770.2
B42: Capitalized Bridge Interest | D42: =+SUM(G42:AD42) -> 432058.4 | G42: =+'Loan Amortization'!C23 -> 0 | H42: =+'Loan Amortization'!D23 -> 0 | I42: =+'Loan Amortization'!E23 -> 0 | J42: =+'Loan Amortization'!F23 -> 0 | K42: =+'Loan Amortization'!G23 -> 0 | L42: =+'Loan Amortization'!H23 -> 0 | M42: =+'Loan Amortization'!I23 -> 1166.9369 | N42: =+'Loan Amortization'!J23 -> 3209.0765 | ... AE42: =+'Loan Amortization'!AA23 -> 262560.81
B44: Total Construction Cost | D44: =+SUM(D41:D42) -> 1940037.6 | E44: =D44-SUM(G44:AD44) -> 0 | G44: =+SUM(G41:G42) -> 15633.215 | H44: =+SUM(H41:H42) -> 16413.645 | I44: =+SUM(I41:I42) -> 17197.996 | J44: =+SUM(J41:J42) -> 17986.289 | K44: =+SUM(K41:K42) -> 18778.543 | L44: =+SUM(L41:L42) -> 20831.06 | M44: =+SUM(M41:M42) -> 24041.382 | N44: =+SUM(N41:N42) -> 29597.071 | ... AE44: =+SUM(AE41:AE42) -> 1860331
B46: Total Other Costs | D46: =+'Financing Assumptions'!D53 -> 980810.23 | E46: =D46-SUM(G46:AE46) -> -2.4447218e-09 | G46: =+D46 -> 980810.23 | H46: 0 | I46: 0 | J46: 0 | K46: 0 | L46: 0 | M46: 0 | N46: 0 | O46: 0 | P46: 0 | Q46: 0 | R46: 0 | S46: 0 | T46: 0 | U46: 0 | V46: 0 | W46: 0 | X46: 0 | Y46: 0 | Z46: 0 | AA46: 0 | AB46: 0 | AC46: 0 | AD46: 0 | AE46: 0
A48: Total Uses of Funds | D48: =+SUM(D37,D39,D44,D46) -> 50848028 | E48: =D48-SUM(G48:AD48) -> 5.0663948e-07 | G48: =+SUM(G37,G39,G44,G46) -> 6043985.4 | H48: =+SUM(H37,H39,H44,H46) -> 156085.91 | I48: =+SUM(I37,I39,I44,I46) -> 156870.26 | J48: =+SUM(J37,J39,J44,J46) -> 157658.55 | K48: =+SUM(K37,K39,K44,K46) -> 158450.8 | L48: =+SUM(L37,L39,L44,L46) -> 410503.32 | M48: =+SUM(M37,M39,M44,M46) -> 834700.82 | N48: =+SUM(N37,N39,N44,N46) -> 1448251.1 | ... AE48: =+SUM(AE37,AE39,AE44,AE46) -> 3.0729687e-05
B49: Check | D49: =D28-D48 -> -1.0751188e-05 | G49: =G28-G48 -> -5.2992254e-07 | H49: =H28-H48 -> 6.1409082e-09 | I49: =I28-I48 -> 6.6647772e-09 | J49: =J28-J48 -> 2.1245796e-09 | K49: =K28-K48 -> -7.21775e-09 | L49: =L28-L48 -> -1.6530976e-08 | M49: =M28-M48 -> -7.7998266e-08 | N49: =N28-N48 -> -1.0500662e-07 | ... AE49: =AE28-AE48 -> -3.1562289e-05
B50: Bonds Fund Needed | G50: =+G48-SUM(G11,G12,G16,G18,G19,G23,G24) -> 3126643.1 | H50: =+H48-SUM(H11,H12,H16,H18,H19,H23,H24) -> 156085.91 | I50: =+I48-SUM(I11,I12,I16,I18,I19,I23,I24) -> 156870.26 | J50: =+J48-SUM(J11,J12,J16,J18,J19,J23,J24) -> 157658.55 | K50: =+K48-SUM(K11,K12,K16,K18,K19,K23,K24) -> 158450.8 | L50: =+L48-SUM(L11,L12,L16,L18,L19,L23,L24) -> 410503.32 | M50: =+M48-SUM(M11,M12,M16,M18,M19,M23,M24) -> 408677.17 | N50: =+N48-SUM(N11,N12,N16,N18,N19,N23,N24) -> 702709.71 | ... AE50: =+AE48-SUM(AE11,AE12,AE16,AE18,AE19,AE23,AE24) -> 3.1562289e-05
B51: Bonds O/S Balance | G51: =+G50 -> 3126643.1 | H51: =+G51+H50 -> 3282729 | I51: =+H51+I50 -> 3439599.3 | J51: =+I51+J50 -> 3597257.8 | K51: =+J51+K50 -> 3755708.6 | L51: =+K51+L50 -> 4166211.9 | M51: =+L51+M50 -> 4574889.1 | N51: =+M51+N50 -> 5277598.8 | O51: =+N51+O50 -> 6276698.2 | ... AE51: =+AD51+AE50 -> 26629504
B52: Tax Equity O/S Balance | G52: =+D16-G11-G16 -> 11669369 | H52: =+G52-H11-H16 -> 11669369 | I52: =+H52-I11-I16 -> 11669369 | J52: =+I52-J11-J16 -> 11669369 | K52: =+J52-K11-K16 -> 11669369 | L52: =+K52-L11-L16 -> 11669369 | M52: =+L52-M11-M16 -> 11435982 | N52: =+M52-N11-N16 -> 11027554 | O52: =+N52-O11-O16 -> 10444085 | ... AE52: =+AD52-AE11-AE16 -> -11669369

Sheet NOI Calc
A1: NET OPERATING INCOME CALCULATION
H3: Per Unit | I3: Monthly | J3: Annual | K3: PUPA
A4: Gross Revenues:
A5: Gross Rental Income | H5: =+I5/'Unit Mix+Rents'!$D$14 -> 1038.0714 | I5: =+J5/12 -> 290660 | J5: ='Unit Mix+Rents'!J14*12 -> 3487920 | K5: =+J5/'Unit Mix+Rents'!$D$14 -> 12456.857
A6: Tenant Charges | H6: 5 | I6: =+J6/12 -> 1400 | J6: =+H6*'Unit Mix+Rents'!$D$14*12 -> 16800 | K6: =+J6/'Unit Mix+Rents'!$D$14 -> 60
A7: Pet Fees | H7: 5 | I7: =+J7/12 -> 1400 | J7: =+H7*'Unit Mix+Rents'!$D$14*12 -> 16800 | K7: =+J7/'Unit Mix+Rents'!$D$14 -> 60
A9: Gross Revenues | H9: =+SUM(H5:H7) -> 1048.0714 | I9: =+SUM(I5:I7) -> 293460 | J9: =+SUM(J5:J7) -> 3521520 | K9: =+SUM(K5:K7) -> 12576.857
A11: Vacancy Adjustment | D11: 0.07 | H11: =+I11/'Unit Mix+Rents'!$D$14 -> -73.365 | I11: =+J11/12 -> -20542.2 | J11: =+J9*-D11 -> -246506.4 | K11: =+J11/'Unit Mix+Rents'!$D$14 -> -880.38
A13: Net Revenues | H13: =+H9+H11 -> 974.70643 | I13: =+I9+I11 -> 272917.8 | J13: =+J9+J11 -> 3275013.6 | K13: =+K9+K11 -> 11696.477
A15: Operating Expenses
A16: Management Fee | D16: 0.035 | H16: =+I16/'Unit Mix+Rents'!$D$14 -> 34.114725 | I16: =+J16/12 -> 9552.123 | J16: =+J13*D16 -> 114625.48 | K16: =+J16/'Unit Mix+Rents'!$D$14 -> 409.3767
A17: Staff Payroll | H17: =+I17/'Unit Mix+Rents'!$D$14 -> 55.838095 | I17: =+J17/12 -> 15634.667 | J17: =+'Expense Detail'!F13 -> 187616 | K17: =+J17/'Unit Mix+Rents'!$D$14 -> 670.05714
A18: Maintenance + Make Ready | H18: =+I18/'Unit Mix+Rents'!$D$14 -> 63.333333 | I18: =+J18/12 -> 17733.333 | J18: =+'Expense Detail'!F20 -> 212800 | K18: =+J18/'Unit Mix+Rents'!$D$14 -> 760
A19: Utilities | H19: =+I19/'Unit Mix+Rents'!$D$14 -> 62.535714 | I19: =+J19/12 -> 17510 | J19: =+'Expense Detail'!F39 -> 210120 | K19: =+J19/'Unit Mix+Rents'!$D$14 -> 750.42857
A20: Contract Services | H20: =+I20/'Unit Mix+Rents'!$D$14 -> 17.857143 | I20: =+J20/12 -> 5000 | J20: =+'Expense Detail'!F50 -> 60000 | K20: =+J20/'Unit Mix+Rents'!$D$14 -> 214.28571
A21: Compliance | H21: 45 | I21: =+J21/12 -> 1050 | J21: =+H21*'Unit Mix+Rents'!$D$14 -> 12600 | K21: =+J21/'Unit Mix+Rents'!$D$14 -> 45
A22: Admin Expenses | H22: 100 | I22: =+J22/12 -> 2333.3333 | J22: =+H22*'Unit Mix+Rents'!$D$14 -> 28000 | K22: =+J22/'Unit Mix+Rents'!$D$14 -> 100
A23: Property Insurance | H23: =+I23/'Unit Mix+Rents'!$D$14 -> 125 | I23: =+J23/12 -> 35000 | J23: =+'Expense Detail'!F65 -> 420000 | K23: =+J23/'Unit Mix+Rents'!$D$14 -> 1500
A24: Property Taxes | H24: =+I24/'Unit Mix+Rents'!$D$14 -> 14.880952 | I24: =+J24/12 -> 4166.6667 | J24: =+'Expense Detail'!F60 -> 50000 | K24: =+J24/'Unit Mix+Rents'!$D$14 -> 178.57143
A26: Total Operating Expenses | H26: =+SUM(H16:H25) -> 518.55996 | I26: =+SUM(I16:I25) -> 107980.12 | J26: =+SUM(J16:J25) -> 1295761.5 | K26: =+SUM(K16:K25) -> 4627.7196
A27: Expenses as a % of Gross Revenues | K27: =+K26/K9 -> 0.36795517
A29: NET OPERATING INCOME | H29: =+H13-H26 -> 456.14647 | I29: =+I13-I26 -> 164937.68 | J29: =+J13-J26 -> 1979252.1 | K29: =+K13-K26 -> 7068.7576
A30: NOI as a % of Gross Revenues | K30: =+K29/K9 -> 0.56204483
A33: Replacement Reserves | H33: =+I33/'Unit Mix+Rents'!$D$14 -> 41.666667 | I33: =+J33/12 -> 11666.667 | J33: =+K33*'Unit Mix+Rents'!$D$14 -> 140000 | K33: 500
A34: Issuer Fee | H34: =+I34/'Unit Mix+Rents'!$D$14 -> 15.850895 | I34: =+J34/12 -> 4438.2506 | J34: =+'17-year Pro Forma'!D35 -> 53259.007 | K34: =+J34/'Unit Mix+Rents'!$D$14 -> 190.21074
A35: Trustee Fee | H35: =+I35/'Unit Mix+Rents'!$D$14 -> 1.4880952 | I35: =+J35/12 -> 416.66667 | J35: =+'17-year Pro Forma'!D36 -> 5000 | K35: =+J35/'Unit Mix+Rents'!$D$14 -> 17.857143
A36: Servicing Fee | H36: =+I36/'Unit Mix+Rents'!$D$14 -> 7.9254475 | I36: =+J36/12 -> 2219.1253 | J36: =+'17-year Pro Forma'!D37 -> 26629.504 | K36: =+J36/'Unit Mix+Rents'!$D$14 -> 95.10537
A38: Operating Cash Flow | H38: =+H29-SUM(H34:H36) -> 430.88203 | I38: =+I29-SUM(I34:I36) -> 157863.63 | J38: =+J29-SUM(J34:J36) -> 1894363.6 | K38: =+K29-SUM(K34:K36) -> 6765.5843
A39: Operating Cash Flow as a % of Gross Revenues | J39: =+J38/J13 -> 0.57842924 | K39: =+K38/K13 -> 0.57842924

Sheet Lease-Up Period
A1: YEAR 1 LEASE-UP — MONTHLY CASH FLOW
D4: Month 1 | E4: Month 2 | F4: Month 3 | G4: Month 4 | H4: Month 5 | I4: Month 6 | J4: Month 7 | K4: Month 8 | L4: Month 9 | M4: Month 10 | N4: Month 11 | O4: Month 12 | P4: Total
A6: Gross Rental Income | D6: =+'NOI Calc'!$J$5/12 -> 290660 | E6: =+'NOI Calc'!$J$5/12 -> 290660 | F6: =+'NOI Calc'!$J$5/12 -> 290660 | G6: =+'NOI Calc'!$J$5/12 -> 290660 | H6: =+'NOI Calc'!$J$5/12 -> 290660 | I6: =+'NOI Calc'!$J$5/12 -> 290660 | J6: =+'NOI Calc'!$J$5/12 -> 290660 | K6: =+'NOI Calc'!$J$5/12 -> 290660 | ... O6: =+'NOI Calc'!$J$5/12 -> 290660 | P6: =SUM(D6:O6) -> 3487920
A7: Other Income | D7: =(+'NOI Calc'!$J$6+'NOI Calc'!$J$7)/12 -> 2800 | E7: =(+'NOI Calc'!$J$6+'NOI Calc'!$J$7)/12 -> 2800 | F7: =(+'NOI Calc'!$J$6+'NOI Calc'!$J$7)/12 -> 2800 | G7: =(+'NOI Calc'!$J$6+'NOI Calc'!$J$7)/12 -> 2800 | H7: =(+'NOI Calc'!$J$6+'NOI Calc'!$J$7)/12 -> 2800 | I7: =(+'NOI Calc'!$J$6+'NOI Calc'!$J$7)/12 -> 2800 | J7: =(+'NOI Calc'!$J$6+'NOI Calc'!$J$7)/12 -> 2800 | K7: =(+'NOI Calc'!$J$6+'NOI Calc'!$J$7)/12 -> 2800 | ... O7: =(+'NOI Calc'!$J$6+'NOI Calc'!$J$7)/12 -> 2800 | P7: =SUM(D7:O7) -> 33600
A9: Gross Revenue | D9: =+SUM(D6:D7) -> 293460 | E9: =+SUM(E6:E7) -> 293460 | F9: =+SUM(F6:F7) -> 293460 | G9: =+SUM(G6:G7) -> 293460 | H9: =+SUM(H6:H7) -> 293460 | I9: =+SUM(I6:I7) -> 293460 | J9: =+SUM(J6:J7) -> 293460 | K9: =+SUM(K6:K7) -> 293460 | ... O9: =+SUM(O6:O7) -> 293460 | P9: =SUM(D9:O9) -> 3521520
A10: Vacancy Adjustment | D10: =-MAX('NOI Calc'!$D$11,1-D$55)*D9 -> -262017.86 | E10: =-MAX('NOI Calc'!$D$11,1-E$55)*E9 -> -230575.71 | F10: =-MAX('NOI Calc'!$D$11,1-F$55)*F9 -> -199133.57 | G10: =-MAX('NOI Calc'!$D$11,1-G$55)*G9 -> -167691.43 | H10: =-MAX('NOI Calc'!$D$11,1-H$55)*H9 -> -136249.29 | I10: =-MAX('NOI Calc'!$D$11,1-I$55)*I9 -> -104807.14 | J10: =-MAX('NOI Calc'!$D$11,1-J$55)*J9 -> -73365 | K10: =-MAX('NOI Calc'!$D$11,1-K$55)*K9 -> -41922.857 | ... O10: =-MAX('NOI Calc'!$D$11,1-O$55)*O9 -> -20542.2 | P10: =SUM(D10:O10) -> -1297931.7
A12: Net Revenue | D12: =+D9+D10 -> 31442.143 | E12: =+E9+E10 -> 62884.286 | F12: =+F9+F10 -> 94326.429 | G12: =+G9+G10 -> 125768.57 | H12: =+H9+H10 -> 157210.71 | I12: =+I9+I10 -> 188652.86 | J12: =+J9+J10 -> 220095 | K12: =+K9+K10 -> 251537.14 | ... O12: =+O9+O10 -> 272917.8 | P12: =SUM(D12:O12) -> 2223588.3
A14: Operating Expenses | C14: Fixed %
B16: Management Fee | D16: =+D12*'NOI Calc'!$D$16 -> 1100.475 | E16: =+E12*'NOI Calc'!$D$16 -> 2200.95 | F16: =+F12*'NOI Calc'!$D$16 -> 3301.425 | G16: =+G12*'NOI Calc'!$D$16 -> 4401.9 | H16: =+H12*'NOI Calc'!$D$16 -> 5502.375 | I16: =+I12*'NOI Calc'!$D$16 -> 6602.85 | J16: =+J12*'NOI Calc'!$D$16 -> 7703.325 | K16: =+K12*'NOI Calc'!$D$16 -> 8803.8 | ... O16: =+O12*'NOI Calc'!$D$16 -> 9552.123 | P16: =SUM(D16:O16) -> 77825.592
B17: Payroll | C17: 1 | D17: =('NOI Calc'!$J$17/12)*($C17+(1-$C17)*D$55) -> 15634.667 | E17: =('NOI Calc'!$J$17/12)*($C17+(1-$C17)*E$55) -> 15634.667 | F17: =('NOI Calc'!$J$17/12)*($C17+(1-$C17)*F$55) -> 15634.667 | G17: =('NOI Calc'!$J$17/12)*($C17+(1-$C17)*G$55) -> 15634.667 | H17: =('NOI Calc'!$J$17/12)*($C17+(1-$C17)*H$55) -> 15634.667 | I17: =('NOI Calc'!$J$17/12)*($C17+(1-$C17)*I$55) -> 15634.667 | J17: =('NOI Calc'!$J$17/12)*($C17+(1-$C17)*J$55) -> 15634.667 | K17: =('NOI Calc'!$J$17/12)*($C17+(1-$C17)*K$55) -> 15634.667 | ... O17: =('NOI Calc'!$J$17/12)*($C17+(1-$C17)*O$55) -> 15634.667 | P17: =SUM(D17:O17) -> 187616
B18: Maintenance | C18: 0 | D18: =('NOI Calc'!$J$18/12)*($C18+(1-$C18)*D$55) -> 1900 | E18: =('NOI Calc'!$J$18/12)*($C18+(1-$C18)*E$55) -> 3800 | F18: =('NOI Calc'!$J$18/12)*($C18+(1-$C18)*F$55) -> 5700 | G18: =('NOI Calc'!$J$18/12)*($C18+(1-$C18)*G$55) -> 7600 | H18: =('NOI Calc'!$J$18/12)*($C18+(1-$C18)*H$55) -> 9500 | I18: =('NOI Calc'!$J$18/12)*($C18+(1-$C18)*I$55) -> 11400 | J18: =('NOI Calc'!$J$18/12)*($C18+(1-$C18)*J$55) -> 13300 | K18: =('NOI Calc'!$J$18/12)*($C18+(1-$C18)*K$55) -> 15200 | ... O18: =('NOI Calc'!$J$18/12)*($C18+(1-$C18)*O$55) -> 17733.333 | P18: =SUM(D18:O18) -> 138700
B19: Utilities | C19: 0.75 | D19: =('NOI Calc'!$J$19/12)*($C19+(1-$C19)*D$55) -> 13601.518 | E19: =('NOI Calc'!$J$19/12)*($C19+(1-$C19)*E$55) -> 14070.536 | F19: =('NOI Calc'!$J$19/12)*($C19+(1-$C19)*F$55) -> 14539.554 | G19: =('NOI Calc'!$J$19/12)*($C19+(1-$C19)*G$55) -> 15008.571 | H19: =('NOI Calc'!$J$19/12)*($C19+(1-$C19)*H$55) -> 15477.589 | I19: =('NOI Calc'!$J$19/12)*($C19+(1-$C19)*I$55) -> 15946.607 | J19: =('NOI Calc'!$J$19/12)*($C19+(1-$C19)*J$55) -> 16415.625 | K19: =('NOI Calc'!$J$19/12)*($C19+(1-$C19)*K$55) -> 16884.643 | ... O19: =('NOI Calc'!$J$19/12)*($C19+(1-$C19)*O$55) -> 17510 | P19: =SUM(D19:O19) -> 191828.3
B20: Administrative | C20: 1 | D20: =(('NOI Calc'!$J$20+'NOI Calc'!$J$21+'NOI Calc'!$J$22)/12)*($C20+(1-$C20)*D$55) -> 8383.3333 | E20: =(('NOI Calc'!$J$20+'NOI Calc'!$J$21+'NOI Calc'!$J$22)/12)*($C20+(1-$C20)*E$55) -> 8383.3333 | F20: =(('NOI Calc'!$J$20+'NOI Calc'!$J$21+'NOI Calc'!$J$22)/12)*($C20+(1-$C20)*F$55) -> 8383.3333 | G20: =(('NOI Calc'!$J$20+'NOI Calc'!$J$21+'NOI Calc'!$J$22)/12)*($C20+(1-$C20)*G$55) -> 8383.3333 | H20: =(('NOI Calc'!$J$20+'NOI Calc'!$J$21+'NOI Calc'!$J$22)/12)*($C20+(1-$C20)*H$55) -> 8383.3333 | I20: =(('NOI Calc'!$J$20+'NOI Calc'!$J$21+'NOI Calc'!$J$22)/12)*($C20+(1-$C20)*I$55) -> 8383.3333 | J20: =(('NOI Calc'!$J$20+'NOI Calc'!$J$21+'NOI Calc'!$J$22)/12)*($C20+(1-$C20)*J$55) -> 8383.3333 | K20: =(('NOI Calc'!$J$20+'NOI Calc'!$J$21+'NOI Calc'!$J$22)/12)*($C20+(1-$C20)*K$55) -> 8383.3333 | ... O20: =(('NOI Calc'!$J$20+'NOI Calc'!$J$21+'NOI Calc'!$J$22)/12)*($C20+(1-$C20)*O$55) -> 8383.3333 | P20: =SUM(D20:O20) -> 100600
B21: Property Insurance | C21: 1 | D21: =('NOI Calc'!$J$23/12)*($C21+(1-$C21)*D$55) -> 35000 | E21: =('NOI Calc'!$J$23/12)*($C21+(1-$C21)*E$55) -> 35000 | F21: =('NOI Calc'!$J$23/12)*($C21+(1-$C21)*F$55) -> 35000 | G21: =('NOI Calc'!$J$23/12)*($C21+(1-$C21)*G$55) -> 35000 | H21: =('NOI Calc'!$J$23/12)*($C21+(1-$C21)*H$55) -> 35000 | I21: =('NOI Calc'!$J$23/12)*($C21+(1-$C21)*I$55) -> 35000 | J21: =('NOI Calc'!$J$23/12)*($C21+(1-$C21)*J$55) -> 35000 | K21: =('NOI Calc'!$J$23/12)*($C21+(1-$C21)*K$55) -> 35000 | ... O21: =('NOI Calc'!$J$23/12)*($C21+(1-$C21)*O$55) -> 35000 | P21: =SUM(D21:O21) -> 420000
B22: Property Taxes | D22: =+'Expense Detail'!$F$60/12 -> 4166.6667 | E22: =+'Expense Detail'!$F$60/12 -> 4166.6667 | F22: =+'Expense Detail'!$F$60/12 -> 4166.6667 | G22: =+'Expense Detail'!$F$60/12 -> 4166.6667 | H22: =+'Expense Detail'!$F$60/12 -> 4166.6667 | I22: =+'Expense Detail'!$F$60/12 -> 4166.6667 | J22: =+'Expense Detail'!$F$60/12 -> 4166.6667 | K22: =+'Expense Detail'!$F$60/12 -> 4166.6667 | ... O22: =+'Expense Detail'!$F$60/12 -> 4166.6667 | P22: =SUM(D22:O22) -> 50000
A24: Total Operating Expenses | D24: =+SUM(D16:D23) -> 79786.66 | E24: =+SUM(E16:E23) -> 83256.152 | F24: =+SUM(F16:F23) -> 86725.645 | G24: =+SUM(G16:G23) -> 90195.138 | H24: =+SUM(H16:H23) -> 93664.631 | I24: =+SUM(I16:I23) -> 97134.124 | J24: =+SUM(J16:J23) -> 100603.62 | K24: =+SUM(K16:K23) -> 104073.11 | ... O24: =+SUM(O16:O23) -> 107980.12 | P24: =SUM(D24:O24) -> 1166569.9
A26: NET OPERATING INCOME | D26: =+D12-D24 -> -48344.517 | E26: =+E12-E24 -> -20371.867 | F26: =+F12-F24 -> 7600.7833 | G26: =+G12-G24 -> 35573.433 | H26: =+H12-H24 -> 63546.083 | I26: =+I12-I24 -> 91518.733 | J26: =+J12-J24 -> 119491.38 | K26: =+K12-K24 -> 147464.03 | ... O26: =+O12-O24 -> 164937.68 | P26: =SUM(D26:O26) -> 1057018.4
A28: Replacement Reserves | D28: =+'NOI Calc'!$J$33/12 -> 11666.667 | E28: =+'NOI Calc'!$J$33/12 -> 11666.667 | F28: =+'NOI Calc'!$J$33/12 -> 11666.667 | G28: =+'NOI Calc'!$J$33/12 -> 11666.667 | H28: =+'NOI Calc'!$J$33/12 -> 11666.667 | I28: =+'NOI Calc'!$J$33/12 -> 11666.667 | J28: =+'NOI Calc'!$J$33/12 -> 11666.667 | K28: =+'NOI Calc'!$J$33/12 -> 11666.667 | ... O28: =+'NOI Calc'!$J$33/12 -> 11666.667 | P28: =SUM(D28:O28) -> 140000
A30: Senior A Bond Interest | D30: =+'Loan Amortization'!$C$28*'Financing Assumptions'!$C$28/12 -> 122051.89 | E30: =+'Loan Amortization'!$C$28*'Financing Assumptions'!$C$28/12 -> 122051.89 | F30: =+'Loan Amortization'!$C$28*'Financing Assumptions'!$C$28/12 -> 122051.89 | G30: =+'Loan Amortization'!$C$28*'Financing Assumptions'!$C$28/12 -> 122051.89 | H30: =+'Loan Amortization'!$C$28*'Financing Assumptions'!$C$28/12 -> 122051.89 | I30: =+'Loan Amortization'!$C$28*'Financing Assumptions'!$C$28/12 -> 122051.89 | J30: =+'Loan Amortization'!$C$28*'Financing Assumptions'!$C$28/12 -> 122051.89 | K30: =+'Loan Amortization'!$C$28*'Financing Assumptions'!$C$28/12 -> 122051.89 | ... O30: =+'Loan Amortization'!$C$28*'Financing Assumptions'!$C$28/12 -> 122051.89 | P30: =SUM(D30:O30) -> 1464622.7
A31: Senior A Bond Principal | D31: 0 | E31: 0 | F31: 0 | G31: 0 | H31: 0 | I31: 0 | J31: 0 | K31: 0 | L31: 0 | M31: 0 | N31: 0 | O31: 0 | P31: =SUM(D31:O31) -> 0
A33: Cash Available after Bond Pmts | D33: =+D26-D28-D30-D31 -> -182063.08 | E33: =+E26-E28-E30-E31 -> -154090.43 | F33: =+F26-F28-F30-F31 -> -126117.78 | G33: =+G26-G28-G30-G31 -> -98145.125 | H33: =+H26-H28-H30-H31 -> -70172.475 | I33: =+I26-I28-I30-I31 -> -42199.825 | J33: =+J26-J28-J30-J31 -> -14227.175 | K33: =+K26-K28-K30-K31 -> 13745.475 | ... O33: =+O26-O28-O30-O31 -> 31219.118 | P33: =SUM(D33:O33) -> -547604.26
A36: Issuer Fee | D36: =+'Loan Amortization'!$C$28*'Financing Assumptions'!$C$30/12 -> 4438.2506 | E36: =+'Loan Amortization'!$C$28*'Financing Assumptions'!$C$30/12 -> 4438.2506 | F36: =+'Loan Amortization'!$C$28*'Financing Assumptions'!$C$30/12 -> 4438.2506 | G36: =+'Loan Amortization'!$C$28*'Financing Assumptions'!$C$30/12 -> 4438.2506 | H36: =+'Loan Amortization'!$C$28*'Financing Assumptions'!$C$30/12 -> 4438.2506 | I36: =+'Loan Amortization'!$C$28*'Financing Assumptions'!$C$30/12 -> 4438.2506 | J36: =+'Loan Amortization'!$C$28*'Financing Assumptions'!$C$30/12 -> 4438.2506 | K36: =+'Loan Amortization'!$C$28*'Financing Assumptions'!$C$30/12 -> 4438.2506 | ... O36: =+'Loan Amortization'!$C$28*'Financing Assumptions'!$C$30/12 -> 4438.2506 | P36: =SUM(D36:O36) -> 53259.007
A37: Trustee Fee | D37: =+'Financing Assumptions'!$C$31/12 -> 416.66667 | E37: =+'Financing Assumptions'!$C$31/12 -> 416.66667 | F37: =+'Financing Assumptions'!$C$31/12 -> 416.66667 | G37: =+'Financing Assumptions'!$C$31/12 -> 416.66667 | H37: =+'Financing Assumptions'!$C$31/12 -> 416.66667 | I37: =+'Financing Assumptions'!$C$31/12 -> 416.66667 | J37: =+'Financing Assumptions'!$C$31/12 -> 416.66667 | K37: =+'Financing Assumptions'!$C$31/12 -> 416.66667 | ... O37: =+'Financing Assumptions'!$C$31/12 -> 416.66667 | P37: =SUM(D37:O37) -> 5000
A38: Servicing Fee | D38: =+'Loan Amortization'!$C$28*'Financing Assumptions'!$C$32/12 -> 2219.1253 | E38: =+'Loan Amortization'!$C$28*'Financing Assumptions'!$C$32/12 -> 2219.1253 | F38: =+'Loan Amortization'!$C$28*'Financing Assumptions'!$C$32/12 -> 2219.1253 | G38: =+'Loan Amortization'!$C$28*'Financing Assumptions'!$C$32/12 -> 2219.1253 | H38: =+'Loan Amortization'!$C$28*'Financing Assumptions'!$C$32/12 -> 2219.1253 | I38: =+'Loan Amortization'!$C$28*'Financing Assumptions'!$C$32/12 -> 2219.1253 | J38: =+'Loan Amortization'!$C$28*'Financing Assumptions'!$C$32/12 -> 2219.1253 | K38: =+'Loan Amortization'!$C$28*'Financing Assumptions'!$C$32/12 -> 2219.1253 | ... O38: =+'Loan Amortization'!$C$28*'Financing Assumptions'!$C$32/12 -> 2219.1253 | P38: =SUM(D38:O38) -> 26629.504
A39: Asset Management Fee - 10% | D39: =IF((0.1*D33)<=0,0,0.1*D33) -> 0 | E39: =IF((0.1*E33)<=0,0,0.1*E33) -> 0 | F39: =IF((0.1*F33)<=0,0,0.1*F33) -> 0 | G39: =IF((0.1*G33)<=0,0,0.1*G33) -> 0 | H39: =IF((0.1*H33)<=0,0,0.1*H33) -> 0 | I39: =IF((0.1*I33)<=0,0,0.1*I33) -> 0 | J39: =IF((0.1*J33)<=0,0,0.1*J33) -> 0 | K39: =IF((0.1*K33)<=0,0,0.1*K33) -> 1374.5475 | ... O39: =IF((0.1*O33)<=0,0,0.1*O33) -> 3121.9118 | P39: =SUM(D39:O39) -> 13941.162
A41: Cash Available after Fees | D41: =+D33-SUM(D36:D40) -> -189137.12 | E41: =+E33-SUM(E36:E40) -> -161164.47 | F41: =+F33-SUM(F36:F40) -> -133191.82 | G41: =+G33-SUM(G36:G40) -> -105219.17 | H41: =+H33-SUM(H36:H40) -> -77246.518 | I41: =+I33-SUM(I36:I40) -> -49273.868 | J41: =+J33-SUM(J36:J40) -> -21301.218 | K41: =+K33-SUM(K36:K40) -> 5296.8847 | ... O41: =+O33-SUM(O36:O40) -> 21023.164 | P41: =SUM(D41:O41) -> -646433.93
A43: RATIOS & ASSUMPTIONS
A45: Senior A Bond DSCR | D45: =IF((D30+D31)=0,"N/A",D26/(D30+D31)) -> -0.39609805 | E45: =IF((E30+E31)=0,"N/A",E26/(E30+E31)) -> -0.16691152 | F45: =IF((F30+F31)=0,"N/A",F26/(F30+F31)) -> 0.062275014 | G45: =IF((G30+G31)=0,"N/A",G26/(G30+G31)) -> 0.29146155 | H45: =IF((H30+H31)=0,"N/A",H26/(H30+H31)) -> 0.52064808 | I45: =IF((I30+I31)=0,"N/A",I26/(I30+I31)) -> 0.74983461 | J45: =IF((J30+J31)=0,"N/A",J26/(J30+J31)) -> 0.97902115 | K45: =IF((K30+K31)=0,"N/A",K26/(K30+K31)) -> 1.2082077 | ... P45: =IF((P30+P31)=0,"N/A",P26/(P30+P31)) -> 0.72170017
A47: Revenue Growth Rate | D47: N/A | E47: =E12/D12-1 -> 1 | F47: =F12/E12-1 -> 0.5 | G47: =G12/F12-1 -> 0.33333333 | H47: =H12/G12-1 -> 0.25 | I47: =I12/H12-1 -> 0.2 | J47: =J12/I12-1 -> 0.16666667 | K47: =K12/J12-1 -> 0.14285714 | L47: =L12/K12-1 -> 0.085 | ... O47: =O12/N12-1 -> 0 | P47: N/A
A48: Expense Growth Rate | D48: N/A | E48: =E24/D24-1 -> 0.043484624 | F48: =F24/E24-1 -> 0.04167251 | G48: =G24/F24-1 -> 0.040005385 | H48: =H24/G24-1 -> 0.038466517 | I48: =I24/H24-1 -> 0.037041654 | J48: =J24/I24-1 -> 0.035718579 | K48: =K24/J24-1 -> 0.034486761 | L48: =L24/K24-1 -> 0.029953375 | ... O48: =O24/N24-1 -> 0 | P48: N/A
A49: Expenses as a % of Gross Revenues | D49: =D24/D9 -> 0.27188257 | E49: =E24/E9 -> 0.28370528 | F49: =F24/F9 -> 0.29552799 | G49: =G24/G9 -> 0.30735071 | H49: =H24/H9 -> 0.31917342 | I49: =I24/I9 -> 0.33099613 | J49: =J24/J9 -> 0.34281884 | K49: =K24/K9 -> 0.35464155 | ... P49: =P24/P9 -> 0.33126885
A50: NOI as a % of Gross Revenues | D50: =+D26/D9 -> -0.16473971 | E50: =+E26/E9 -> -0.069419569 | F50: =+F26/F9 -> 0.025900577 | G50: =+G26/G9 -> 0.12122072 | H50: =+H26/H9 -> 0.21654087 | I50: =+I26/I9 -> 0.31186101 | J50: =+J26/J9 -> 0.40718116 | K50: =+K26/K9 -> 0.50250131 | ... P50: =+P26/P9 -> 0.30015972
A52: LEASE-UP ASSUMPTIONS
A53: Units Leased per Month | D53: 30 | E53: =D53 -> 30 | F53: =E53 -> 30 | G53: =F53 -> 30 | H53: =G53 -> 30 | I53: =H53 -> 30 | J53: =I53 -> 30 | K53: =J53 -> 30 | L53: =K53 -> 30 | M53: 10 | N53: 0 | O53: 0 | P53: =SUM(D53:O53) -> 280
A54: Cumulative Units Occupied | D54: =MIN(SUM($D$53:D53),'Unit Mix+Rents'!$D$14) -> 30 | E54: =D53+E53 -> 60 | F54: =E54+F53 -> 90 | G54: =F54+G53 -> 120 | H54: =G54+H53 -> 150 | I54: =H54+I53 -> 180 | J54: =I54+J53 -> 210 | K54: =J54+K53 -> 240 | L54: =K54+L53 -> 270 | M54: =L54+M53 -> 280 | ... O54: =N54+O53 -> 280
A55: Occupancy % | D55: =D54/'Unit Mix+Rents'!$D$14 -> 0.10714286 | E55: =E54/'Unit Mix+Rents'!$D$14 -> 0.21428571 | F55: =F54/'Unit Mix+Rents'!$D$14 -> 0.32142857 | G55: =G54/'Unit Mix+Rents'!$D$14 -> 0.42857143 | H55: =H54/'Unit Mix+Rents'!$D$14 -> 0.53571429 | I55: =I54/'Unit Mix+Rents'!$D$14 -> 0.64285714 | J55: =J54/'Unit Mix+Rents'!$D$14 -> 0.75 | K55: =K54/'Unit Mix+Rents'!$D$14 -> 0.85714286 | ... O55: =O54/'Unit Mix+Rents'!$D$14 -> 1

Sheet 17-year Pro Forma
A1: CASH FLOW FORECAST
D4: Yr 1 | E4: Yr 2 | F4: Yr 3 | G4: Yr 4 | H4: Yr 5 | I4: Yr 6 | J4: Yr 7 | K4: Yr 8 | L4: Yr 9 | M4: Yr 10 | N4: Yr 11 | O4: Yr 12 | P4: Yr 13 | Q4: Yr 14 | R4: Yr 15 | S4: Yr 16 | T4: Yr 17 | U4: Yrs 11-17 | V4: TOTAL
A6: Gross Rental Income | D6: =+'Lease-Up Period'!P6 -> 3487920 | E6: =+D6*(1+$D$48) -> 3557678.4 | F6: =+E6*(1+$D$48) -> 3628832 | G6: =+F6*(1+$D$48) -> 3701408.6 | H6: =+G6*(1+$D$48) -> 3775436.8 | I6: =+H6*(1+$D$48) -> 3850945.5 | J6: =+I6*(1+$D$48) -> 3927964.4 | K6: =+J6*(1+$D$48) -> 4006523.7 | L6: =+K6*(1+$D$48) -> 4086654.2 | ... T6: =+S6*(1+$D$48) -> 4788166.7 | U6: =+SUM(N6:T6) -> 31608752 | V6: =+SUM(D6:M6,U6) -> 69800503
A7: Other Income | D7: =+'Lease-Up Period'!P7 -> 33600 | E7: =+D7*(1+$D$48) -> 34272 | F7: =+E7*(1+$D$48) -> 34957.44 | G7: =+F7*(1+$D$48) -> 35656.589 | H7: =+G7*(1+$D$48) -> 36369.721 | I7: =+H7*(1+$D$48) -> 37097.115 | J7: =+I7*(1+$D$48) -> 37839.057 | K7: =+J7*(1+$D$48) -> 38595.838 | L7: =+K7*(1+$D$48) -> 39367.755 | ... T7: =+S7*(1+$D$48) -> 46125.6 | U7: =+SUM(N7:T7) -> 304494.96 | V7: =+SUM(D7:M7,U7) -> 672405.58
A9: Gross Revenue | D9: =+SUM(D6:D7) -> 3521520 | E9: =+SUM(E6:E7) -> 3591950.4 | F9: =+SUM(F6:F7) -> 3663789.4 | G9: =+SUM(G6:G7) -> 3737065.2 | H9: =+SUM(H6:H7) -> 3811806.5 | I9: =+SUM(I6:I7) -> 3888042.6 | J9: =+SUM(J6:J7) -> 3965803.5 | K9: =+SUM(K6:K7) -> 4045119.6 | ... V9: =+SUM(V6:V7) -> 70472908
A10: Vacancy Adjustment | D10: =+'Lease-Up Period'!P10 -> -1297931.7 | E10: =-'NOI Calc'!$D$11*'17-year Pro Forma'!E9 -> -251436.53 | F10: =-'NOI Calc'!$D$11*'17-year Pro Forma'!F9 -> -256465.26 | G10: =-'NOI Calc'!$D$11*'17-year Pro Forma'!G9 -> -261594.56 | H10: =-'NOI Calc'!$D$11*'17-year Pro Forma'!H9 -> -266826.46 | I10: =-'NOI Calc'!$D$11*'17-year Pro Forma'!I9 -> -272162.98 | J10: =-'NOI Calc'!$D$11*'17-year Pro Forma'!J9 -> -277606.24 | K10: =-'NOI Calc'!$D$11*'17-year Pro Forma'!K9 -> -283158.37 | L10: =-'NOI Calc'!$D$11*'17-year Pro Forma'!L9 -> -288821.54 | ... T10: =-'NOI Calc'!$D$11*'17-year Pro Forma'!T9 -> -338400.46 | U10: =+SUM(N10:T10) -> -2233927.3 | V10: =+SUM(D10:M10,U10) -> -5984528.8
A12: Net Revenue | D12: =+D9+D10 -> 2223588.3 | E12: =+E9+E10 -> 3340513.9 | F12: =+F9+F10 -> 3407324.1 | G12: =+G9+G10 -> 3475470.6 | H12: =+H9+H10 -> 3544980 | I12: =+I9+I10 -> 3615879.6 | J12: =+J9+J10 -> 3688197.2 | K12: =+K9+K10 -> 3761961.2 | ... V12: =+V9+V10 -> 64488379
A14: Operating Expenses
B16: Management Fee | D16: =+'Lease-Up Period'!P16 -> 77825.592 | E16: =+E12*'NOI Calc'!$D$16 -> 116917.99 | F16: =+F12*'NOI Calc'!$D$16 -> 119256.35 | G16: =+G12*'NOI Calc'!$D$16 -> 121641.47 | H16: =+H12*'NOI Calc'!$D$16 -> 124074.3 | I16: =+I12*'NOI Calc'!$D$16 -> 126555.79 | J16: =+J12*'NOI Calc'!$D$16 -> 129086.9 | K16: =+K12*'NOI Calc'!$D$16 -> 131668.64 | L16: =+L12*'NOI Calc'!$D$16 -> 134302.01 | ... T16: =+T12*'NOI Calc'!$D$16 -> 157356.21 | U16: =+SUM(N16:T16) -> 1038776.2 | V16: =+SUM(D16:M16,U16) -> 2257093.3
B17: Payroll | D17: =+'Lease-Up Period'!P17 -> 187616 | E17: =+D17*(1+$D$49) -> 193244.48 | F17: =+E17*(1+$D$49) -> 199041.81 | G17: =+F17*(1+$D$49) -> 205013.07 | H17: =+G17*(1+$D$49) -> 211163.46 | I17: =+H17*(1+$D$49) -> 217498.36 | J17: =+I17*(1+$D$49) -> 224023.32 | K17: =+J17*(1+$D$49) -> 230744.02 | L17: =+K17*(1+$D$49) -> 237666.34 | ... T17: =+S17*(1+$D$49) -> 301068.6 | U17: =+SUM(N17:T17) -> 1932014.9 | V17: =+SUM(D17:M17,U17) -> 4082822
B18: Maintenance | D18: =+'Lease-Up Period'!P18 -> 138700 | E18: =+'NOI Calc'!J18*(1+$D$49) -> 219184 | F18: =+E18*(1+$D$49) -> 225759.52 | G18: =+F18*(1+$D$49) -> 232532.31 | H18: =+G18*(1+$D$49) -> 239508.27 | I18: =+H18*(1+$D$49) -> 246693.52 | J18: =+I18*(1+$D$49) -> 254094.33 | K18: =+J18*(1+$D$49) -> 261717.16 | L18: =+K18*(1+$D$49) -> 269568.67 | M18: =+L18*(1+$D$49) -> 277655.73 | ... T18: =+S18*(1+$D$49) -> 341481.53 | U18: =+SUM(N18:T18) -> 2191352.4 | V18: =+SUM(D18:M18,U18) -> 4556765.9
B19: Utilities | D19: =+'Lease-Up Period'!P19 -> 191828.3 | E19: =+'NOI Calc'!J19*(1+$D$49) -> 216423.6 | F19: =+E19*(1+$D$49) -> 222916.31 | G19: =+F19*(1+$D$49) -> 229603.8 | H19: =+G19*(1+$D$49) -> 236491.91 | I19: =+H19*(1+$D$49) -> 243586.67 | J19: =+I19*(1+$D$49) -> 250894.27 | K19: =+J19*(1+$D$49) -> 258421.1 | L19: =+K19*(1+$D$49) -> 266173.73 | M19: =+L19*(1+$D$49) -> 274158.94 | ... T19: =+S19*(1+$D$49) -> 337180.92 | U19: =+SUM(N19:T19) -> 2163754.5 | V19: =+SUM(D19:M19,U19) -> 4554253.1
B20: Administrative | D20: =+'Lease-Up Period'!P20 -> 100600 | E20: =+D20*(1+$D$49) -> 103618 | F20: =+E20*(1+$D$49) -> 106726.54 | G20: =+F20*(1+$D$49) -> 109928.34 | H20: =+G20*(1+$D$49) -> 113226.19 | I20: =+H20*(1+$D$49) -> 116622.97 | J20: =+I20*(1+$D$49) -> 120121.66 | K20: =+J20*(1+$D$49) -> 123725.31 | L20: =+K20*(1+$D$49) -> 127437.07 | ... T20: =+S20*(1+$D$49) -> 161433.47 | U20: =+SUM(N20:T20) -> 1035949.5 | V20: =+SUM(D20:M20,U20) -> 2189215.7
B21: Property Insurance | D21: =+'Lease-Up Period'!P21 -> 420000 | E21: =+D21*(1+$D$49) -> 432600 | F21: =+E21*(1+$D$49) -> 445578 | G21: =+F21*(1+$D$49) -> 458945.34 | H21: =+G21*(1+$D$49) -> 472713.7 | I21: =+H21*(1+$D$49) -> 486895.11 | J21: =+I21*(1+$D$49) -> 501501.96 | K21: =+J21*(1+$D$49) -> 516547.02 | L21: =+K21*(1+$D$49) -> 532043.43 | ... T21: =+S21*(1+$D$49) -> 673976.7 | U21: =+SUM(N21:T21) -> 4325037.5 | V21: =+SUM(D21:M21,U21) -> 9139866.9
B22: Property Taxes | D22: =+'Lease-Up Period'!P22 -> 50000 | E22: =$D$22 -> 50000 | F22: =$D$22 -> 50000 | G22: =$D$22 -> 50000 | H22: =$D$22 -> 50000 | I22: =$D$22 -> 50000 | J22: =$D$22 -> 50000 | K22: =$D$22 -> 50000 | L22: =$D$22 -> 50000 | M22: =$D$22 -> 50000 | N22: =+'NOI Calc'!J24 -> 50000 | O22: =N22*(1+$D$49) -> 51500 | P22: =O22*(1+$D$49) -> 53045 | Q22: =P22*(1+$D$49) -> 54636.35 | R22: =Q22*(1+$D$49) -> 56275.44 | S22: =R22*(1+$D$49) -> 57963.704 | T22: =S22*(1+$D$49) -> 59702.615 | U22: =+SUM(N22:T22) -> 383123.11 | V22: =+SUM(D22:M22,U22) -> 883123.11
A24: Total Operating Expenses | D24: =+SUM(D16:D23) -> 1166569.9 | E24: =+SUM(E16:E23) -> 1331988.1 | F24: =+SUM(F16:F23) -> 1369278.5 | G24: =+SUM(G16:G23) -> 1407664.3 | H24: =+SUM(H16:H23) -> 1447177.8 | I24: =+SUM(I16:I23) -> 1487852.4 | J24: =+SUM(J16:J23) -> 1529722.4 | K24: =+SUM(K16:K23) -> 1572823.2 | ... V24: =+SUM(V16:V23) -> 27663140
A26: NET OPERATING INCOME | D26: =+D12-D24 -> 1057018.4 | E26: =+E12-E24 -> 2008525.8 | F26: =+F12-F24 -> 2038045.6 | G26: =+G12-G24 -> 2067806.3 | H26: =+H12-H24 -> 2097802.2 | I26: =+I12-I24 -> 2128027.2 | J26: =+J12-J24 -> 2158474.8 | K26: =+K12-K24 -> 2189137.9 | ... V26: =+V12-V24 -> 36825239
A28: Replacement Reserves | D28: =+'Lease-Up Period'!P28 -> 140000 | E28: =+D28*(1+$D$49) -> 144200 | F28: =+E28*(1+$D$49) -> 148526 | G28: =+F28*(1+$D$49) -> 152981.78 | H28: =+G28*(1+$D$49) -> 157571.23 | I28: =+H28*(1+$D$49) -> 162298.37 | J28: =+I28*(1+$D$49) -> 167167.32 | K28: =+J28*(1+$D$49) -> 172182.34 | L28: =+K28*(1+$D$49) -> 177347.81 | ... T28: =+S28*(1+$D$49) -> 224658.9 | U28: =+SUM(N28:T28) -> 1441679.2 | V28: =+SUM(D28:M28,U28) -> 3046622.3
B30: Senior A Bond Interest | D30: =+'Lease-Up Period'!P30 -> 1464622.7 | E30: =+'Loan Amortization'!D35 -> 1464622.7 | F30: =+'Loan Amortization'!E35 -> 1464622.7 | G30: =+'Loan Amortization'!F35 -> 1464622.7 | H30: =+'Loan Amortization'!G35 -> 1453901.2 | I30: =+'Loan Amortization'!H35 -> 1442589.9 | J30: =+'Loan Amortization'!I35 -> 1430656.6 | K30: =+'Loan Amortization'!J35 -> 1418066.9 | L30: =+'Loan Amortization'!K35 -> 1404784.8 | ... T30: =+'Loan Amortization'!S35 -> 1268560 | U30: =+SUM(N30:T30) -> 9272667.7 | V30: =+SUM(D30:M30,U30) -> 23671930
B31: Senior A Bond Principal | D31: =+'Lease-Up Period'!P31 -> 0 | E31: =+'Loan Amortization'!D36 -> 3.0500814e-07 | F31: =+'Loan Amortization'!E36 -> 4.2980537e-07 | G31: =+'Loan Amortization'!F36 -> 194937.11 | H31: =+'Loan Amortization'!G36 -> 205658.65 | I31: =+'Loan Amortization'!H36 -> 216969.88 | J31: =+'Loan Amortization'!I36 -> 228903.22 | K31: =+'Loan Amortization'!J36 -> 241492.9 | L31: =+'Loan Amortization'!K36 -> 254775.01 | ... T31: =+'Loan Amortization'!S36 -> 390999.77 | U31: =+SUM(N31:T31) -> 2344251 | V31: =+SUM(D31:M31,U31) -> 3955775.4
A33: Cash Available after Bond Pmts | D33: =+D26-D28-D30-D31 -> -547604.26 | E33: =+E26-E28-E30-E31 -> 399703.1 | F33: =+F26-F28-F30-F31 -> 424896.92 | G33: =+G26-G28-G30-G31 -> 255264.72 | H33: =+H26-H28-H30-H31 -> 280671.16 | I33: =+I26-I28-I30-I31 -> 306169.04 | J33: =+J26-J28-J30-J31 -> 331747.66 | K33: =+K26-K28-K30-K31 -> 357395.78 | ... V33: =+V26-V28-V30-V31 -> 6150911.5
B35: Issuer Fee | D35: =+'Lease-Up Period'!P36 -> 53259.007 | E35: =+'Loan Amortization'!D38 -> 53259.007 | F35: =+'Loan Amortization'!E38 -> 53259.007 | G35: =+'Loan Amortization'!F38 -> 53259.007 | H35: =+'Loan Amortization'!G38 -> 52869.133 | I35: =+'Loan Amortization'!H38 -> 52457.816 | J35: =+'Loan Amortization'!I38 -> 52023.876 | K35: =+'Loan Amortization'!J38 -> 51566.07 | L35: =+'Loan Amortization'!K38 -> 51083.084 | ... T35: =+'Loan Amortization'!S38 -> 46129.456 | U35: =+SUM(N35:T35) -> 337187.92 | V35: =+SUM(D35:M35,U35) -> 860797.46
B36: Trustee Fee | D36: =+'Lease-Up Period'!P37 -> 5000 | E36: =+'Loan Amortization'!D39 -> 5000 | F36: =+'Loan Amortization'!E39 -> 5000 | G36: =+'Loan Amortization'!F39 -> 5000 | H36: =+'Loan Amortization'!G39 -> 5000 | I36: =+'Loan Amortization'!H39 -> 5000 | J36: =+'Loan Amortization'!I39 -> 5000 | K36: =+'Loan Amortization'!J39 -> 5000 | L36: =+'Loan Amortization'!K39 -> 5000 | ... T36: =+'Loan Amortization'!S39 -> 5000 | U36: =+SUM(N36:T36) -> 35000 | V36: =+SUM(D36:M36,U36) -> 85000
B37: Servicing Fee | D37: =+'Lease-Up Period'!P38 -> 26629.504 | E37: =+'Loan Amortization'!D40 -> 26629.504 | F37: =+'Loan Amortization'!E40 -> 26629.504 | G37: =+'Loan Amortization'!F40 -> 26629.504 | H37: =+'Loan Amortization'!G40 -> 26434.567 | I37: =+'Loan Amortization'!H40 -> 26228.908 | J37: =+'Loan Amortization'!I40 -> 26011.938 | K37: =+'Loan Amortization'!J40 -> 25783.035 | L37: =+'Loan Amortization'!K40 -> 25541.542 | ... T37: =+'Loan Amortization'!S40 -> 23064.728 | U37: =+SUM(N37:T37) -> 168593.96 | V37: =+SUM(D37:M37,U37) -> 430398.73
B38: Asset Management Fee - 10% | D38: =+'Lease-Up Period'!P39 -> 13941.162 | E38: =IF((0.1*E33)<=0,0,0.1*E33) -> 39970.31 | F38: =IF((0.1*F33)<=0,0,0.1*F33) -> 42489.692 | G38: =IF((0.1*G33)<=0,0,0.1*G33) -> 25526.472 | H38: =IF((0.1*H33)<=0,0,0.1*H33) -> 28067.116 | I38: =IF((0.1*I33)<=0,0,0.1*I33) -> 30616.904 | J38: =IF((0.1*J33)<=0,0,0.1*J33) -> 33174.766 | K38: =IF((0.1*K33)<=0,0,0.1*K33) -> 35739.578 | L38: =IF((0.1*L33)<=0,0,0.1*L33) -> 38310.153 | ... T38: =IF((0.1*T33)<=0,0,0.1*T33) -> 57947.309 | U38: =+SUM(N38:T38) -> 355071.35 | V38: =+SUM(D38:M38,U38) -> 683792.74
A40: Cash Available after Fees | D40: =+D33-SUM(D35:D39) -> -646433.93 | E40: =+E33-SUM(E35:E39) -> 274844.28 | F40: =+F33-SUM(F35:F39) -> 297518.72 | G40: =+G33-SUM(G35:G39) -> 144849.74 | H40: =+H33-SUM(H35:H39) -> 168300.35 | I40: =+I33-SUM(I35:I39) -> 191865.41 | J40: =+J33-SUM(J35:J39) -> 215537.08 | K40: =+K33-SUM(K35:K39) -> 239307.1 | ... V40: =+V33-SUM(V35:V39) -> 4090922.6
A42: Surplus cash distribution — see Surplus Cash Waterfall' sheet
A44: RATIOS & ASSUMPTIONS
A46: Senior A Bond DSCR | D46: N/A | E46: =+E26/(E30+E31) -> 1.3713606 | F46: =+F26/(F30+F31) -> 1.3915158 | G46: =+G26/(G30+G31) -> 1.2459969 | H46: =+H26/(H30+H31) -> 1.2640715 | I46: =+I26/(I30+I31) -> 1.2822841 | J46: =+J26/(J30+J31) -> 1.3006309 | K46: =+K26/(K30+K31) -> 1.3191076 | L46: =+L26/(L30+L31) -> 1.3377096 | ... V46: =+V26/(V30+V31) -> 1.3329098
A48: Revenue Growth Rate | D48: 0.02 | E48: =E12/D12-1 -> 0.50230769 | F48: =F12/E12-1 -> 0.02 | G48: =G12/F12-1 -> 0.02 | H48: =H12/G12-1 -> 0.02 | I48: =I12/H12-1 -> 0.02 | J48: =J12/I12-1 -> 0.02 | K48: =K12/J12-1 -> 0.02 | L48: =L12/K12-1 -> 0.02 | ... T48: =T12/S12-1 -> 0.02 | U48: N/A | V48: N/A
A49: Expense Growth Rate | D49: 0.03 | E49: =E24/D24-1 -> 0.14179876 | F49: =F24/E24-1 -> 0.027996093 | G49: =G24/F24-1 -> 0.02803359 | H49: =H24/G24-1 -> 0.028070268 | I49: =I24/H24-1 -> 0.028106146 | J49: =J24/I24-1 -> 0.028141242 | K49: =K24/J24-1 -> 0.028175572 | L49: =L24/K24-1 -> 0.028209153 | ... T49: =T24/S24-1 -> 0.029218687 | U49: N/A | V49: N/A
A50: Expenses as a % of Gross Revenues | D50: =D24/D9 -> 0.33126885 | E50: =E24/E9 -> 0.37082585 | F50: =F24/F9 -> 0.37373287 | G50: =G24/G9 -> 0.37667641 | H50: =H24/H9 -> 0.37965669 | I50: =I24/I9 -> 0.3826739 | J50: =J24/J9 -> 0.38572825 | K50: =K24/K9 -> 0.38881997 | ... V50: =V24/V9 -> 0.39253581
A51: NOI as a % of Gross Revenues | D51: =+D26/D9 -> 0.30015972 | E51: =+E26/E9 -> 0.55917415 | F51: =+F26/F9 -> 0.55626713 | G51: =+G26/G9 -> 0.55332359 | H51: =+H26/H9 -> 0.55034331 | I51: =+I26/I9 -> 0.5473261 | J51: =+J26/J9 -> 0.54427175 | K51: =+K26/K9 -> 0.54118003 | ... V51: =+V26/V9 -> 0.52254462

Sheet Surplus Cash-Reserve Waterfall
A1: Surplus Cash Distribution & Paydown Schedules
B3: ="Yr "&(COLUMN()-1) -> Yr 1 | C3: ="Yr "&(COLUMN()-1) -> Yr 2 | D3: ="Yr "&(COLUMN()-1) -> Yr 3 | E3: ="Yr "&(COLUMN()-1) -> Yr 4 | F3: ="Yr "&(COLUMN()-1) -> Yr 5 | G3: ="Yr "&(COLUMN()-1) -> Yr 6 | H3: ="Yr "&(COLUMN()-1) -> Yr 7 | I3: ="Yr "&(COLUMN()-1) -> Yr 8 | ... R3: ="Yr "&(COLUMN()-1) -> Yr 17
A5: SURPLUS CASH AVAILABLE | B5: ='17-year Pro Forma'!D40 -> -646433.93 | C5: ='17-year Pro Forma'!E40 -> 274844.28 | D5: ='17-year Pro Forma'!F40 -> 297518.72 | E5: ='17-year Pro Forma'!G40 -> 144849.74 | F5: ='17-year Pro Forma'!H40 -> 168300.35 | G5: ='17-year Pro Forma'!I40 -> 191865.41 | H5: ='17-year Pro Forma'!J40 -> 215537.08 | I5: ='17-year Pro Forma'!K40 -> 239307.1 | ... R5: ='17-year Pro Forma'!T40 -> 447331.59
A7: Less: Deferred Developer Fee Payment | B7: =MIN(B17,MAX(0,B5)) -> 0 | C7: =MIN(C17,MAX(0,C5)) -> 274844.28 | D7: =MIN(D17,MAX(0,D5)) -> 297518.72 | E7: =MIN(E17,MAX(0,E5)) -> 144849.74 | F7: =MIN(F17,MAX(0,F5)) -> 168300.35 | G7: =MIN(G17,MAX(0,G5)) -> 191865.41 | H7: =MIN(H17,MAX(0,H5)) -> 215537.08 | I7: =MIN(I17,MAX(0,I5)) -> 239307.1 | ... R7: =MIN(R17,MAX(0,R5)) -> 6.6490029e-06
A8: Less: CDBG / LHC Loan Payment | B8: =MIN(B23,MAX(0,B5)-B7) -> 0 | C8: =MIN(C23,MAX(0,C5)-C7) -> 0 | D8: =MIN(D23,MAX(0,D5)-D7) -> 0 | E8: =MIN(E23,MAX(0,E5)-E7) -> 0 | F8: =MIN(F23,MAX(0,F5)-F7) -> 0 | G8: =MIN(G23,MAX(0,G5)-G7) -> 0 | H8: =MIN(H23,MAX(0,H5)-H7) -> 0 | I8: =MIN(I23,MAX(0,I5)-I7) -> 0 | ... R8: =MIN(R23,MAX(0,R5)-R7) -> 447331.59
A9: Less: Reserve Funding | B9: =MIN(MAX(0,B33-(B29-B31)),MAX(0,B5)-B7-B8) -> 0 | C9: =MIN(MAX(0,C33-(C29-C31)),MAX(0,C5)-C7-C8) -> 0 | D9: =MIN(MAX(0,D33-(D29-D31)),MAX(0,D5)-D7-D8) -> 0 | E9: =MIN(MAX(0,E33-(E29-E31)),MAX(0,E5)-E7-E8) -> 0 | F9: =MIN(MAX(0,F33-(F29-F31)),MAX(0,F5)-F7-F8) -> 0 | G9: =MIN(MAX(0,G33-(G29-G31)),MAX(0,G5)-G7-G8) -> 0 | H9: =MIN(MAX(0,H33-(H29-H31)),MAX(0,H5)-H7-H8) -> 0 | I9: =MIN(MAX(0,I33-(I29-I31)),MAX(0,I5)-I7-I8) -> 0 | ... R9: =MIN(MAX(0,R33-(R29-R31)),MAX(0,R5)-R7-R8) -> 0
A11: Total Distributed | B11: =B7+B8+B9 -> 0 | C11: =C7+C8+C9 -> 274844.28 | D11: =D7+D8+D9 -> 297518.72 | E11: =E7+E8+E9 -> 144849.74 | F11: =F7+F8+F9 -> 168300.35 | G11: =G7+G8+G9 -> 191865.41 | H11: =H7+H8+H9 -> 215537.08 | I11: =I7+I8+I9 -> 239307.1 | ... R11: =R7+R8+R9 -> 447331.59
A13: Undistributed Surplus / (Deficit) | B13: =B5-B11 -> -646433.93 | C13: =C5-C11 -> 0 | D13: =D5-D11 -> 0 | E13: =E5-E11 -> 0 | F13: =F5-F11 -> 0 | G13: =G5-G11 -> 0 | H13: =H5-H11 -> 0 | I13: =I5-I11 -> 0 | ... R13: =R5-R11 -> 0
A16: DEFERRED DEVELOPER FEE PAYDOWN | B16: ="Yr "&(COLUMN()-1) -> Yr 1 | C16: ="Yr "&(COLUMN()-1) -> Yr 2 | D16: ="Yr "&(COLUMN()-1) -> Yr 3 | E16: ="Yr "&(COLUMN()-1) -> Yr 4 | F16: ="Yr "&(COLUMN()-1) -> Yr 5 | G16: ="Yr "&(COLUMN()-1) -> Yr 6 | H16: ="Yr "&(COLUMN()-1) -> Yr 7 | I16: ="Yr "&(COLUMN()-1) -> Yr 8 | ... R16: ="Yr "&(COLUMN()-1) -> Yr 17
A17: Beginning Balance | B17: ='Sources & Uses'!I24 -> 2131813.1 | C17: =B19 -> 2131813.1 | D17: =C19 -> 1856968.8 | E17: =D19 -> 1559450.1 | F17: =E19 -> 1414600.3 | G17: =F19 -> 1246300 | H17: =G19 -> 1054434.6 | I17: =H19 -> 838897.5 | J17: =I19 -> 599590.4 | ... R17: =Q19 -> 1.3893819e-05
A18: Less: Payment (from surplus) | B18: =B7 -> 0 | C18: =C7 -> 274844.28 | D18: =D7 -> 297518.72 | E18: =E7 -> 144849.74 | F18: =F7 -> 168300.35 | G18: =G7 -> 191865.41 | H18: =H7 -> 215537.08 | I18: =I7 -> 239307.1 | ... R18: =R7 -> 6.6490029e-06
A19: Ending Balance | B19: =B17-B18 -> 2131813.1 | C19: =C17-C18 -> 1856968.8 | D19: =D17-D18 -> 1559450.1 | E19: =E17-E18 -> 1414600.3 | F19: =F17-F18 -> 1246300 | G19: =G17-G18 -> 1054434.6 | H19: =H17-H18 -> 838897.5 | I19: =I17-I18 -> 599590.4 | ... R19: =R17-R18 -> 7.2448165e-06
A22: CDBG / LHC SOFT LOAN PAYDOWN | B22: ="Yr "&(COLUMN()-1) -> Yr 1 | C22: ="Yr "&(COLUMN()-1) -> Yr 2 | D22: ="Yr "&(COLUMN()-1) -> Yr 3 | E22: ="Yr "&(COLUMN()-1) -> Yr 4 | F22: ="Yr "&(COLUMN()-1) -> Yr 5 | G22: ="Yr "&(COLUMN()-1) -> Yr 6 | H22: ="Yr "&(COLUMN()-1) -> Yr 7 | I22: ="Yr "&(COLUMN()-1) -> Yr 8 | ... R22: ="Yr "&(COLUMN()-1) -> Yr 17
A23: Beginning Balance | B23: ='Sources & Uses'!I16 -> 7500000 | C23: =B25 -> 7500000 | D23: =C25 -> 7500000 | E23: =D25 -> 7500000 | F23: =E25 -> 7500000 | G23: =F25 -> 7500000 | H23: =G25 -> 7500000 | I23: =H25 -> 7500000 | J23: =I25 -> 7500000 | ... R23: =Q25 -> 5341788.1
A24: Less: Payment (from surplus) | B24: =B8 -> 0 | C24: =C8 -> 0 | D24: =D8 -> 0 | E24: =E8 -> 0 | F24: =F8 -> 0 | G24: =G8 -> 0 | H24: =H8 -> 0 | I24: =I8 -> 0 | ... R24: =R8 -> 447331.59
A25: Ending Balance | B25: =B23-B24 -> 7500000 | C25: =C23-C24 -> 7500000 | D25: =D23-D24 -> 7500000 | E25: =E23-E24 -> 7500000 | F25: =F23-F24 -> 7500000 | G25: =G23-G24 -> 7500000 | H25: =H23-H24 -> 7500000 | I25: =I23-I24 -> 7500000 | ... R25: =R23-R24 -> 4894456.6
A28: RESERVE ACCOUNT BALANCE | B28: ="Yr "&(COLUMN()-1) -> Yr 1 | C28: ="Yr "&(COLUMN()-1) -> Yr 2 | D28: ="Yr "&(COLUMN()-1) -> Yr 3 | E28: ="Yr "&(COLUMN()-1) -> Yr 4 | F28: ="Yr "&(COLUMN()-1) -> Yr 5 | G28: ="Yr "&(COLUMN()-1) -> Yr 6 | H28: ="Yr "&(COLUMN()-1) -> Yr 7 | I28: ="Yr "&(COLUMN()-1) -> Yr 8 | ... R28: ="Yr "&(COLUMN()-1) -> Yr 17
A29: Beginning Balance | B29: =B48 -> 1398305.4 | C29: =B32 -> 751871.46 | D29: =C32 -> 751871.46 | E29: =D32 -> 751871.46 | F29: =E32 -> 751871.46 | G29: =F32 -> 751871.46 | H29: =G32 -> 751871.46 | I29: =H32 -> 751871.46 | J29: =I32 -> 751871.46 | ... R29: =Q32 -> 751871.46
A30: Plus: Reserve Funding (replenishment) | B30: =B9 -> 0 | C30: =C9 -> 0 | D30: =D9 -> 0 | E30: =E9 -> 0 | F30: =F9 -> 0 | G30: =G9 -> 0 | H30: =H9 -> 0 | I30: =I9 -> 0 | ... R30: =R9 -> 0
A31: Less: Reserve Draw (lease-up) | B31: =MIN(B29,MAX(0,-B5)) -> 646433.93 | C31: =MIN(C29,MAX(0,-C5)) -> 0 | D31: =MIN(D29,MAX(0,-D5)) -> 0 | E31: =MIN(E29,MAX(0,-E5)) -> 0 | F31: =MIN(F29,MAX(0,-F5)) -> 0 | G31: =MIN(G29,MAX(0,-G5)) -> 0 | H31: =MIN(H29,MAX(0,-H5)) -> 0 | I31: =MIN(I29,MAX(0,-I5)) -> 0 | ... R31: =MIN(R29,MAX(0,-R5)) -> 0
A32: Ending Balance | B32: =B29+B30-B31 -> 751871.46 | C32: =C29+C30-C31 -> 751871.46 | D32: =D29+D30-D31 -> 751871.46 | E32: =E29+E30-E31 -> 751871.46 | F32: =F29+F30-F31 -> 751871.46 | G32: =G29+G30-G31 -> 751871.46 | H32: =H29+H30-H31 -> 751871.46 | I32: =I29+I30-I31 -> 751871.46 | ... R32: =R29+R30-R31 -> 751871.46
A33: Target (LP cushion) | B33: =$B$48 -> 1398305.4 | C33: =$B$48 -> 1398305.4 | D33: =$B$48 -> 1398305.4 | E33: =$B$48 -> 1398305.4 | F33: =$B$48 -> 1398305.4 | G33: =$B$48 -> 1398305.4 | H33: =$B$48 -> 1398305.4 | I33: =$B$48 -> 1398305.4 | ... R33: =$B$48 -> 1398305.4
A36: RESERVE DRAWDOWN DURING LEASE-UP | B36: ="Mo "&(COLUMN()-1) -> Mo 1 | C36: ="Mo "&(COLUMN()-1) -> Mo 2 | D36: ="Mo "&(COLUMN()-1) -> Mo 3 | E36: ="Mo "&(COLUMN()-1) -> Mo 4 | F36: ="Mo "&(COLUMN()-1) -> Mo 5 | G36: ="Mo "&(COLUMN()-1) -> Mo 6 | H36: ="Mo "&(COLUMN()-1) -> Mo 7 | I36: ="Mo "&(COLUMN()-1) -> Mo 8 | ... M36: ="Mo "&(COLUMN()-1) -> Mo 12 | N36: Total
A37: Cash after Fees | B37: ='Lease-Up Period'!D41 -> -189137.12 | C37: ='Lease-Up Period'!E41 -> -161164.47 | D37: ='Lease-Up Period'!F41 -> -133191.82 | E37: ='Lease-Up Period'!G41 -> -105219.17 | F37: ='Lease-Up Period'!H41 -> -77246.518 | G37: ='Lease-Up Period'!I41 -> -49273.868 | H37: ='Lease-Up Period'!J41 -> -21301.218 | I37: ='Lease-Up Period'!K41 -> 5296.8847 | ... M37: ='Lease-Up Period'!O41 -> 21023.164 | N37: =SUM(B37:M37) -> -646433.93
A38: Add: Debt Service (IO) | B38: ='Lease-Up Period'!D30+'Lease-Up Period'!D31 -> 122051.89 | C38: ='Lease-Up Period'!E30+'Lease-Up Period'!E31 -> 122051.89 | D38: ='Lease-Up Period'!F30+'Lease-Up Period'!F31 -> 122051.89 | E38: ='Lease-Up Period'!G30+'Lease-Up Period'!G31 -> 122051.89 | F38: ='Lease-Up Period'!H30+'Lease-Up Period'!H31 -> 122051.89 | G38: ='Lease-Up Period'!I30+'Lease-Up Period'!I31 -> 122051.89 | H38: ='Lease-Up Period'!J30+'Lease-Up Period'!J31 -> 122051.89 | I38: ='Lease-Up Period'!K30+'Lease-Up Period'!K31 -> 122051.89 | ... M38: ='Lease-Up Period'!O30+'Lease-Up Period'!O31 -> 122051.89 | N38: =SUM(B38:M38) -> 1464622.7
A39: Op Cash before Debt Service | B39: =B37+B38 -> -67085.226 | C39: =C37+C38 -> -39112.576 | D39: =D37+D38 -> -11139.926 | E39: =E37+E38 -> 16832.724 | F39: =F37+F38 -> 44805.374 | G39: =G37+G38 -> 72778.024 | H39: =H37+H38 -> 100750.67 | I39: =I37+I38 -> 127348.78 | ... M39: =M37+M38 -> 143075.06 | N39: =SUM(B39:M39) -> 818188.77
A40: Operating Deficit Funding | B40: =MAX(0,-B39) -> 67085.226 | C40: =MAX(0,-C39) -> 39112.576 | D40: =MAX(0,-D39) -> 11139.926 | E40: =MAX(0,-E39) -> 0 | F40: =MAX(0,-F39) -> 0 | G40: =MAX(0,-G39) -> 0 | H40: =MAX(0,-H39) -> 0 | I40: =MAX(0,-I39) -> 0 | ... M40: =MAX(0,-M39) -> 0 | N40: =SUM(B40:M40) -> 117337.73
A41: Cash Available for Debt Service | B41: =B39+B40 -> 0 | C41: =C39+C40 -> 0 | D41: =D39+D40 -> 0 | E41: =E39+E40 -> 16832.724 | F41: =F39+F40 -> 44805.374 | G41: =G39+G40 -> 72778.024 | H41: =H39+H40 -> 100750.67 | I41: =I39+I40 -> 127348.78 | ... N41: =N39+N40 -> 935526.5
A42: Debt Service (IO) | B42: =-B38 -> -122051.89 | C42: =-C38 -> -122051.89 | D42: =-D38 -> -122051.89 | E42: =-E38 -> -122051.89 | F42: =-F38 -> -122051.89 | G42: =-G38 -> -122051.89 | H42: =-H38 -> -122051.89 | I42: =-I38 -> -122051.89 | ... N42: =-N38 -> -1464622.7
A43: Funds Needed from Interest Reserve | B43: =IF((B41+B42)<0,(B41+B42),0) -> -122051.89 | C43: =IF((C41+C42)<0,(C41+C42),0) -> -122051.89 | D43: =IF((D41+D42)<0,(D41+D42),0) -> -122051.89 | E43: =IF((E41+E42)<0,(E41+E42),0) -> -105219.17 | F43: =IF((F41+F42)<0,(F41+F42),0) -> -77246.518 | G43: =IF((G41+G42)<0,(G41+G42),0) -> -49273.868 | H43: =IF((H41+H42)<0,(H41+H42),0) -> -21301.218 | I43: =IF((I41+I42)<0,(I41+I42),0) -> 0 | ... M43: =IF((M41+M42)<0,(M41+M42),0) -> 0 | N43: =SUM(B43:M43) -> -619196.45
A44: Interest Reserve Funding | B44: =-B43 -> 122051.89 | C44: =-C43 -> 122051.89 | D44: =-D43 -> 122051.89 | E44: =-E43 -> 105219.17 | F44: =-F43 -> 77246.518 | G44: =-G43 -> 49273.868 | H44: =-H43 -> 21301.218 | I44: =-I43 -> 0 | ... M44: =-M43 -> 0 | N44: =SUM(B44:M44) -> 619196.45
A46: Operating Deficit Reserve | B46: =MAX(N40,0.5*'17-year Pro Forma'!E24) -> 665994.03
A47: Interest Expense Reserve | B47: =MAX(N42,0.5*'Lease-Up Period'!P30) -> 732311.35
A48: Total Reserve Requirement | B48: =B46+B47 -> 1398305.4

Sheet Tax Credit Calc
A1: LIHTC CREDIT CALCULATIONS
A4: Tax Credit Equity Price | F4: 0.8
A6: Total Development Costs | F6: =+'Sources & Uses'!I26 -> 50848028
A7: Less: Acquisition Cost | F7: =-'Sources & Uses'!I30 -> -4000000
A8: Add: Building Basis | F8: 2000000
A9: Less: Community Facilities | F9: =-'Sources & Uses'!I37 -> -425000
A10: Less: Federal Grants | F10: 0
A11: Less: Home Loans | F11: =-'Sources & Uses'!I17 -> 0
A12: Less: Reserves | F12: =-'Sources & Uses'!I72 -> -1398305.4
A13: Less: Financing Fees | F13: =-'Sources & Uses'!I76 -> -980810.23
A15: Adjusted Construction Basis | F15: =+SUM(F6:F14) -> 46043913
B16: Applicable Fraction | F16: 1
A17: Basis Boost | F17: 0
A19: Qualified Construction Basis | F19: =+(F15*F16)*(1+F17) -> 46043913
A20: Credit Rate | F20: 0.04
A22: Annual Allocation of Tax Credits | F22: =+F19*F20 -> 1841756.5
A24: Schedule of Projected Credit Delivery
A26: Year | C26: Credits Delivered | D26: GP Credits | E26: LP Credits | F26: Cash Value
A28: Year 1 | C28: =+F22 -> 1841756.5 | D28: =+C28*0.01 -> 18417.565 | E28: =+C28-D28 -> 1823338.9 | F28: =+E28*$F$4 -> 1458671.2
A29: Year 2 | C29: =+C28 -> 1841756.5 | D29: =+C29*0.01 -> 18417.565 | E29: =+C29-D29 -> 1823338.9 | F29: =+E29*$F$4 -> 1458671.2
A30: Year 3 | C30: =+$F$22 -> 1841756.5 | D30: =+C30*0.01 -> 18417.565 | E30: =+C30-D30 -> 1823338.9 | F30: =+E30*$F$4 -> 1458671.2
A31: Year 4 | C31: =+$F$22 -> 1841756.5 | D31: =+C31*0.01 -> 18417.565 | E31: =+C31-D31 -> 1823338.9 | F31: =+E31*$F$4 -> 1458671.2
A32: Year 5 | C32: =+$F$22 -> 1841756.5 | D32: =+C32*0.01 -> 18417.565 | E32: =+C32-D32 -> 1823338.9 | F32: =+E32*$F$4 -> 1458671.2
A33: Year 6 | C33: =+$F$22 -> 1841756.5 | D33: =+C33*0.01 -> 18417.565 | E33: =+C33-D33 -> 1823338.9 | F33: =+E33*$F$4 -> 1458671.2
A34: Year 7 | C34: =+$F$22 -> 1841756.5 | D34: =+C34*0.01 -> 18417.565 | E34: =+C34-D34 -> 1823338.9 | F34: =+E34*$F$4 -> 1458671.2
A35: Year 8 | C35: =+$F$22 -> 1841756.5 | D35: =+C35*0.01 -> 18417.565 | E35: =+C35-D35 -> 1823338.9 | F35: =+E35*$F$4 -> 1458671.2
A36: Year 9 | C36: =+$F$22 -> 1841756.5 | D36: =+C36*0.01 -> 18417.565 | E36: =+C36-D36 -> 1823338.9 | F36: =+E36*$F$4 -> 1458671.2
A37: Year 10 | C37: =+$F$22 -> 1841756.5 | D37: =+C37*0.01 -> 18417.565 | E37: =+C37-D37 -> 1823338.9 | F37: =+E37*$F$4 -> 1458671.2
A39: Total | C39: =+SUM(C28:C37) -> 18417565 | D39: =+SUM(D28:D37) -> 184175.65 | E39: =+SUM(E28:E37) -> 18233389 | F39: =+SUM(F28:F37) -> 14586712
A41: Tax Credit Equity | F41: =+F39 -> 14586712

Sheet Financing Assumptions
A1: FINANCING FEES & ASSUMPTION
A4: FINANCING FEES
A6: Bond Amount | D6: ='S&U Timing'!D10 -> 26629504
A7: As % of Developmen Cost | D7: =+D6/'Sources & Uses'!I78 -> 0.52370769
A9: Construction Bonds
A11: Base Interest Rate | C11: 0.06
A12: Loan Origination | C12: 0.005 | D12: =+C12*D6 -> 133147.52
A13: Legal | C13: =+D13/D6 -> 0.001689855 | D13: 45000
A14: Servicing Setup | C14: =+D14/D6 -> 0.00037552333 | D14: 10000
A16: Bridge Loan
A18: Base Interest Rate | C18: 0.06
A19: Loan Origination | C19: 0.01 | D19: =+C19*D13 -> 450
A20: Legal | C20: =D20/'S&U Timing'!D16 -> 0.0030849997 | D20: 45000
A21: Servicing Setup | C21: =D21/'S&U Timing'!D16 -> 0.00068555548 | D21: 10000
A23: Permanent Bonds
A25: Stablization NOI - YR2 | C25: =+'NOI Calc'!J29+('Expense Detail'!F61-'Expense Detail'!F60) -> 1979252.1
A26: Stabilized DSCR - Sizing | C26: 1.15
A27: Mortgage Rate Constant | C27: =-PMT(C28/12,C29*12,1)*12 -> 0.061892434
A28: Coupon Rate | C28: 0.055
A29: Amortization | C29: 40
A30: Annual Issuer Fee | C30: 0.002
A31: Annual Trustee Fee | C31: 5000
A32: Servicing Fee | C32: 0.001
A33: Loan Origination | C33: 0.01 | D33: =+C33*D6 -> 266295.04
A34: Placement Fee | C34: 0.0025 | D34: =+C34*D6 -> 66573.759
A35: Legal | C35: =+D35/D6 -> 0.001689855 | D35: 45000
A36: Supportable Perm Loan (NOI/DSCR) | C36: =C25/(C26*C27) -> 27807742
A37: Bond Cost of Issuance
A39: Bond Counsel | C39: =+D39/$D$6 -> 0.001689855 | D39: 45000
A40: Financial Advisor | C40: =+D40/$D$6 -> 0.0013143317 | D40: 35000
A41: Trustee Setup | C41: =+D41/$D$6 -> 0.00046940417 | D41: 12500
A42: Issuer Closing Fee | C42: 0.0042 | D42: =+C42*D6 -> 111843.92
A43: Bond Issuance Misc | C43: =+D43/$D$6 -> 0.0013143317 | D43: 35000
A44: As % of Bond Amount | D44: =+SUM(C39:C43) -> 0.0089879225
A46: Equity/Partnership
A48: Legal | D48: 45000
A49: Syndication Costs | D49: 50000
A51: Miscellaneous | D51: 25000
A53: Total Financing Fees | D53: =++SUM(D12:D43,D48:D52) -> 980810.23

Sheet Valuation
A1: EQUITY VALUATION SCHEDULE
A2: Direct capitalization: same-year NOI ÷ flat cap rate. Equity = capitalized value less end-of-year balances of senior bonds, deferred developer fee, and CDBG/LHC soft loan.
B4: ='17-year Pro Forma'!D4 -> Yr 1 | C4: ='17-year Pro Forma'!E4 -> Yr 2 | D4: ='17-year Pro Forma'!F4 -> Yr 3 | E4: ='17-year Pro Forma'!G4 -> Yr 4 | F4: ='17-year Pro Forma'!H4 -> Yr 5 | G4: ='17-year Pro Forma'!I4 -> Yr 6 | H4: ='17-year Pro Forma'!J4 -> Yr 7 | I4: ='17-year Pro Forma'!K4 -> Yr 8 | ... R4: ='17-year Pro Forma'!T4 -> Yr 17
A6: Net Operating Income | B6: ='17-year Pro Forma'!D26 -> 1057018.4 | C6: ='17-year Pro Forma'!E26 -> 2008525.8 | D6: ='17-year Pro Forma'!F26 -> 2038045.6 | E6: ='17-year Pro Forma'!G26 -> 2067806.3 | F6: ='17-year Pro Forma'!H26 -> 2097802.2 | G6: ='17-year Pro Forma'!I26 -> 2128027.2 | H6: ='17-year Pro Forma'!J26 -> 2158474.8 | I6: ='17-year Pro Forma'!K26 -> 2189137.9 | ... R6: ='17-year Pro Forma'!T26 -> 2463691.8
A7: Cap Rate | B7: =$B$22 -> 0.06 | C7: =$B$22 -> 0.06 | D7: =$B$22 -> 0.06 | E7: =$B$22 -> 0.06 | F7: =$B$22 -> 0.06 | G7: =$B$22 -> 0.06 | H7: =$B$22 -> 0.06 | I7: =$B$22 -> 0.06 | ... R7: =$B$22 -> 0.06
A9: CAPITALIZED PROPERTY VALUE | B9: =B6/B7 -> 17616974 | C9: =C6/C7 -> 33475430 | D9: =D6/D7 -> 33967427 | E9: =E6/E7 -> 34463439 | F9: =F6/F7 -> 34963370 | G9: =G6/G7 -> 35467120 | H9: =H6/H7 -> 35974580 | I9: =I6/I7 -> 36485632 | ... R9: =R6/R7 -> 41061530
A11: Less: Senior Bond Balance | B11: ='Loan Amortization'!D33 -> 26629504 | C11: ='Loan Amortization'!D37 -> 26629504 | D11: ='Loan Amortization'!E37 -> 26629504 | E11: ='Loan Amortization'!F37 -> 26434567 | F11: ='Loan Amortization'!G37 -> 26228908 | G11: ='Loan Amortization'!H37 -> 26011938 | H11: ='Loan Amortization'!I37 -> 25783035 | I11: ='Loan Amortization'!J37 -> 25541542 | J11: ='Loan Amortization'!K37 -> 25286767 | ... R11: ='Loan Amortization'!S37 -> 22673728
A12: Less: Deferred Developer Fee Balance | B12: ='Surplus Cash-Reserve Waterfall'!B19 -> 2131813.1 | C12: ='Surplus Cash-Reserve Waterfall'!C19 -> 1856968.8 | D12: ='Surplus Cash-Reserve Waterfall'!D19 -> 1559450.1 | E12: ='Surplus Cash-Reserve Waterfall'!E19 -> 1414600.3 | F12: ='Surplus Cash-Reserve Waterfall'!F19 -> 1246300 | G12: ='Surplus Cash-Reserve Waterfall'!G19 -> 1054434.6 | H12: ='Surplus Cash-Reserve Waterfall'!H19 -> 838897.5 | I12: ='Surplus Cash-Reserve Waterfall'!I19 -> 599590.4 | ... R12: ='Surplus Cash-Reserve Waterfall'!R19 -> 7.2448165e-06
A13: Less: CDBG / LHC Soft Loan Balance | B13: ='Surplus Cash-Reserve Waterfall'!B25 -> 7500000 | C13: ='Surplus Cash-Reserve Waterfall'!C25 -> 7500000 | D13: ='Surplus Cash-Reserve Waterfall'!D25 -> 7500000 | E13: ='Surplus Cash-Reserve Waterfall'!E25 -> 7500000 | F13: ='Surplus Cash-Reserve Waterfall'!F25 -> 7500000 | G13: ='Surplus Cash-Reserve Waterfall'!G25 -> 7500000 | H13: ='Surplus Cash-Reserve Waterfall'!H25 -> 7500000 | I13: ='Surplus Cash-Reserve Waterfall'!I25 -> 7500000 | ... R13: ='Surplus Cash-Reserve Waterfall'!R25 -> 4894456.6
A15: NET EQUITY VALUE | B15: =B9-SUM(B11:B13) -> -18644343 | C15: =C9-SUM(C11:C13) -> -2511042.4 | D15: =D9-SUM(D11:D13) -> -1721526.7 | E15: =E9-SUM(E11:E13) -> -885728.38 | F15: =F9-SUM(F11:F13) -> -11837.749 | G15: =G9-SUM(G11:G13) -> 900747.68 | H15: =H9-SUM(H11:H13) -> 1852647.6 | I15: =I9-SUM(I11:I13) -> 2844500 | ... R15: =R9-SUM(R11:R13) -> 13493345
A17: Net Equity excl. Soft Loan | B17: =B9-SUM(B11:B12) -> -11144343 | C17: =C9-SUM(C11:C12) -> 4988957.6 | D17: =D9-SUM(D11:D12) -> 5778473.3 | E17: =E9-SUM(E11:E12) -> 6614271.6 | F17: =F9-SUM(F11:F12) -> 7488162.3 | G17: =G9-SUM(G11:G12) -> 8400747.7 | H17: =H9-SUM(H11:H12) -> 9352647.6 | I17: =I9-SUM(I11:I12) -> 10344500 | ... R17: =R9-SUM(R11:R12) -> 18387802
A19: Equity as % of Property Value | B19: =B15/B9 -> -1.058317 | C19: =C15/C9 -> -0.075011504 | D19: =D15/D9 -> -0.050681694 | E19: =E15/E9 -> -0.025700523 | F19: =F15/F9 -> -0.00033857575 | G19: =G15/G9 -> 0.025396696 | H19: =H15/H9 -> 0.051498798 | I19: =I15/I9 -> 0.077962194 | ... R19: =R15/R9 -> 0.32861282
A21: ASSUMPTIONS
A22: Cap Rate (flat, all years) | B22: 0.06

Sheet Loan Amortization
A1: CONSTRUCTION DEBT
A3: Construction Bonds
A5: Amount Needed | C5: =+'S&U Timing'!D10 -> 26629504
A6: Base Interest Rate | C6: =+'Financing Assumptions'!C11 -> 0.06
A8: Period | C8: =+'S&U Timing'!G6 -> 1 | D8: =+C8+1 -> 2 | E8: =+D8+1 -> 3 | F8: =+E8+1 -> 4 | G8: =+F8+1 -> 5 | H8: =+G8+1 -> 6 | I8: =+H8+1 -> 7 | J8: =+I8+1 -> 8 | K8: =+J8+1 -> 9 | ... Z8: =+Y8+1 -> 24 | AA8: YR1
A9: Beginning Balance | C9: 0 | D9: =+C12 -> 3126643.1 | E9: =+D12 -> 3282729 | F9: =+E12 -> 3439599.3 | G9: =+F12 -> 3597257.8 | H9: =+G12 -> 3755708.6 | I9: =+H12 -> 4166211.9 | J9: =+I12 -> 4574889.1 | K9: =+J12 -> 5277598.8 | ... AA9: =+Z12 -> 26629504
A10: Draw Amount | C10: =+'S&U Timing'!G10 -> 3126643.1 | D10: =+'S&U Timing'!H10 -> 156085.91 | E10: =+'S&U Timing'!I10 -> 156870.26 | F10: =+'S&U Timing'!J10 -> 157658.55 | G10: =+'S&U Timing'!K10 -> 158450.8 | H10: =+'S&U Timing'!L10 -> 410503.32 | I10: =+'S&U Timing'!M10 -> 408677.17 | J10: =+'S&U Timing'!N10 -> 702709.71 | ... AA10: =+'S&U Timing'!AE10 -> 0
A11: Interest Expense | C11: =(C9+C10)*($C$6/12) -> 15633.215 | D11: =(D9+D10)*($C$6/12) -> 16413.645 | E11: =(E9+E10)*($C$6/12) -> 17197.996 | F11: =(F9+F10)*($C$6/12) -> 17986.289 | G11: =(G9+G10)*($C$6/12) -> 18778.543 | H11: =(H9+H10)*($C$6/12) -> 20831.06 | I11: =(I9+I10)*($C$6/12) -> 22874.446 | J11: =(J9+J10)*($C$6/12) -> 26387.994 | ... Z11: =(Z9+Z10)*($C$6/12) -> 133147.52 | AA11: =(AA9+AA10)*($C$6) -> 1597770.2
A12: Ending Balance | C12: =+C9+C10 -> 3126643.1 | D12: =+D9+D10 -> 3282729 | E12: =+E9+E10 -> 3439599.3 | F12: =+F9+F10 -> 3597257.8 | G12: =+G9+G10 -> 3755708.6 | H12: =+H9+H10 -> 4166211.9 | I12: =+I9+I10 -> 4574889.1 | J12: =+J9+J10 -> 5277598.8 | ... AA12: =+AA9+AA10 -> 26629504
A14: Equity Bridge Loan
A16: Amount Needed | C16: =+SUM('S&U Timing'!G11:AE11) -> 11669369
A17: Base Interest Rate | C17: =+'Financing Assumptions'!C18 -> 0.06
A19: Period | C19: 1 | D19: =+C19+1 -> 2 | E19: =+D19+1 -> 3 | F19: =+E19+1 -> 4 | G19: =+F19+1 -> 5 | H19: =+G19+1 -> 6 | I19: =+H19+1 -> 7 | J19: =+I19+1 -> 8 | K19: =+J19+1 -> 9 | ... Z19: =+Y19+1 -> 24 | AA19: YR1
A20: Beginning Balance | C20: 0 | D20: =+C24 -> 0 | E20: =+D24 -> 0 | F20: =+E24 -> 0 | G20: =+F24 -> 0 | H20: =+G24 -> 0 | I20: =+H24 -> 0 | J20: =+I24 -> 233387.38 | K20: =+J24 -> 641815.31 | ... AA20: =+Z24 -> 4376013.5
A21: Draw Amount | C21: =+'S&U Timing'!G11 -> 0 | D21: =+'S&U Timing'!H11 -> 0 | E21: =+'S&U Timing'!I11 -> 0 | F21: =+'S&U Timing'!J11 -> 0 | G21: =+'S&U Timing'!K11 -> 0 | H21: =+'S&U Timing'!L11 -> 0 | I21: =+'S&U Timing'!M11 -> 233387.38 | J21: =+'S&U Timing'!N11 -> 408427.92 | ... AA21: =+'S&U Timing'!AE11 -> 0
A22: Payment | C22: =+'S&U Timing'!G12 -> 0 | D22: =+'S&U Timing'!H12 -> 0 | E22: =+'S&U Timing'!I12 -> 0 | F22: =+'S&U Timing'!J12 -> 0 | G22: =+'S&U Timing'!K12 -> 0 | H22: =+'S&U Timing'!L12 -> 0 | I22: =+'S&U Timing'!M12 -> 0 | J22: =+'S&U Timing'!N12 -> 0 | ... AA22: =+'S&U Timing'!AE12 -> -4376013.5
A23: Interest Expense | C23: =(C20+C21)*($C$17/12) -> 0 | D23: =(D20+D21)*($C$17/12) -> 0 | E23: =(E20+E21)*($C$17/12) -> 0 | F23: =(F20+F21)*($C$17/12) -> 0 | G23: =(G20+G21)*($C$17/12) -> 0 | H23: =(H20+H21)*($C$17/12) -> 0 | I23: =(I20+I21)*($C$17/12) -> 1166.9369 | J23: =(J20+J21)*($C$17/12) -> 3209.0765 | ... Z23: =(Z20+Z21)*($C$17/12) -> 21880.067 | AA23: =(AA20+AA21)*($C$17) -> 262560.81
A24: Ending Balance | C24: =+C20+C21+C22 -> 0 | D24: =+D20+D21+D22 -> 0 | E24: =+E20+E21+E22 -> 0 | F24: =+F20+F21+F22 -> 0 | G24: =+G20+G21+G22 -> 0 | H24: =+H20+H21+H22 -> 0 | I24: =+I20+I21+I22 -> 233387.38 | J24: =+J20+J21+J22 -> 641815.31 | ... AA24: =+AA20+AA21+AA22 -> 3.7599355e-05
A26: Perm Loan
A28: Loan Sizing | C28: =+C5 -> 26629504
A29: Takeout (Gap)/Surplus | D29: =+C28-C5 -> 0
A30: Base Interest Rate | C30: =+'Financing Assumptions'!C28 -> 0.055
A32: Period | C32: 1 | D32: =+C32+1 -> 2 | E32: =+D32+1 -> 3 | F32: =+E32+1 -> 4 | G32: =+F32+1 -> 5 | H32: =+G32+1 -> 6 | I32: =+H32+1 -> 7 | J32: =+I32+1 -> 8 | K32: =+J32+1 -> 9 | ... S32: =+R32+1 -> 17
A33: Beginning Balance | C33: 0 | D33: =+C28 -> 26629504 | E33: =+D37 -> 26629504 | F33: =+E37 -> 26629504 | G33: =+F37 -> 26434567 | H33: =+G37 -> 26228908 | I33: =+H37 -> 26011938 | J33: =+I37 -> 25783035 | K33: =+J37 -> 25541542 | L33: =+K37 -> 25286767 | ... S33: =+R37 -> 23064728
A34: Payment | C34: 0 | D34: =+D35 -> 1464622.7 | E34: =+E35 -> 1464622.7 | F34: =-PMT($C$30,'Financing Assumptions'!$C$29,$C$28) -> 1659559.8 | G34: =-PMT($C$30,'Financing Assumptions'!$C$29,$C$28) -> 1659559.8 | H34: =-PMT($C$30,'Financing Assumptions'!$C$29,$C$28) -> 1659559.8 | I34: =-PMT($C$30,'Financing Assumptions'!$C$29,$C$28) -> 1659559.8 | J34: =-PMT($C$30,'Financing Assumptions'!$C$29,$C$28) -> 1659559.8 | K34: =-PMT($C$30,'Financing Assumptions'!$C$29,$C$28) -> 1659559.8 | L34: =-PMT($C$30,'Financing Assumptions'!$C$29,$C$28) -> 1659559.8 | M34: =-PMT($C$30,'Financing Assumptions'!$C$29,$C$28) -> 1659559.8 | ... S34: =-PMT($C$30,'Financing Assumptions'!$C$29,$C$28) -> 1659559.8
A35: Interest Expense | C35: =+C33*$C$30 -> 0 | D35: =+D33*$C$30 -> 1464622.7 | E35: =+E33*$C$30 -> 1464622.7 | F35: =+F33*$C$30 -> 1464622.7 | G35: =+G33*$C$30 -> 1453901.2 | H35: =+H33*$C$30 -> 1442589.9 | I35: =+I33*$C$30 -> 1430656.6 | J35: =+J33*$C$30 -> 1418066.9 | ... S35: =+S33*$C$30 -> 1268560
A36: Principal | C36: =+C34-C35 -> 0 | D36: =+D34-D35 -> 6.2864274e-09 | E36: =+E34-E35 -> 2.9895455e-07 | F36: =+F34-F35 -> 194937.11 | G36: =+G34-G35 -> 205658.65 | H36: =+H34-H35 -> 216969.88 | I36: =+I34-I35 -> 228903.22 | J36: =+J34-J35 -> 241492.9 | ... S36: =+S34-S35 -> 390999.77
A37: Ending Balance | C37: =+C33-C36 -> 0 | D37: =+D33-D36 -> 26629504 | E37: =+E33-E36 -> 26629504 | F37: =+F33-F36 -> 26434567 | G37: =+G33-G36 -> 26228908 | H37: =+H33-H36 -> 26011938 | I37: =+I33-I36 -> 25783035 | J37: =+J33-J36 -> 25541542 | ... S37: =+S33-S36 -> 22673728
A38: Issuer Fee | C38: =+C34-C37 -> 0 | D38: =+D33*'Financing Assumptions'!$C$30 -> 53259.007 | E38: =+E33*'Financing Assumptions'!$C$30 -> 53259.007 | F38: =+F33*'Financing Assumptions'!$C$30 -> 53259.007 | G38: =+G33*'Financing Assumptions'!$C$30 -> 52869.133 | H38: =+H33*'Financing Assumptions'!$C$30 -> 52457.816 | I38: =+I33*'Financing Assumptions'!$C$30 -> 52023.876 | J38: =+J33*'Financing Assumptions'!$C$30 -> 51566.07 | K38: =+K33*'Financing Assumptions'!$C$30 -> 51083.084 | ... S38: =+S33*'Financing Assumptions'!$C$30 -> 46129.456
A39: Trustee Fee | C39: =+C35-C38 -> 0 | D39: =+'Financing Assumptions'!C31 -> 5000 | E39: =+D39 -> 5000 | F39: =+E39 -> 5000 | G39: =+F39 -> 5000 | H39: =+G39 -> 5000 | I39: =+H39 -> 5000 | J39: =+I39 -> 5000 | K39: =+J39 -> 5000 | L39: =+K39 -> 5000 | ... S39: =+R39 -> 5000
A40: Servicing Fee | C40: =+C36-C39 -> 0 | D40: =+D33*'Financing Assumptions'!$C$32 -> 26629.504 | E40: =+E33*'Financing Assumptions'!$C$32 -> 26629.504 | F40: =+F33*'Financing Assumptions'!$C$32 -> 26629.504 | G40: =+G33*'Financing Assumptions'!$C$32 -> 26434.567 | H40: =+H33*'Financing Assumptions'!$C$32 -> 26228.908 | I40: =+I33*'Financing Assumptions'!$C$32 -> 26011.938 | J40: =+J33*'Financing Assumptions'!$C$32 -> 25783.035 | K40: =+K33*'Financing Assumptions'!$C$32 -> 25541.542 | ... S40: =+S33*'Financing Assumptions'!$C$32 -> 23064.728
A42: GP Loan
A44: Amount Needed | C44: =+'Sources & Uses'!I24 -> 2131813.1
A45: Base Interest Rate | C45: 0
A47: Period | C47: 1 | D47: =+C47+1 -> 2 | E47: =+D47+1 -> 3 | F47: =+E47+1 -> 4 | G47: =+F47+1 -> 5 | H47: =+G47+1 -> 6 | I47: =+H47+1 -> 7 | J47: =+I47+1 -> 8 | K47: =+J47+1 -> 9 | ... S47: =+R47+1 -> 17
A48: Beginning Balance | C48: =+C44 -> 2131813.1 | D48: =+C51 -> 2131813.1 | E48: =+D51 -> 1856968.8 | F48: =+E51 -> 1559450.1 | G48: =+F51 -> 1414600.3 | H48: =+G51 -> 1246300 | I48: =+H51 -> 1054434.6 | J48: =+I51 -> 838897.5 | K48: =+J51 -> 599590.4 | ... S48: =+R51 -> 0
A49: Payment | C49: =MAX(0,MIN(C48,'17-year Pro Forma'!D40)) -> 0 | D49: =MAX(0,MIN(D48,'17-year Pro Forma'!E40)) -> 274844.28 | E49: =MAX(0,MIN(E48,'17-year Pro Forma'!F40)) -> 297518.72 | F49: =MAX(0,MIN(F48,'17-year Pro Forma'!G40)) -> 144849.74 | G49: =MAX(0,MIN(G48,'17-year Pro Forma'!H40)) -> 168300.35 | H49: =MAX(0,MIN(H48,'17-year Pro Forma'!I40)) -> 191865.41 | I49: =MAX(0,MIN(I48,'17-year Pro Forma'!J40)) -> 215537.08 | J49: =MAX(0,MIN(J48,'17-year Pro Forma'!K40)) -> 239307.1 | ... S49: =MAX(0,MIN(S48,'17-year Pro Forma'!T40)) -> 0
A50: Interest Expense | C50: =(C48)*($C$45) -> 0 | D50: =(D48)*($C$45) -> 0 | E50: =(E48)*($C$45) -> 0 | F50: =(F48)*($C$45) -> 0 | G50: =(G48)*($C$45) -> 0 | H50: =(H48)*($C$45) -> 0 | I50: =(I48)*($C$45) -> 0 | J50: =(J48)*($C$45) -> 0 | ... S50: =(S48)*($C$45) -> 0
A51: Ending Balance | C51: =+C48-C49 -> 2131813.1 | D51: =+D48-D49 -> 1856968.8 | E51: =+E48-E49 -> 1559450.1 | F51: =+F48-F49 -> 1414600.3 | G51: =+G48-G49 -> 1246300 | H51: =+H48-H49 -> 1054434.6 | I51: =+I48-I49 -> 838897.5 | J51: =+J48-J49 -> 599590.4 | ... S51: =+S48-S49 -> 0

Sheet QAP_Rule_Register
A1: QAP RULE REGISTER
A2: LIHTC deal-tracker — QAP rules engine mirror · 32 rules · one-way offline mirror of the platform rules engine
A3: QAP Basis: | B3: Louisiana 2025 QAP
A5: rule_id | B5: group | C5: metric | D5: category | E5: severity | F5: scope | G5: operator | H5: threshold_value | I5: threshold_text | J5: pass_logic | K5: model_cells | L5: dashboard_kpi_id | M5: citation | N5: notes
A6: ELG-9PCT-BOND | B6: Credit Structure | C6: 9% credit + tax-exempt bonds | D6: eligibility | E6: error | F6: COMPUTED | G6: eq | H6: 0 | I6: Mutually exclusive | J6: IF CreditType=9% then 'Sources & Uses'!I12 = 0 | K6: Sources & Uses'!I12 | L6: ELG-9PCT-BOND | M6: QAP §II · IRC §42(h)(4) | N6: Evaluated only when 9% competitive; N/A for 4% bond.
A7: ELG-4PCT-BOND | B7: Credit Structure | C7: 4% credit requires bonds | D7: eligibility | E7: error | F7: COMPUTED | G7: gt | H7: 0 | I7: Bonds required | J7: IF CreditType=4% then 'Sources & Uses'!I12 > 0 | K7: Sources & Uses'!I12 | L7: ELG-4PCT-BOND | M7: QAP §II · IRC §42(h)(4) | N7: Westbend I12=$30.19M > 0.
A8: ELG-POOL-CAP | B8: Credit Sizing | C8: Per-project LIHTC pool cap | D8: eligibility | E8: error | F8: COMPUTED | G8: lte | I8: $1.0M rural / $1.5M metro / $1.0M rural QNP-CHDO / uncapped reprocessing | J8: IF 9%: 'Tax Credit Calc'!F21 <= pool cap (by pool toggle); 4% -> N/A | K8: Tax Credit Calc'!F21 | L8: ELG-POOL-CAP | M8: QAP §II.B.1 | N8: Cap toggle-dependent (see params). N/A for 4% bond (draws PAB volume cap).
A9: ELG-CREDIT-MAX | B9: Credit Sizing | C9: Maximum allowable credit | D9: eligibility | E9: error | F9: COMPUTED | G9: lte | I9: MIN(basis method, equity-gap method) | J9: Tax Credit Calc'!F21 <= MIN(basis credit, gap credit) | K9: Tax Credit Calc'!F21 | L9: ELG-CREDIT-MAX | M9: QAP §II.B · §IV.D | N9: Gap credit = (TDC-debt-soft-deferred)/price/10 / LP-fraction. Assumption flagged.
A10: ELG-BOOST-30 | B10: Credit Sizing | C10: Construction basis boost cap | D10: eligibility | E10: error | F10: COMPUTED | G10: lte | H10: 0.3 | I10: <= 30% | J10: Tax Credit Calc'!F16 <= 30% | K10: Tax Credit Calc'!F16 | L10: ELG-BOOST-30 | M10: QAP §II.C | N10: Westbend boost F16 = 0%.
A11: ELG-BOOST-ELIGIBILITY | B11: Credit Sizing | C11: Basis boost geographic eligibility | D11: eligibility | E11: warning | F11: INPUT | G11: info | I11: Qualifying geography required | J11: IF boost claimed: geography eligible (input M6) | K11: Dashboard input M6 | L11: ELG-BOOST-ELIGIBILITY | M11: QAP §II.C | N11: QCT/DDA/Tribal/disaster/FFIEC (9%); QCT or DDA only (bond). Needs input M6.
A12: ELG-EQUITY-MATCH | B12: Credit Structure | C12: LIHTC equity reconciliation | D12: eligibility | E12: error | F12: APP-SIDE | G12: info | I12: Must match | J12: §18.10 LIHTC equity = syndication gross equity (app-form) | K12: (application form) | L12: ELG-EQUITY-MATCH | M12: QAP §IV.D.2 | N12: App-side: needs §18.10 equity field. Excluded from verdict rollup.
A13: UW-DSCR-Y1 | B13: DSCR | C13: Annual DSCR band (house rule, all yrs) | D13: underwriting | E13: error | F13: COMPUTED | G13: between | I13: 1.15 – 1.40 | J13: MIN(DSCR Yr2-17) >= 1.15 AND MAX <= 1.40 | K13: 17-year Pro Forma'! row26 / (row30+row31), cols E:T | L13: DSCR-GATE | M13: QAP §IV.D.6 | N13: Primary gate. Numerator = NOI before repl reserves. Yr1 excluded (lease-up). DSCR floor is a house rule.
A14: UW-DSCR-15 | B14: DSCR | C14: 15-year projected DSCR (QAP spot) | D14: underwriting | E14: error | F14: COMPUTED | G14: between | I14: 1.00 – 1.40 | J14: 1.00 <= DSCR <= 1.40 at Yr5/10/15 | K14: 17-year Pro Forma'! row26/(row30+row31) cols H,M,R | L14: DSCR-GATE | M14: QAP §IV.D.6 | N14: QAP spot-check subset of the annual gate.
A15: FEE-DEVELOPER | B15: Fee Limits | C15: Developer fee | D15: underwriting | E15: error | F15: COMPUTED | G15: lte | I15: MIN($2.0M, 15% of base); no cap for 4% bond | J15: IF 4% bond: PASS (no cap); else I66 <= MIN(2,000,000, 15%*I83) | K15: Sources & Uses'!I66 (base I83) | L15: FEE-DEVELOPER | M15: QAP §IV.D.18 | N15: Replaces model placeholder I84 ($9,999,999). Westbend 4% bond -> no cap.
A16: FEE-ARCHITECT | B16: Fee Limits | C16: Architect / build-design fee | D16: underwriting | E16: error | F16: COMPUTED | G16: lte | H16: 0.07 | I16: <= 7% of construction contract | J16: Sources & Uses'!I46 <= 7% * I43 | K16: Sources & Uses'!I46 (contract I43) | L16: FEE-ARCHITECT | M16: QAP §IV.D.19 | N16: Construction contract = Total Hard Costs I43 (assumption).
A17: FEE-BUILDER-PROFIT | B17: Fee Limits | C17: Builder profit | D17: underwriting | E17: error | F17: COMPUTED | G17: lte | H17: 0.06 | I17: <= 6% of builder-profit base | J17: Sources & Uses'!I40 <= 6% * I82 | K17: Sources & Uses'!I40 (base I82) | L17: FEE-BUILDER-PROFIT | M17: QAP §IV.D.20 | N17: Westbend exactly at 6% cap (zero cushion).
A18: FEE-BUILDER-OVERHEAD | B18: Fee Limits | C18: Builder overhead | D18: underwriting | E18: error | F18: COMPUTED | G18: lte | H18: 0.02 | I18: <= 2% of builder-profit base | J18: Sources & Uses'!I39 <= 2% * I82 | K18: Sources & Uses'!I39 (base I82) | L18: FEE-BUILDER-OVERHEAD | M18: QAP §IV.D.21 | N18: Exactly at 2% cap.
A19: FEE-GENERAL-REQUIREMENTS | B19: Fee Limits | C19: General requirements | D19: underwriting | E19: error | F19: COMPUTED | G19: lte | H19: 0.06 | I19: <= 6% of builder-profit base | J19: Sources & Uses'!I38 <= 6% * I82 | K19: Sources & Uses'!I38 (base I82) | L19: FEE-GENERAL-REQUIREMENTS | M19: QAP §IV.D.23 | N19: Exactly at 6% cap.
A20: FEE-CONTINGENCY | B20: Fee Limits | C20: Construction contingency | D20: underwriting | E20: error | F20: COMPUTED | G20: lte | H20: 0.1 | I20: <= 10% of construction contract | J20: Sources & Uses'!I41 <= 10% * I43 | K20: Sources & Uses'!I41 (contract I43) | L20: FEE-CONTINGENCY | M20: QAP §IV.D | N20: Westbend ~4.8% <= 10%.
A21: UW-OPEX-MIN | B21: Operating & Reserves | C21: Minimum operating expenses | D21: underwriting | E21: warning | F21: COMPUTED | G21: gte | H21: 4500 | I21: >= $4,500 per unit per year | J21: 17-year Pro Forma'!E24 >= 4500 * units | K21: 17-year Pro Forma'!E24; Units | L21: UW-OPEX-MIN | M21: QAP §IV.D.13 | N21: Units = 'Unit Mix+Rents'!D15 = 280.
A22: UW-OPERATING-RESERVE-6MO | B22: Operating & Reserves | C22: Operating reserve minimum | D22: underwriting | E22: warning | F22: COMPUTED | G22: gte | H22: 0.5 | I22: >= 6 months (0.5x annual opex) | J22: Sources & Uses'!I68 >= 0.5 * 'PF'!E24 | K22: Sources & Uses'!I68; 'PF'!E24 | L22: UW-OPERATING-RESERVE-6MO | M22: QAP §IV.D.14 | N22: 6-mo = half of annual stabilized opex.
A23: FEE-ASSET-MGMT-CAP | B23: Operating & Reserves | C23: Asset-management fee cap (opex) | D23: underwriting | E23: warning | F23: APP-SIDE | G23: lte | H23: 5000 | I23: <= $5,000 / year | J23: Combined AM fee in OPEX <= $5,000/yr | K23: (no AM line inside opex) | L23: FEE-ASSET-MGMT-CAP | M23: QAP §IV.D.3 · §44 | N23: N/A: Westbend opex has no AM line. PF row38 AM fee is a below-NOI partnership fee, NOT opex. Excluded from rollup.
A24: UW-RESERVE-PUPA | B24: Operating & Reserves | C24: Replacement-reserve deposit minimum | D24: underwriting | E24: warning | F24: COMPUTED | G24: gte | I24: $300 senior / $350 family / $500 rehab per unit/yr | J24: 17-year Pro Forma'!D28 / units >= project-type floor | K24: 17-year Pro Forma'!D28; Units | L24: UW-RESERVE-PUPA | M24: QAP §IV.D.10 | N24: Floor toggle-dependent (params). Westbend $350/unit = Family floor.
A25: UW-RESERVE-ADEQUACY | B25: Operating & Reserves | C25: Replacement-reserve adequacy | D25: underwriting | E25: warning | F25: COMPUTED | G25: gte | I25: >= per-unit min balance every year | J25: Cumulative repl-reserve balance >= per-unit min every yr | K25: 17-year Pro Forma'! row28 cumulative | L25: UW-RESERVE-ADEQUACY | M25: QAP §IV.D.10 | N25: Helper: cumulative deposits vs floor*units each year.
A26: UW-VACANCY13 | B26: Vacancy & Trending | C26: Vacancy, years 1-3 | D26: underwriting | E26: warning | F26: COMPUTED | G26: gte | H26: 0.07 | I26: >= 7% (normal market) | J26: Rev+Expenses'!D30 >= 7% | K26: Rev+Expenses'!D30 | L26: UW-VACANCY13 | M26: QAP §IV.D.5 | N26: Westbend 7%.
A27: UW-VACANCY4 | B27: Vacancy & Trending | C27: Vacancy, years 4+ | D27: underwriting | E27: warning | F27: COMPUTED | G27: gte | H27: 0.07 | I27: >= 7% (normal market) | J27: Rev+Expenses'!D30 >= 7% | K27: Rev+Expenses'!D30 | L27: UW-VACANCY4 | M27: QAP §IV.D.5 | N27: Same vacancy assumption Yr4+.
A28: UW-TREND-RENT13 | B28: Vacancy & Trending | C28: Rent inflation, years 1-3 | D28: underwriting | E28: warning | F28: COMPUTED | G28: lte | H28: 0.02 | I28: <= 2.0% (LHC standard) | J28: 17-year Pro Forma'!E6/D6-1 <= 2.0% | K28: 17-year Pro Forma'! row6 YoY / D48 | L28: UW-TREND-RENT13 | M28: QAP §IV.D.4 | N28: Revenue growth D48 = 2%.
A29: UW-TREND-RENT415 | B29: Vacancy & Trending | C29: Rent inflation, years 4-15 | D29: underwriting | E29: warning | F29: COMPUTED | G29: lte | H29: 0.02 | I29: <= 2.0% (LHC standard) | J29: PF row6 YoY <= 2.0% | K29: 17-year Pro Forma'! row6 YoY / D48 | L29: UW-TREND-RENT415 | M29: QAP §IV.D.4 | N29: Same 2% trend Yr4-15.
A30: UW-TREND-EXPENSE | B30: Vacancy & Trending | C30: Expense inflation | D30: underwriting | E30: warning | F30: COMPUTED | G30: gte | H30: 0.028 | I30: >= 2.8% (LHC standard) | J30: PF expense growth D49 >= 2.8% | K30: 17-year Pro Forma'!D49 | L30: UW-TREND-EXPENSE | M30: QAP §IV.D.4 | N30: Expense growth D49 = 3%.
A31: UW-HUD-TDC | B31: Cost & TDC | C31: HUD Total Development Cost limit | D31: underwriting | E31: error | F31: INPUT | G31: lte | I31: <= 100% of HUD per-unit TDC limit (summed) | J31: Adjusted TDC 'Sources & Uses'!I79 <= HUD limit (input M10) | K31: Sources & Uses'!I79; input M10 | L31: UW-HUD-TDC | M31: QAP §IV.D.25 | N31: Model I86 ($287,704) is a QAP figure, NOT the HUD limit. Enter M10 per deal.
A32: UW-SOURCES-USES | B32: Cost & TDC | C32: Sources & Uses balance | D32: underwriting | E32: warning | F32: COMPUTED | G32: eq | H32: 1 | I32: Sources = Uses (to $1) | J32: ABS('Sources & Uses'!I81) <= 1 | K32: Sources & Uses'!I81 | L32: UW-SOURCES-USES | M32: QAP §IV.D.2 | N32: Westbend balance ~$0.
A33: UW-BASIS-RECON | B33: Cost & TDC | C33: Eligible-basis reconciliation | D33: underwriting | E33: warning | F33: APP-SIDE | G33: info | I33: No reconciliation errors | J33: Eligible-basis config reconciles with unit-mix (app-form) | K33: (application form) | L33: UW-BASIS-RECON | M33: IRC §42(d) | N33: App-side: needs eligible-basis config. Excluded from rollup.
A34: UW-SYND-COSTCAP | B34: Syndication | C34: Syndication cost cap | D34: underwriting | E34: error | F34: COMPUTED | G34: lte | I34: <= 10% private / 15% public of proceeds | J34: Financing Assumptions'!D49 <= rate * 'Tax Credit Calc'!F40 | K34: Financing Assumptions'!D49; 'Tax Credit Calc'!F40 | L34: UW-SYND-COSTCAP | M34: QAP §IV.D.24 | N34: Rate by offering toggle (M8). Westbend $50K << 10%*$15.19M.
A35: UW-SYND-PARTVI | B35: Syndication | C35: Syndication cost reconciliation | D35: underwriting | E35: warning | F35: APP-SIDE | G35: info | I35: Part VI = Dev Costs syndication total | J35: Part VI syndication = Dev Costs syndication subtotal (app-form) | K35: (application form) | L35: UW-SYND-PARTVI | M35: QAP §IV.D.24 | N35: App-side: needs Part VI form. Excluded from rollup.
A36: UW-CASHFLOW-10PCT | B36: Cash Flow | C36: Year-1 cash flow ceiling | D36: underwriting | E36: warning | F36: COMPUTED | G36: lte | H36: 0.1 | I36: <= 10% of operating expenses | J36: Stabilized cash 'PF'!E40 <= 10% * 'PF'!E24 | K36: 17-year Pro Forma'!E40; E24 | L36: UW-CASHFLOW-10PCT | M36: QAP §IV.D.4 | N36: Stabilized (Yr2) cash vs 10% of opex.
A37: UW-DEFERRED-DEV-FEE-15YR | B37: Deferred Developer Fee | C37: Deferred developer fee payoff | D37: underwriting | E37: warning | F37: COMPUTED | G37: gte | I37: Fully repaid by year 15 | J37: Cumulative 'PF'! row40 (Yr2->) at Yr15 >= deferred fee (input M11) | K37: 17-year Pro Forma'! row40 cumulative; input M11 | L37: UW-DEF-FEE | M37: QAP §IV.D.3 · §IV.D.9 | N37: Source = PF row40 cumulative (waterfall is a stub - not used). Default deferred fee = 'Sources & Uses'!I22.
A39: THRESHOLD PARAMETERS (toggle-dependent & shared) — dashboard binds here via named ranges
A40: Parameter | B40: Value
A41: Replacement reserve floor — Senior ($/unit/yr) | B41: 300
A42: Replacement reserve floor — Family ($/unit/yr) | B42: 350
A43: Replacement reserve floor — Rehab ($/unit/yr) | B43: 500
A44: Pool cap — Metro ($) | B44: 1500000
A45: Pool cap — Rural ($) | B45: 1000000
A46: Pool cap — Rural QNP-CHDO ($) | B46: 1000000
A47: Pool cap — Reprocessing (uncapped) | B47: 1000000000000
A48: Developer fee cap — absolute ($) | B48: 2000000
A49: Developer fee cap — % of dev fee base | B49: 0.15
A50: Syndication cost cap — Private (% proceeds) | B50: 0.1
A51: Syndication cost cap — Public (% proceeds) | B51: 0.15
A52: DSCR floor — house rule | B52: 1.15
... A54: DSCR 15-yr floor — QAP | B54: 1
A57: LEGEND
A58: error | B58: Hard fail — ineligible, disqualifying, or a credit reduction.
A59: warning | B59: LHC standard / scrutiny — may reduce credits or subordinate loan; not an automatic disqualifier.
A60: COMPUTED | B60: Derivable from the model; drives the dashboard.
A61: INPUT | B61: Needs a per-deal external value (dashboard inputs); computed once supplied.
A62: APP-SIDE | B62: Needs application-form data absent from the model; 'Verify in platform'. Excluded from rollup.
A63: yellow cell | B63: Value not sourced — pull from engine JSON, do not fabricate.

Sheet Dashboard Calc
A1: DEAL INPUTS | D1: HELPER — DSCR & CASH BY YEAR | J1: KPI RULE REGISTER
A2: Input | B2: Value | D2: Yr# | E2: DSCR (pre-res) | F2: DSCR (aft-res) | G2: Cash aft fees | H2: Cum cash | J2: # | K2: kpi_id | L2: group | M2: metric | N2: value | O2: threshold | P2: status | Q2: severity | R2: scope | S2: message | T2: rank | U2: citation | V2: sortkey
A3: Project name | B3: Westbend | D3: 2 | E3: {=IF((INDEX('17-year Pro Forma'!$D$30:$T$30,1,$D3)+INDEX('17-year Pro Forma'!$D$31:$T$31,1,$D3))=0,"",INDEX('17-year Pro Forma'!$D$26:$T$26,1,$D3)/(INDEX('17-year Pro Forma'!$D$30:$T$30,1,$D3)+INDEX('17-year Pro Forma'!$D$31:$T$31,1,$D3)))} -> 1.3713606 | F3: {=IF((INDEX('17-year Pro Forma'!$D$30:$T$30,1,$D3)+INDEX('17-year Pro Forma'!$D$31:$T$31,1,$D3))=0,"",(INDEX('17-year Pro Forma'!$D$26:$T$26,1,$D3)-INDEX('17-year Pro Forma'!$D$28:$T$28,1,$D3))/(INDEX('17-year Pro Forma'!$D$30:$T$30,1,$D3)+INDEX('17-year Pro Forma'!$D$31:$T$31,1,$D3)))} -> 1.2729052 | G3: {=INDEX('17-year Pro Forma'!$D$40:$T$40,1,$D3)} -> 274844.28 | H3: =G3 -> 274844.28 | J3: 1 | K3: ELG-4PCT-BOND | L3: Credit Structure | M3: 4% credit requires bonds | N3: =IF(CreditType="4% bond",'Sources & Uses'!I12,"n/a") -> 26629504 | O3: Bonds > $0 | P3: =IF(CreditType="4% bond",IF('Sources & Uses'!I12>0,"PASS","FAIL"),"N/A") -> PASS | Q3: error | R3: COMPUTED | S3: =IF(P3="FAIL","4% credit elected but no tax-exempt bonds present","") | T3: =IF($R3="APP-SIDE",99,IF($P3="FAIL",IF($Q3="error",1,2),IF($P3="PENDING",3,90))) -> 90 | U3: =IFERROR(INDEX(QAP_Rule_Register!$M$6:$M$37,MATCH(K3,QAP_Rule_Register!$A$6:$A$37,0)),"") -> QAP §II · IRC §42(h)(4) | V3: =IF(T3<90,T3*1000+ROW(),"")
A4: Project type | B4: Family | D4: =D3+1 -> 3 | E4: {=IF((INDEX('17-year Pro Forma'!$D$30:$T$30,1,$D4)+INDEX('17-year Pro Forma'!$D$31:$T$31,1,$D4))=0,"",INDEX('17-year Pro Forma'!$D$26:$T$26,1,$D4)/(INDEX('17-year Pro Forma'!$D$30:$T$30,1,$D4)+INDEX('17-year Pro Forma'!$D$31:$T$31,1,$D4)))} -> 1.3915158 | F4: {=IF((INDEX('17-year Pro Forma'!$D$30:$T$30,1,$D4)+INDEX('17-year Pro Forma'!$D$31:$T$31,1,$D4))=0,"",(INDEX('17-year Pro Forma'!$D$26:$T$26,1,$D4)-INDEX('17-year Pro Forma'!$D$28:$T$28,1,$D4))/(INDEX('17-year Pro Forma'!$D$30:$T$30,1,$D4)+INDEX('17-year Pro Forma'!$D$31:$T$31,1,$D4)))} -> 1.2901067 | G4: {=INDEX('17-year Pro Forma'!$D$40:$T$40,1,$D4)} -> 297518.72 | H4: =H3+G4 -> 572363 | J4: 2 | K4: ELG-9PCT-BOND | L4: Credit Structure | M4: 9% + bonds mutually exclusive | N4: =IF(CreditType="9% competitive",'Sources & Uses'!I12,"n/a") -> n/a | O4: Bonds = $0 | P4: =IF(CreditType="9% competitive",IF('Sources & Uses'!I12=0,"PASS","FAIL"),"N/A") -> N/A | Q4: error | R4: COMPUTED | S4: =IF(P4="FAIL","9% credit cannot combine with tax-exempt bonds","") | T4: =IF($R4="APP-SIDE",99,IF($P4="FAIL",IF($Q4="error",1,2),IF($P4="PENDING",3,90))) -> 90 | U4: =IFERROR(INDEX(QAP_Rule_Register!$M$6:$M$37,MATCH(K4,QAP_Rule_Register!$A$6:$A$37,0)),"") -> QAP §II · IRC §42(h)(4) | V4: =IF(T4<90,T4*1000+ROW(),"")
A5: Credit type | B5: 4% bond | D5: =D4+1 -> 4 | E5: {=IF((INDEX('17-year Pro Forma'!$D$30:$T$30,1,$D5)+INDEX('17-year Pro Forma'!$D$31:$T$31,1,$D5))=0,"",INDEX('17-year Pro Forma'!$D$26:$T$26,1,$D5)/(INDEX('17-year Pro Forma'!$D$30:$T$30,1,$D5)+INDEX('17-year Pro Forma'!$D$31:$T$31,1,$D5)))} -> 1.2459969 | F5: {=IF((INDEX('17-year Pro Forma'!$D$30:$T$30,1,$D5)+INDEX('17-year Pro Forma'!$D$31:$T$31,1,$D5))=0,"",(INDEX('17-year Pro Forma'!$D$26:$T$26,1,$D5)-INDEX('17-year Pro Forma'!$D$28:$T$28,1,$D5))/(INDEX('17-year Pro Forma'!$D$30:$T$30,1,$D5)+INDEX('17-year Pro Forma'!$D$31:$T$31,1,$D5)))} -> 1.1538147 | G5: {=INDEX('17-year Pro Forma'!$D$40:$T$40,1,$D5)} -> 144849.74 | H5: =H4+G5 -> 717212.73 | J5: 3 | K5: ELG-BOOST-30 | L5: Credit Sizing | M5: Construction basis boost cap | N5: ='Tax Credit Calc'!F17 -> 0 | O5: =BoostCapPct -> 0.3 | P5: =IF('Tax Credit Calc'!F17<=BoostCapPct,"PASS","FAIL") -> PASS | Q5: error | R5: COMPUTED | S5: =IF(P5="FAIL","Basis boost "&TEXT('Tax Credit Calc'!F17,"0.0%")&" exceeds 30% cap","") | T5: =IF($R5="APP-SIDE",99,IF($P5="FAIL",IF($Q5="error",1,2),IF($P5="PENDING",3,90))) -> 90 | U5: =IFERROR(INDEX(QAP_Rule_Register!$M$6:$M$37,MATCH(K5,QAP_Rule_Register!$A$6:$A$37,0)),"") -> QAP §II.C | V5: =IF(T5<90,T5*1000+ROW(),"")
A6: Basis-boost geography eligible | B6: No | D6: =D5+1 -> 5 | E6: {=IF((INDEX('17-year Pro Forma'!$D$30:$T$30,1,$D6)+INDEX('17-year Pro Forma'!$D$31:$T$31,1,$D6))=0,"",INDEX('17-year Pro Forma'!$D$26:$T$26,1,$D6)/(INDEX('17-year Pro Forma'!$D$30:$T$30,1,$D6)+INDEX('17-year Pro Forma'!$D$31:$T$31,1,$D6)))} -> 1.2640715 | F6: {=IF((INDEX('17-year Pro Forma'!$D$30:$T$30,1,$D6)+INDEX('17-year Pro Forma'!$D$31:$T$31,1,$D6))=0,"",(INDEX('17-year Pro Forma'!$D$26:$T$26,1,$D6)-INDEX('17-year Pro Forma'!$D$28:$T$28,1,$D6))/(INDEX('17-year Pro Forma'!$D$30:$T$30,1,$D6)+INDEX('17-year Pro Forma'!$D$31:$T$31,1,$D6)))} -> 1.1691239 | G6: {=INDEX('17-year Pro Forma'!$D$40:$T$40,1,$D6)} -> 168300.35 | H6: =H5+G6 -> 885513.08 | J6: 4 | K6: ELG-BOOST-ELIGIBILITY | L6: Credit Sizing | M6: Basis-boost geo eligibility | N6: =BoostEligible -> No | O6: Qualifying geo | P6: =IF(BoostEligible="","PENDING",IF(OR('Tax Credit Calc'!F17=0,BoostEligible="Yes"),"PASS","FAIL")) -> PASS | Q6: warning | R6: INPUT | S6: =IF(P6="FAIL","Boost claimed but geography not eligible ('Dashboard Calc' M6)",IF(P6="PENDING","Set basis-boost geography eligibility on 'Dashboard Calc' M6","")) | T6: =IF($R6="APP-SIDE",99,IF($P6="FAIL",IF($Q6="error",1,2),IF($P6="PENDING",3,90))) -> 90 | U6: =IFERROR(INDEX(QAP_Rule_Register!$M$6:$M$37,MATCH(K6,QAP_Rule_Register!$A$6:$A$37,0)),"") -> QAP §II.C | V6: =IF(T6<90,T6*1000+ROW(),"")
A7: RD/HUD financed | B7: No | D7: =D6+1 -> 6 | E7: {=IF((INDEX('17-year Pro Forma'!$D$30:$T$30,1,$D7)+INDEX('17-year Pro Forma'!$D$31:$T$31,1,$D7))=0,"",INDEX('17-year Pro Forma'!$D$26:$T$26,1,$D7)/(INDEX('17-year Pro Forma'!$D$30:$T$30,1,$D7)+INDEX('17-year Pro Forma'!$D$31:$T$31,1,$D7)))} -> 1.2822841 | F7: {=IF((INDEX('17-year Pro Forma'!$D$30:$T$30,1,$D7)+INDEX('17-year Pro Forma'!$D$31:$T$31,1,$D7))=0,"",(INDEX('17-year Pro Forma'!$D$26:$T$26,1,$D7)-INDEX('17-year Pro Forma'!$D$28:$T$28,1,$D7))/(INDEX('17-year Pro Forma'!$D$30:$T$30,1,$D7)+INDEX('17-year Pro Forma'!$D$31:$T$31,1,$D7)))} -> 1.1844881 | G7: {=INDEX('17-year Pro Forma'!$D$40:$T$40,1,$D7)} -> 191865.41 | H7: =H6+G7 -> 1077378.5 | J7: 5 | K7: ELG-POOL-CAP | L7: Credit Sizing | M7: Per-project pool cap | N7: =IF(CreditType="4% bond","n/a",'Tax Credit Calc'!F22) -> n/a | O7: =IF(CreditType="4% bond","N/A (PAB cap)",IF(Pool="Metro",PoolCapMetro,IF(Pool="Rural",PoolCapRural,IF(Pool="Rural QNP-CHDO",PoolCapRuralQNP,PoolCapReproc)))) -> N/A (PAB cap) | P7: =IF(CreditType="4% bond","N/A",IF('Tax Credit Calc'!F22<=IF(Pool="Metro",PoolCapMetro,IF(Pool="Rural",PoolCapRural,IF(Pool="Rural QNP-CHDO",PoolCapRuralQNP,PoolCapReproc))),"PASS","FAIL")) -> N/A | Q7: error | R7: COMPUTED | S7: =IF(P7="FAIL","Annual credits exceed the "&Pool&" pool cap","") | T7: =IF($R7="APP-SIDE",99,IF($P7="FAIL",IF($Q7="error",1,2),IF($P7="PENDING",3,90))) -> 90 | U7: =IFERROR(INDEX(QAP_Rule_Register!$M$6:$M$37,MATCH(K7,QAP_Rule_Register!$A$6:$A$37,0)),"") -> QAP §II.B.1 | V7: =IF(T7<90,T7*1000+ROW(),"")
A8: Syndication offering | B8: Private | D8: =D7+1 -> 7 | E8: {=IF((INDEX('17-year Pro Forma'!$D$30:$T$30,1,$D8)+INDEX('17-year Pro Forma'!$D$31:$T$31,1,$D8))=0,"",INDEX('17-year Pro Forma'!$D$26:$T$26,1,$D8)/(INDEX('17-year Pro Forma'!$D$30:$T$30,1,$D8)+INDEX('17-year Pro Forma'!$D$31:$T$31,1,$D8)))} -> 1.3006309 | F8: {=IF((INDEX('17-year Pro Forma'!$D$30:$T$30,1,$D8)+INDEX('17-year Pro Forma'!$D$31:$T$31,1,$D8))=0,"",(INDEX('17-year Pro Forma'!$D$26:$T$26,1,$D8)-INDEX('17-year Pro Forma'!$D$28:$T$28,1,$D8))/(INDEX('17-year Pro Forma'!$D$30:$T$30,1,$D8)+INDEX('17-year Pro Forma'!$D$31:$T$31,1,$D8)))} -> 1.199901 | G8: {=INDEX('17-year Pro Forma'!$D$40:$T$40,1,$D8)} -> 215537.08 | H8: =H7+G8 -> 1292915.6 | J8: 6 | K8: ELG-CREDIT-MAX | L8: Credit Sizing | M8: Maximum allowable credit | N8: ='Tax Credit Calc'!F22 -> 1841756.5 | O8: =MIN('Tax Credit Calc'!F22,$B$25) -> 1841756.5 | P8: =IF('Tax Credit Calc'!F22<=MIN('Tax Credit Calc'!F22,$B$25)*1.001,"PASS","FAIL") -> PASS | Q8: error | R8: COMPUTED | S8: =IF(P8="FAIL","Credits requested exceed MIN(basis, equity-gap)","") | T8: =IF($R8="APP-SIDE",99,IF($P8="FAIL",IF($Q8="error",1,2),IF($P8="PENDING",3,90))) -> 90 | U8: =IFERROR(INDEX(QAP_Rule_Register!$M$6:$M$37,MATCH(K8,QAP_Rule_Register!$A$6:$A$37,0)),"") -> QAP §II.B · §IV.D | V8: =IF(T8<90,T8*1000+ROW(),"")
A9: Pool (if 9%) | B9: Metro | D9: =D8+1 -> 8 | E9: {=IF((INDEX('17-year Pro Forma'!$D$30:$T$30,1,$D9)+INDEX('17-year Pro Forma'!$D$31:$T$31,1,$D9))=0,"",INDEX('17-year Pro Forma'!$D$26:$T$26,1,$D9)/(INDEX('17-year Pro Forma'!$D$30:$T$30,1,$D9)+INDEX('17-year Pro Forma'!$D$31:$T$31,1,$D9)))} -> 1.3191076 | F9: {=IF((INDEX('17-year Pro Forma'!$D$30:$T$30,1,$D9)+INDEX('17-year Pro Forma'!$D$31:$T$31,1,$D9))=0,"",(INDEX('17-year Pro Forma'!$D$26:$T$26,1,$D9)-INDEX('17-year Pro Forma'!$D$28:$T$28,1,$D9))/(INDEX('17-year Pro Forma'!$D$30:$T$30,1,$D9)+INDEX('17-year Pro Forma'!$D$31:$T$31,1,$D9)))} -> 1.2153558 | G9: {=INDEX('17-year Pro Forma'!$D$40:$T$40,1,$D9)} -> 239307.1 | H9: =H8+G9 -> 1532222.7 | J9: 7 | K9: UW-DSCR-Y1 | L9: DSCR | M9: Annual DSCR band (Yr2-17) | N9: =$B$18 -> 1.2459969 | O9: 1.15-1.40 | P9: =$B$21 -> FAIL | Q9: error | R9: COMPUTED | S9: =IF(P9="FAIL","Min DSCR "&TEXT($B$18,"0.00")&"x at Yr "&$B$19&" below 1.15 floor (P&I starts Yr4)","") -> Min DSCR 1.25x at Yr 4 below 1.15 floor (P&I starts Yr4) | T9: =IF($R9="APP-SIDE",99,IF($P9="FAIL",IF($Q9="error",1,2),IF($P9="PENDING",3,90))) -> 1 | U9: =IFERROR(INDEX(QAP_Rule_Register!$M$6:$M$37,MATCH(K9,QAP_Rule_Register!$A$6:$A$37,0)),"") -> QAP §IV.D.6 | V9: =IF(T9<90,T9*1000+ROW(),"") -> 1009
A10: Building / product type | B10: Walk-up | D10: =D9+1 -> 9 | E10: {=IF((INDEX('17-year Pro Forma'!$D$30:$T$30,1,$D10)+INDEX('17-year Pro Forma'!$D$31:$T$31,1,$D10))=0,"",INDEX('17-year Pro Forma'!$D$26:$T$26,1,$D10)/(INDEX('17-year Pro Forma'!$D$30:$T$30,1,$D10)+INDEX('17-year Pro Forma'!$D$31:$T$31,1,$D10)))} -> 1.3377096 | F10: {=IF((INDEX('17-year Pro Forma'!$D$30:$T$30,1,$D10)+INDEX('17-year Pro Forma'!$D$31:$T$31,1,$D10))=0,"",(INDEX('17-year Pro Forma'!$D$26:$T$26,1,$D10)-INDEX('17-year Pro Forma'!$D$28:$T$28,1,$D10))/(INDEX('17-year Pro Forma'!$D$30:$T$30,1,$D10)+INDEX('17-year Pro Forma'!$D$31:$T$31,1,$D10)))} -> 1.2308453 | G10: {=INDEX('17-year Pro Forma'!$D$40:$T$40,1,$D10)} -> 263166.75 | H10: =H9+G10 -> 1795389.4 | J10: 8 | K10: UW-DSCR-15 | L10: DSCR | M10: 15-yr projected DSCR (y5/10/15) | N10: =$B$22 -> 1.2640715 | O10: 1.00-1.40 | P10: =IF(AND($B$22>=DSCR15Floor,MAX(E6,E11,E16)<=DSCRCeil),"PASS","FAIL") -> FAIL | Q10: error | R10: COMPUTED | S10: =IF(P10="FAIL","QAP checkpoint DSCR out of 1.00-1.40 band","") -> QAP checkpoint DSCR out of 1.00-1.40 band | T10: =IF($R10="APP-SIDE",99,IF($P10="FAIL",IF($Q10="error",1,2),IF($P10="PENDING",3,90))) -> 1 | U10: =IFERROR(INDEX(QAP_Rule_Register!$M$6:$M$37,MATCH(K10,QAP_Rule_Register!$A$6:$A$37,0)),"") -> QAP §IV.D.6 | V10: =IF(T10<90,T10*1000+ROW(),"") -> 1010
A11: TDC cost region | B11: New Orleans | D11: =D10+1 -> 10 | E11: {=IF((INDEX('17-year Pro Forma'!$D$30:$T$30,1,$D11)+INDEX('17-year Pro Forma'!$D$31:$T$31,1,$D11))=0,"",INDEX('17-year Pro Forma'!$D$26:$T$26,1,$D11)/(INDEX('17-year Pro Forma'!$D$30:$T$30,1,$D11)+INDEX('17-year Pro Forma'!$D$31:$T$31,1,$D11)))} -> 1.3564322 | F11: {=IF((INDEX('17-year Pro Forma'!$D$30:$T$30,1,$D11)+INDEX('17-year Pro Forma'!$D$31:$T$31,1,$D11))=0,"",(INDEX('17-year Pro Forma'!$D$26:$T$26,1,$D11)-INDEX('17-year Pro Forma'!$D$28:$T$28,1,$D11))/(INDEX('17-year Pro Forma'!$D$30:$T$30,1,$D11)+INDEX('17-year Pro Forma'!$D$31:$T$31,1,$D11)))} -> 1.2463619 | G11: {=INDEX('17-year Pro Forma'!$D$40:$T$40,1,$D11)} -> 287106.84 | H11: =H10+G11 -> 2082496.3 | J11: 9 | K11: FEE-DEVELOPER | L11: Fee Limits | M11: Developer fee | N11: ='Sources & Uses'!I65 -> 5921703 | O11: =IF(CreditType="4% bond","No cap (4% bond)",MIN(DevFeeCapAbs,DevFeeCapPct*'Sources & Uses'!I82)) -> No cap (4% bond) | P11: =IF(CreditType="4% bond","PASS",IF('Sources & Uses'!I65<=MIN(DevFeeCapAbs,DevFeeCapPct*'Sources & Uses'!I82),"PASS","FAIL")) -> PASS | Q11: error | R11: COMPUTED | S11: =IF(P11="FAIL","Developer fee exceeds MIN($2.0M, 15% x base)","") | T11: =IF($R11="APP-SIDE",99,IF($P11="FAIL",IF($Q11="error",1,2),IF($P11="PENDING",3,90))) -> 90 | U11: =IFERROR(INDEX(QAP_Rule_Register!$M$6:$M$37,MATCH(K11,QAP_Rule_Register!$A$6:$A$37,0)),"") -> QAP §IV.D.18 | V11: =IF(T11<90,T11*1000+ROW(),"")
A12: HUD TDC limit | B12: =S63 -> 69223310 | D12: =D11+1 -> 11 | E12: {=IF((INDEX('17-year Pro Forma'!$D$30:$T$30,1,$D12)+INDEX('17-year Pro Forma'!$D$31:$T$31,1,$D12))=0,"",INDEX('17-year Pro Forma'!$D$26:$T$26,1,$D12)/(INDEX('17-year Pro Forma'!$D$30:$T$30,1,$D12)+INDEX('17-year Pro Forma'!$D$31:$T$31,1,$D12)))} -> 1.3752703 | F12: {=IF((INDEX('17-year Pro Forma'!$D$30:$T$30,1,$D12)+INDEX('17-year Pro Forma'!$D$31:$T$31,1,$D12))=0,"",(INDEX('17-year Pro Forma'!$D$26:$T$26,1,$D12)-INDEX('17-year Pro Forma'!$D$28:$T$28,1,$D12))/(INDEX('17-year Pro Forma'!$D$30:$T$30,1,$D12)+INDEX('17-year Pro Forma'!$D$31:$T$31,1,$D12)))} -> 1.2618979 | G12: {=INDEX('17-year Pro Forma'!$D$40:$T$40,1,$D12)} -> 311117.73 | H12: =H11+G12 -> 2393614 | J12: 10 | K12: FEE-ARCHITECT | L12: Fee Limits | M12: Architect / design fee | N12: ='Sources & Uses'!I46 -> 750000 | O12: =ArchPct*'Sources & Uses'!I43 -> 2440288.8 | P12: =IF('Sources & Uses'!I46<=ArchPct*'Sources & Uses'!I43,"PASS","FAIL") -> PASS | Q12: error | R12: COMPUTED | S12: =IF(P12="FAIL","Architect fee exceeds 7% of hard costs","") | T12: =IF($R12="APP-SIDE",99,IF($P12="FAIL",IF($Q12="error",1,2),IF($P12="PENDING",3,90))) -> 90 | U12: =IFERROR(INDEX(QAP_Rule_Register!$M$6:$M$37,MATCH(K12,QAP_Rule_Register!$A$6:$A$37,0)),"") -> QAP §IV.D.19 | V12: =IF(T12<90,T12*1000+ROW(),"")
A13: Deferred developer fee | B13: ='Sources & Uses'!I22 -> 2131813.1 | D13: =D12+1 -> 12 | E13: {=IF((INDEX('17-year Pro Forma'!$D$30:$T$30,1,$D13)+INDEX('17-year Pro Forma'!$D$31:$T$31,1,$D13))=0,"",INDEX('17-year Pro Forma'!$D$26:$T$26,1,$D13)/(INDEX('17-year Pro Forma'!$D$30:$T$30,1,$D13)+INDEX('17-year Pro Forma'!$D$31:$T$31,1,$D13)))} -> 1.3933144 | F13: {=IF((INDEX('17-year Pro Forma'!$D$30:$T$30,1,$D13)+INDEX('17-year Pro Forma'!$D$31:$T$31,1,$D13))=0,"",(INDEX('17-year Pro Forma'!$D$26:$T$26,1,$D13)-INDEX('17-year Pro Forma'!$D$28:$T$28,1,$D13))/(INDEX('17-year Pro Forma'!$D$30:$T$30,1,$D13)+INDEX('17-year Pro Forma'!$D$31:$T$31,1,$D13)))} -> 1.2765408 | G13: {=INDEX('17-year Pro Forma'!$D$40:$T$40,1,$D13)} -> 333839.25 | H13: =H12+G13 -> 2727453.2 | J13: 11 | K13: FEE-BUILDER-PROFIT | L13: Fee Limits | M13: Builder profit | N13: ='Sources & Uses'!I40 -> 1834803.6 | O13: =BuilderProfitPct*'Sources & Uses'!I81 -> 1834803.6 | P13: =IF('Sources & Uses'!I40<=BuilderProfitPct*'Sources & Uses'!I81+1,"PASS","FAIL") -> PASS | Q13: error | R13: COMPUTED | S13: =IF(P13="FAIL","Builder profit exceeds 6% of base","") | T13: =IF($R13="APP-SIDE",99,IF($P13="FAIL",IF($Q13="error",1,2),IF($P13="PENDING",3,90))) -> 90 | U13: =IFERROR(INDEX(QAP_Rule_Register!$M$6:$M$37,MATCH(K13,QAP_Rule_Register!$A$6:$A$37,0)),"") -> QAP §IV.D.20 | V13: =IF(T13<90,T13*1000+ROW(),"")
D14: =D13+1 -> 13 | E14: {=IF((INDEX('17-year Pro Forma'!$D$30:$T$30,1,$D14)+INDEX('17-year Pro Forma'!$D$31:$T$31,1,$D14))=0,"",INDEX('17-year Pro Forma'!$D$26:$T$26,1,$D14)/(INDEX('17-year Pro Forma'!$D$30:$T$30,1,$D14)+INDEX('17-year Pro Forma'!$D$31:$T$31,1,$D14)))} -> 1.4114356 | F14: {=IF((INDEX('17-year Pro Forma'!$D$30:$T$30,1,$D14)+INDEX('17-year Pro Forma'!$D$31:$T$31,1,$D14))=0,"",(INDEX('17-year Pro Forma'!$D$26:$T$26,1,$D14)-INDEX('17-year Pro Forma'!$D$28:$T$28,1,$D14))/(INDEX('17-year Pro Forma'!$D$30:$T$30,1,$D14)+INDEX('17-year Pro Forma'!$D$31:$T$31,1,$D14)))} -> 1.2911588 | G14: {=INDEX('17-year Pro Forma'!$D$40:$T$40,1,$D14)} -> 356570.23 | H14: =H13+G14 -> 3084023.5 | J14: 12 | K14: FEE-BUILDER-OVERHEAD | L14: Fee Limits | M14: Builder overhead | N14: ='Sources & Uses'!I39 -> 611601.21 | O14: =BuilderOHPct*'Sources & Uses'!I81 -> 611601.21 | P14: =IF('Sources & Uses'!I39<=BuilderOHPct*'Sources & Uses'!I81+1,"PASS","FAIL") -> PASS | Q14: error | R14: COMPUTED | S14: =IF(P14="FAIL","Builder overhead exceeds 2% of base","") | T14: =IF($R14="APP-SIDE",99,IF($P14="FAIL",IF($Q14="error",1,2),IF($P14="PENDING",3,90))) -> 90 | U14: =IFERROR(INDEX(QAP_Rule_Register!$M$6:$M$37,MATCH(K14,QAP_Rule_Register!$A$6:$A$37,0)),"") -> QAP §IV.D.21 | V14: =IF(T14<90,T14*1000+ROW(),"")
D15: =D14+1 -> 14 | E15: {=IF((INDEX('17-year Pro Forma'!$D$30:$T$30,1,$D15)+INDEX('17-year Pro Forma'!$D$31:$T$31,1,$D15))=0,"",INDEX('17-year Pro Forma'!$D$26:$T$26,1,$D15)/(INDEX('17-year Pro Forma'!$D$30:$T$30,1,$D15)+INDEX('17-year Pro Forma'!$D$31:$T$31,1,$D15)))} -> 1.4296269 | F15: {=IF((INDEX('17-year Pro Forma'!$D$30:$T$30,1,$D15)+INDEX('17-year Pro Forma'!$D$31:$T$31,1,$D15))=0,"",(INDEX('17-year Pro Forma'!$D$26:$T$26,1,$D15)-INDEX('17-year Pro Forma'!$D$28:$T$28,1,$D15))/(INDEX('17-year Pro Forma'!$D$30:$T$30,1,$D15)+INDEX('17-year Pro Forma'!$D$31:$T$31,1,$D15)))} -> 1.3057418 | G15: {=INDEX('17-year Pro Forma'!$D$40:$T$40,1,$D15)} -> 379298.26 | H15: =H14+G15 -> 3463321.7 | J15: 13 | K15: FEE-GENERAL-REQUIREMENTS | L15: Fee Limits | M15: General requirements | N15: ='Sources & Uses'!I38 -> 1834803.6 | O15: =GenReqPct*'Sources & Uses'!I81 -> 1834803.6 | P15: =IF('Sources & Uses'!I38<=GenReqPct*'Sources & Uses'!I81+1,"PASS","FAIL") -> PASS | Q15: error | R15: COMPUTED | S15: =IF(P15="FAIL","General requirements exceed 6% of base","") | T15: =IF($R15="APP-SIDE",99,IF($P15="FAIL",IF($Q15="error",1,2),IF($P15="PENDING",3,90))) -> 90 | U15: =IFERROR(INDEX(QAP_Rule_Register!$M$6:$M$37,MATCH(K15,QAP_Rule_Register!$A$6:$A$37,0)),"") -> QAP §IV.D.23 | V15: =IF(T15<90,T15*1000+ROW(),"")
A16: SCORECARD SUMMARY | D16: =D15+1 -> 15 | E16: {=IF((INDEX('17-year Pro Forma'!$D$30:$T$30,1,$D16)+INDEX('17-year Pro Forma'!$D$31:$T$31,1,$D16))=0,"",INDEX('17-year Pro Forma'!$D$26:$T$26,1,$D16)/(INDEX('17-year Pro Forma'!$D$30:$T$30,1,$D16)+INDEX('17-year Pro Forma'!$D$31:$T$31,1,$D16)))} -> 1.4478809 | F16: {=IF((INDEX('17-year Pro Forma'!$D$30:$T$30,1,$D16)+INDEX('17-year Pro Forma'!$D$31:$T$31,1,$D16))=0,"",(INDEX('17-year Pro Forma'!$D$26:$T$26,1,$D16)-INDEX('17-year Pro Forma'!$D$28:$T$28,1,$D16))/(INDEX('17-year Pro Forma'!$D$30:$T$30,1,$D16)+INDEX('17-year Pro Forma'!$D$31:$T$31,1,$D16)))} -> 1.3202792 | G16: {=INDEX('17-year Pro Forma'!$D$40:$T$40,1,$D16)} -> 402010.34 | H16: =H15+G16 -> 3865332.1 | J16: 14 | K16: FEE-CONTINGENCY | L16: Fee Limits | M16: Construction contingency | N16: ='Sources & Uses'!I41 -> 1660060.4 | O16: =ContingencyPct*'Sources & Uses'!I43 -> 3486126.9 | P16: =IF('Sources & Uses'!I41<=ContingencyPct*'Sources & Uses'!I43,"PASS","FAIL") -> PASS | Q16: error | R16: COMPUTED | S16: =IF(P16="FAIL","Contingency exceeds 10% of hard costs","") | T16: =IF($R16="APP-SIDE",99,IF($P16="FAIL",IF($Q16="error",1,2),IF($P16="PENDING",3,90))) -> 90 | U16: =IFERROR(INDEX(QAP_Rule_Register!$M$6:$M$37,MATCH(K16,QAP_Rule_Register!$A$6:$A$37,0)),"") -> QAP §IV.D | V16: =IF(T16<90,T16*1000+ROW(),"")
A17: Metric | B17: Value | D17: =D16+1 -> 16 | E17: {=IF((INDEX('17-year Pro Forma'!$D$30:$T$30,1,$D17)+INDEX('17-year Pro Forma'!$D$31:$T$31,1,$D17))=0,"",INDEX('17-year Pro Forma'!$D$26:$T$26,1,$D17)/(INDEX('17-year Pro Forma'!$D$30:$T$30,1,$D17)+INDEX('17-year Pro Forma'!$D$31:$T$31,1,$D17)))} -> 1.4661897 | F17: {=IF((INDEX('17-year Pro Forma'!$D$30:$T$30,1,$D17)+INDEX('17-year Pro Forma'!$D$31:$T$31,1,$D17))=0,"",(INDEX('17-year Pro Forma'!$D$26:$T$26,1,$D17)-INDEX('17-year Pro Forma'!$D$28:$T$28,1,$D17))/(INDEX('17-year Pro Forma'!$D$30:$T$30,1,$D17)+INDEX('17-year Pro Forma'!$D$31:$T$31,1,$D17)))} -> 1.33476 | G17: {=INDEX('17-year Pro Forma'!$D$40:$T$40,1,$D17)} -> 424692.86 | H17: =H16+G17 -> 4290024.9 | J17: 15 | K17: UW-OPEX-MIN | L17: Operating & Reserves | M17: Minimum operating expenses | N17: ='17-year Pro Forma'!E24 -> 1331988.1 | O17: =OpexMinPU*'Unit Mix+Rents'!$D$14 -> 1260000 | P17: =IF('17-year Pro Forma'!E24>=OpexMinPU*'Unit Mix+Rents'!$D$14,"PASS","FAIL") -> PASS | Q17: warning | R17: COMPUTED | S17: =IF(P17="FAIL","Opex "&TEXT('17-year Pro Forma'!E24/'Unit Mix+Rents'!$D$14,"$#,##0")&"/unit below $4,500 floor","") | T17: =IF($R17="APP-SIDE",99,IF($P17="FAIL",IF($Q17="error",1,2),IF($P17="PENDING",3,90))) -> 90 | U17: =IFERROR(INDEX(QAP_Rule_Register!$M$6:$M$37,MATCH(K17,QAP_Rule_Register!$A$6:$A$37,0)),"") -> QAP §IV.D.13 | V17: =IF(T17<90,T17*1000+ROW(),"")
A18: Min DSCR (pre-res) | B18: =MIN(E3:E18) -> 1.2459969 | D18: =D17+1 -> 17 | E18: {=IF((INDEX('17-year Pro Forma'!$D$30:$T$30,1,$D18)+INDEX('17-year Pro Forma'!$D$31:$T$31,1,$D18))=0,"",INDEX('17-year Pro Forma'!$D$26:$T$26,1,$D18)/(INDEX('17-year Pro Forma'!$D$30:$T$30,1,$D18)+INDEX('17-year Pro Forma'!$D$31:$T$31,1,$D18)))} -> 1.4845453 | F18: {=IF((INDEX('17-year Pro Forma'!$D$30:$T$30,1,$D18)+INDEX('17-year Pro Forma'!$D$31:$T$31,1,$D18))=0,"",(INDEX('17-year Pro Forma'!$D$26:$T$26,1,$D18)-INDEX('17-year Pro Forma'!$D$28:$T$28,1,$D18))/(INDEX('17-year Pro Forma'!$D$30:$T$30,1,$D18)+INDEX('17-year Pro Forma'!$D$31:$T$31,1,$D18)))} -> 1.3491728 | G18: {=INDEX('17-year Pro Forma'!$D$40:$T$40,1,$D18)} -> 447331.59 | H18: =H17+G18 -> 4737356.5 | J18: 16 | K18: UW-OPERATING-RESERVE-6MO | L18: Operating & Reserves | M18: Operating reserve (6 mo) | N18: ='Sources & Uses'!I67 -> 665994.03 | O18: =OpReserveFrac*'17-year Pro Forma'!E24 -> 665994.03 | P18: =IF('Sources & Uses'!I67>=OpReserveFrac*'17-year Pro Forma'!E24,"PASS","FAIL") -> PASS | Q18: warning | R18: COMPUTED | S18: =IF(P18="FAIL","Operating reserve below 6 months of opex","") | T18: =IF($R18="APP-SIDE",99,IF($P18="FAIL",IF($Q18="error",1,2),IF($P18="PENDING",3,90))) -> 90 | U18: =IFERROR(INDEX(QAP_Rule_Register!$M$6:$M$37,MATCH(K18,QAP_Rule_Register!$A$6:$A$37,0)),"") -> QAP §IV.D.14 | V18: =IF(T18<90,T18*1000+ROW(),"")
A19: Min DSCR year | B19: =INDEX(D3:D18,MATCH(B18,E3:E18,0)) -> 4 | J19: 17 | K19: UW-RESERVE-PUPA | L19: Operating & Reserves | M19: Repl-reserve deposit / unit | N19: ='17-year Pro Forma'!D28/'Unit Mix+Rents'!$D$14 -> 500 | O19: =IF(ProjectType="Senior",ReserveFloorSenior,IF(ProjectType="Rehab",ReserveFloorRehab,ReserveFloorFamily)) -> 350 | P19: =IF('17-year Pro Forma'!D28/'Unit Mix+Rents'!$D$14>=O19,"PASS","FAIL") -> PASS | Q19: warning | R19: EXCLUDED | S19: =IF(P19="FAIL","Reserve deposit "&TEXT('17-year Pro Forma'!D28/'Unit Mix+Rents'!$D$14,"$#,##0")&"/unit below "&TEXT(O19,"$#,##0")&" floor","") | T19: =IF($R19="APP-SIDE",99,IF($P19="FAIL",IF($Q19="error",1,2),IF($P19="PENDING",3,90))) -> 90 | U19: =IFERROR(INDEX(QAP_Rule_Register!$M$6:$M$37,MATCH(K19,QAP_Rule_Register!$A$6:$A$37,0)),"") -> QAP §IV.D.10 | V19: =IF(T19<90,T19*1000+ROW(),"")
A20: Max DSCR (pre-res) | B20: =MAX(E3:E18) -> 1.4845453 | J20: 18 | K20: UW-RESERVE-ADEQUACY | L20: Operating & Reserves | M20: Repl-reserve adequacy (all yrs) | N20: =MIN('17-year Pro Forma'!$D$28:$T$28)/'Unit Mix+Rents'!$D$14 -> 500 | O20: =O19 -> 350 | P20: =IF(N20>=O20,"PASS","FAIL") -> PASS | Q20: warning | R20: COMPUTED | S20: =IF(P20="FAIL","Reserve deposit/unit dips below floor in some year","") | T20: =IF($R20="APP-SIDE",99,IF($P20="FAIL",IF($Q20="error",1,2),IF($P20="PENDING",3,90))) -> 90 | U20: =IFERROR(INDEX(QAP_Rule_Register!$M$6:$M$37,MATCH(K20,QAP_Rule_Register!$A$6:$A$37,0)),"") -> QAP §IV.D.10 | V20: =IF(T20<90,T20*1000+ROW(),"")
A21: DSCR band status | B21: =IF(AND(B18>=DSCRFloor,B20<=DSCRCeil),"PASS","FAIL") -> FAIL | J21: 19 | K21: UW-VACANCY13 | L21: Vacancy & Trending | M21: Vacancy, years 1-3 | N21: ='NOI Calc'!D11 -> 0.07 | O21: =VacancyMin -> 0.07 | P21: =IF('NOI Calc'!D11>=VacancyMin,"PASS","FAIL") -> PASS | Q21: warning | R21: COMPUTED | S21: =IF(P21="FAIL","Yr1-3 vacancy below 7%","") | T21: =IF($R21="APP-SIDE",99,IF($P21="FAIL",IF($Q21="error",1,2),IF($P21="PENDING",3,90))) -> 90 | U21: =IFERROR(INDEX(QAP_Rule_Register!$M$6:$M$37,MATCH(K21,QAP_Rule_Register!$A$6:$A$37,0)),"") -> QAP §IV.D.5 | V21: =IF(T21<90,T21*1000+ROW(),"")
A22: DSCR-15 QAP (y5/10/15) min | B22: =MIN(E6,E11,E16) -> 1.2640715 | J22: 20 | K22: UW-VACANCY4 | L22: Vacancy & Trending | M22: Vacancy, years 4+ | N22: ='NOI Calc'!D11 -> 0.07 | O22: =VacancyMin -> 0.07 | P22: =IF('NOI Calc'!D11>=VacancyMin,"PASS","FAIL") -> PASS | Q22: warning | R22: COMPUTED | S22: =IF(P22="FAIL","Yr4+ vacancy below 7%","") | T22: =IF($R22="APP-SIDE",99,IF($P22="FAIL",IF($Q22="error",1,2),IF($P22="PENDING",3,90))) -> 90 | U22: =IFERROR(INDEX(QAP_Rule_Register!$M$6:$M$37,MATCH(K22,QAP_Rule_Register!$A$6:$A$37,0)),"") -> QAP §IV.D.5 | V22: =IF(T22<90,T22*1000+ROW(),"")
A23: Cum cash @ Yr15 | B23: =H16 -> 3865332.1 | J23: 21 | K23: UW-TREND-RENT13 | L23: Vacancy & Trending | M23: Rent inflation, years 1-3 | N23: =('17-year Pro Forma'!E6/'17-year Pro Forma'!D6)-1 -> 0.02 | O23: =RentTrendMax -> 0.02 | P23: =IF(('17-year Pro Forma'!E6/'17-year Pro Forma'!D6)-1<=RentTrendMax+0.0001,"PASS","FAIL") -> PASS | Q23: warning | R23: COMPUTED | S23: =IF(P23="FAIL","Yr1-3 rent trend above 2%","") | T23: =IF($R23="APP-SIDE",99,IF($P23="FAIL",IF($Q23="error",1,2),IF($P23="PENDING",3,90))) -> 90 | U23: =IFERROR(INDEX(QAP_Rule_Register!$M$6:$M$37,MATCH(K23,QAP_Rule_Register!$A$6:$A$37,0)),"") -> QAP §IV.D.4 | V23: =IF(T23<90,T23*1000+ROW(),"")
A24: Deferred payback year | B24: {=IFERROR(INDEX(D3:D18,MATCH(1,INDEX(--(H3:H18>=DeferredFee),0),0)),"not by Yr17")} -> 11 | J24: 22 | K24: UW-TREND-RENT415 | L24: Vacancy & Trending | M24: Rent inflation, years 4-15 | N24: =('17-year Pro Forma'!H6/'17-year Pro Forma'!G6)-1 -> 0.02 | O24: =RentTrendMax -> 0.02 | P24: =IF(('17-year Pro Forma'!H6/'17-year Pro Forma'!G6)-1<=RentTrendMax+0.0001,"PASS","FAIL") -> PASS | Q24: warning | R24: COMPUTED | S24: =IF(P24="FAIL","Yr4-15 rent trend above 2%","") | T24: =IF($R24="APP-SIDE",99,IF($P24="FAIL",IF($Q24="error",1,2),IF($P24="PENDING",3,90))) -> 90 | U24: =IFERROR(INDEX(QAP_Rule_Register!$M$6:$M$37,MATCH(K24,QAP_Rule_Register!$A$6:$A$37,0)),"") -> QAP §IV.D.4 | V24: =IF(T24<90,T24*1000+ROW(),"")
A25: Equity-gap max credit | B25: =('Sources & Uses'!I78-'Sources & Uses'!I12-'Sources & Uses'!I19-'Sources & Uses'!I24)/'Tax Credit Calc'!F4/10/('Tax Credit Calc'!E39/'Tax Credit Calc'!C39) -> 1841756.5 | J25: 23 | K25: UW-TREND-EXPENSE | L25: Vacancy & Trending | M25: Expense inflation (payroll YoY) | N25: =('17-year Pro Forma'!F17/'17-year Pro Forma'!E17)-1 -> 0.03 | O25: =ExpTrendMin -> 0.028 | P25: =IF(('17-year Pro Forma'!F17/'17-year Pro Forma'!E17)-1>=ExpTrendMin-0.0001,"PASS","FAIL") -> PASS | Q25: warning | R25: COMPUTED | S25: =IF(P25="FAIL","Expense trend below 2.8%","") | T25: =IF($R25="APP-SIDE",99,IF($P25="FAIL",IF($Q25="error",1,2),IF($P25="PENDING",3,90))) -> 90 | U25: =IFERROR(INDEX(QAP_Rule_Register!$M$6:$M$37,MATCH(K25,QAP_Rule_Register!$A$6:$A$37,0)),"") -> QAP §IV.D.4 | V25: =IF(T25<90,T25*1000+ROW(),"")
A26: Hard fails | B26: =COUNTIFS($P$3:$P$36,"FAIL",$Q$3:$Q$36,"error",$R$3:$R$36,"<>APP-SIDE",$R$3:$R$36,"<>EXCLUDED") -> 2 | J26: 24 | K26: UW-HUD-TDC | L26: Cost & TDC | M26: HUD Total Dev Cost limit | N26: ='Sources & Uses'!I78 -> 50848028 | O26: =IF(HUDTDCLimit="","(enter on calc sheet)",HUDTDCLimit) -> 69223310 | P26: =IF(HUDTDCLimit="","PENDING",IF('Sources & Uses'!I78<=HUDTDCLimit,"PASS","FAIL")) -> PASS | Q26: error | R26: INPUT | S26: =IF(P26="PENDING","Enter summed HUD per-unit TDC limit on 'Dashboard Calc' M10",IF(P26="FAIL","Adjusted TDC exceeds HUD limit","")) | T26: =IF($R26="APP-SIDE",99,IF($P26="FAIL",IF($Q26="error",1,2),IF($P26="PENDING",3,90))) -> 90 | U26: =IFERROR(INDEX(QAP_Rule_Register!$M$6:$M$37,MATCH(K26,QAP_Rule_Register!$A$6:$A$37,0)),"") -> QAP §IV.D.25 | V26: =IF(T26<90,T26*1000+ROW(),"")
A27: Warnings | B27: =COUNTIFS($P$3:$P$36,"FAIL",$Q$3:$Q$36,"warning",$R$3:$R$36,"<>APP-SIDE",$R$3:$R$36,"<>EXCLUDED") -> 1 | J27: 25 | K27: UW-SOURCES-USES | L27: Cost & TDC | M27: Sources = Uses balance | N27: ='Sources & Uses'!I80 -> 1.1451542e-05 | O27: =SUBalanceTol -> 1 | P27: =IF(ABS('Sources & Uses'!I80)<=SUBalanceTol,"PASS","FAIL") -> PASS | Q27: warning | R27: EXCLUDED | S27: =IF(P27="FAIL","Sources and uses out of balance","") | T27: =IF($R27="APP-SIDE",99,IF($P27="FAIL",IF($Q27="error",1,2),IF($P27="PENDING",3,90))) -> 90 | U27: =IFERROR(INDEX(QAP_Rule_Register!$M$6:$M$37,MATCH(K27,QAP_Rule_Register!$A$6:$A$37,0)),"") -> QAP §IV.D.2 | V27: =IF(T27<90,T27*1000+ROW(),"")
A28: Pending | B28: =COUNTIFS($P$3:$P$36,"PENDING",$R$3:$R$36,"<>APP-SIDE",$R$3:$R$36,"<>EXCLUDED") -> 0 | J28: 26 | K28: UW-SYND-COSTCAP | L28: Syndication | M28: Syndication cost cap | N28: ='Financing Assumptions'!D49 -> 50000 | O28: =IF(Syndication="Public",SyndCapPub,SyndCapPriv)*'Tax Credit Calc'!F41 -> 1458671.2 | P28: =IF('Financing Assumptions'!D49<=IF(Syndication="Public",SyndCapPub,SyndCapPriv)*'Tax Credit Calc'!F41,"PASS","FAIL") -> PASS | Q28: error | R28: EXCLUDED | S28: =IF(P28="FAIL","Syndication costs exceed proceeds cap","") | T28: =IF($R28="APP-SIDE",99,IF($P28="FAIL",IF($Q28="error",1,2),IF($P28="PENDING",3,90))) -> 90 | U28: =IFERROR(INDEX(QAP_Rule_Register!$M$6:$M$37,MATCH(K28,QAP_Rule_Register!$A$6:$A$37,0)),"") -> QAP §IV.D.24 | V28: =IF(T28<90,T28*1000+ROW(),"")
A29: VERDICT | B29: =IF(B26>0,"FAIL",IF(OR(B27>0,B28>0),"MARGINAL","PENCILS")) -> FAIL | J29: 27 | K29: UW-CASHFLOW-10PCT | L29: Cash Flow | M29: Year-1 cash-flow ceiling | N29: ='17-year Pro Forma'!E40 -> 274844.28 | O29: =CashFlowCeilPct*'17-year Pro Forma'!E24 -> 133198.81 | P29: =IF('17-year Pro Forma'!E40<=CashFlowCeilPct*'17-year Pro Forma'!E24,"PASS","FAIL") -> FAIL | Q29: warning | R29: COMPUTED | S29: =IF(P29="FAIL","Stabilized cash "&TEXT('17-year Pro Forma'!E40,"$#,##0")&" exceeds 10% of opex","") -> Stabilized cash $274,844 exceeds 10% of opex | T29: =IF($R29="APP-SIDE",99,IF($P29="FAIL",IF($Q29="error",1,2),IF($P29="PENDING",3,90))) -> 2 | U29: =IFERROR(INDEX(QAP_Rule_Register!$M$6:$M$37,MATCH(K29,QAP_Rule_Register!$A$6:$A$37,0)),"") -> QAP §IV.D.4 | V29: =IF(T29<90,T29*1000+ROW(),"") -> 2029
J30: 28 | K30: UW-DEFERRED-DEV-FEE-15YR | L30: Deferred Fee | M30: Deferred dev-fee payoff by Yr15 | N30: =$B$23 -> 3865332.1 | O30: =DeferredFee -> 2131813.1 | P30: =IF(DeferredFee=0,"N/A",IF($B$23>=DeferredFee,"PASS","FAIL")) -> PASS | Q30: warning | R30: COMPUTED | S30: =IF(P30="FAIL","Cum cash "&TEXT($B$23,"$#,##0")&" < deferred fee by Yr15; repaid Yr "&$B$24,"") | T30: =IF($R30="APP-SIDE",99,IF($P30="FAIL",IF($Q30="error",1,2),IF($P30="PENDING",3,90))) -> 90 | U30: =IFERROR(INDEX(QAP_Rule_Register!$M$6:$M$37,MATCH(K30,QAP_Rule_Register!$A$6:$A$37,0)),"") -> QAP §IV.D.3 · §IV.D.9 | V30: =IF(T30<90,T30*1000+ROW(),"")
J31: 29 | K31: FEE-ASSET-MGMT-CAP | L31: Operating & Reserves | M31: Asset-mgmt fee cap (opex) | N31: n/a | O31: $5,000/yr | P31: N/A | Q31: info | R31: APP-SIDE | S31: No asset-mgmt line inside operating expenses (row-38 AM fee is below-NOI partnership fee) — verify in platform | T31: =IF($R31="APP-SIDE",99,IF($P31="FAIL",IF($Q31="error",1,2),IF($P31="PENDING",3,90))) -> 99 | U31: =IFERROR(INDEX(QAP_Rule_Register!$M$6:$M$37,MATCH(K31,QAP_Rule_Register!$A$6:$A$37,0)),"") -> QAP §IV.D.3 · §44 | V31: =IF(T31<90,T31*1000+ROW(),"")
J32: 30 | K32: ELG-EQUITY-MATCH | L32: Credit Structure | M32: LIHTC equity reconciliation | N32: n/a | O32: Must match | P32: N/A | Q32: info | R32: APP-SIDE | S32: §18.10 LIHTC equity vs syndication gross — verify in platform | T32: =IF($R32="APP-SIDE",99,IF($P32="FAIL",IF($Q32="error",1,2),IF($P32="PENDING",3,90))) -> 99 | U32: =IFERROR(INDEX(QAP_Rule_Register!$M$6:$M$37,MATCH(K32,QAP_Rule_Register!$A$6:$A$37,0)),"") -> QAP §IV.D.2 | V32: =IF(T32<90,T32*1000+ROW(),"")
J33: 31 | K33: UW-BASIS-RECON | L33: Cost & TDC | M33: Eligible-basis reconciliation | N33: n/a | O33: No recon errors | P33: N/A | Q33: info | R33: APP-SIDE | S33: Eligible-basis config vs unit-mix aggregates — verify in platform | T33: =IF($R33="APP-SIDE",99,IF($P33="FAIL",IF($Q33="error",1,2),IF($P33="PENDING",3,90))) -> 99 | U33: =IFERROR(INDEX(QAP_Rule_Register!$M$6:$M$37,MATCH(K33,QAP_Rule_Register!$A$6:$A$37,0)),"") -> IRC §42(d) | V33: =IF(T33<90,T33*1000+ROW(),"")
J34: 32 | K34: UW-SYND-PARTVI | L34: Syndication | M34: Syndication cost reconciliation | N34: n/a | O34: Part VI = Dev Costs | P34: N/A | Q34: info | R34: APP-SIDE | S34: Part VI syndication vs Development Costs subtotal — verify in platform | T34: =IF($R34="APP-SIDE",99,IF($P34="FAIL",IF($Q34="error",1,2),IF($P34="PENDING",3,90))) -> 99 | U34: =IFERROR(INDEX(QAP_Rule_Register!$M$6:$M$37,MATCH(K34,QAP_Rule_Register!$A$6:$A$37,0)),"") -> QAP §IV.D.24 | V34: =IF(T34<90,T34*1000+ROW(),"")
J35: 33 | K35: QAP-TDC-PERUNIT | L35: Cost & TDC | M35: Per-unit TDC vs QAP max | N35: ='Sources & Uses'!I78/'Unit Mix+Rents'!$D$14 -> 181600.1 | O35: ='Sources & Uses'!I85 -> 247226.11 | P35: =IF(N35<=O35,"PASS","FAIL") -> PASS | Q35: error | R35: COMPUTED | S35: =IF(P35="FAIL","Per-unit TDC "&TEXT(N35,"$#,##0")&" exceeds QAP max "&TEXT(O35,"$#,##0"),"") | T35: =IF($R35="APP-SIDE",99,IF($P35="FAIL",IF($Q35="error",1,2),IF($P35="PENDING",3,90))) -> 90 | V35: =IF(T35<90,T35*1000+ROW(),"")
J36: 34 | K36: QAP-TDC-TOTAL | L36: Cost & TDC | M36: Total TDC vs QAP max | N36: ='Sources & Uses'!I78 -> 50848028 | O36: ='Sources & Uses'!I86 -> 69223310 | P36: =IF(N36<=O36,"PASS","FAIL") -> PASS | Q36: error | R36: COMPUTED | S36: =IF(P36="FAIL","Total TDC "&TEXT(N36,"$#,##0")&" exceeds QAP max "&TEXT(O36,"$#,##0"),"") | T36: =IF($R36="APP-SIDE",99,IF($P36="FAIL",IF($Q36="error",1,2),IF($P36="PENDING",3,90))) -> 90 | V36: =IF(T36<90,T36*1000+ROW(),"")
L56: HUD 2024 TDC LIMITS — New Orleans, LA (TDC $/unit by building type)
L57: BR | M57: Units | N57: Detached/Semi-Detached | O57: Row House | P57: Walk-up | Q57: Elevator | R57: TDC/unit (active) | S57: Subtotal
L58: 0 | M58: =SUMIF('Unit Mix+Rents'!$A$4:$A$13,L58,'Unit Mix+Rents'!$D$4:$D$13) -> 0 | N58: 199618 | O58: 172976 | P58: 156737 | Q58: 161035 | R58: =INDEX(N58:Q58,MATCH($B$10,$N$57:$Q$57,0)) -> 156737 | S58: =M58*R58 -> 0
L59: 1 | M59: =SUMIF('Unit Mix+Rents'!$A$4:$A$13,L59,'Unit Mix+Rents'!$D$4:$D$13) -> 110 | N59: 258890 | O59: 227077 | P59: 213098 | Q59: 225448 | R59: =INDEX(N59:Q59,MATCH($B$10,$N$57:$Q$57,0)) -> 213098 | S59: =M59*R59 -> 23440780
L60: 2 | M60: =SUMIF('Unit Mix+Rents'!$A$4:$A$13,L60,'Unit Mix+Rents'!$D$4:$D$13) -> 170 | N60: 310326 | O60: 276477 | P60: 269309 | Q60: 289862 | R60: =INDEX(N60:Q60,MATCH($B$10,$N$57:$Q$57,0)) -> 269309 | S60: =M60*R60 -> 45782530
L61: 3 | M61: =SUMIF('Unit Mix+Rents'!$A$4:$A$13,L61,'Unit Mix+Rents'!$D$4:$D$13) -> 0 | N61: 370970 | O61: 339946 | P61: 354388 | Q61: 386483 | R61: =INDEX(N61:Q61,MATCH($B$10,$N$57:$Q$57,0)) -> 354388 | S61: =M61*R61 -> 0
L62: 4 | M62: =SUMIF('Unit Mix+Rents'!$A$4:$A$13,L62,'Unit Mix+Rents'!$D$4:$D$13) -> 0 | N62: 437537 | O62: 404791 | P62: 438588 | Q62: 483104 | R62: =INDEX(N62:Q62,MATCH($B$10,$N$57:$Q$57,0)) -> 438588 | S62: =M62*R62 -> 0
R63: Total → | S63: =SUM(S58:S62) -> 69223310
